Workbook
Name _Hlk102822595: 'BASE DE PONTOS V+'!#REF!
Name _Hlk102822605: 'BASE DE PONTOS V+'!#REF!
Name _Hlk44932008: 'Matriz de Risco'!$C$9
Name _Hlk44932008: 'RESUMO DE PONTOS'!#REF!
Name _Hlk44932008: 'RESUMO DE PONTOS Original'!$C$8
Name _Hlk44932282: 'Matriz de Risco'!$C$13
Name _Hlk44933547: 'Matriz de Risco'!$C$17
Name _Hlk44933737: 'Matriz de Risco'!$C$18
Name _Toc54348655: 'BASE DA MATRIZ DE RISCOS'!$C$19
Name _Toc54348656: 'BASE DA MATRIZ DE RISCOS'!$C$20
Name _Toc54348657: 'BASE DA MATRIZ DE RISCOS'!$C$37
Name _Toc54348658: 'BASE DA MATRIZ DE RISCOS'!$C$46
Name _Toc54348659: 'BASE DA MATRIZ DE RISCOS'!$C$75
Name _Toc54348660: 'BASE DA MATRIZ DE RISCOS'!$C$76
Name _Toc54348662: 'BASE DA MATRIZ DE RISCOS'!$C$119
Name _Toc70060767: TESTES!#REF!
Name _Toc70060768: TESTES!#REF!
Name _Toc70060769: TESTES!#REF!
Name _Toc70060770: TESTES!#REF!
Name _Toc70060771: TESTES!#REF!
Name _Toc70060772: TESTES!#REF!
Name _Toc70060773: TESTES!#REF!
Name _Toc70060774: TESTES!#REF!
Name _Toc70060775: TESTES!#REF!
Name _Toc70060776: TESTES!#REF!
Name _Toc70060777: TESTES!#REF!
Name _Toc70060778: TESTES!#REF!
Name _Toc70060779: TESTES!#REF!
Name _Toc70060780: TESTES!#REF!
Name _Toc70060781: TESTES!#REF!
Name _Toc70060782: TESTES!#REF!
Name _Toc70060783: TESTES!#REF!
Name _Toc70060784: TESTES!#REF!
Name _Toc70060785: TESTES!#REF!
Name _Toc70060786: TESTES!#REF!
Name _Toc70060787: TESTES!#REF!
Name _Toc70060788: TESTES!#REF!
Name _Toc70060789: TESTES!#REF!
Name _Toc70060790: TESTES!#REF!
Name _Toc70060791: TESTES!#REF!
Name _Toc70060792: TESTES!#REF!
Name _Toc70060793: TESTES!#REF!
Name _Toc70060794: TESTES!#REF!
Name _Toc70060795: TESTES!#REF!
Name _Toc70060796: TESTES!#REF!
Name _Toc70060797: TESTES!#REF!
Name _Toc70060798: TESTES!#REF!
Name _Toc70060799: TESTES!#REF!
Name _Toc70060800: TESTES!#REF!
Name _Toc70060801: TESTES!#REF!
Name _Toc70060802: TESTES!#REF!
Name _Toc70060803: TESTES!#REF!
Name _Toc70060804: TESTES!#REF!
Name _Toc70060805: TESTES!#REF!
Name _Toc70060806: TESTES!#REF!
Name _Toc70060807: TESTES!#REF!
Name _Toc70060808: TESTES!#REF!
Name _Toc70060809: TESTES!#REF!
Name _Toc70060810: TESTES!#REF!
Name _Toc70060811: TESTES!#REF!

Sheet TESTES
B2: Condomínio Mar de Itapuã
B3: Testes e Procedimentos da Auditoira Condominial
B4: Data base: 01/01/2021 à 31/12/2021
B6: Etapas | C6: Análise do Contrato - Auditoria conforme a NBC TA 800 | D6: Responsável | E6: Código Vorcon | F6: Cliente | G6: Testes e Procedimentos de Auditoria realizados | H6: Código do Teste | I6: Status testes | J6: Responsável | K6: Pedido de análise | L6: Descrição no Pedido de Análise | M6: Status pedido de análise | N6: Observações | P6: Simbolo | Q6: Tipo | R6: Conclusão
B7: Planejamento | E7: 01.1.1 | F7: CRP | G7: Confirmação de Independência | H7: 01.1.1 - CRP - Confirmação de Independência | M7: x | P7: a | Q7: OK | R7: =COUNTIFS(I7:I54,"a")/COUNTA(H7:H54) -> 0
B8: Planejamento | E8: 01.1.2 | F8: CRP | G8: Pedido de Análise | H8: 01.1.2 - CRP - Pedido de Análise | M8: x | P8: x | Q8: Não Aplicável | R8: =COUNTIFS(I7:I54,"x")/COUNTA(H7:H54) -> 0
B9: Planejamento | E9: 01.1.3 | F9: CRP | G9: Entrevista para entendimento dos controles internos do condomínio (Inquiries) | H9: 01.1.3 - CRP - Entrevista para entendimento dos controles internos do condomínio | M9: x | P9: r | Q9: Pendente | R9: =COUNTIFS(I7:I54,"")/COUNTA(H7:H54) -> 1
B10: Planejamento | E10: 01.1.4 | F10: CRP | G10: Cálculo da Materialidade | H10: 01.1.4 - CRP - Cálculo da Materialidade | M10: a | P10: q | Q10: Em Andamento | R10: =COUNTIFS(I9:I56,"q")/COUNTA(H9:H56) -> 0
B11: Planejamento | E11: 01.1.5 | F11: CRP | G11: Follow Up CCI | H11: 01.1.5 - CRP - Follow Up CCI | M11: a
B12: Preparação | E12: 01.1.6 | F12: CRP | G12: Voucher documental | H12: 01.1.6 - CRP - Voucher documental | M12: a
B13: Preparação | E13: 01.1.7 | F13: CRP | G13: Constituição e operação do Condomínio | H13: 01.1.7 - CRP - Constituição e operação do Condomínio | M13: a
B14: Preparação | E14: 01.1.8 | F14: CRP | G14: Resumo Regimento | H14: 01.1.8 - CRP - Resumo Regimento | M14: a
B15: Preparação | E15: 01.1.9 | F15: CRP | G15: Resumo Convenção | H15: 01.1.9 - CRP - Resumo Convenção | M15: a
B16: Preparação | E16: 01.1.10 | F16: CRP | G16: Resumo do Manual de Obrigações Trabalhistas | H16: 01.1.10 - CRP - Resumo do Manual de Obrigações Trabalhistas | M16: x
B17: Preparação | E17: 01.1.11 | F17: CRP | G17: Resumo do Manual Operacional de Receitas | H17: 01.1.11 - CRP - Resumo do Manual Operacional de Receitas | M17: x
B18: Preparação | E18: 01.1.12 | F18: CRP | G18: Resumo do Manual de Contratação | H18: 01.1.12 - CRP - Resumo do Manual de Contratação | M18: x
B19: Preparação | E19: 01.1.13 | F19: CRP | G19: Carta de Representação de Atas | H19: 01.1.13 - CRP - Carta de Representação de Atas | M19: a
B20: Preparação | E20: 01.1.14 | F20: CRP | G20: Resumo Atas | H20: 01.1.14 - CRP - Resumo Atas | M20: a
B21: Preparação | E21: 01.1.15 | F21: CRP | G21: Teste de voucher (inspeção das guias e confronto dos saldos demonstrativos) | H21: 01.1.15 - CRP - Teste de voucher (inspeção das guias e confronto dos saldos demonstrativos) | M21: a
B22: Preparação | E22: 01.1.16 | F22: CRP | G22: Consolidação dos saldos dos demonstrativos financeiro + Voucher Documental | H22: 01.1.16 - CRP - Consolidação dos saldos dos demonstrativos financeiro + Voucher Documental | M22: a
... B50: Revisão | E50: 01.1.43 | F50: CRP | G50: Consolidação de pontos (baseado no novo modelo com matriz de risco.) | H50: 01.1.43 - CRP - Consolidação de pontos (baseado no novo modelo com matriz de risco.) | M50: x
B51: Revisão | E51: 01.1.44 | F51: CRP | G51: Carta de Representação da Administração | H51: 01.1.44 - CRP - Carta de Representação da Administração
B52: Revisão | E52: 01.1.45 | F52: CRP | G52: Minuta da Auditoria NBC TA 800 | H52: 01.1.45 - CRP - Minuta da Auditoria NBC TA 800
B53: Revisão | E53: 01.1.46 | F53: CRP | G53: Minuta da Apresentação da Auditoria NBC TA 800 | H53: 01.1.46 - CRP - Minuta da Apresentação da Auditoria NBC TA 800
B54: Revisão | E54: 01.1.47 | F54: CRP | G54: Relatório Final da Auditoria NBC TA 800 | H54: 01.1.47 - CRP - Relatório Final da Auditoria NBC TA 800

Sheet OPNIÃO
B1: Condomínios
B2: APROVA | C2: RELATÓRIO COM OPINIÃO SEM RESSALVA | D2: O relatório sem ressalva é emitido quando o auditor está convencido sobre todos os aspectos relevantes dos assuntos tratados no item 4 deste Pronunciamento. O relatório do auditor independente deve expressar essa convicção de forma clara e objetiva. | E2: O relatório sem ressalva implica afirmação de que, em tendo havido alterações em princípios contábeis ou no método de sua aplicação, o fato e os efeitos dele decorrentes foram adequadamente determinados e revelados nas demonstrações contábeis e/ou nas notas explicativas. | F2: O auditor não deve emitir um relatório sem ressalva quando existirem quaisquer das circunstâncias seguintes, que, na sua opinião, tenham efeitos relevantes para as demonstrações contábeis.
B3: APROVA COM RESSALVA | C3: RELATÓRIO COM OPINIÃO COM RESSALVA | D3: O relatório com ressalva é emitido quando o auditor conclui que o efeito de qualquer discordância ou restrição na extensão de um trabalho não é de tal magnitude que requeira relatório adverso ou abstenção de opinião. | E3: O relatório com ressalva deve obedecer ao modelo do relatório sem ressalva, com a utilização das expressões "exceto por", "exceto quanto" ou "com exceção de", referindo-se aos efeitos do assunto objeto da ressalva. Não é aceitável nenhuma outra expressão na redação desse tipo de relatório.
B4: Não APROVA | C4: RELATÓRIO COM OPINIÃO ADVERSO | D4: O auditor deve emitir relatório adverso quando verificar que as demonstrações contábeis estão incorretas ou incompletas, em tal magnitude que impossibilite a emissão do relatório com ressalvas. | E4: Assim, relatório adverso é o que exprime a opinião de que as demonstrações contábeis não representam adequadamente a posição patrimonial e financeira, nem o resultado das operações, e/ou as mutações do patrimônio líquido, e/ou as origens e aplicações de recursos de acordo com os Princípios Fundamentais de Contabilidade. | F4: O auditor deve, portanto, emitir relatório adverso quando verificar efeitos que, em sua opinião, comprometam em tal magnitude das demonstrações contábeis examinadas a ponto de não ser suficiente a simples ressalva no relatório. Nessas circunstâncias, uma ressalva não é considerada apropriada, uma vez que o auditor possui informações suficientes para declarar que as demonstrações contábeis não estão adequadamente apresentadas.
B5: Não APROVA | C5: RELATÓRIO COM ABSTENÇÃO DE OPINIÃO | D5: O relatório com abstenção de opinião é emitido quando houver uma limitação significativa na extensão de seus exames que impossibilite o auditor expressar opinião sobre as demonstrações contábeis por não ter obtido comprovação suficiente para fundamentá-la. Abstenção de opinião por limitação da extensão | E5: Nos casos de limitações significativas, o auditor deve, no parágrafo da extensão, indicar claramente os procedimentos omitidos e suas circunstâncias ou fazer uma referência a um parágrafo intermediário específico do relatório que descreva tal limitação. Em quaisquer desses casos, em parágrafo final do relatório, o auditor deve mencionar claramente que o exame não foi suficiente para permitir emissão de opinião sobre as demonstrações contábeis tomadas em conjunto. A abstenção de opinião não elimina a responsabilidade do auditor em mencionar, no relatório, qualquer desvio relevante que possa influenciar a decisão do usuário dessas informações.
C7: Análise: Quando houver distorção relevante ou não identificação de evidências de que as demonstrações não apresentam distorções relevantes, o auditor deverá modificar sua opinião, entre: opinião com ressalva, adversa ou com abstenção de opinião.
C9: Nessas ocasiões, deve-se atentar para as seguintes palavras-chave:
C11: RELEVANTE + NÃO GENERALIZADA (com ou sem evidências): Opinião com ressalva;
C12: RELEVANTE + GENERALIZADA (com evidência): Opinião Adversa;
C13: RELEVANTE + GENERALIZADA (sem evidência): Abstenção de Opinião.
C15: Tipos de Opinião do Auditor
C17: 1. Opinião com ressalva
C19: O auditor deve expressar uma “Opinião com ressalva” quando:
C21: ele, tendo obtido evidência de auditoria apropriada e suficiente, conclui que as distorções, individualmente ou em conjunto, são relevantes, mas Não Generalizadas nas demonstrações contábeis; ou
C22: não é possível para ele obter evidência apropriada e suficiente de auditoria para fundamentar sua opinião, mas ele conclui que os possíveis efeitos de distorções não detectadas sobre as demonstrações contábeis, se houver, poderiam ser relevantes, MAS NÃO GENERALIZADOS.
C24: 2. Opinião adversa
C26: O auditor deve expressar uma “Opinião adversa” quando, tendo obtido evidência de auditoria apropriada e suficiente, conclui que as distorções, individualmente ou em conjunto, são RELEVANTES E GENERALIZADAS para as demonstrações contábeis.
... C30: O auditor deve se abster de expressar uma opinião quando não consegue obter evidência de auditoria apropriada e suficiente para fundamentar sua opinião e ele concluir que os possíveis efeitos de distorções não detectadas sobre as demonstrações contábeis, se houver, poderiam ser relevantes e generalizados.
D32: Natureza do assunto que gerou a modificação | E32: Julgamento do auditor sobre a disseminação de forma generalizada dos efeitos ou possíveis efeitos sobre as DFs
E33: Não Generalizado | F33: Generalizado
D34: DFs apresentam Distorsões Relevantes | E34: Opinião com Ressalva | F34: Opinião Adversa
D35: Impossibilidade de se Obter Evidência de Auditoria Apropriada e Suficiente | E35: Opinião com Ressalva | F35: Abstenção de Opinião

Sheet VELOCIMETRO
E1: =SUM(E2:E4) -> 0.5
D2: Não Aprova | E2: =50%-E3-E4 -> 0.125 | F2: =E2/$E$1 -> 0.25
D3: Aprova c/Ressalva | E3: 0.125 | F3: =E3/$E$1 -> 0.25
D4: Aprova | E4: 0.25 | F4: =E4/$E$1 -> 0.5
E5: 0.5
E6: Aprova | G6: Aprova c/ Ressalva | I6: Não Aprova | K6: Não Aprova
D7: Total de Pontos de baixo Impacto | E7: 0 | F7: =K23 -> 0.15384615 | G7: 2 | H7: =G7/$G$10 -> 0.14285714 | I7: 15 | J7: =I7/$I$10 -> 0.6 | K7: 15 | L7: =K7/$K$10 -> 0.42857143
D8: Ponteiro | E8: 5 | F8: 0.01 | G8: 5 | H8: =G8/$G$10 -> 0.35714286 | I8: 5 | J8: =I8/$I$10 -> 0.2 | K8: 10 | L8: =K8/$K$10 -> 0.28571429
D9: Total de Pontos de alto Impacto | E9: 15 | F9: =K21 -> 0.61538462 | G9: 7 | H9: =G9/$G$10 -> 0.5 | I9: 5 | J9: =I9/$I$10 -> 0.2 | K9: 10 | L9: =K9/$K$10 -> 0.28571429
E10: =SUM(E7:E9) -> 20 | F10: =SUM(F7:F9) -> 0.77923077 | G10: =SUM(G7:G9) -> 14 | H10: =SUM(H7:H9) -> 1 | I10: =SUM(I7:I9) -> 25 | J10: =SUM(J7:J9) -> 1 | K10: =SUM(K7:K9) -> 35 | L10: =SUM(L7:L9) -> 1
D12: 0% - 50% | E12: Se, pelo menos 75% dos pontos forem de baixo impacto e não houver nenhum ponto de Alto impacto crítico o bastante para reprovar as contas
D13: 51% - 75% | E13: Se a maioria dos pontos forem de Média e Baixo Impacto e houverem pouco s pontos de alto impacto ( pelo menos 75% forem de pontos de médio e baixo impacto e nos pontos de alto impacto não haver nenhum ponto crítico o bastante para reprovar as contas.
D14: 75% - 90% | E14: Se a maioria dos pontos forem de alto Impacto e houverem poucos pontos de baixo e médio impacto ( pelo menos 75% forem de pontos de alto impacto e nos pontos de alto impacto não haver nenhum ponto crítico o bastante para reprovar as contas.
D15: Crítico ( 100% ) | E15: Se houver algum ponto crítico o bastante que a auditoria julgue que seja impactante o suficiente para não permitir a aprovação das contas ou haja limitação de escopo que não permita que a auditoria seja realizada.
E20: Ponto | F20: Tipo | G20: Quantidade
E21: P01 | F21: ALTO | G21: 1 | I21: Alto | J21: =SUMIF($F$21:$F$46,$I21,$G$21:$G$46) -> 8 | K21: =J21/$J$24 -> 0.61538462
E22: P02 | F22: ALTO | G22: 1 | I22: Médio | J22: =SUMIF($F$21:$F$46,$I22,$G$21:$G$46) -> 3 | K22: =J22/$J$24 -> 0.23076923
E23: P03 | F23: ALTO | G23: 1 | I23: Baixo | J23: =SUMIF($F$21:$F$46,$I23,$G$21:$G$46) -> 2 | K23: =J23/$J$24 -> 0.15384615
E24: P04 | F24: ALTO | G24: 1 | J24: =SUM(J21:J23) -> 13 | K24: =SUM(K21:K23) -> 1
E25: P05 | F25: ALTO | G25: 1
E26: P06 | F26: ALTO | G26: 1
E27: P07 | F27: MÉDIO | G27: 1
E28: P08 | F28: BAIXO | G28: 1
E29: P09 | F29: ALTO | G29: 1
E30: P10 | F30: ALTO | G30: 1
E31: P11 | F31: BAIXO | G31: 1
E32: P12 | F32: MÉDIO | G32: 1
E33: P13 | F33: MÉDIO | G33: 1
E34: P14 | G34: 1
E35: P15 | G35: 1
E36: P16
E37: P17
E38: P18
E39: P19
E40: P20
E41: P21
E42: P22
E43: P23
E44: P24
E45: P25
E46: P26
B47: x | C47: x | D47: x | E47: x | F47: x | G47: x | H47: x | I47: x

Sheet RESUMO DE PONTOS
B3: ='BASE DE PONTOS V+'!B2 -> Condomínio Reserva das Plantas | E3: Materialidade | F3: 149800
B4: RESUMO DE PONTOS | E4: PM | F4: 93650 | G4: 4994518.8
B5: Data base: | E5: AMPT | F5: 7490 | M5: ATUALIZAR
G6: Avaliação da soma das NFs Identificadas
B7: COD | C7: 1 | D7: 2 | E7: 3 | F7: 4 | G7: 5 | H7: 6 | I7: 7 | J7: 8 | L7: 9 | M7: Status | N7: Perdas/Impacto
B8: Código | C8: Ponto | D8: Descrição Resumida | E8: Descrição do Ponto | F8: Riscos e Implicações | G8: Impacto Financeiro | H8: Recomendações | I8: Tipo | J8: Tipo de Teste | K8: Tipo de Teste | L8: Julgamento Profissional
B9: V01 | C9: [P1] | D9: Pagamento sem documento fiscal | E9: =_xlfn.XLOOKUP($B9,'BASE DE PONTOS V+'!$B:$B,'BASE DE PONTOS V+'!$D:$D) -> Verificamos que ocorreram gastos sem a respectiva emissão de documento fiscal pelos fornecedores e/ou prestadores de serviços. | F9: =_xlfn.XLOOKUP($B9,'BASE DE PONTOS V+'!$B:$B,'BASE DE PONTOS V+'!$F:$F) -> Pagamentos sem os respectivos documentos fiscais dos fornecedores/prestadores de serviços não são permitidos pela legislação brasileira, assim como Convenção e Regimento Interno do Condomínio. Dessa forma, o mesmo pode ser multado e/ou sofrer outras penalidades impostas pelo fisco. | G9: =_xlfn.XLOOKUP(B9,'BASE DE PONTOS V+'!B:B,'BASE DE PONTOS V+'!E:E) -> 17679.82 | H9: =_xlfn.XLOOKUP($B9,'BASE DE PONTOS V+'!$B:$B,'BASE DE PONTOS V+'!$G:$G) -> Sugerimos que seja solicitado aos respectivos fornecedores/ prestadores de serviços a nota fiscal pelo fornecimento de material ou de prestação de serviço. | I9: =_xlfn.XLOOKUP($B9,'BASE DE PONTOS V+'!$B:$B,'BASE DE PONTOS V+'!$H:$H) -> Legal | J9: Voucher documental | K9: =_xlfn.XLOOKUP($B9,'BASE DE PONTOS V+'!$B:$B,'BASE DE PONTOS V+'!$M:$M) -> 0 | L9: =_xlfn.XLOOKUP(B9,'BASE DE PONTOS V+'!B:B,'BASE DE PONTOS V+'!J:J) -> Alto Impacto | M9: =_xlfn.XLOOKUP(D9,'BASE DE PONTOS V+'!C:C,'BASE DE PONTOS V+'!L:L) -> • 08/11/2022 • Novo ■ Vorcon Auditoria & Consultoria | N9: =IF(B9="","",IFERROR(IF(I9="Financeiro",VLOOKUP(G9,'BASE DA MATRIZ DE RISCOS'!$O$58:$Q$62,3,1),"Avaliar por julgameto"),"1")) -> Avaliar por julgameto
B10: V02 | C10: [P2] | D10: Pagamentos realizados sem os respectivos comprovantes de pagamento anexados | E10: =_xlfn.XLOOKUP($B10,'BASE DE PONTOS V+'!$B:$B,'BASE DE PONTOS V+'!$D:$D) -> Constatamos que alguns pagamentos foram realizados sem que fossem anexados os respectivos comprovantes de pagamentos ou documentos equivalentes dando a respectiva quitação. | F10: =_xlfn.XLOOKUP($B10,'BASE DE PONTOS V+'!$B:$B,'BASE DE PONTOS V+'!$F:$F) -> Possibilidade de pagamento duplicado dos valores, ou caso haja a solicitação dos comprovantes de pagamentos o Condomínio não os possua. | G10: =_xlfn.XLOOKUP(B10,'BASE DE PONTOS V+'!B:B,'BASE DE PONTOS V+'!E:E) -> 1558.24 | H10: =_xlfn.XLOOKUP($B10,'BASE DE PONTOS V+'!$B:$B,'BASE DE PONTOS V+'!$G:$G) -> Sugerimos que sejam criados controles para que os comprovantes de pagamentos estejam anexados com seus respectivos documentos. | I10: =_xlfn.XLOOKUP($B10,'BASE DE PONTOS V+'!$B:$B,'BASE DE PONTOS V+'!$H:$H) -> Financeiro | J10: Voucher documental | K10: =_xlfn.XLOOKUP($B10,'BASE DE PONTOS V+'!$B:$B,'BASE DE PONTOS V+'!$M:$M) -> 0 | L10: =_xlfn.XLOOKUP(B10,'BASE DE PONTOS V+'!B:B,'BASE DE PONTOS V+'!J:J) -> Baixo Impacto | M10: =_xlfn.XLOOKUP(D10,'BASE DE PONTOS V+'!C:C,'BASE DE PONTOS V+'!L:L) -> • 08/11/2022 • Novo ■ Vorcon Auditoria & Consultoria | N10: =IF(B10="","",IFERROR(IF(I10="Financeiro",VLOOKUP(G10,'BASE DA MATRIZ DE RISCOS'!$O$58:$Q$62,3,1),"Avaliar por julgameto"),"1")) -> 1
B11: V03 | C11: [P3] | D11: Negligência na gestão dos Documentos que compõe os Demonstrativos | E11: =_xlfn.XLOOKUP($B11,'BASE DE PONTOS V+'!$B:$B,'BASE DE PONTOS V+'!$D:$D) -> Verificamos que alguns comprovantes não estão sendo arquivados com os cuidados necessários, com isso alguns estão ilegíveis. | F11: =_xlfn.XLOOKUP($B11,'BASE DE PONTOS V+'!$B:$B,'BASE DE PONTOS V+'!$F:$F) -> Possível dificuldade e/ou impossibilidade na visualização dos gastos e dúvidas quanto a possíveis consultas no futuro em função do estado dos documentos. | G11: =_xlfn.XLOOKUP(B11,'BASE DE PONTOS V+'!B:B,'BASE DE PONTOS V+'!E:E) -> 118.82 | H11: =_xlfn.XLOOKUP($B11,'BASE DE PONTOS V+'!$B:$B,'BASE DE PONTOS V+'!$G:$G) -> Sugerimos aperfeiçoamento dos controles internos para que no momento do recebimento das documentações sejam retiradas as cópias ou ocorram as digitalizações visando preservar as informações. | I11: =_xlfn.XLOOKUP($B11,'BASE DE PONTOS V+'!$B:$B,'BASE DE PONTOS V+'!$H:$H) -> Operacional | J11: Voucher documental | K11: =_xlfn.XLOOKUP($B11,'BASE DE PONTOS V+'!$B:$B,'BASE DE PONTOS V+'!$M:$M) -> 0 | L11: =_xlfn.XLOOKUP(B11,'BASE DE PONTOS V+'!B:B,'BASE DE PONTOS V+'!J:J) -> Baixo Impacto | M11: =_xlfn.XLOOKUP(D11,'BASE DE PONTOS V+'!C:C,'BASE DE PONTOS V+'!L:L) -> • 08/11/2022 • Novo ■ Vorcon Auditoria & Consultoria | N11: =IF(B11="","",IFERROR(IF(I11="Financeiro",VLOOKUP(G11,'BASE DA MATRIZ DE RISCOS'!$O$58:$Q$62,3,1),"Avaliar por julgameto"),"1")) -> Avaliar por julgameto
B12: V04 | C12: [P4] | D12: Conjunto de documentos anexados fora do mês correspondente no Balancete. | E12: =_xlfn.XLOOKUP($B12,'BASE DE PONTOS V+'!$B:$B,'BASE DE PONTOS V+'!$D:$D) -> Desorganização da documentação suporte dificultam a análise de todas as partes envolvidas. | F12: =_xlfn.XLOOKUP($B12,'BASE DE PONTOS V+'!$B:$B,'BASE DE PONTOS V+'!$F:$F) -> A ausência de apresentação de forma tempestiva dos documentos financeiros poderá afetar diretamente o fluxo de caixa e o controle do financeiro do condomínio. | G12: =_xlfn.XLOOKUP(B12,'BASE DE PONTOS V+'!B:B,'BASE DE PONTOS V+'!E:E) -> 418.07 | H12: =_xlfn.XLOOKUP($B12,'BASE DE PONTOS V+'!$B:$B,'BASE DE PONTOS V+'!$G:$G) -> Recomendamos que a prestação de contas seja realizada conforme o período correspondente as despesas. | I12: =_xlfn.XLOOKUP($B12,'BASE DE PONTOS V+'!$B:$B,'BASE DE PONTOS V+'!$H:$H) -> Operacional | J12: Voucher documental | K12: =_xlfn.XLOOKUP($B12,'BASE DE PONTOS V+'!$B:$B,'BASE DE PONTOS V+'!$M:$M) -> 0 | L12: =_xlfn.XLOOKUP(B12,'BASE DE PONTOS V+'!B:B,'BASE DE PONTOS V+'!J:J) -> Baixo Impacto | M12: =_xlfn.XLOOKUP(D12,'BASE DE PONTOS V+'!C:C,'BASE DE PONTOS V+'!L:L) -> • 08/11/2022 • Novo ■ Vorcon Auditoria & Consultoria | N12: =IF(B12="","",IFERROR(IF(I12="Financeiro",VLOOKUP(G12,'BASE DA MATRIZ DE RISCOS'!$O$58:$Q$62,3,1),"Avaliar por julgameto"),"1")) -> Avaliar por julgameto
B13: V05 | C13: [P5] | D13: Informações apresentado fora do mês correspondente na demonstração financeira. | E13: =_xlfn.XLOOKUP($B13,'BASE DE PONTOS V+'!$B:$B,'BASE DE PONTOS V+'!$D:$D) -> Verificamos que há desorganização das informações na demonstração financeira que dificultam na análise de todas as partes envolvidas. | F13: =_xlfn.XLOOKUP($B13,'BASE DE PONTOS V+'!$B:$B,'BASE DE PONTOS V+'!$F:$F) -> A falta de apresentação de maneira tempestiva das informações financeiras poderá afetar diretamente o controle financeiro do condomínio e o entendimento dos Demonstrativos. | G13: =_xlfn.XLOOKUP(B13,'BASE DE PONTOS V+'!B:B,'BASE DE PONTOS V+'!E:E) -> 418.07 | H13: =_xlfn.XLOOKUP($B13,'BASE DE PONTOS V+'!$B:$B,'BASE DE PONTOS V+'!$G:$G) -> Indicamos que as informações apresentadas nas Demonstrações Financeiras sejam realizadas conforme o período correspondente. | I13: =_xlfn.XLOOKUP($B13,'BASE DE PONTOS V+'!$B:$B,'BASE DE PONTOS V+'!$H:$H) -> Financeiro | J13: Voucher documental | K13: =_xlfn.XLOOKUP($B13,'BASE DE PONTOS V+'!$B:$B,'BASE DE PONTOS V+'!$M:$M) -> 0 | L13: =_xlfn.XLOOKUP(B13,'BASE DE PONTOS V+'!B:B,'BASE DE PONTOS V+'!J:J) -> Baixo Impacto | M13: =_xlfn.XLOOKUP(D13,'BASE DE PONTOS V+'!C:C,'BASE DE PONTOS V+'!L:L) -> • 08/11/2022 • Novo ■ Vorcon Auditoria & Consultoria | N13: =IF(B13="","",IFERROR(IF(I13="Financeiro",VLOOKUP(G13,'BASE DA MATRIZ DE RISCOS'!$O$58:$Q$62,3,1),"Avaliar por julgameto"),"1")) -> 1
B14: V07 | C14: [P6] | D14: Diferenças entre: Valor do comprovante de pagamento X Valor da documentação suporte. | E14: =_xlfn.XLOOKUP($B14,'BASE DE PONTOS V+'!$B:$B,'BASE DE PONTOS V+'!$D:$D) -> Verificamos que alguns pagamentos foram realizados após a data de vencimento acarretando em gastos adicionais. | F14: =_xlfn.XLOOKUP($B14,'BASE DE PONTOS V+'!$B:$B,'BASE DE PONTOS V+'!$F:$F) -> Possibilidade do condomínio incorrer em gastos desnecessários | G14: =_xlfn.XLOOKUP(B14,'BASE DE PONTOS V+'!B:B,'BASE DE PONTOS V+'!E:E) -> 10.37 | H14: =_xlfn.XLOOKUP($B14,'BASE DE PONTOS V+'!$B:$B,'BASE DE PONTOS V+'!$G:$G) -> Sugerimos que seja elaborado um controle de vencimento das despesas e que sejam efetuados os pagamentos até o vencimento. | I14: =_xlfn.XLOOKUP($B14,'BASE DE PONTOS V+'!$B:$B,'BASE DE PONTOS V+'!$H:$H) -> Financeiro | J14: Voucher documental | K14: =_xlfn.XLOOKUP($B14,'BASE DE PONTOS V+'!$B:$B,'BASE DE PONTOS V+'!$M:$M) -> 0 | L14: =_xlfn.XLOOKUP(B14,'BASE DE PONTOS V+'!B:B,'BASE DE PONTOS V+'!J:J) -> Baixo Impacto | M14: =_xlfn.XLOOKUP(D14,'BASE DE PONTOS V+'!C:C,'BASE DE PONTOS V+'!L:L) -> • 08/11/2022 • Novo ■ Vorcon Auditoria & Consultoria | N14: =IF(B14="","",IFERROR(IF(I14="Financeiro",VLOOKUP(G14,'BASE DA MATRIZ DE RISCOS'!$O$58:$Q$62,3,1),"Avaliar por julgameto"),"1")) -> 1
B15: V08 | C15: [P7] | D15: Pagamentos realizados antes da emissão da nota fiscal. | E15: =_xlfn.XLOOKUP($B15,'BASE DE PONTOS V+'!$B:$B,'BASE DE PONTOS V+'!$D:$D) -> Verificamos que ocorreram pagamentos onde a emissão da documentação fiscal é posterior a data em que a transação bancária foi realizada. | F15: =_xlfn.XLOOKUP($B15,'BASE DE PONTOS V+'!$B:$B,'BASE DE PONTOS V+'!$F:$F) -> O pagamento antes da emissão das notas fiscais traz uma vulnerabilidade a respeito do cumprimento das melhores práticas de gestão podendo gerar penalidades tributárias. | G15: =_xlfn.XLOOKUP(B15,'BASE DE PONTOS V+'!B:B,'BASE DE PONTOS V+'!E:E) -> 3563.16 | H15: =_xlfn.XLOOKUP($B15,'BASE DE PONTOS V+'!$B:$B,'BASE DE PONTOS V+'!$G:$G) -> Recomendamos que seja verificada a emissão da nota fiscal antes da realização do pagamento. | I15: =_xlfn.XLOOKUP($B15,'BASE DE PONTOS V+'!$B:$B,'BASE DE PONTOS V+'!$H:$H) -> Legal | J15: Voucher documental | K15: =_xlfn.XLOOKUP($B15,'BASE DE PONTOS V+'!$B:$B,'BASE DE PONTOS V+'!$M:$M) -> 0 | L15: =_xlfn.XLOOKUP(B15,'BASE DE PONTOS V+'!B:B,'BASE DE PONTOS V+'!J:J) -> médio impacto | M15: =_xlfn.XLOOKUP(D15,'BASE DE PONTOS V+'!C:C,'BASE DE PONTOS V+'!L:L) -> • 08/11/2022 • Novo ■ Vorcon Auditoria & Consultoria | N15: =IF(B15="","",IFERROR(IF(I15="Financeiro",VLOOKUP(G15,'BASE DA MATRIZ DE RISCOS'!$O$58:$Q$62,3,1),"Avaliar por julgameto"),"1")) -> Avaliar por julgameto
B16: V10 | C16: [P8] | D16: Os balancetes sem aprovação dos conselheiros fiscais e do síndico no termo de aprovação. | E16: No período de 03/2021 a 02/2022 não constam as assinaturas do síndico e dos conselheiros fiscais para aprovação dos balancetes. Porém, conforme a Convenção do Subcondomínio Reserva das Plantas na cláusula 4.9.1 - f) "O Síndico de cada Subcondomínio tem as seguintes atribuições [...] rubrica[...] dos livros". Além disso, no item G-4.21-c) "Cada Conselho Fiscal [...] terá as seguintes atribuições: emitir parecer sobre as contas [...] do Síndico do Subcondomínio Residencial [...], conferindo-as, aprovando-as ou rejeitando-as". | F16: A falta das assinaturas dos conselheiros fiscais nos termos de aprovação dos balancetes indica que as contas do condomínio não foram submetidas ao exame, podendo acarretar a redução do nível de confiança dos demonstrativos e prejudicar a leitura dos usuários. | G16: NA | H16: Sugerimos que os conselheiros fiscais realizem o exame dos balancetes e caso ocorra a aprovação dos mesmos, confirmem com as suas assinaturas nos termos de aprovação. Mesmo com as demonstrações financeiras sendo auditadas mensalmente, é necessário a validação do conselho fiscal. | I16: Legal | J16: Resumo Convenção | K16: 0 | L16: Alto Impacto | M16: • 08/11/2022 • Novo ■ Vorcon Auditoria & Consultoria | N16: Avaliar por julgameto
B17: V11 | C17: [P9] | D17: Falta de registro de Ata's em cartório | E17: Não identificamos o registro em cartório das Ata's: 16/12/2021, 09/09/2021, 14/10/2021, 27/01/2022, 03/02/2022. Conforme a Convenção do Subcondomínio Reserva das Plantas na cláusula 4.9.1 - f) "O Síndico de cada Subcondomínio tem as seguintes atribuições [...] Providenciar abertura, numeração, rubrica e encerramento dos livros, bem como o registro das atas em Cartório de Registro de Títulos e Documentos". | F17: Possível questionamento dos Condominos quanto a validação das Ata's por falta de registo no cartório. | G17: NA | H17: Sugerimos que haja registro das Ata's em cartório, conforme convenção. | I17: Legal | J17: Resumo Convenção | K17: 0 | L17: médio impacto | M17: • 08/11/2022 • Novo ■ Vorcon Auditoria & Consultoria | N17: Avaliar por julgameto
B18: V12 | C18: [P10] | D18: Falta relatório de auditoria do período anterior. | E18: Conforme a Convenção do Subcondomínio Reserva das Plantas na cláusula 4.9.1 - h) "O Síndico de cada Subcondomínio tem as seguintes atribuições [...] Contratar, anualmente, empresa de auditoria para fiscalizar as contas do Subcondomínio." Dessa forma, não foi identificado o relatório da auditoria do período que antecedeu a auditoria atual (03/2021 a 02/2022). No entanto, analisamos conforme entendimento com o cliente que o condomínio realizou a auditoria em 2021 e não receberam o relatório. | F18: A ausência de contratação da auditoria e apresentação do relatório em relação ao período anterior, além de infringir a convenção condomonial, prejudica a transparência na prestação de contas podendo causar danos a situação financeira, econômica, legal e imagem da entidade. | G18: NA | H18: Recomendamos que a administração sempre realize auditorias preventivas. | I18: Estratégico | J18: Follow Up CCI | K18: 0 | L18: Alto Impacto | M18: • 08/11/2022 • Novo ■ Vorcon Auditoria & Consultoria | N18: Avaliar por julgameto
B19: V13 | C19: [P11] | D19: Falta de Planejamento Orçamentário Anual | E19: Conforme a Convenção do Subcondomínio Reserva das Plantas na cláusula 4.36.1 "A assembleia geral ordinária do Condomínio realizar-se-á anualmente [...] outra assembleia geral ordinária do CONDOMÍNIO [Sic], sempre até o final do mês de novembro de cada ano e a ela competirá especificamente fixar o orçamento anual do CONDOMÍNIO para o exercicio social vindouro e a forma de cobrança das respectivas despesas." Dessa forma, não foi identificado o Planejamento Orçamentário para o ano de 2021. Além disso, identificamos nas Atas que o Sr. Marco Ribeiro, demonstrou as prinipais causas do aumento das despesas e informou que o condomíno está lidando com o mesmo planejamento orçamentário há 03 anos e que com a pandemia, todos os produtos e serviços tem sofrido aumentos fora do comum. | F19: A falta da elaboração do planejamento orçamentário poderá prejudicar o controle das contas condominiais e a prevenção dos gastos desnecerrários ou demasiados. | G19: NA | H19: Recomendamos que o o planejamento orçamentário ocorra dentro do período previsto em convenção. | I19: Estratégico | J19: Orçado X Realizado | K19: 0 | L19: Alto Impacto | M19: • 08/11/2022 • Novo ■ Vorcon Auditoria & Consultoria | N19: Avaliar por julgameto
B20: V14 | C20: [P12] | D20: Sistema de medição da água realizado de forma não individualizada | E20: Segundo a ATA Reunião de Moradores do dia 09/09/2021 o "Sr. Roque Andrade entrou na tratativa da individualização da água e falou sobre os benefícios que isso traria por conta do consumo desigual entre as unidades [...]". Dessa forma, identificamos que o sistema de medição da água não é realizado de forma individualizada, infringindo assim, a cláusula 15.1 - e) da Convenção Condominial. | F20: A infração em relação a item previsto na Convenção Condominial pode gerar questionamentos, reclamações, impactos em relação a sustentabilidade e prejuizos de ordem legal para o condominio. | G20: NA | H20: Recomendamos que a administração analise a viabilidade da individualização de medição da água junto aos condominos e profissionais técnicos. Após isso, se for viável planeje a implementação e caso contrário, atualize a convenção para modificar a previsão desse item. | I20: Legal | J20: Resumo Convenção | K20: 0 | L20: médio impacto | M20: • 08/11/2022 • Novo ■ Vorcon Auditoria & Consultoria | N20: Avaliar por julgameto
B21: V15 | C21: [P13] | D21: Valor apresentado no comprovante de pagamento, mas que não consta no extrato bancário | E21: Identificamos comprovante de pagamento do dia 19/10/2021 informando que foi realizado o pagamento no valor de R$ 1000,00 através da Agência: 4306 e Conta: 130035030. No entanto, essas informações não constam no extrato bancário dessa respectiva conta. | F21: A divergência de informações entre comprovante de pagamento e o extrato bancário pode indicar erro ou fraude na gestão financeira condominial e impactar nas disponibilidades da entidade. | G21: 1000 | H21: Indicamos que a Administração promova melhorias em seus controles interno tendo como finalidade a apresentação de informações financeiras convergentes com os registros expostos nos extratos bancários. | I21: Financeiro | J21: Demonstrativo Financeiro + voucher nos extratos | K21: 0 | L21: Baixo Impacto | M21: #N/A | N21: 1
B22: V16 | C22: [P14] | D22: Falta de apresentação de extratos bancários | E22: Verificamos que em alguns meses não foram apresentados à auditoria os extratos do Banco Santander, agência: 4306 e contas: 13.003502-3 / 13.003496-7, além das aplicações financeiras. | F22: A falta dos extratos bancários prejudica a análise das informações, o entendimento e a validação das entradas e saídas financeiras do condomínio. | G22: NA | H22: Visando aumentar a transparência na prestação de contas do condomínio, sugerimos à Administração que envie os extratos bancários emitidos diretamente pelas instituições financeiras para que as análises dessas informações se tornem possíveis. | I22: Financeiro | J22: Demonstrativo Financeiro + voucher nos extratos | K22: 0 | L22: Baixo Impacto | M22: • 08/11/2022 • Novo ■ Vorcon Auditoria & Consultoria | N22: 1
B23: V17 | C23: [P15] | D23: Saídas nos extratos não validados com a voucher | E23: Identificamos no momento do confronto entre os extratos bancários e a Voucher Documental produzida com as informações apresentadas pelo condomínio, a existência de saídas de recursos dos extratos que não constam na Voucher. Diante disso, não ocorre a verificação dos documentos comprobatórios dos respectivos dispêndios realizados pelo condomínio | F23: As saídas de recursos dos extratos sem a validação da Voucher Documental poderão prejudicar a transparência e afetar a prestação de contas, dando oportunidade de os valores não serem utilizados para fins que geram benefícios econômicos ao condomínio. | G23: 2117.99 | H23: Indicamos ao Conselho Fiscal a estruturação de procedimentos de controles internos que garantam destinação adequada dos recursos condominiais sendo apresentados todos os documentos comprobatórios da realização de suas despesas e validados por uma auditoria contínua. | I23: Financeiro | J23: Demonstrativo Financeiro + voucher nos extratos | K23: 0 | L23: Baixo Impacto | M23: • 08/11/2022 • Novo ■ Vorcon Auditoria & Consultoria | N23: 1
B24: V18 | C24: [P16] | D24: Apresentação incompleta de extrato bancário | E24: Recebemos o extrato do Banco Santander, agência: 4306 e conta: 13.003503-0 referente ao mês 02/2022 de forma incompleta, impossibilitando assim, a conferência de todas as suas informações. | F24: A entrega de extrato realizada de forma incompleta impede a análise, o entendimento e a validação das entradas e saídas financeiras, reduzindo assim, a transparência nas prestação de contas do condomínio. | G24: NA | H24: Recomendamos à Administração que envie os extratos bancários emitidos diretamente pelas instituições financeiras contemplando todas as informações do período solicitado. | I24: Financeiro | J24: Demonstrativo Financeiro + voucher nos extratos | K24: 0 | L24: Baixo Impacto | M24: • 08/11/2022 • Novo ■ Vorcon Auditoria & Consultoria | N24: 1
B25: V19 | C25: [P17] | D25: Diferenças entre os saldos dos Demonstrativos Financeiros de Receitas e Despesas em relação a Demonstração dos Saldos Financeiros. | E25: Verificamos os saldos finais dos demonstrativos financeiros de receitas e despesas (DF) e confrontamos com os valores finais dos demonstrativos dos saldos financeiros (DSF), nos quais foram identificadas divergências. | F25: A apresentação dos saldos divergentes nos demonstrativos financeiros de receita e despesas, poderá prejudicar a transparência e afetar a prestação de contas comprometendo a interpretação dos usuários das informações financeiras do condomínio. | G25: 109 | H25: Recomendamos que os demonstrativos dos saldos financeiros assim como os demonstrativo de receita e despesas sejam revisados para reduzir os riscos de divergências. | I25: Financeiro | J25: Conciliação Bancária + Elaboração dos quadros dos Demonstrativos Financeiros | K25: 0 | L25: Baixo Impacto | M25: • 08/11/2022 • Novo ■ Vorcon Auditoria & Consultoria | N25: 1
B26: V20 | C26: [P18] | D26: Ausência de apresentação de mapa de cotação | E26: Verificamos que algumas compras realizadas não estavam sendo efetuado o mapa de cotação. | F26: A falta da cotação mínima de 3 orçamentos poderá prejudicar o condomínio através de aquisições de bens e/ou serviços de baixa qualidade, com fornecedores sem conhecimento ou respaldo técnico e entregas diferente do escopo esperado. | G26: NA | H26: Recomendamos a administração que seja realizado mapa de orçamento no mínimo de 3 cotações para as aquisições dos bens ou serviços do condomínio. | I26: Operacional | J26: Voucher documental | K26: 0 | L26: Baixo Impacto | M26: • 08/11/2022 • Novo ■ Vorcon Auditoria & Consultoria | N26: Avaliar por julgameto
B27: V21 | C27: [P19] | D27: Ausência de inventário dos ativos imobilizados | E27: Não identificamos o controle patrimonial dos ativos imobilizados para atualização do saldo em decorrência dos bens adquiridos, obsoletos e/ou perdidos para realização da baixa, assim como as depreciações. | F27: A ausência do controle patrimonial do condomínio poderá impactar em possíveis perdas ou desvios do ativo imobilizado. | G27: NA | H27: Sugerimos que à Administração do condomínio busque realizar o inventário dos ativos imobilizados anualmente. | I27: Financeiro | J27: Inspeção estatística dos itens do Imobilizado | K27: 0 | L27: Alto Impacto | M27: • 08/11/2022 • Novo ■ Vorcon Auditoria & Consultoria | N27: 1
B28: V22 | C28: [P20] | D28: Inexistência de valor estimado dos honorários advocatícios | E28: Não identificamos o valor estimado da expectativa de exito nos casos de processos onde o condomínio esteja como polo ativo ou passivo para período de 03/2021 até 02/2022 | F28: 0 | G28: N/A | H28: 0 | I28: Financeiro | J28: Teste de Contingência | K28: 0 | L28: médio impacto | M28: #N/A | N28: 1
B29: V23 | C29: [P21] | D29: Perda Possível de Causa Judicial | E29: Identificamos no período de 28 de fevereiro 2022 a perda possível de R$ 406.946,20. Salientamos que a Perda Possível é aquela que o condomínio tem ou não uma obrigação presente legal como resultado de evento passado que haverá uma saída de recursos para liquidar essa obrigação. | F29: 0 | G29: 396946.2 | H29: 0 | I29: Legal | J29: Teste de Contingência | K29: 0 | L29: Alto Impacto | M29: • 08/11/2022 • Novo ■ Vorcon Auditoria & Consultoria | N29: Avaliar por julgameto
B30: V24 | C30: [P22] | D30: Perda Provável de Causa Judicial | E30: Identificamos no período de 28 de fevereiro 2022, uma perda provável de R$ 32.000,00 referente ao processo de FELIPE FERREIRA OLIVEIRA X SUBCONDOMÍNIO RESERVA DAS PLANTAS, tendo como objeto AÇÃO DECLARATÓRIA E INDENIZATÓRIA. Salientamos que a perda provável é quando o condomínio tem uma obrigação presente legal como resultado de evento passado e seja provável que será necessária a saída de recurso para liquidar a obrigação. Nesse sentido, a perda da causa judicial é mais provável que sim do que não. | F30: 0 | G30: 32000 | H30: Recomendamos que seja realizado uma Provisão para Perda .... | I30: Financeiro | J30: Teste de Contingência | K30: 0 | L30: médio impacto | M30: • 08/11/2022 • Novo ■ Vorcon Auditoria & Consultoria | N30: 2
B31: V25 | C31: [P23] | D31: Perda Remota de Causa Judicial | E31: Identificamos no período de 28 de fevereiro 2022, uma perda Remota de R$ 1.503.630,42. Salientamos que a perda remota é quando o condomínio não tem uma obrigação presente legal como resultado de evento passado e seja remoto que haverá uma saída de recurso para liquidar essa obrigação. Nesse sentido, a perda da causa judicial é menos provável que sim do que não. | F31: 0 | G31: 1503630.4 | H31: 0 | I31: Legal | J31: Teste de Contingência | K31: 0 | L31: médio impacto | M31: • 08/11/2022 • Novo ■ Vorcon Auditoria & Consultoria | N31: Avaliar por julgameto
B32: V26 | C32: [P24] | D32: Ausência de registro do Regimento do condomínio em cartório. | E32: Não foi possível validar a data do registro do condomínio no cartório a partir do documento recebido. | F32: A falta de registro em cartório do Regimento do Condomínio poderá gerar problemas relacionados a validade jurídica da documentação. | G32: NA | H32: Sugerimos que o Regimento seja registrado em cartório. | I32: Legal | J32: Regimento Interno | K32: 0 | L32: Baixo Impacto | M32: • 08/11/2022 • Novo ■ Vorcon Auditoria & Consultoria | N32: Avaliar por julgameto
B33: V27 | C33: [P25] | D33: Impossibilidade de identificação da conclusão da Obra do Parquinho e seu pagamento. | E33: Analisamos as Atas e os demonstrativos financeiros e identificamos a obra do parquinho pela empresa Danielson Alcantra Contruções e Reformas de 16/11/2021. Porém, não identificamos a ATA com informação de prestação de serviço concluída, como também, não localizamos o pagamento referente a terceira parcela do serviço prestado. | F33: 0 | G33: N/A | H33: 0 | I33: Operacional | J33: Resumo das Atas | K33: 0 | L33: Baixo Impacto | M33: #N/A | N33: Avaliar por julgameto
B34: V28 | C34: [P26] | D34: Falta de questionamentos do Conselho Fiscal nas Assembleias | E34: Analisamos 100% das atas de reuniões, Assembleia Geral Extraordinária (AGE), Assembleia Geral Ordinária (AGO), Conselho de Administração, Conselho Fiscal e outras atas de reuniões formalizadas do período de de 01/03/2021 a 28/02/2022 e não identificamos a fala do conselho fiscal. Inclusive, foi mencionado na AGE 28/10/2021 que o Conselho Consultivo foi o único a realizar a seleção para a eleição do síndico duas vezes sem a participação do Conselho Fiscal. | F34: 0 | G34: N/A | H34: 0 | I34: Legal | J34: Resumo das Atas | K34: 0 | L34: Alto Impacto | M34: • 08/11/2022 • Novo ■ Vorcon Auditoria & Consultoria | N34: Avaliar por julgameto
B35: V29 | C35: [P27] | D35: Cargo de Síndico Interino e de Conselheiro Fiscal ocupado pelo mesmo condômino | E35: Conforme a Convenção do Subcondomínio Reserva das Plantas na item G - 4.21 c) "Cada Conselho Fiscal [...] terá as seguintes atribuições: emitir parecer sobre as contas [...] do Síndico do Subcondomínio Residencial [...], conferindo-as, aprovando-as ou rejeitando-as" e também o segundo o Código Civil no Art. 1.356 "Poderá haver no condomínio um conselho fiscal [...]ao qual compete dar parecer sobre as contas do síndico". Dessa forma, analisamos 100% das atas e identificamos na AGE de 28/10/2021 que o Sr. Roque da Silva Pereira Andrade do Prédio Vitórioa Régia, 907 ocupa os cargos de Síndico Interino e Conselheiro fiscal ao mesmo tempo. | F35: Os dois cargos ocupado pelo condômino Sr. Roque da Silva ao mesmo tempo, pode afetar a independência do Conselho Fiscal em relação aos atos do Síndico Interino, influenciando o julgamento profissional do conselho e permitindo que o mesmo não atue com integridade, objetividade e ceticismo conforme NBC PA 400. | G35: N/A | H35: Recomendamos que a Administração do Condomínio promova melhorias nos seus controles internos e que não seja permitido que uma mesma pessoa ocupa os cargos de Síndico e Conselheiros simultaneamente. | I35: Estratégico | J35: Resumo das Atas | K35: 0 | L35: Alto Impacto | M35: • 08/11/2022 • Novo ■ Vorcon Auditoria & Consultoria | N35: Avaliar por julgameto
B36: V30 | C36: [P28] | D36: Inexistência da ATA do Conselho Consultivo na Assembleia Geral Extraordinária | E36: Conforme a Convenção do Subcondomínio Reserva das Plantas o síndico necessita obrigatoriamente ter a relação de todas as atas bem como o seu registro. Dessa forma, analisamos 100% das atas e identificamos na AGE de 28/10/2021 que conforme o síndico e o Gerente a ATA de Reunião do Conselho Consultivo não existia na Administradora no dia da Assembleia Geral Extraordinária. Assim, a ata não foi apresentada para o Advogado e por essa razão, o processo discutido pelo Conselho consultivo ficou nulo para a Assembleia Geral Extraordinária. | F36: 0 | G36: N/A | H36: 0 | I36: Legal | J36: Resumo das Atas | K36: 0 | L36: médio impacto | M36: • 08/11/2022 • Novo ■ Vorcon Auditoria & Consultoria | N36: Avaliar por julgameto
B37: V31 | C37: [P29] | D37: Impacto significativo com os inadimplentes | E37: Mês 02/2022 | F37: 0 | G37: 598391.24 | H37: 0 | I37: Financeiro | J37: Teste de Inadimplência | K37: 0 | L37: Alto Impacto | M37: #N/A | N37: 5
M45: =_xlfn.XLOOKUP(D45,'BASE DE PONTOS V+'!C:C,'BASE DE PONTOS V+'!L:L) -> 0 | N45: =IF(B45="","",IFERROR(IF(I45="Financeiro",VLOOKUP(G45,'BASE DA MATRIZ DE RISCOS'!$O$58:$Q$62,3,1),"Avaliar por julgameto"),"1"))
M46: =_xlfn.XLOOKUP(D46,'BASE DE PONTOS V+'!C:C,'BASE DE PONTOS V+'!L:L) -> 0 | N46: =IF(B46="","",IFERROR(IF(I46="Financeiro",VLOOKUP(G46,'BASE DA MATRIZ DE RISCOS'!$O$58:$Q$62,3,1),"Avaliar por julgameto"),"1"))
M47: =_xlfn.XLOOKUP(D47,'BASE DE PONTOS V+'!C:C,'BASE DE PONTOS V+'!L:L) -> 0 | N47: =IF(B47="","",IFERROR(IF(I47="Financeiro",VLOOKUP(G47,'BASE DA MATRIZ DE RISCOS'!$O$58:$Q$62,3,1),"Avaliar por julgameto"),"1"))
M48: =_xlfn.XLOOKUP(D48,'BASE DE PONTOS V+'!C:C,'BASE DE PONTOS V+'!L:L) -> 0 | N48: =IF(B48="","",IFERROR(IF(I48="Financeiro",VLOOKUP(G48,'BASE DA MATRIZ DE RISCOS'!$O$58:$Q$62,3,1),"Avaliar por julgameto"),"1"))
M49: =_xlfn.XLOOKUP(D49,'BASE DE PONTOS V+'!C:C,'BASE DE PONTOS V+'!L:L) -> 0 | N49: =IF(B49="","",IFERROR(IF(I49="Financeiro",VLOOKUP(G49,'BASE DA MATRIZ DE RISCOS'!$O$58:$Q$62,3,1),"Avaliar por julgameto"),"1"))

Sheet Planilha1
B2: Ponto de Controle | C2: Título | D2: Tipo | E2: Tipo | F2: Probabilidade | G2: Perdas/ | H2: Exposição | I2: Setor | J2: Classificação por Pontuação
G3: Impacto
B4: [P1] | C4: Pagamento sem documento fiscal | D4: Legal | E4: 3 | F4: 4 | G4: 2 | H4: 24 | I4: Voucher documental | J4: BAIXO IMPACTO
B5: [P2] | C5: Pagamentos realizados sem os respectivos comprovantes de pagamento anexados | D5: Financeiro | E5: 5 | F5: 3 | G5: 1 | H5: 15 | I5: Voucher documental | J5: BAIXO IMPACTO
B6: [P3] | C6: Negligência na gestão dos Documentos que compõe os Demonstrativos | D6: Operacional | E6: 4 | F6: 3 | G6: 1 | H6: 12 | I6: Voucher documental | J6: BAIXO IMPACTO
B7: [P4] | C7: Conjunto de documentos anexados fora do mês correspondente no Balancete. | D7: Operacional | E7: 4 | F7: 1 | G7: 1 | H7: 4 | I7: Voucher documental | J7: BAIXO IMPACTO
B8: [P5] | C8: Informações apresentado fora do mês correspondente na demonstração financeira. | D8: Financeiro | E8: 5 | F8: 1 | G8: 1 | H8: 5 | I8: Voucher documental | J8: BAIXO IMPACTO
B9: [P6] | C9: Diferenças entre: Valor do comprovante de pagamento X Valor da documentação suporte. | D9: Financeiro | E9: 5 | F9: 3 | G9: 1 | H9: 15 | I9: Voucher documental | J9: BAIXO IMPACTO
B10: [P7] | C10: Pagamento realizado após data de vencimento com incidência de multa e juros. | D10: Financeiro | E10: 5 | F10: 2 | G10: 1 | H10: 10 | I10: Voucher documental | J10: BAIXO IMPACTO
B11: [P8] | C11: Pagamentos realizados antes da emissão da nota fiscal. | D11: Legal | E11: 3 | F11: 3 | G11: 1 | H11: 9 | I11: Voucher documental | J11: BAIXO IMPACTO
B12: [P9] | C12: Emissão de nota de simples remessa após o pagamento do produto. | D12: Financeiro | E12: 5 | F12: 1 | G12: 1 | H12: 5 | I12: Voucher documental | J12: BAIXO IMPACTO
B13: [P10] | C13: Os balancetes sem aprovação dos conselheiros fiscais e do síndico no termo de aprovação. | D13: Legal | E13: 3 | F13: 5 | G13: 4 | H13: 60 | I13: Resumo Convenção | J13: MÉDIO IMPACTO
B14: [P11] | C14: Falta de registro de Ata's em cartório | D14: Legal | E14: 3 | F14: 5 | G14: 4 | H14: 60 | I14: Resumo Convenção | J14: MÉDIO IMPACTO
B15: [P12] | C15: Falta relatório de auditoria do período anterior. | D15: Estratégico | E15: 4 | F15: 5 | G15: 4 | H15: 80 | I15: Follow Up CCI | J15: ALTO IMPACTO
... B34: [P31] | C34: Impacto significativo com os inadimplentes | D34: Financeiro | E34: 5 | F34: 5 | G34: 5 | H34: 125 | I34: Teste de Inadimplência | J34: ALTO IMPACTO

Sheet BASE DE PONTOS V+
B2: Condomínio Reserva das Plantas
B3: BASE DE PONTOS V+
B4: Data base:
B6: 2 | C6: 2 | H6: 7 | I6: 8 | J6: 8 | K6: 8 | M6: 8
B7: V+ | C7: Descrição Resumida | D7: Descrição | E7: Impacto Financeiro | F7: Riscos e Impactos | G7: Recomendação | H7: Tipo | I7: Tipo de Teste | J7: Julgamento | K7: Tipo de Teste | L7: x | M7: Tipo de Teste
B8: V01 | C8: Pagamento sem documento fiscal | D8: Verificamos que ocorreram gastos sem a respectiva emissão de documento fiscal pelos fornecedores e/ou prestadores de serviços. | E8: 17679.82 | F8: Pagamentos sem os respectivos documentos fiscais dos fornecedores/prestadores de serviços não são permitidos pela legislação brasileira, assim como Convenção e Regimento Interno do Condomínio. Dessa forma, o mesmo pode ser multado e/ou sofrer outras penalidades impostas pelo fisco. | G8: Sugerimos que seja solicitado aos respectivos fornecedores/ prestadores de serviços a nota fiscal pelo fornecimento de material ou de prestação de serviço. | H8: Legal | I8: 6 - 01.1.6 - CRP - Voucher documental - 01.03.2021 a 28.02.2022 | J8: Alto Impacto | L8: • 08/11/2022 • Novo ■ Vorcon Auditoria & Consultoria
B9: V02 | C9: Pagamentos realizados sem os respectivos comprovantes de pagamento anexados | D9: Constatamos que alguns pagamentos foram realizados sem que fossem anexados os respectivos comprovantes de pagamentos ou documentos equivalentes dando a respectiva quitação. | E9: 1558.24 | F9: Possibilidade de pagamento duplicado dos valores, ou caso haja a solicitação dos comprovantes de pagamentos o Condomínio não os possua. | G9: Sugerimos que sejam criados controles para que os comprovantes de pagamentos estejam anexados com seus respectivos documentos. | H9: Financeiro | I9: 6 - 01.1.6 - CRP - Voucher documental - 01.03.2021 a 28.02.2022 | J9: Baixo Impacto | L9: • 08/11/2022 • Novo ■ Vorcon Auditoria & Consultoria
B10: V03 | C10: Negligência na gestão dos Documentos que compõe os Demonstrativos | D10: Verificamos que alguns comprovantes não estão sendo arquivados com os cuidados necessários, com isso alguns estão ilegíveis. | E10: 118.82 | F10: Possível dificuldade e/ou impossibilidade na visualização dos gastos e dúvidas quanto a possíveis consultas no futuro em função do estado dos documentos. | G10: Sugerimos aperfeiçoamento dos controles internos para que no momento do recebimento das documentações sejam retiradas as cópias ou ocorram as digitalizações visando preservar as informações. | H10: Operacional | I10: 6 - 01.1.6 - CRP - Voucher documental - 01.03.2021 a 28.02.2022 | J10: Baixo Impacto | L10: • 08/11/2022 • Novo ■ Vorcon Auditoria & Consultoria
B11: V04 | C11: Conjunto de documentos anexados fora do mês correspondente no Balancete. | D11: Desorganização da documentação suporte dificultam a análise de todas as partes envolvidas. | E11: 418.07 | F11: A ausência de apresentação de forma tempestiva dos documentos financeiros poderá afetar diretamente o fluxo de caixa e o controle do financeiro do condomínio. | G11: Recomendamos que a prestação de contas seja realizada conforme o período correspondente as despesas. | H11: Operacional | I11: 6 - 01.1.6 - CRP - Voucher documental - 01.03.2021 a 28.02.2022 | J11: Baixo Impacto | L11: • 08/11/2022 • Novo ■ Vorcon Auditoria & Consultoria
B12: V05 | C12: Informações apresentado fora do mês correspondente na demonstração financeira. | D12: Verificamos que há desorganização das informações na demonstração financeira que dificultam na análise de todas as partes envolvidas. | E12: 418.07 | F12: A falta de apresentação de maneira tempestiva das informações financeiras poderá afetar diretamente o controle financeiro do condomínio e o entendimento dos Demonstrativos. | G12: Indicamos que as informações apresentadas nas Demonstrações Financeiras sejam realizadas conforme o período correspondente. | H12: Financeiro | I12: 6 - 01.1.6 - CRP - Voucher documental - 01.03.2021 a 28.02.2022 | J12: Baixo Impacto | L12: • 08/11/2022 • Novo ■ Vorcon Auditoria & Consultoria
B13: V06 | C13: Diferenças entre: Valor do comprovante de pagamento X Valor da documentação suporte. | D13: Identificamos que há diferença entre os valores apresentados não sendo justificados por parcelamentos ou multas. | E13: De - R$ 1.062,75 até R$ 3.750,00 | F13: Possíveis pagamentos realizados com valores incorretos podendo gerar prejuízos financeiros ao condomínio. | G13: Sugerimos que os pagamentos sejam realizados com os valores que constam no documento auxiliar. | H13: Financeiro | I13: 6 - 01.1.6 - CRP - Voucher documental - 01.03.2021 a 28.02.2022 | J13: Baixo Impacto | L13: • 08/11/2022 • Novo ■ Vorcon Auditoria & Consultoria
B14: V07 | C14: Pagamento realizado após data de vencimento com incidência de multa e juros. | D14: Verificamos que alguns pagamentos foram realizados após a data de vencimento acarretando em gastos adicionais. | E14: 10.37 | F14: Possibilidade do condomínio incorrer em gastos desnecessários | G14: Sugerimos que seja elaborado um controle de vencimento das despesas e que sejam efetuados os pagamentos até o vencimento. | H14: Financeiro | I14: 6 - 01.1.6 - CRP - Voucher documental - 01.03.2021 a 28.02.2022 | J14: Baixo Impacto | L14: • 08/11/2022 • Novo ■ Vorcon Auditoria & Consultoria
B15: V08 | C15: Pagamentos realizados antes da emissão da nota fiscal. | D15: Verificamos que ocorreram pagamentos onde a emissão da documentação fiscal é posterior a data em que a transação bancária foi realizada. | E15: 3563.16 | F15: O pagamento antes da emissão das notas fiscais traz uma vulnerabilidade a respeito do cumprimento das melhores práticas de gestão podendo gerar penalidades tributárias. | G15: Recomendamos que seja verificada a emissão da nota fiscal antes da realização do pagamento. | H15: Legal | I15: 6 - 01.1.6 - CRP - Voucher documental - 01.03.2021 a 28.02.2022 | J15: médio impacto | L15: • 08/11/2022 • Novo ■ Vorcon Auditoria & Consultoria
B16: V09 | C16: Emissão de nota de simples remessa após o pagamento do produto. | D16: Identificamos que foi emitida uma nota de simples remessa para produto pago através de outra nota fiscal | E16: 42.4 | F16: A emissão da nota fiscal de simples remessa após o pagamento do produto realizado através de outra nota poderá indicar falha operacional e causar prejuízos financeiros ao condomínio. | G16: Indicamos a Administração que promova melhoria dos controles internos visando mitigar falhas operacionais e possíveis prejuizos financeiros à entidade. | H16: Financeiro | I16: 6 - 01.1.6 - CRP - Voucher documental - 01.03.2021 a 28.02.2022 | J16: Baixo Impacto | L16: • 08/11/2022 • Novo ■ Vorcon Auditoria & Consultoria
B17: V10 | C17: Os balancetes sem aprovação dos conselheiros fiscais e do síndico no termo de aprovação. | D17: No período de 03/2021 a 02/2022 não constam as assinaturas do síndico e dos conselheiros fiscais para aprovação dos balancetes. Porém, conforme a Convenção do Subcondomínio Reserva das Plantas na cláusula 4.9.1 - f) "O Síndico de cada Subcondomínio tem as seguintes atribuições [...] rubrica[...] dos livros". Além disso, no item G-4.21-c) "Cada Conselho Fiscal [...] terá as seguintes atribuições: emitir parecer sobre as contas [...] do Síndico do Subcondomínio Residencial [...], conferindo-as, aprovando-as ou rejeitando-as". | E17: NA | F17: A falta das assinaturas dos conselheiros fiscais nos termos de aprovação dos balancetes indica que as contas do condomínio não foram submetidas ao exame, podendo acarretar a redução do nível de confiança dos demonstrativos e prejudicar a leitura dos usuários. | G17: Sugerimos que os conselheiros fiscais realizem o exame dos balancetes e caso ocorra a aprovação dos mesmos, confirmem com as suas assinaturas nos termos de aprovação. Mesmo com as demonstrações financeiras sendo auditadas mensalmente, é necessário a validação do conselho fiscal. | H17: Legal | I17: 9 - 01.1.9 - CRP - Resumo Convenção - 01.03.2021 a 28.02.2022 | J17: Alto Impacto | L17: • 08/11/2022 • Novo ■ Vorcon Auditoria & Consultoria
B18: V11 | C18: Falta de registro de Ata's em cartório | D18: Não identificamos o registro em cartório das Ata's: 16/12/2021, 09/09/2021, 14/10/2021, 27/01/2022, 03/02/2022. Conforme a Convenção do Subcondomínio Reserva das Plantas na cláusula 4.9.1 - f) "O Síndico de cada Subcondomínio tem as seguintes atribuições [...] Providenciar abertura, numeração, rubrica e encerramento dos livros, bem como o registro das atas em Cartório de Registro de Títulos e Documentos". | E18: NA | F18: Possível questionamento dos Condominos quanto a validação das Ata's por falta de registo no cartório. | G18: Sugerimos que haja registro das Ata's em cartório, conforme convenção. | H18: Legal | I18: 9 - 01.1.9 - CRP - Resumo Convenção - 01.03.2021 a 28.02.2022 | J18: médio impacto | L18: • 08/11/2022 • Novo ■ Vorcon Auditoria & Consultoria
B19: V12 | C19: Falta relatório de auditoria do período anterior. | D19: Conforme a Convenção do Subcondomínio Reserva das Plantas na cláusula 4.9.1 - h) "O Síndico de cada Subcondomínio tem as seguintes atribuições [...] Contratar, anualmente, empresa de auditoria para fiscalizar as contas do Subcondomínio." Dessa forma, não foi identificado o relatório da auditoria do período que antecedeu a auditoria atual (03/2021 a 02/2022). No entanto, analisamos conforme entendimento com o cliente que o condomínio realizou a auditoria em 2021 e não receberam o relatório. | E19: NA | F19: A ausência de contratação da auditoria e apresentação do relatório em relação ao período anterior, além de infringir a convenção condomonial, prejudica a transparência na prestação de contas podendo causar danos a situação financeira, econômica, legal e imagem da entidade. | G19: Recomendamos que a administração sempre realize auditorias preventivas. | H19: Estratégico | I19: 5 - 01.1.5 - CRP - Follow Up CCI - 01.03.2021 a 28.02.2022 | J19: Alto Impacto | L19: • 08/11/2022 • Novo ■ Vorcon Auditoria & Consultoria
B20: V13 | C20: Falta de Planejamento Orçamentário Anual | D20: Conforme a Convenção do Subcondomínio Reserva das Plantas na cláusula 4.36.1 "A assembleia geral ordinária do Condomínio realizar-se-á anualmente [...] outra assembleia geral ordinária do CONDOMÍNIO [Sic], sempre até o final do mês de novembro de cada ano e a ela competirá especificamente fixar o orçamento anual do CONDOMÍNIO para o exercicio social vindouro e a forma de cobrança das respectivas despesas." Dessa forma, não foi identificado o Planejamento Orçamentário para o ano de 2021. Além disso, identificamos nas Atas que o Sr. Marco Ribeiro, demonstrou as prinipais causas do aumento das despesas e informou que o condomíno está lidando com o mesmo planejamento orçamentário há 03 anos e que com a pandemia, todos os produtos e serviços tem sofrido aumentos fora do comum. | E20: NA | F20: A falta da elaboração do planejamento orçamentário poderá prejudicar o controle das contas condominiais e a prevenção dos gastos desnecerrários ou demasiados. | G20: Recomendamos que o o planejamento orçamentário ocorra dentro do período previsto em convenção. | H20: Estratégico | I20: 22 - 01.1.22 - CRP - Orçado X Realizado - 01.03.2021 a 28.02.2022 | J20: Alto Impacto | L20: • 08/11/2022 • Novo ■ Vorcon Auditoria & Consultoria
B21: V14 | C21: Sistema de medição da água realizado de forma não individualizada | D21: Segundo a ATA Reunião de Moradores do dia 09/09/2021 o "Sr. Roque Andrade entrou na tratativa da individualização da água e falou sobre os benefícios que isso traria por conta do consumo desigual entre as unidades [...]". Dessa forma, identificamos que o sistema de medição da água não é realizado de forma individualizada, infringindo assim, a cláusula 15.1 - e) da Convenção Condominial. | E21: NA | F21: A infração em relação a item previsto na Convenção Condominial pode gerar questionamentos, reclamações, impactos em relação a sustentabilidade e prejuizos de ordem legal para o condominio. | G21: Recomendamos que a administração analise a viabilidade da individualização de medição da água junto aos condominos e profissionais técnicos. Após isso, se for viável planeje a implementação e caso contrário, atualize a convenção para modificar a previsão desse item. | H21: Legal | I21: 9 - 01.1.9 - CRP - Resumo Convenção - 01.03.2021 a 28.02.2022 | J21: médio impacto | L21: • 08/11/2022 • Novo ■ Vorcon Auditoria & Consultoria
B22: V15 | C22: Valor apresentado no comprovante de pagamento mas que não consta no extrato bancário | D22: Identificamos comprovante de pagamento do dia 19/10/2021 informando que foi realizado o pagamento no valor de R$ 1000,00 através da Agência: 4306 e Conta: 130035030. No entanto, essas informações não constam no extrato bancário dessa respectiva conta. | E22: 1000 | F22: A divergência de informações entre comprovante de pagamento e o extrato bancário pode indicar erro ou fraude na gestão financeira condominial e impactar nas disponibilidades da entidade. | G22: Indicamos que a Administração promova melhorias em seus controles interno tendo como finalidade a apresentação de informações financeiras convergentes com os registros expostos nos extratos bancários. | H22: Financeiro | I22: 20 - 01.1.20 - CRP - Demonstrativo Financeiro + voucher nos extratos - 01.03.2021 a 28.02.2022 | J22: Baixo Impacto | L22: • 08/11/2022 • Novo ■ Vorcon Auditoria & Consultoria
B23: V16 | C23: Falta de apresentação de extratos bancários | D23: Verificamos que em alguns meses não foram apresentados à auditoria os extratos do Banco Santander, agência: 4306 e contas: 13.003502-3 / 13.003496-7, além das aplicações financeiras. | E23: NA | F23: A falta dos extratos bancários prejudica a análise das informações, o entendimento e a validação das entradas e saídas financeiras do condomínio. | G23: Visando aumentar a transparência na prestação de contas do condomínio, sugerimos à Administração que envie os extratos bancários emitidos diretamente pelas instituições financeiras para que as análises dessas informações se tornem possíveis. | H23: Financeiro | I23: 20 - 01.1.20 - CRP - Demonstrativo Financeiro + voucher nos extratos - 01.03.2021 a 28.02.2022 | J23: Baixo Impacto | L23: • 08/11/2022 • Novo ■ Vorcon Auditoria & Consultoria
B24: V17 | C24: Saídas nos extratos não validados com a voucher | D24: Identificamos no momento do confronto entre os extratos bancários e a Voucher Documental produzida com as informações apresentadas pelo condomínio, a existência de saídas de recursos dos extratos que não constam na Voucher. Diante disso, não ocorre a verificação dos documentos comprobatórios dos respectivos dispêndios realizados pelo condomínio | E24: 2117.99 | F24: As saídas de recursos dos extratos sem a validação da Voucher Documental poderão prejudicar a transparência e afetar a prestação de contas, dando oportunidade de os valores não serem utilizados para fins que geram benefícios econômicos ao condomínio. | G24: Indicamos ao Conselho Fiscal a estruturação de procedimentos de controles internos que garantam destinação adequada dos recursos condominiais sendo apresentados todos os documentos comprobatórios da realização de suas despesas e validados por uma auditoria contínua. | H24: Financeiro | I24: 20 - 01.1.20 - CRP - Demonstrativo Financeiro + voucher nos extratos - 01.03.2021 a 28.02.2022 | J24: Baixo Impacto | L24: • 08/11/2022 • Novo ■ Vorcon Auditoria & Consultoria
B25: V18 | C25: Apresentação incompleta de extrato bancário | D25: Recebemos o extrato do Banco Santander, agência: 4306 e conta: 13.003503-0 referente ao mês 02/2022 de forma incompleta, impossibilitando assim, a conferência de todas as suas informações. | E25: NA | F25: A entrega de extrato realizada de forma incompleta impede a análise, o entendimento e a validação das entradas e saídas financeiras, reduzindo assim, a transparência nas prestação de contas do condomínio. | G25: Recomendamos à Administração que envie os extratos bancários emitidos diretamente pelas instituições financeiras contemplando todas as informações do período solicitado. | H25: Financeiro | I25: 20 - 01.1.20 - CRP - Demonstrativo Financeiro + voucher nos extratos - 01.03.2021 a 28.02.2022 | J25: Baixo Impacto | L25: • 08/11/2022 • Novo ■ Vorcon Auditoria & Consultoria
B26: V19 | C26: Diferenças entre os saldos dos Demonstrativos Financeiros de Receitas e Despesas em relação a Demonstração dos Saldos Financeiros. | D26: Verificamos os saldos finais dos demonstrativos financeiros de receitas e despesas (DF) e confrontamos com os valores finais dos demonstrativos dos saldos financeiros (DSF), nos quais foram identificadas divergências. | E26: 109 | F26: A apresentação dos saldos divergentes nos demonstrativos financeiros de receita e despesas, poderá prejudicar a transparência e afetar a prestação de contas comprometendo a interpretação dos usuários das informações financeiras do condomínio. | G26: Recomendamos que os demonstrativos dos saldos financeiros assim como os demonstrativo de receita e despesas sejam revisados para reduzir os riscos de divergências. | H26: Financeiro | I26: 21 - 01.1.21 - CRP - Conciliação Bancária + Elaboração dos quadros dos Demonstrativos Financeiros - 01.03.2021 a 28.02.2022 | J26: Baixo Impacto | L26: • 08/11/2022 • Novo ■ Vorcon Auditoria & Consultoria
B27: V20 | C27: Ausência de apresentação de mapa de cotação | D27: Verificamos que algumas compras realizadas não estavam sendo efetuado o mapa de cotação. | E27: NA | F27: A falta da cotação mínima de 3 orçamentos poderá prejudicar o condomínio através de aquisições de bens e/ou serviços de baixa qualidade, com fornecedores sem conhecimento ou respaldo técnico e entregas diferente do escopo esperado. | G27: Recomendamos a administração que seja realizado mapa de orçamento no mínimo de 3 cotações para as aquisições dos bens ou serviços do condomínio. | H27: Operacional | I27: 6 - 01.1.6 - CRP - Voucher documental - 01.03.2021 a 28.02.2022 | J27: Baixo Impacto | L27: • 08/11/2022 • Novo ■ Vorcon Auditoria & Consultoria
B28: V21 | C28: Ausência de inventário dos ativos imobilizados | D28: Não identificamos o controle patrimonial dos ativos imobilizados para atualização do saldo em decorrência dos bens adquiridos, obsoletos e/ou perdidos para realização da baixa, assim como as depreciações. | E28: NA | F28: A ausência do controle patrimonial do condomínio poderá impactar em possíveis perdas ou desvios do ativo imobilizado. | G28: Sugerimos que à Administração do condomínio busque realizar o inventário dos ativos imobilizados anualmente. | H28: Financeiro | I28: 38 - 01.1.37 - CRP - Inspeção estatística dos itens do Imobilizado ( Itens individualmente significantes) - 01.03.2021 a 28.02.2022 | J28: Alto Impacto | L28: • 08/11/2022 • Novo ■ Vorcon Auditoria & Consultoria
B29: V22 | C29: Inexistência de valor estimado dos honorarios advocatícios | D29: Não identificamos o valor estimado da expectativa de exito nos casos de processos onde o condomínio esteja como polo ativo ou passivo para período de 03/2021 até 02/2022 | E29: N/A | H29: Financeiro | J29: médio impacto | L29: • 08/11/2022 • Novo ■ Vorcon Auditoria & Consultoria
B30: V23 | C30: Perda Possível de Causa Judicial | D30: Identificamos no período de 28 de fevereiro 2022 a perda possível de R$ 406.946,20. Salientamos que a Perda Possível é aquela que o condomínio tem ou não uma obrigação presente legal como resultado de evento passado que haverá uma saída de recursos para liquidar essa obrigação. | E30: 396946.2 | H30: Legal | J30: Alto Impacto | L30: • 08/11/2022 • Novo ■ Vorcon Auditoria & Consultoria
B31: V24 | C31: Perda Provável de Causa Judicial | D31: Identificamos no período de 28 de fevereiro 2022, uma perda provável de R$ 32.000,00 referente ao processo de FELIPE FERREIRA OLIVEIRA X SUBCONDOMÍNIO RESERVA DAS PLANTAS, tendo como objeto AÇÃO DECLARATÓRIA E INDENIZATÓRIA. Salientamos que a perda provável é quando o condomínio tem uma obrigação presente legal como resultado de evento passado e seja provável que será necessária a saída de recurso para liquidar a obrigação. Nesse sentido, a perda da causa judicial é mais provável que sim do que não. | E31: 32000 | G31: Recomendamos que seja realizado uma Provisão para Perda .... | H31: Financeiro | J31: médio impacto | L31: • 08/11/2022 • Novo ■ Vorcon Auditoria & Consultoria
B32: V25 | C32: Perda Remota de Causa Judicial | D32: Identificamos no período de 28 de fevereiro 2022, uma perda Remota de R$ 1.503.630,42. Salientamos que a perda remota é quando o condomínio não tem uma obrigação presente legal como resultado de evento passado e seja remoto que haverá uma saída de recurso para liquidar essa obrigação. Nesse sentido, a perda da causa judicial é menos provável que sim do que não. | E32: 1503630.4 | H32: Legal | J32: médio impacto | L32: • 08/11/2022 • Novo ■ Vorcon Auditoria & Consultoria
B33: V26 | C33: Ausência de registro do Regimento do condomínio em cartório. | D33: Não foi possível validar a data do registro do condomínio no cartório a partir do documento recebido. | E33: NA | F33: A falta de registro em cartório do Regimento do Condomínio poderá gerar problemas relacionados a validade jurídica da documentação. | G33: Sugerimos que o Regimento seja registrado em cartório. | H33: Legal | J33: Baixo Impacto | L33: • 08/11/2022 • Novo ■ Vorcon Auditoria & Consultoria
B34: V27 | C34: Impossíbilidade de identificação da conclusão da Obra do Parquinho e seu pagamento. | D34: Analisamos as Atas e os demonstrativos financeiros e identificamos a obra do parquinho pela empresa Danielson Alcantra Contruções e Reformas de 16/11/2021. Porém, não identificamos a ATA com informação de prestação de serviço concluída, como também, não localizamos o pagamento referente a terceira parcela do serviço prestado. | E34: N/A | H34: Operacional | J34: Baixo Impacto | L34: • 08/11/2022 • Novo ■ Vorcon Auditoria & Consultoria
B35: V28 | C35: Falta de questionamentos do Conselho Fiscal nas Assembleias | D35: Analisamos 100% das atas de reuniões, Assembleia Geral Extraordinária (AGE), Assembleia Geral Ordinária (AGO), Conselho de Administração, Conselho Fiscal e outras atas de reuniões formalizadas do período de de 01/03/2021 a 28/02/2022 e não identificamos a fala do conselho fiscal. Inclusive, foi mencionado na AGE 28/10/2021 que o Conselho Consultivo foi o único a realizar a seleção para a eleição do síndico duas vezes sem a participação do Conselho Fiscal. | E35: N/A | H35: Legal | J35: Alto Impacto | L35: • 08/11/2022 • Novo ■ Vorcon Auditoria & Consultoria
B36: V29 | C36: Cargo de Síndico Interino e de Conselheiro Fiscal ocupado pelo mesmo condômino | D36: Conforme a Convenção do Subcondomínio Reserva das Plantas na item G - 4.21 c) "Cada Conselho Fiscal [...] terá as seguintes atribuições: emitir parecer sobre as contas [...] do Síndico do Subcondomínio Residencial [...], conferindo-as, aprovando-as ou rejeitando-as" e também o segundo o Código Civil no Art. 1.356 "Poderá haver no condomínio um conselho fiscal [...]ao qual compete dar parecer sobre as contas do síndico". Dessa forma, analisamos 100% das atas e identificamos na AGE de 28/10/2021 que o Sr. Roque da Silva Pereira Andrade do Prédio Vitórioa Régia, 907 ocupa os cargos de Síndico Interino e Conselheiro fiscal ao mesmo tempo. | E36: N/A | F36: Os dois cargos ocupado pelo condômino Sr. Roque da Silva ao mesmo tempo, pode afetar a independência do Conselho Fiscal em relação aos atos do Síndico Interino, influenciando o julgamento profissional do conselho e permitindo que o mesmo não atue com integridade, objetividade e ceticismo conforme NBC PA 400. | G36: Recomendamos que a Administração do Condomínio promova melhorias nos seus controles internos e que não seja permitido que uma mesma pessoa ocupa os cargos de Síndico e Conselheiros simultaneamente. | H36: Estratégico | J36: Alto Impacto | L36: • 08/11/2022 • Novo ■ Vorcon Auditoria & Consultoria
B37: V30 | C37: Inexistência da ATA do Conselho Consultivo na Assembleia Geral Extraordinária | D37: Conforme a Convenção do Subcondomínio Reserva das Plantas o síndico necessita obrigatoriamente ter a relação de todas as atas bem como o seu registro. Dessa forma, analisamos 100% das atas e identificamos na AGE de 28/10/2021 que conforme o síndico e o Gerente a ATA de Reunião do Conselho Consultivo não existia na Administradora no dia da Assembleia Geral Extraordinária. Assim, a ata não foi apresentada para o Advogado e por essa razão, o processo discutido pelo Conselho consultivo ficou nulo para a Assembleia Geral Extraordinária. | E37: N/A | H37: Legal | J37: médio impacto | L37: • 08/11/2022 • Novo ■ Vorcon Auditoria & Consultoria
B38: V31 | C38: Inadimplencia | D38: Mês 02/2022 | E38: 598391.24 | H38: Financeiro | J38: Alto Impacto | L38: • 08/11/2022 • Novo ■ Vorcon Auditoria & Consultoria

Sheet Matriz de Risco
B6: BASE DA MATRIZ
B7: [P01] | C7: Não foi estabelecida a confiança nos controles que estão implementados no Condomínio Le Parc Residential Resort. | D7: Alto Impacto | E7: Operação Administrativa do Condomínio
B8: [P02] | C8: Ausência de manual de normas e procedimentos | D8: Alto Impacto | E8: Manual de normas e procedimentos
B9: [P03] | C9: Diferenças entre: Favorecido do documento X Beneficiário do pagamento | D9: Alto Impacto | E9: Inspeção Documental - Gastos
B10: [P04] | C10: Pagamentos realizados sem os respectivos comprovantes de pagamento anexados | D10: Alto Impacto | E10: Inspeção Documental - Gastos
B11: [P05] | C11: Diferenças entre: Valor do comprovante de pagamento X Valor da documentação suporte. | D11: Alto Impacto | E11: Inspeção Documental - Gastos
B12: [P06] | C12: Inexistência de rotina de inventário físico do ativo imobilizado. | D12: Alto Impacto | E12: Imobilizado
B13: [P07] | C13: Definição de vida útil do ativo imobilizado | D13: Médio Impacto | E13: Imobilizado
B14: [P08] | C14: Páginas não numeradas ou numeradas de forma incorreta. | D14: Baixo Impacto | E14: Controle Interno
B15: [P09] | C15: Registro da Convenção do Condomínio Le Parc Residential Resort em cartório. | D15: Alto Impacto | E15: Convenção
B16: [P10] | C16: Registro do Regimento do Condomínio Le Parc Residential Resort em cartório. | D16: Alto Impacto | E16: Regimento do Condomínio
B17: [P11] | C17: Não há classificação de expectativa de ganho para algumas causas ativas e de perda para as passivas. | D17: Baixo Impacto | E17: Contingências
B18: [P12] | C18: Inexistência de padronização dos relatórios mensais de contingência | D18: Médio Impacto | E18: Contingências
B19: [P13] | C19: Relatório de encaminhamento aos órgãos de proteção ao crédito. | D19: Médio Impacto | E19: Contingências

Sheet RESUMO DE PONTOS Original
F3: Avaliação da soma das NFs Identificadas | I3: Leilane ajustar | J3: JULGAMENTO PROFISSIONAL | L3: Utilizar essa estrutura no Status
B4: 1 | C4: 2 | D4: 3 | E4: 4 | F4: 5 | G4: 6 | H4: 7 | I4: 8 | J4: 9 | K4: Status | L4: Estrutura
B5: Ponto | C5: Descrição Resumida | D5: Descrição do Ponto | E5: Riscos e Implicações | F5: Impacto Financeiro | G5: Recomendações | H5: Tipo | I5: Tipo de Teste
B6: [P1] | C6: Pagamento sem nota fiscal | D6: Verificamos que ocorreram gastos sem a respectiva emissão de nota fiscal pelos fornecedores e prestadores de serviços. | E6: Pagamento sem os respectivos Fornecedores/ Prestadores de serviços não é permitido pela legislação brasileira assim como Convenção e Regimento Interno do Condomínio. | F6: N/A | G6: Sugerimos que seja solicitado aos respectivos Fornecedores/ Prestadores de serviços ou fornecedores a nota fiscal pelo fornecimento de material ou de prestação de serviços. | H6: Estratégico | I6: Operação Administrativa do Condomínio | J6: MÉDIO IMPACTO | K6: • 31/12/2020 • Recorrente ■ Vorcon Auditoria & Consultoria ■ 22 de abril de 2021 | L6: • [Data base do relatório] • Ponto Novo ou Recorrente??? ■ Empresa que Identificou o Ponto ■ 22 de abril de 2021 [Data do relatório]
B7: [P2] | C7: Diferenças entre: Favorecido do documento X Beneficiário do pagamento | D7: O fornecedor apresentado no comprovante de pagamento não é o mesmo da Nota Fiscal. | E7: Pagamento sem as respectivas notas fiscais não é permitido pela legislação brasileira assim como Convenção e Regimento Interno do Condomínio. | F7: N/A | G7: Sugerimos que seja solicitado aos respectivos prestadores de serviço ou fornecedores a nota fiscal pelo fornecimento de material ou de prestação de serviços. | H7: Operacional | I7: Manual de normas e procedimentos | J7: BAIXO IMPACTO | K7: • 31/12/2020 ■ Vorcon Auditoria & Consultoria ■ 22 de abril de 2021
B8: [P3] | C8: Pagamentos realizados sem os respectivos comprovantes de pagamento anexados | D8: Verificamos que alguns pagamentos foram realizados sem que fossem anexados os respectivos comprovantes de pagamentos ou documentos equivalentes dando a respectiva quitação. | E8: Pagamento duplicado dos valores, ou caso haja a solicitação do comprovante de pagamento o Condomínio não os possua. | F8: N/A | G8: Sugerimos que sejam criados processos para que os comprovantes de pagamentos estejam anexados ao processo de pagamentos. | H8: Operacional | I8: Inspeção Documental - Gastos | J8: ALTO IMPACTO | K8: • 31/12/2020 ■ Vorcon Auditoria & Consultoria ■ 22 de abril de 2021
B9: [P4] | C9: Pagamento de impostos sem identificação do prestador de serviços | D9: Não identificamos documentação suporte que indique a origem dos impostos e os respectivos prestadores de serviço. | E9: Possíveis pagamentos duplicado dos valores, ou caso haja a solicitação do comprovante de pagamento o Condomínio não os possua | F9: N/A | G9: Sugerimos que sejam criados processos para que todos os documentos estejam anexados ao processo de prestação de contas no demonstrativo financeiros. | H9: Operacional | I9: Inspeção Documental - Receitas | J9: MÉDIO IMPACTO | K9: • 31/12/2020 ■ Vorcon Auditoria & Consultoria ■ 22 de abril de 2021
B10: [P5] | C10: Conjunto de documentos sem apresentação de mapa de orçamentos. | D10: Verificamos que muitas das compras realizadas não estavam anexados os mapas de orçamento. | E10: Agindo dessa forma, não estão em conformidade com as normas do estatuto vigente do condomínio. | F10: N/A | G10: Seja realizada a conferência na pré-compra, se estão observando as normas do mapa do orçamento | H10: Estratégico | I10: Imobilizado | J10: BAIXO IMPACTO | K10: • 31/12/2020 ■ Vorcon Auditoria & Consultoria ■ 22 de abril de 2021
B11: [P6] | C11: Inexistência de tempestividade na prestação de contas do fundo fixo | D11: Verificamos que o fundo fixo do Condomínio, por diversas vezes, possui valores retirados onde existe a prestação de contas nos meses não referentes. | E11: Não sendo apresentadas tempestivamentes as apresentações das contas do fundo fixo, afetará diretamente o fluxo de caixa e o controle do fundo fixo do condomínio. | F11: N/A | G11: Seja elaborada uma periodicidade fixa para apresentação das contas do fundo fixo, e que seja realizado as prestações dos períodos correspondentes as despesas. | H11: Operacional | I11: Controle Interno | J11: ALTO IMPACTO | K11: • 31/12/2020 ■ Vorcon Auditoria & Consultoria ■ 22 de abril de 2021
B12: [P7] | C12: Inconsistência na apresentação da atividade da empresa | D12: O serviço/produto adquirido não condiz com a atividade econômica apresentada no CNPJ da empresa. | E12: Afeta diretamente nos cálculos de retenções de impostos do condomínio, se a empresa prestadora de serviço siga a legislação que não à apresentada. | F12: N/A | G12: Criação de um passo a passo na empresa contratada na intenção de verificar a sua atividade perante a forma de tributação. | H12: Estratégico | I12: Regimento | J12: MÉDIO IMPACTO | K12: • 31/12/2020 ■ Vorcon Auditoria & Consultoria ■ 22 de abril de 2021
B13: [P8] | C13: Negligência na gestão dos Documentos que compõe os Demonstrativos | D13: Verificamos que alguns comprovantes não estão sendo arquivados com os cuidados necessários, com isso alguns estão ilegíveis. | E13: Dificuldade na visualização dos gastos e impossibilidade e dúvidas quanto a possíveis consultas no futuro em função do estado dos documentos. | F13: N/A | G13: Sugerimos que sejam criados processos para que os comprovantes sejam de responsabilidade de quem incorre no gasto sendo de responsabilidade do financeiro tirar cópia dos comprovantes ou digitaliza-los assim que os receber. | H13: Operacional | I13: 02.1.2 STC - Voucher documental | J13: BAIXO IMPACTO | K13: • 31/12/2020 • Recorrente ■ Vorcon Auditoria & Consultoria ■ 22 de abril de 2021
B14: [P9] | C14: Conjunto de documentos sem composição clara do valor pago | D14: Verificamos que existe apresentação de despesa sem os respectivos comprovantes de pagamentos. | E14: Pagamento sem os respectivos comprovante de pagamento não é permitido pela Convenção e Regimento Interno do Condomínio. | F14: N/A | G14: Criação de um passo a passo para verificação nos comprovantes de pagamentos das despesas do condomínios. | H14: Operacional | I14: Inspeção Documental - Gastos | J14: ALTO IMPACTO | K14: • 31/12/2020 ■ Vorcon Auditoria & Consultoria ■ 22 de abril de 2021
B15: [P10] | C15: Páginas não numeradas ou numeradas de forma incorreta | D15: Verificamos que algumas páginas do Demonstrativo Financeiro não estão sendo numeradas ou não seguem uma ordem sequencial. | E15: Falhas na padronização implica em perda de eficiência na conferência das prestações de contas. | F15: N/A | G15: Sugerimos que seja criada rotina de revisão da padronização dos Demonstrativos Financeiros mensais, pois isso mitigará possivéis falhas. | H15: Operacional | I15: 02.1.2 STC - Voucher documental | J15: MÉDIO IMPACTO | K15: • 31/12/2020 • Recorrente ■ Vorcon Auditoria & Consultoria ■ 22 de abril de 2021
B16: [P11] | C16: Pagamento de tarifa bancária. | D16: Verificamos que ocorreram pagamento de fornecedores e prestadores de serviços por meio de transferência bancária. | E16: Pagamento de encargos financeiros que deveriam ser de responsabilidade dos Fornecedores/Prestadores de serviços. | F16: N/A | G16: Sugerimos que seja solicitado boleto para pagamento de todos os Fornecedores/Prestadores de serviços e em caso de negativa o valor dos encargos financeiros deve ser subtraído do pagamento. | H16: Financeiro | I16: Inspeção Documental - Gastos | J16: BAIXO IMPACTO | K16: • 31/12/2020 • Recorrente ■ Vorcon Auditoria & Consultoria ■ 22 de abril de 2021
B17: [P12] | C17: Conjunto de documentos anexados fora do mês correspondente. | D17: Desorganização da documentação suporte dificultam a análise de todas as partes envolvidas. | E17: Não sendo apresentadas tempestivamentes as apresentações das contas, afetará diretamente o fluxo de caixa e o controle do financeiro do condomínio. | F17: N/A | G17: Seja elaborada uma periodicidade fixa para apresentação das despesas, e que seja realizado as prestações dos períodos correspondentes as despesas. | H17: Operacional | I17: Inspeção Documental - Gastos | J17: ALTO IMPACTO | K17: • 31/12/2020 ■ Vorcon Auditoria & Consultoria ■ 22 de abril de 2021
B18: [P13] | C18: Conjunto de documentos anexados no balancete sem o mesmo constarem nos demonstrativos financeiros mensais de gastos. | D18: Ausência de transparência na prestação de contas e aumento do risco de pagamentos indevidos. | E18: A apresentação no balancetes sem os respectivos comprovantes do demonstrativos financeiros não é permitido pela legislação brasileira e pela Convenção e Regimento Interno do Condomínio. | F18: N/A | G18: Seja elaborada uma periodicidade fixa para apresentação dos respectivos comprovantes nos balancetes e que seja realizado as prestações dos períodos correspondentes as despesas. | H18: Operacional | I18: Inspeção Documental - Gastos | J18: MÉDIO IMPACTO | K18: • 31/12/2020 ■ Vorcon Auditoria & Consultoria ■ 22 de abril de 2021
... B30: [P28] | C30: Fornecedores citados na resposta de circulação indevidamente | D30: Em resposta na carta de circularização foram citados os seguintes fornecedores: Grupo Contínua - 07.536.483/0001-92, Ecowash - 11.877.873/0001-01, Elemidia - 03.616.039/0001-26, Izar Park - 18.021.222/0001-56, Posto Mataripe - 13.578.265/0001-13, LA Construções - 20.726.309/0001-70, Softdados - 17.869.823/0001-50, Grupo Solução - 23.105.423/0001-71 e Coopcicla - 01.397.759/0001-12, contudo não houveram pagamentos no período em que a auditoria está sendo realizada, informação confirmada posteriormente pela Administração. | E30: Dificuldade quanto ao rastreamentos dos contratos e incerteza quanto a informação apresentada. | F30: N/A | G30: Recomendamos que sejam tomadas as medidas necessárias para que haja um padrão sobre apresentação das informações do contrato e sejam apresentadas conforme solicitado. | H30: Operacional | I30: 02.2.9 STC - Validação da carta de representação de contratos | J30: BAIXO IMPACTO | K30: • 31/12/2020 • Recorrente ■ Vorcon Auditoria & Consultoria ■ 22 de abril de 2021
B31: [P29] | C31: Não há controle de recolhimento do FGTS das empresas terceirizadas | D31: Não nos foi encaminhado um controle de recolhimento a respeito do recolhimento do FGTS dos funcionários que trabalham de forma terceirizada no condomínio. Esse controle é necessário tendo em vista que o condomínio é subsidiariamente responsável pelos recolhimentos tributários e trabalhistas assim como legisla a Súmula 331, IV, do TST | E31: Recolhimento do FGTS sobre os funcinonarios contratados de forma terceirizados. | F31: 1086628.7 | G31: Recomendamos ter um controle de recolhimentos dos funcionários contratados de forma terceirizado. | H31: Operacional | I31: 02.3.3 STC - Recalculo individual de Colaboradores (Validar quantidade com o gestor do projeto) | J31: ALTO IMPACTO | K31: • 31/12/2020 • Novo ■ Vorcon Auditoria & Consultoria ■ 22 de abril de 2021
B32: [P30] | C32: Inexistência de atualização dos Relatórios Jurídicos | D32: Solicitamos a Administração os relatórios jurídicos para o período do trabalho realizado, contudo após a relaização dos testes verificamos que os relatórios disponibilizados apesar de serem de meses diferentes não possuem diferença. Dessa forma há dúvidas se os mesmos estão sendo atualizados ou não. | E32: Possível risco de informações desatualizadas que podem gerar saídas de caixa não programadas para o Condomínio. | F32: N/A | G32: Sugerimso que os relatórios sejam atualizados mensalmente com a expectativa real do valores e ações. Conforme atualização dos processos. | H32: Financeiro | I32: Contingências | J32: BAIXO IMPACTO | K32: • 31/12/2020 • Novo ■ Vorcon Auditoria & Consultoria ■ 22 de abril de 2021
B33: [P31] | C33: Inexistência de expectativa de Ganho e Perda para os Relatórios Jurídicos. | D33: Os relatórios jurídicos apresentados pela Administração não possuem a expectativa de perda ou ganho dos mesmos, conforme prática usual dos assesores jurídicos. | E33: A inêxistência da classificação quanto a possiveis perdas faz com que a Adiministração não possa planejar possiveis saídas de caixas futuras, e além disso tal prática não contempla as melhores práticas de mercado. | F33: N/A | G33: Sugiro que a Administração solicite aos seus Assessores jurídicos que mensalmente os relatórios sejam classificados tanto para perda ou para ganho como: Remota: Prognóstico de perda deve ser menos do que 25% Possível: Prognóstico de perda desde que o risco não seja remoto Provável: Prognóstico de perda deve ser mais do que 50% | H33: Financeiro | I33: 02.3.6 STC - Validação da Carta de Representação de Assessores Jurídicos | J33: BAIXO IMPACTO | K33: • 31/12/2020 • Novo ■ Vorcon Auditoria & Consultoria ■ 22 de abril de 2021
B34: [P32] | C34: Inexistência de politica de acompanhamento das principais certidões. | D34: A Administração não possui como rotina o acompanhamento das principais certidões: Municipal; Estaduas; Federal e; Serviço de proteção de Crédito. | E34: A inexistência do acompanhamento de forma preventiva das certidões pode vir a gerar desembolsados não esperados assim como possíveis bloqueios que podem vir a afetar a rotina do Condomínio. | F34: N/A | G34: Sugerimos que a Administração avalie adicionar em sua rotina, pelo menos trimestral, a emissão dessas certidões como forma de mitigar possíveis problemas. | H34: Legal | I34: 02.3.4 STC - Certidões | J34: MÉDIO IMPACTO | K34: • 31/12/2020 • Novo ■ Vorcon Auditoria & Consultoria ■ 22 de abril de 2021
B35: [P33] | C35: Limitação de escopo | D35: A administração não possui acompanhamento para a rotina de cobrança feita aos condominos inadimplentes | E35: A não entrega de documentos ou evidencias solicitadas impedem que processos possam ser avaliados no decorrer da auditoria | F35: N/A | G35: Se faz necessário que a administração do condominio possua uma rotina ou sistema de cobrança de inadimplentes | H35: Operacional | I35: 02.2.5 STC - Walkthrough de Receita | J35: MÉDIO IMPACTO | K35: • 31/12/2020 • Recorrente ■ Vorcon Auditoria & Consultoria ■ 22 de abril de 2021

Sheet FREQ. X PONTOS
A1: Ponto V+ | B1: Pontos | C1: Ponto de forma resumida | D1: Descrição do ponto: | F1: Ponto | G1: Total | H1: Probabilidade | I1: Frequência | J1: Peso
B2: P01 | C2: Pagamento sem documento fiscal | D2: Verificamos que ocorreram gastos sem a respectiva emissão de nota fiscal pelos fornecedores e prestadores de serviços. | F2: P01 | G2: 8 | H2: 0.28571429 | I2: Frequente | J2: 4
B3: P02 | C3: Diferenças entre: Favorecido do documento X Beneficiário do pagamento | D3: O fornecedor apresentado no comprovante de pagamento não é o mesmo da Nota Fiscal. | F3: P02 | G3: 0
B4: P03 | C4: Pagamentos realizados sem os respectivos comprovantes de pagamento anexados | D4: Verificamos que alguns pagamentos foram realizados sem que fossem anexados os respectivos comprovantes de pagamentos ou documentos equivalentes dando a respectiva quitação. | F4: P03 | G4: 4 | H4: 0.14285714 | I4: Eventual | J4: 3
B5: P04 | C5: Pagamento de impostos sem identificação do prestador de serviços | D5: Não identificamos documentação suporte que indique a origem dos impostos e os respectivos prestadores de serviço. | F5: P04 | G5: 0
B6: P05 | C6: Ausência de apresentação de mapa de orçamentos | D6: Verificamos que muitas das compras realizadas não estavam anexados os mapas de orçamento. | F6: P05 | G6: 0
B7: P06 | C7: Inexistência de tempestividade na prestação de contas do fundo fixo | D7: Verificamos que o fundo fixo do Condomínio, por diversas vezes, possui valores retirados onde existe a prestação de contas nos meses não referentes. | F7: P06 | G7: 0
B8: P07 | C8: Inconsistência na apresentação da atividade da empresa | D8: O serviço/produto adquirido não condiz com a atividade econômica apresentada no CNPJ da empresa. | F8: P07 | G8: 0
B9: P08 | C9: Negligência na gestão dos Documentos que compõe os Demonstrativos | D9: Verificamos que alguns comprovantes não estão sendo arquivados com os cuidados necessários, com isso alguns estão ilegíveis. | F9: P08 | G9: 3 | H9: 0.10714286 | I9: Eventual | J9: 3
B10: P09 | C10: Conjunto de documentos sem composição clara do valor pago | D10: Verificamos que algumas páginas do Demonstrativo Financeiro não estão sendo numeradas ou não seguem uma ordem sequencial. | F10: P09 | G10: 0
B11: P10 | C11: Páginas não numeradas ou numeradas de forma incorreta | D11: Verificamos que algumas páginas do Demonstrativo Financeiro não estão sendo numeradas ou não seguem uma ordem sequencial. | F11: P10 | G11: 0
B12: P11 | C12: Pagamento de tarifa bancária. | D12: Verificamos que ocorreram pagamento de fornecedores e prestadores de serviços por meio de transferência bancária. | F12: P11 | G12: 0
B13: P12 | C13: Conjunto de documentos anexados fora do mês correspondente no Balancete. | D13: Desorganização da documentação suporte dificultam a análise de todas as partes envolvidas. | F13: P12 | G13: 1 | H13: 0.035714286 | I13: Raríssimo | J13: 1
B14: P13 | C14: Informações apresentado fora do mês correspondente na demonstração financeira. | D14: Ausência de transparência na prestação de contas e aumento do risco de pagamentos indevidos. | F14: P13 | G14: 1 | H14: 0.035714286 | I14: Raríssimo | J14: 1
B15: P14 | C15: Conjunto de documentos anexados no balancete sem o mesmo constarem nos demonstrativos financeiros mensais de gastos. | D15: Verificamos que há diferença entre os valores apresentados,não justificada por parcelamento ou multa. | F15: P14 | G15: 0
B16: P15 | C16: Informações na Demonstração Financeira sem o mesmo constarem nos Balancetes mensais de gastos. | D16: Verificamos a existência de saidas no extrato duplicadas e pagamentos de despesas já encerradas. | F16: P15 | G16: 0
B17: P16 | C17: Diferenças entre: Valor do comprovante de pagamento X Valor da documentação suporte. | D17: Verificamos que alguns pagamentos foram realizados após a data de vencimento acarretando em gastos adicionais. | F17: P16 | G17: 3 | H17: 0.10714286 | I17: Eventual | J17: 3
B18: P17 | C18: Pagamento realizado em duplicidade. | D18: Verificamos que ocorreram pagamentos com documentação fiscal com emissão posterior a data em que a transação bancária foi realizada. | F18: P17 | G18: 0
B19: P18 | C19: Pagamento realizado após data de vencimento com incidência de multa e juros. | D19: Verificamos que há desorganização das informações na demonstração financeira que dificultam na análise de todas as partes envolvidas. | F19: P18 | G19: 2 | H19: 0.071428571 | I19: Raro | J19: 2
B20: P19 | C20: Pagamentos realizados antes da emissão da nota fiscal. | F20: P19 | G20: 5 | H20: 0.17857143 | I20: Eventual | J20: 3
B21: P20 | C21: Emissão de nota de simples remessa após o pagamento do produto. | F21: P20 | G21: 1 | H21: 0.035714286 | I21: Raríssimo | J21: 1
B22: P21
H26: 1

Sheet Lista Suspensa
C3: TESTES | H3: Legenda
C4: 02.1.1 - CRA - Follow Up CCI | H4: a | I4: Feito
C5: 02.1.2 - CRA - Confirmação de Independência | H5: r | I5: Pendente
C6: 02.1.3 - CRA - Cálculo da Materialidade | H6: s | I6: Dúvida
C7: 02.1.4 - CRA - Planejamento dos testes e das contas Significativas conforme MATERIALIDADE | H7: x | I7: Ponto de escopo
C8: 02.1.5 - CRA - Voucher documental
C9: 02.1.6 - CRA - Voucher documental + voucher nos extratos
C10: 02.1.7 - CRA - Teste de voucher (inspeção das guias e confronto dos saldos demonstrativos)
C11: 02.1.8 - CRA - Consolidação dos saldos
C12: 02.1.9 - CRA - Resumo Regimento
C13: 02.1.10 - CRA - Resumo Convenção
C14: 02.1.11 - CRA - Carta de Representação de Atas
C15: 02.1.12 - CRA - Resumo Atas
C16: 02.1.13 - CRA - Analise do resumo de atas e verificação das despesas aprovadas
C17: 02.1.14 - CRA - Seguros
C18: 02.1.15 - CRA - Orçado X Realizado
C19: 02.1.16 - CRA - Revisão analitica de demonstrativos
... C62: 02.4.9 - CRA - Relatório Final da Apresentação da Auditoria

Sheet BASE DA MATRIZ DE RISCOS
C2: Item | D2: Descrição
C3: Impacto | D3: ALTO IMPACTO
C4: Status | D4: Explicação se é um ponto novo ou recorrente e quem identificou o ponto e/ou quando.
C5: Código | D5: [PX] Representa a numeração sequencial do Ponto de Controle;
C6: Título | D6: Explicação sintética e ideia central do Ponto de Controle;
C7: Tipo | D7: Cada Ponto de Controle é enquadrado em um tipo que implicará em um peso para o cálculo da exposição a risco;
C8: Probabilidade | D8: Frequência associada ao procedimento levantado no Ponto de Controle;
C9: Impacto | D9: Mensuração do impacto causado em cada ocasião de acontecimento do Ponto de Controle;
C10: Exposição | D10: Exposição = (PesoTipo*Probabilidade*Impacto);
C11: Setor | D11: A área da Empresa a qual o Ponto de Controle implica;
C12: Descrição | D12: Detalhamento conceitual do Ponto de Contole;
C13: Riscos e Implicações | D13: Consequências da não resolução do Ponto de Controle; usada também como base de mensuração para o Impacto;
... C17: Data Limite para Resolução do Ponto Identificado | D17: Prazo estipulado pela Administração do Condomínio Le Parc Residential Resort para que o ponto identificado deixe de existir.
C19: Critérios e Classificações dos Pontos de Controle
C20: Tipos de Pontos de Controle
C21: Tipo | D21: Descrição | E21: Peso
C22: Estratégico | D22: Inerentes às ações de longo prazo que visam a perpetuidade e transparência das operações; | E22: 4
C23: Financeiro | D23: Quando se tem risco de impacto financerio e/ou contingências financeiras evidentes; | E23: 5
C24: Operacional | D24: Riscos quanto a procedimentos executados no dia a dia para a prestação dos serviços; | E24: 4
C25: Legal | D25: Relativos a riscos e impactos jurídicos; | E25: 3
C26: Tecnologia | D26: Relativos a integração de sistema e LGPD; | E26: 3
C27: Imagem | D27: Referente a riscos de provável perda de credibilidade e desgaste da instituição. | E27: 3
C29: Tipo | D29: Descrição | E29: Peso | F29: Tipo | G29: Tipo | H29: % | I29: Tipo
C30: Estratégico | D30: Inerentes às ações de longo prazo que visam a perpetuidade e transparência das operações; | E30: 4 | F30: Estratégico | G30: Estratégico | H30: =I30/$J$36 -> 0.068965517 | I30: =COUNTIFS($E$78:$E$106,$C30) -> 2
C31: Financeiro | D31: Quando se tem risco de impacto financerio e/ou contingências financeiras evidentes; | E31: 5 | F31: Financeiro | G31: Financeiro | H31: =I31/$J$36 -> 0.48275862 | I31: =COUNTIFS($E$78:$E$106,$C31) -> 14
C32: Operacional | D32: Riscos quanto a procedimentos executados no dia a dia para a prestação dos serviços; | E32: 4 | F32: Operacional | G32: Operacional | H32: =I32/$J$36 -> 0.10344828 | I32: =COUNTIFS($E$78:$E$106,$C32) -> 3
C33: Legal | D33: Relativos a riscos e impactos jurídicos; | E33: 3 | F33: Legal | G33: Legal | H33: =I33/$J$36 -> 0.34482759 | I33: =COUNTIFS($E$78:$E$106,$C33) -> 10
C34: Tecnologia | D34: Relativos a integração de sistema e LGPD; | E34: 3 | F34: Tecnologia | G34: Tecnologia | H34: =I34/$J$36 -> 0 | I34: =COUNTIFS($E$78:$E$106,$C34) -> 0
C35: Imagem | D35: Referente a riscos de provável perda de credibilidade e desgaste da instituição. | E35: 3 | F35: Imagem | G35: Imagem | H35: =I35/$J$36 -> 0 | I35: =COUNTIFS($E$78:$E$106,$C35) -> 0
I36: =SUM(H30:H35) -> 1 | J36: =SUM(I30:I35) -> 29
C37: Probabilidade dos Pontos de Controle
C38: Probabilidade | D38: Frequencia | E38: Peso
C39: Muito frequente | D39: Frequencia de pontos incidentes em mais de 30% dos itens analisados | E39: 5
C40: Frequente | D40: Frequencia de pontos incidentes entre 20% e 30% analisados | E40: 4
C41: Eventual | D41: Frequencia de pontos incidentes entre 10% e 20% analisados | E41: 3
C42: Raro | D42: Frequencia de pontos incidentes entre 5% e 10% analisados | E42: 2
C43: Raríssimo | D43: Frequencia de pontos incidentes menor de 5% | E43: 1
C44: WP – Work Papers (Papéis de Trabalho)
C46: Impacto dos Pontos de Controle
J47: ='RESUMO DE PONTOS'!E3 -> Materialidade | K47: ='RESUMO DE PONTOS'!F3 -> 149800 | L47: =K47/$H$49 -> 0.02999288
F48: Impacto Faturamento | H48: ='RESUMO DE PONTOS'!G3 -> 0 | J48: ='RESUMO DE PONTOS'!E4 -> PM | K48: ='RESUMO DE PONTOS'!F4 -> 93650 | L48: =K48/$H$49 -> 0.018750555
C49: Impacto | D49: Mensuração | E49: Peso | H49: ='RESUMO DE PONTOS'!G4 -> 4994518.8 | J49: ='RESUMO DE PONTOS'!E5 -> AMPT | K49: ='RESUMO DE PONTOS'!F5 -> 7490 | L49: =K49/$H$49 -> 0.001499644
C50: Perdas graves | D50: - Impactos financeiros diretos superiores a M ( Materiality); | E50: 5 | F50: =G54+0.0000001% -> 0.029992881 | H50: =$H$49*F50 -> 149800 | I50: 10000000 | J50: 5
D51: - Riscos quanto a perpetuidade da operação;
D52: - Riscos críticos operacionais ligados à prestação do serviço;
D53: - Risco de morte/invalidez/doenças.
C54: Perdas grandes | D54: - Impactos financeiros diretos do PM até a M; | E54: 4 | F54: =G60+0.0000001% -> 0.018750556 | G54: =L47 -> 0.02999288 | H54: =$H$49*F54 -> 93650.005 | I54: =$H$49*G54 -> 149800 | J54: 4
D55: - Necessidade de contingências de 5;00% ou mais do faturamento;
D56: - Riscos operacionais ligados à prestação do serviço;
D57: - Riscos críticos gerenciais;
D58: - Riscos críticos de imagem; | O58: =H70 -> 0 | P58: =I70 -> 7490 | Q58: 1
D59: - Riscos críticos de clima organizacional. | O59: =H66 -> 7490.0499 | P59: =I66 -> 70237.5 | Q59: 2
C60: Perdas médias | D60: - Impactos financeiros diretos de até 75% do PM até o PM; | E60: 3 | F60: =G66+0.000001% -> 0.014062926 | G60: =L48 -> 0.018750555 | H60: =$H$49*F60-0.01 -> 70237.54 | I60: =$H$49*G60-0.01 -> 93649.99 | J60: 3 | O60: =H60 -> 70237.54 | P60: =I60 -> 93649.99 | Q60: 3
D61: - Necessidade de contingências de 1;00% a 4;99% do faturamento; | O61: =H54 -> 93650.005 | P61: =I54 -> 149800 | Q61: 4
D62: - Riscos leves operacionais ligados à prestação do serviço; | O62: =H50 -> 149800 | P62: =I50 -> 10000000 | Q62: 5
D63: - Riscos gerenciais. | O63: =H49 -> 4994518.8
D64: - Riscos de clima organizacional
D65: - Riscos de imagem. | L65: =VLOOKUP($L$78,H50:J71,2,1) -> #N/A
C66: Perdas moderadas | D66: - Impactos financeiros diretos de entre o nosso AMPT e 75% do PM | E66: 2 | F66: =L49+0.000001% -> 0.001499654 | G66: =L48*75% -> 0.014062916 | H66: =$H$49*F66 -> 7490.0499 | I66: =$H$49*G66 -> 70237.5 | J66: 2
D67: - Riscos leves gerenciais;
D68: - Riscos leves de imagem;
D69: - Riscos leves de clima organizacional
C70: Perdas pequenas | D70: - Impactos financeiros diretos de até o nosso AMPT; | E70: 1 | F70: 0 | G70: =L49 -> 0.001499644 | H70: =$H$49*F70 -> 0 | I70: =$H$49*G70 -> 7490 | J70: 1
D71: - Falhas técnicas e/ou humanas em procedimentos que não irão impactar diretamente a qualidade dos dados. | L71: Avaliar por julgameto
C75: 3 – Pontos de Controle | M75: PRIORIDADE
C76: Sumário de Pontos | D76: Fórmula | E76: Fórmula | F76: Fórmula | G76: Avaliar/Fórmula | H76: Avaliar/Fórmula | I76: Fórmula | J76: Fórmula | K76: Fórmula | M76: Avaliação
A77: Link | C77: Ponto de Controle | D77: Título | E77: Tipo | F77: Tipo | G77: Probabilidade | H77: Perdas/ Impacto | I77: Exposição | J77: Setor | K77: Classificação por Pontuação | L77: Valor | M77: Classificação Por Julgamento
A78: [P1] | C78: ='RESUMO DE PONTOS'!C9 -> [P1] | D78: =IFERROR(VLOOKUP(C78,'RESUMO DE PONTOS'!$C$9:$D$38,2,),"") -> Pagamento sem documento fiscal | E78: =IFERROR(VLOOKUP($C78,'RESUMO DE PONTOS'!$C$9:$L$38,7,),"") -> Legal | F78: =VLOOKUP(E78,$C$30:$E$35,3,) -> 3 | G78: =_xlfn.XLOOKUP(D78,Planilha1!C:C,Planilha1!F:F) -> 4 | H78: =_xlfn.XLOOKUP(D78,Planilha1!C:C,Planilha1!G:G) -> 2 | I78: 48 | J78: =IFERROR(VLOOKUP(C78,'RESUMO DE PONTOS'!$C$9:$J$38,8,),"") -> Voucher documental | K78: =IF(I78>=75,"ALTO IMPACTO",IF(I78<=50,"BAIXO IMPACTO","MÉDIO IMPACTO")) -> BAIXO IMPACTO | L78: =_xlfn.XLOOKUP(D78,'BASE DE PONTOS V+'!C:C,'BASE DE PONTOS V+'!E:E) -> 17679.82 | M78: =_xlfn.XLOOKUP(C78,'RESUMO DE PONTOS'!C:C,'RESUMO DE PONTOS'!L:L) -> Alto Impacto | N78: =C78 -> [P1] | O78: =I78 -> 48
A79: [P2] | C79: ='RESUMO DE PONTOS'!C10 -> [P2] | D79: =IFERROR(VLOOKUP(C79,'RESUMO DE PONTOS'!$C$9:$D$38,2,),"") -> Pagamentos realizados sem os respectivos comprovantes de pagamento anexados | E79: =IFERROR(VLOOKUP($C79,'RESUMO DE PONTOS'!$C$9:$L$38,7,),"") -> Financeiro | F79: =VLOOKUP(E79,$C$30:$E$35,3,) -> 5 | G79: =_xlfn.XLOOKUP(D79,Planilha1!C:C,Planilha1!F:F) -> 3 | H79: =_xlfn.XLOOKUP(D79,Planilha1!C:C,Planilha1!G:G) -> 1 | I79: 45 | J79: =IFERROR(VLOOKUP(C79,'RESUMO DE PONTOS'!$C$9:$J$38,8,),"") -> Voucher documental | K79: =IF(I79>=75,"ALTO IMPACTO",IF(I79<=50,"BAIXO IMPACTO","MÉDIO IMPACTO")) -> BAIXO IMPACTO | L79: =_xlfn.XLOOKUP(D79,'BASE DE PONTOS V+'!C:C,'BASE DE PONTOS V+'!E:E) -> 1558.24 | M79: =_xlfn.XLOOKUP(C79,'RESUMO DE PONTOS'!C:C,'RESUMO DE PONTOS'!L:L) -> Baixo Impacto | N79: =C79 -> [P2] | O79: =I79 -> 45
A80: [P3] | C80: ='RESUMO DE PONTOS'!C11 -> [P3] | D80: =IFERROR(VLOOKUP(C80,'RESUMO DE PONTOS'!$C$9:$D$38,2,),"") -> Negligência na gestão dos Documentos que compõe os Demonstrativos | E80: =IFERROR(VLOOKUP($C80,'RESUMO DE PONTOS'!$C$9:$L$38,7,),"") -> Operacional | F80: =VLOOKUP(E80,$C$30:$E$35,3,) -> 4 | G80: =_xlfn.XLOOKUP(D80,Planilha1!C:C,Planilha1!F:F) -> 3 | H80: =_xlfn.XLOOKUP(D80,Planilha1!C:C,Planilha1!G:G) -> 1 | I80: 24 | J80: =IFERROR(VLOOKUP(C80,'RESUMO DE PONTOS'!$C$9:$J$38,8,),"") -> Voucher documental | K80: =IF(I80>=75,"ALTO IMPACTO",IF(I80<=50,"BAIXO IMPACTO","MÉDIO IMPACTO")) -> BAIXO IMPACTO | L80: =_xlfn.XLOOKUP(D80,'BASE DE PONTOS V+'!C:C,'BASE DE PONTOS V+'!E:E) -> 118.82 | M80: =_xlfn.XLOOKUP(C80,'RESUMO DE PONTOS'!C:C,'RESUMO DE PONTOS'!L:L) -> Baixo Impacto | N80: =C80 -> [P3] | O80: =I80 -> 24
A81: [P4] | C81: ='RESUMO DE PONTOS'!C12 -> [P4] | D81: =IFERROR(VLOOKUP(C81,'RESUMO DE PONTOS'!$C$9:$D$38,2,),"") -> Conjunto de documentos anexados fora do mês correspondente no Balancete. | E81: =IFERROR(VLOOKUP($C81,'RESUMO DE PONTOS'!$C$9:$L$38,7,),"") -> Operacional | F81: =VLOOKUP(E81,$C$30:$E$35,3,) -> 4 | G81: =_xlfn.XLOOKUP(D81,Planilha1!C:C,Planilha1!F:F) -> 1 | H81: =_xlfn.XLOOKUP(D81,Planilha1!C:C,Planilha1!G:G) -> 1 | I81: 40 | J81: =IFERROR(VLOOKUP(C81,'RESUMO DE PONTOS'!$C$9:$J$38,8,),"") -> Voucher documental | K81: =IF(I81>=75,"ALTO IMPACTO",IF(I81<=50,"BAIXO IMPACTO","MÉDIO IMPACTO")) -> BAIXO IMPACTO | L81: =_xlfn.XLOOKUP(D81,'BASE DE PONTOS V+'!C:C,'BASE DE PONTOS V+'!E:E) -> 418.07 | M81: =_xlfn.XLOOKUP(C81,'RESUMO DE PONTOS'!C:C,'RESUMO DE PONTOS'!L:L) -> Baixo Impacto | N81: =C81 -> [P4] | O81: =I81 -> 40
C82: ='RESUMO DE PONTOS'!C13 -> [P5] | D82: =IFERROR(VLOOKUP(C82,'RESUMO DE PONTOS'!$C$9:$D$38,2,),"") -> Informações apresentado fora do mês correspondente na demonstração financeira. | E82: =IFERROR(VLOOKUP($C82,'RESUMO DE PONTOS'!$C$9:$L$38,7,),"") -> Financeiro | F82: =VLOOKUP(E82,$C$30:$E$35,3,) -> 5 | G82: =_xlfn.XLOOKUP(D82,Planilha1!C:C,Planilha1!F:F) -> 1 | H82: =_xlfn.XLOOKUP(D82,Planilha1!C:C,Planilha1!G:G) -> 1 | I82: 12 | J82: =IFERROR(VLOOKUP(C82,'RESUMO DE PONTOS'!$C$9:$J$38,8,),"") -> Voucher documental | K82: =IF(I82>=75,"ALTO IMPACTO",IF(I82<=50,"BAIXO IMPACTO","MÉDIO IMPACTO")) -> BAIXO IMPACTO | L82: =_xlfn.XLOOKUP(D82,'BASE DE PONTOS V+'!C:C,'BASE DE PONTOS V+'!E:E) -> 418.07 | M82: =_xlfn.XLOOKUP(C82,'RESUMO DE PONTOS'!C:C,'RESUMO DE PONTOS'!L:L) -> Baixo Impacto | N82: =C82 -> [P5] | O82: =I82 -> 12
C83: ='RESUMO DE PONTOS'!C14 -> [P6] | D83: =IFERROR(VLOOKUP(C83,'RESUMO DE PONTOS'!$C$9:$D$38,2,),"") -> Diferenças entre: Valor do comprovante de pagamento X Valor da documentação suporte. | E83: =IFERROR(VLOOKUP($C83,'RESUMO DE PONTOS'!$C$9:$L$38,7,),"") -> Financeiro | F83: =VLOOKUP(E83,$C$30:$E$35,3,) -> 5 | G83: =_xlfn.XLOOKUP(D83,Planilha1!C:C,Planilha1!F:F) -> 3 | H83: =_xlfn.XLOOKUP(D83,Planilha1!C:C,Planilha1!G:G) -> 1 | I83: 20 | J83: =IFERROR(VLOOKUP(C83,'RESUMO DE PONTOS'!$C$9:$J$38,8,),"") -> Voucher documental | K83: =IF(I83>=75,"ALTO IMPACTO",IF(I83<=50,"BAIXO IMPACTO","MÉDIO IMPACTO")) -> BAIXO IMPACTO | L83: =_xlfn.XLOOKUP(D83,'BASE DE PONTOS V+'!C:C,'BASE DE PONTOS V+'!E:E) -> De - R$ 1.062,75 até R$ 3.750,00 | M83: =_xlfn.XLOOKUP(C83,'RESUMO DE PONTOS'!C:C,'RESUMO DE PONTOS'!L:L) -> Baixo Impacto | N83: =C83 -> [P6] | O83: =I83 -> 20
C84: ='RESUMO DE PONTOS'!C15 -> [P7] | D84: =IFERROR(VLOOKUP(C84,'RESUMO DE PONTOS'!$C$9:$D$38,2,),"") -> Pagamentos realizados antes da emissão da nota fiscal. | E84: =IFERROR(VLOOKUP($C84,'RESUMO DE PONTOS'!$C$9:$L$38,7,),"") -> Legal | F84: =VLOOKUP(E84,$C$30:$E$35,3,) -> 3 | G84: =_xlfn.XLOOKUP(D84,Planilha1!C:C,Planilha1!F:F) -> 3 | H84: =_xlfn.XLOOKUP(D84,Planilha1!C:C,Planilha1!G:G) -> 1 | I84: 125 | J84: =IFERROR(VLOOKUP(C84,'RESUMO DE PONTOS'!$C$9:$J$38,8,),"") -> Voucher documental | K84: =IF(I84>=75,"ALTO IMPACTO",IF(I84<=50,"BAIXO IMPACTO","MÉDIO IMPACTO")) -> ALTO IMPACTO | L84: =_xlfn.XLOOKUP(D84,'BASE DE PONTOS V+'!C:C,'BASE DE PONTOS V+'!E:E) -> 3563.16 | M84: =_xlfn.XLOOKUP(C84,'RESUMO DE PONTOS'!C:C,'RESUMO DE PONTOS'!L:L) -> médio impacto | N84: =C84 -> [P7] | O84: =I84 -> 125
C85: ='RESUMO DE PONTOS'!C16 -> [P8] | D85: =IFERROR(VLOOKUP(C85,'RESUMO DE PONTOS'!$C$9:$D$38,2,),"") -> Os balancetes sem aprovação dos conselheiros fiscais e do síndico no termo de aprovação. | E85: =IFERROR(VLOOKUP($C85,'RESUMO DE PONTOS'!$C$9:$L$38,7,),"") -> Legal | F85: =VLOOKUP(E85,$C$30:$E$35,3,) -> 3 | G85: =_xlfn.XLOOKUP(D85,Planilha1!C:C,Planilha1!F:F) -> 5 | H85: =_xlfn.XLOOKUP(D85,Planilha1!C:C,Planilha1!G:G) -> 4 | I85: 60 | J85: =IFERROR(VLOOKUP(C85,'RESUMO DE PONTOS'!$C$9:$J$38,8,),"") -> Resumo Convenção | K85: =IF(I85>=75,"ALTO IMPACTO",IF(I85<=50,"BAIXO IMPACTO","MÉDIO IMPACTO")) -> MÉDIO IMPACTO | L85: =_xlfn.XLOOKUP(D85,'BASE DE PONTOS V+'!C:C,'BASE DE PONTOS V+'!E:E) -> NA | M85: =_xlfn.XLOOKUP(C85,'RESUMO DE PONTOS'!C:C,'RESUMO DE PONTOS'!L:L) -> Alto Impacto | N85: =C85 -> [P8] | O85: =I85 -> 60
C86: ='RESUMO DE PONTOS'!C17 -> [P9] | D86: =IFERROR(VLOOKUP(C86,'RESUMO DE PONTOS'!$C$9:$D$38,2,),"") -> Falta de registro de Ata's em cartório | E86: =IFERROR(VLOOKUP($C86,'RESUMO DE PONTOS'!$C$9:$L$38,7,),"") -> Legal | F86: =VLOOKUP(E86,$C$30:$E$35,3,) -> 3 | G86: =_xlfn.XLOOKUP(D86,Planilha1!C:C,Planilha1!F:F) -> 5 | H86: =_xlfn.XLOOKUP(D86,Planilha1!C:C,Planilha1!G:G) -> 4 | I86: 45 | J86: =IFERROR(VLOOKUP(C86,'RESUMO DE PONTOS'!$C$9:$J$38,8,),"") -> Resumo Convenção | K86: =IF(I86>=75,"ALTO IMPACTO",IF(I86<=50,"BAIXO IMPACTO","MÉDIO IMPACTO")) -> BAIXO IMPACTO | L86: =_xlfn.XLOOKUP(D86,'BASE DE PONTOS V+'!C:C,'BASE DE PONTOS V+'!E:E) -> NA | M86: =_xlfn.XLOOKUP(C86,'RESUMO DE PONTOS'!C:C,'RESUMO DE PONTOS'!L:L) -> médio impacto | N86: =C86 -> [P9] | O86: =I86 -> 45
C87: ='RESUMO DE PONTOS'!C18 -> [P10] | D87: =IFERROR(VLOOKUP(C87,'RESUMO DE PONTOS'!$C$9:$D$38,2,),"") -> Falta relatório de auditoria do período anterior. | E87: =IFERROR(VLOOKUP($C87,'RESUMO DE PONTOS'!$C$9:$L$38,7,),"") -> Estratégico | F87: =VLOOKUP(E87,$C$30:$E$35,3,) -> 4 | G87: =_xlfn.XLOOKUP(D87,Planilha1!C:C,Planilha1!F:F) -> 5 | H87: =_xlfn.XLOOKUP(D87,Planilha1!C:C,Planilha1!G:G) -> 4 | I87: 125 | J87: =IFERROR(VLOOKUP(C87,'RESUMO DE PONTOS'!$C$9:$J$38,8,),"") -> Follow Up CCI | K87: =IF(I87>=75,"ALTO IMPACTO",IF(I87<=50,"BAIXO IMPACTO","MÉDIO IMPACTO")) -> ALTO IMPACTO | L87: =_xlfn.XLOOKUP(D87,'BASE DE PONTOS V+'!C:C,'BASE DE PONTOS V+'!E:E) -> NA | M87: =_xlfn.XLOOKUP(C87,'RESUMO DE PONTOS'!C:C,'RESUMO DE PONTOS'!L:L) -> Alto Impacto | N87: =C87 -> [P10] | O87: =I87 -> 125
C88: ='RESUMO DE PONTOS'!C19 -> [P11] | D88: =IFERROR(VLOOKUP(C88,'RESUMO DE PONTOS'!$C$9:$D$38,2,),"") -> Falta de Planejamento Orçamentário Anual | E88: =IFERROR(VLOOKUP($C88,'RESUMO DE PONTOS'!$C$9:$L$38,7,),"") -> Estratégico | F88: =VLOOKUP(E88,$C$30:$E$35,3,) -> 4 | G88: =_xlfn.XLOOKUP(D88,Planilha1!C:C,Planilha1!F:F) -> 5 | H88: =_xlfn.XLOOKUP(D88,Planilha1!C:C,Planilha1!G:G) -> 5 | I88: 100 | J88: =IFERROR(VLOOKUP(C88,'RESUMO DE PONTOS'!$C$9:$J$38,8,),"") -> Orçado X Realizado | K88: =IF(I88>=75,"ALTO IMPACTO",IF(I88<=50,"BAIXO IMPACTO","MÉDIO IMPACTO")) -> ALTO IMPACTO | L88: =_xlfn.XLOOKUP(D88,'BASE DE PONTOS V+'!C:C,'BASE DE PONTOS V+'!E:E) -> NA | M88: =_xlfn.XLOOKUP(C88,'RESUMO DE PONTOS'!C:C,'RESUMO DE PONTOS'!L:L) -> Alto Impacto | N88: =C88 -> [P11] | O88: =I88 -> 100
C89: ='RESUMO DE PONTOS'!C20 -> [P12] | D89: =IFERROR(VLOOKUP(C89,'RESUMO DE PONTOS'!$C$9:$D$38,2,),"") -> Sistema de medição da água realizado de forma não individualizada | E89: =IFERROR(VLOOKUP($C89,'RESUMO DE PONTOS'!$C$9:$L$38,7,),"") -> Legal | F89: =VLOOKUP(E89,$C$30:$E$35,3,) -> 3 | G89: =_xlfn.XLOOKUP(D89,Planilha1!C:C,Planilha1!F:F) -> 5 | H89: =_xlfn.XLOOKUP(D89,Planilha1!C:C,Planilha1!G:G) -> 4 | I89: 64 | J89: =IFERROR(VLOOKUP(C89,'RESUMO DE PONTOS'!$C$9:$J$38,8,),"") -> Resumo Convenção | K89: =IF(I89>=75,"ALTO IMPACTO",IF(I89<=50,"BAIXO IMPACTO","MÉDIO IMPACTO")) -> MÉDIO IMPACTO | L89: =-_xlfn.XLOOKUP(D89,'BASE DE PONTOS V+'!C:C,'BASE DE PONTOS V+'!E:E) -> #VALUE! | M89: =_xlfn.XLOOKUP(C89,'RESUMO DE PONTOS'!C:C,'RESUMO DE PONTOS'!L:L) -> médio impacto | N89: =C89 -> [P12] | O89: =I89 -> 64
C90: ='RESUMO DE PONTOS'!C21 -> [P13] | D90: =IFERROR(VLOOKUP(C90,'RESUMO DE PONTOS'!$C$9:$D$38,2,),"") -> Valor apresentado no comprovante de pagamento, mas que não consta no extrato bancário | E90: =IFERROR(VLOOKUP($C90,'RESUMO DE PONTOS'!$C$9:$L$38,7,),"") -> Financeiro | F90: =VLOOKUP(E90,$C$30:$E$35,3,) -> 5 | G90: =_xlfn.XLOOKUP(D90,Planilha1!C:C,Planilha1!F:F) -> 3 | H90: =_xlfn.XLOOKUP(D90,Planilha1!C:C,Planilha1!G:G) -> 3 | I90: 36 | J90: =IFERROR(VLOOKUP(C90,'RESUMO DE PONTOS'!$C$9:$J$38,8,),"") -> Demonstrativo Financeiro + voucher nos extratos | K90: =IF(I90>=75,"ALTO IMPACTO",IF(I90<=50,"BAIXO IMPACTO","MÉDIO IMPACTO")) -> BAIXO IMPACTO | L90: =_xlfn.XLOOKUP(D90,'BASE DE PONTOS V+'!C:C,'BASE DE PONTOS V+'!E:E) -> #N/A | M90: =_xlfn.XLOOKUP(C90,'RESUMO DE PONTOS'!C:C,'RESUMO DE PONTOS'!L:L) -> Baixo Impacto | N90: =C90 -> [P13] | O90: =I90 -> 36
C91: ='RESUMO DE PONTOS'!C22 -> [P14] | D91: =IFERROR(VLOOKUP(C91,'RESUMO DE PONTOS'!$C$9:$D$38,2,),"") -> Falta de apresentação de extratos bancários | E91: =IFERROR(VLOOKUP($C91,'RESUMO DE PONTOS'!$C$9:$L$38,7,),"") -> Financeiro | F91: =VLOOKUP(E91,$C$30:$E$35,3,) -> 5 | G91: =_xlfn.XLOOKUP(D91,Planilha1!C:C,Planilha1!F:F) -> 4 | H91: =_xlfn.XLOOKUP(D91,Planilha1!C:C,Planilha1!G:G) -> 4 | I91: 48 | J91: =IFERROR(VLOOKUP(C91,'RESUMO DE PONTOS'!$C$9:$J$38,8,),"") -> Demonstrativo Financeiro + voucher nos extratos | K91: =IF(I91>=75,"ALTO IMPACTO",IF(I91<=50,"BAIXO IMPACTO","MÉDIO IMPACTO")) -> BAIXO IMPACTO | L91: =_xlfn.XLOOKUP(D91,'BASE DE PONTOS V+'!C:C,'BASE DE PONTOS V+'!E:E) -> NA | M91: =_xlfn.XLOOKUP(C91,'RESUMO DE PONTOS'!C:C,'RESUMO DE PONTOS'!L:L) -> Baixo Impacto | N91: =C91 -> [P14] | O91: =I91 -> 48
C92: ='RESUMO DE PONTOS'!C23 -> [P15] | D92: =IFERROR(VLOOKUP(C92,'RESUMO DE PONTOS'!$C$9:$D$38,2,),"") -> Saídas nos extratos não validados com a voucher | E92: =IFERROR(VLOOKUP($C92,'RESUMO DE PONTOS'!$C$9:$L$38,7,),"") -> Financeiro | F92: =VLOOKUP(E92,$C$30:$E$35,3,) -> 5 | G92: =_xlfn.XLOOKUP(D92,Planilha1!C:C,Planilha1!F:F) -> 3 | H92: =_xlfn.XLOOKUP(D92,Planilha1!C:C,Planilha1!G:G) -> 3 | I92: 36 | J92: =IFERROR(VLOOKUP(C92,'RESUMO DE PONTOS'!$C$9:$J$38,8,),"") -> Demonstrativo Financeiro + voucher nos extratos | K92: =IF(I92>=75,"ALTO IMPACTO",IF(I92<=50,"BAIXO IMPACTO","MÉDIO IMPACTO")) -> BAIXO IMPACTO | L92: =_xlfn.XLOOKUP(D92,'BASE DE PONTOS V+'!C:C,'BASE DE PONTOS V+'!E:E) -> 2117.99 | M92: =_xlfn.XLOOKUP(C92,'RESUMO DE PONTOS'!C:C,'RESUMO DE PONTOS'!L:L) -> Baixo Impacto | N92: =C92 -> [P15] | O92: =I92 -> 36
C93: ='RESUMO DE PONTOS'!C24 -> [P16] | D93: =IFERROR(VLOOKUP(C93,'RESUMO DE PONTOS'!$C$9:$D$38,2,),"") -> Apresentação incompleta de extrato bancário | E93: =IFERROR(VLOOKUP($C93,'RESUMO DE PONTOS'!$C$9:$L$38,7,),"") -> Financeiro | F93: =VLOOKUP(E93,$C$30:$E$35,3,) -> 5 | G93: =_xlfn.XLOOKUP(D93,Planilha1!C:C,Planilha1!F:F) -> 3 | H93: =_xlfn.XLOOKUP(D93,Planilha1!C:C,Planilha1!G:G) -> 4 | I93: 125 | J93: =IFERROR(VLOOKUP(C93,'RESUMO DE PONTOS'!$C$9:$J$38,8,),"") -> Demonstrativo Financeiro + voucher nos extratos | K93: =IF(I93>=75,"ALTO IMPACTO",IF(I93<=50,"BAIXO IMPACTO","MÉDIO IMPACTO")) -> ALTO IMPACTO | L93: =_xlfn.XLOOKUP(D93,'BASE DE PONTOS V+'!C:C,'BASE DE PONTOS V+'!E:E) -> NA | M93: =_xlfn.XLOOKUP(C93,'RESUMO DE PONTOS'!C:C,'RESUMO DE PONTOS'!L:L) -> Baixo Impacto | N93: =C93 -> [P16] | O93: =I93 -> 125
C94: ='RESUMO DE PONTOS'!C25 -> [P17] | D94: =IFERROR(VLOOKUP(C94,'RESUMO DE PONTOS'!$C$9:$D$38,2,),"") -> Diferenças entre os saldos dos Demonstrativos Financeiros de Receitas e Despesas em relação a Demonstração dos Saldos Financeiros. | E94: =IFERROR(VLOOKUP($C94,'RESUMO DE PONTOS'!$C$9:$L$38,7,),"") -> Financeiro | F94: =VLOOKUP(E94,$C$30:$E$35,3,) -> 5 | G94: =_xlfn.XLOOKUP(D94,Planilha1!C:C,Planilha1!F:F) -> 2 | H94: =_xlfn.XLOOKUP(D94,Planilha1!C:C,Planilha1!G:G) -> 2 | I94: 125 | J94: =IFERROR(VLOOKUP(C94,'RESUMO DE PONTOS'!$C$9:$J$38,8,),"") -> Conciliação Bancária + Elaboração dos quadros dos Demonstrativos Financeiros | K94: =IF(I94>=75,"ALTO IMPACTO",IF(I94<=50,"BAIXO IMPACTO","MÉDIO IMPACTO")) -> ALTO IMPACTO | L94: =_xlfn.XLOOKUP(D94,'BASE DE PONTOS V+'!C:C,'BASE DE PONTOS V+'!E:E) -> 109 | M94: =_xlfn.XLOOKUP(C94,'RESUMO DE PONTOS'!C:C,'RESUMO DE PONTOS'!L:L) -> Baixo Impacto | N94: =C94 -> [P17] | O94: =I94 -> 125
C95: ='RESUMO DE PONTOS'!C26 -> [P18] | D95: =IFERROR(VLOOKUP(C95,'RESUMO DE PONTOS'!$C$9:$D$38,2,),"") -> Ausência de apresentação de mapa de cotação | E95: =IFERROR(VLOOKUP($C95,'RESUMO DE PONTOS'!$C$9:$L$38,7,),"") -> Operacional | F95: =VLOOKUP(E95,$C$30:$E$35,3,) -> 4 | G95: =_xlfn.XLOOKUP(D95,Planilha1!C:C,Planilha1!F:F) -> 4 | H95: =_xlfn.XLOOKUP(D95,Planilha1!C:C,Planilha1!G:G) -> 3 | I95: 60 | J95: =IFERROR(VLOOKUP(C95,'RESUMO DE PONTOS'!$C$9:$J$38,8,),"") -> Voucher documental | K95: =IF(I95>=75,"ALTO IMPACTO",IF(I95<=50,"BAIXO IMPACTO","MÉDIO IMPACTO")) -> MÉDIO IMPACTO | L95: =_xlfn.XLOOKUP(D95,'BASE DE PONTOS V+'!C:C,'BASE DE PONTOS V+'!E:E) -> NA | M95: =_xlfn.XLOOKUP(C95,'RESUMO DE PONTOS'!C:C,'RESUMO DE PONTOS'!L:L) -> Baixo Impacto | N95: =C95 -> [P18] | O95: =I95 -> 60
C96: ='RESUMO DE PONTOS'!C27 -> [P19] | D96: =IFERROR(VLOOKUP(C96,'RESUMO DE PONTOS'!$C$9:$D$38,2,),"") -> Ausência de inventário dos ativos imobilizados | E96: =IFERROR(VLOOKUP($C96,'RESUMO DE PONTOS'!$C$9:$L$38,7,),"") -> Financeiro | F96: =VLOOKUP(E96,$C$30:$E$35,3,) -> 5 | G96: =_xlfn.XLOOKUP(D96,Planilha1!C:C,Planilha1!F:F) -> 4 | H96: =_xlfn.XLOOKUP(D96,Planilha1!C:C,Planilha1!G:G) -> 3 | I96: =F96*G96*H96 -> 60 | J96: =IFERROR(VLOOKUP(C96,'RESUMO DE PONTOS'!$C$9:$J$38,8,),"") -> Inspeção estatística dos itens do Imobilizado | K96: =IF(I96>=75,"ALTO IMPACTO",IF(I96<=50,"BAIXO IMPACTO","MÉDIO IMPACTO")) -> MÉDIO IMPACTO | L96: =-_xlfn.XLOOKUP(D96,'BASE DE PONTOS V+'!C:C,'BASE DE PONTOS V+'!E:E) -> #VALUE! | M96: =_xlfn.XLOOKUP(C96,'RESUMO DE PONTOS'!C:C,'RESUMO DE PONTOS'!L:L) -> Alto Impacto | N96: =C96 -> [P19] | O96: =I96 -> 60
C97: ='RESUMO DE PONTOS'!C28 -> [P20] | D97: =IFERROR(VLOOKUP(C97,'RESUMO DE PONTOS'!$C$9:$D$38,2,),"") -> Inexistência de valor estimado dos honorários advocatícios | E97: =IFERROR(VLOOKUP($C97,'RESUMO DE PONTOS'!$C$9:$L$38,7,),"") -> Financeiro | F97: =VLOOKUP(E97,$C$30:$E$35,3,) -> 5 | G97: 3 | H97: 1 | I97: =F97*G97*H97 -> 15 | J97: =IFERROR(VLOOKUP(C97,'RESUMO DE PONTOS'!$C$9:$J$38,8,),"") -> Teste de Contingência | K97: =IF(I97>=75,"ALTO IMPACTO",IF(I97<=50,"BAIXO IMPACTO","MÉDIO IMPACTO")) -> BAIXO IMPACTO | L97: =-_xlfn.XLOOKUP(D97,'BASE DE PONTOS V+'!C:C,'BASE DE PONTOS V+'!E:E) -> #N/A | M97: =_xlfn.XLOOKUP(C97,'RESUMO DE PONTOS'!C:C,'RESUMO DE PONTOS'!L:L) -> médio impacto | N97: =C97 -> [P20] | O97: =I97 -> 15
C98: ='RESUMO DE PONTOS'!C29 -> [P21] | D98: =IFERROR(VLOOKUP(C98,'RESUMO DE PONTOS'!$C$9:$D$38,2,),"") -> Perda Possível de Causa Judicial | E98: =IFERROR(VLOOKUP($C98,'RESUMO DE PONTOS'!$C$9:$L$38,7,),"") -> Legal | F98: =VLOOKUP(E98,$C$30:$E$35,3,) -> 3 | G98: =_xlfn.XLOOKUP(D98,Planilha1!C:C,Planilha1!F:F) -> 5 | H98: =_xlfn.XLOOKUP(D98,Planilha1!C:C,Planilha1!G:G) -> 4 | I98: =F98*G98*H98 -> 60 | J98: =IFERROR(VLOOKUP(C98,'RESUMO DE PONTOS'!$C$9:$J$38,8,),"") -> Teste de Contingência | K98: =IF(I98>=75,"ALTO IMPACTO",IF(I98<=50,"BAIXO IMPACTO","MÉDIO IMPACTO")) -> MÉDIO IMPACTO | L98: =_xlfn.XLOOKUP(D98,'BASE DE PONTOS V+'!C:C,'BASE DE PONTOS V+'!E:E) -> 396946.2 | M98: =_xlfn.XLOOKUP(C98,'RESUMO DE PONTOS'!C:C,'RESUMO DE PONTOS'!L:L) -> Alto Impacto | N98: =C98 -> [P21] | O98: =I98 -> 60
B99: x | C99: ='RESUMO DE PONTOS'!C30 -> [P22] | D99: =IFERROR(VLOOKUP(C99,'RESUMO DE PONTOS'!$C$9:$D$38,2,),"") -> Perda Provável de Causa Judicial | E99: =IFERROR(VLOOKUP($C99,'RESUMO DE PONTOS'!$C$9:$L$38,7,),"") -> Financeiro | F99: =VLOOKUP(E99,$C$30:$E$35,3,) -> 5 | G99: 4 | H99: 2 | I99: =F99*G99*H99 -> 40 | J99: =IFERROR(VLOOKUP(C99,'RESUMO DE PONTOS'!$C$9:$J$38,8,),"") -> Teste de Contingência | K99: =IF(I99>=75,"ALTO IMPACTO",IF(I99<=50,"BAIXO IMPACTO","MÉDIO IMPACTO")) -> BAIXO IMPACTO | L99: =_xlfn.XLOOKUP(D99,'BASE DE PONTOS V+'!C:C,'BASE DE PONTOS V+'!E:E) -> 32000 | M99: =_xlfn.XLOOKUP(C99,'RESUMO DE PONTOS'!C:C,'RESUMO DE PONTOS'!L:L) -> médio impacto | N99: =C99 -> [P22] | O99: =I99 -> 40
C100: ='RESUMO DE PONTOS'!C31 -> [P23] | D100: =IFERROR(VLOOKUP(C100,'RESUMO DE PONTOS'!$C$9:$D$38,2,),"") -> Perda Remota de Causa Judicial | E100: =IFERROR(VLOOKUP($C100,'RESUMO DE PONTOS'!$C$9:$L$38,7,),"") -> Legal | F100: =VLOOKUP(E100,$C$30:$E$35,3,) -> 3 | G100: 4 | H100: =_xlfn.XLOOKUP(D100,Planilha1!C:C,Planilha1!G:G) -> 4 | I100: =F100*G100*H100 -> 48 | J100: =IFERROR(VLOOKUP(C100,'RESUMO DE PONTOS'!$C$9:$J$38,8,),"") -> Teste de Contingência | K100: =IF(I100>=75,"ALTO IMPACTO",IF(I100<=50,"BAIXO IMPACTO","MÉDIO IMPACTO")) -> BAIXO IMPACTO | L100: =_xlfn.XLOOKUP(D100,'BASE DE PONTOS V+'!C:C,'BASE DE PONTOS V+'!E:E) -> 1503630.4 | M100: =_xlfn.XLOOKUP(C100,'RESUMO DE PONTOS'!C:C,'RESUMO DE PONTOS'!L:L) -> médio impacto | N100: =C100 -> [P23] | O100: =I100 -> 48
C101: ='RESUMO DE PONTOS'!C32 -> [P24] | D101: =IFERROR(VLOOKUP(C101,'RESUMO DE PONTOS'!$C$9:$D$38,2,),"") -> Ausência de registro do Regimento do condomínio em cartório. | E101: =IFERROR(VLOOKUP($C101,'RESUMO DE PONTOS'!$C$9:$L$38,7,),"") -> Legal | F101: =VLOOKUP(E101,$C$30:$E$35,3,) -> 3 | G101: =_xlfn.XLOOKUP(D101,Planilha1!C:C,Planilha1!F:F) -> 4 | H101: =_xlfn.XLOOKUP(D101,Planilha1!C:C,Planilha1!G:G) -> 3 | I101: =F101*G101*H101 -> 36 | J101: =IFERROR(VLOOKUP(C101,'RESUMO DE PONTOS'!$C$9:$J$38,8,),"") -> Regimento Interno | K101: =IF(I101>=75,"ALTO IMPACTO",IF(I101<=50,"BAIXO IMPACTO","MÉDIO IMPACTO")) -> BAIXO IMPACTO | L101: =_xlfn.XLOOKUP(D101,'BASE DE PONTOS V+'!C:C,'BASE DE PONTOS V+'!E:E) -> NA | M101: =_xlfn.XLOOKUP(C101,'RESUMO DE PONTOS'!C:C,'RESUMO DE PONTOS'!L:L) -> Baixo Impacto | N101: =C101 -> [P24] | O101: =I101 -> 36
C102: ='RESUMO DE PONTOS'!C33 -> [P25] | D102: =IFERROR(VLOOKUP(C102,'RESUMO DE PONTOS'!$C$9:$D$38,2,),"") -> Impossibilidade de identificação da conclusão da Obra do Parquinho e seu pagamento. | E102: Financeiro | F102: 5 | G102: =_xlfn.XLOOKUP(D102,Planilha1!C:C,Planilha1!F:F) -> 3 | H102: =_xlfn.XLOOKUP(D102,Planilha1!C:C,Planilha1!G:G) -> 4 | I102: =F102*G102*H102 -> 60 | J102: =IFERROR(VLOOKUP(C102,'RESUMO DE PONTOS'!$C$9:$J$38,8,),"") -> Resumo das Atas | K102: =IF(I102>=75,"ALTO IMPACTO",IF(I102<=50,"BAIXO IMPACTO","MÉDIO IMPACTO")) -> MÉDIO IMPACTO | L102: =_xlfn.XLOOKUP(D102,'BASE DE PONTOS V+'!C:C,'BASE DE PONTOS V+'!E:E) -> #N/A | M102: =_xlfn.XLOOKUP(C102,'RESUMO DE PONTOS'!C:C,'RESUMO DE PONTOS'!L:L) -> Baixo Impacto | N102: =C102 -> [P25] | O102: =I102 -> 60
C103: ='RESUMO DE PONTOS'!C34 -> [P26] | D103: =IFERROR(VLOOKUP(C103,'RESUMO DE PONTOS'!$C$9:$D$38,2,),"") -> Falta de questionamentos do Conselho Fiscal nas Assembleias | E103: =IFERROR(VLOOKUP($C103,'RESUMO DE PONTOS'!$C$9:$L$38,7,),"") -> Legal | F103: =VLOOKUP(E103,$C$30:$E$35,3,) -> 3 | G103: =_xlfn.XLOOKUP(D103,Planilha1!C:C,Planilha1!F:F) -> 4 | H103: =_xlfn.XLOOKUP(D103,Planilha1!C:C,Planilha1!G:G) -> 5 | I103: =F103*G103*H103 -> 60 | J103: =IFERROR(VLOOKUP(C103,'RESUMO DE PONTOS'!$C$9:$J$38,8,),"") -> Resumo das Atas | K103: =IF(I103>=75,"ALTO IMPACTO",IF(I103<=50,"BAIXO IMPACTO","MÉDIO IMPACTO")) -> MÉDIO IMPACTO | L103: =_xlfn.XLOOKUP(D103,'BASE DE PONTOS V+'!C:C,'BASE DE PONTOS V+'!E:E) -> N/A | M103: =_xlfn.XLOOKUP(C103,'RESUMO DE PONTOS'!C:C,'RESUMO DE PONTOS'!L:L) -> Alto Impacto | N103: =C103 -> [P26] | O103: =I103 -> 60
C104: ='RESUMO DE PONTOS'!C35 -> [P27] | D104: =IFERROR(VLOOKUP(C104,'RESUMO DE PONTOS'!$C$9:$D$38,2,),"") -> Cargo de Síndico Interino e de Conselheiro Fiscal ocupado pelo mesmo condômino | E104: Financeiro | F104: 5 | G104: =_xlfn.XLOOKUP(D104,Planilha1!C:C,Planilha1!F:F) -> 5 | H104: =_xlfn.XLOOKUP(D104,Planilha1!C:C,Planilha1!G:G) -> 4 | I104: =F104*G104*H104 -> 100 | J104: =IFERROR(VLOOKUP(C104,'RESUMO DE PONTOS'!$C$9:$J$38,8,),"") -> Resumo das Atas | K104: =IF(I104>=75,"ALTO IMPACTO",IF(I104<=50,"BAIXO IMPACTO","MÉDIO IMPACTO")) -> ALTO IMPACTO | L104: =_xlfn.XLOOKUP(D104,'BASE DE PONTOS V+'!C:C,'BASE DE PONTOS V+'!E:E) -> N/A | M104: =_xlfn.XLOOKUP(C104,'RESUMO DE PONTOS'!C:C,'RESUMO DE PONTOS'!L:L) -> Alto Impacto | N104: =C104 -> [P27] | O104: =I104 -> 100
C105: ='RESUMO DE PONTOS'!C36 -> [P28] | D105: =IFERROR(VLOOKUP(C105,'RESUMO DE PONTOS'!$C$9:$D$38,2,),"") -> Inexistência da ATA do Conselho Consultivo na Assembleia Geral Extraordinária | E105: =IFERROR(VLOOKUP($C105,'RESUMO DE PONTOS'!$C$9:$L$38,7,),"") -> Legal | F105: =VLOOKUP(E105,$C$30:$E$35,3,) -> 3 | G105: =_xlfn.XLOOKUP(D105,Planilha1!C:C,Planilha1!F:F) -> 3 | H105: =_xlfn.XLOOKUP(D105,Planilha1!C:C,Planilha1!G:G) -> 4 | I105: =F105*G105*H105 -> 36 | J105: =IFERROR(VLOOKUP(C105,'RESUMO DE PONTOS'!$C$9:$J$38,8,),"") -> Resumo das Atas | K105: =IF(I105>=75,"ALTO IMPACTO",IF(I105<=50,"BAIXO IMPACTO","MÉDIO IMPACTO")) -> BAIXO IMPACTO | L105: =_xlfn.XLOOKUP(D105,'BASE DE PONTOS V+'!C:C,'BASE DE PONTOS V+'!E:E) -> N/A | M105: =_xlfn.XLOOKUP(C105,'RESUMO DE PONTOS'!C:C,'RESUMO DE PONTOS'!L:L) -> médio impacto | N105: =C105 -> [P28] | O105: =I105 -> 36
B106: x | C106: ='RESUMO DE PONTOS'!C37 -> [P29] | D106: =IFERROR(VLOOKUP(C106,'RESUMO DE PONTOS'!$C$9:$D$38,2,),"") -> Impacto significativo com os inadimplentes | E106: =IFERROR(VLOOKUP($C106,'RESUMO DE PONTOS'!$C$9:$L$38,7,),"") -> Financeiro | F106: 3 | G106: =_xlfn.XLOOKUP(D106,Planilha1!C:C,Planilha1!F:F) -> 5 | H106: =_xlfn.XLOOKUP(D106,Planilha1!C:C,Planilha1!G:G) -> 5 | I106: =F106*G106*H106 -> 75 | J106: =IFERROR(VLOOKUP(C106,'RESUMO DE PONTOS'!$C$9:$J$38,8,),"") -> Teste de Inadimplência | K106: =IF(I106>=75,"ALTO IMPACTO",IF(I106<=50,"BAIXO IMPACTO","MÉDIO IMPACTO")) -> ALTO IMPACTO | L106: =_xlfn.XLOOKUP(D106,'BASE DE PONTOS V+'!C:C,'BASE DE PONTOS V+'!E:E) -> #N/A | M106: =_xlfn.XLOOKUP(C106,'RESUMO DE PONTOS'!C:C,'RESUMO DE PONTOS'!L:L) -> Alto Impacto | N106: =C106 -> [P29] | O106: =I106 -> 75

Sheet Planilha2

Sheet GRÁFICOS
H69: BAIXO IMPACTO | I69: =COUNTIF($F$70:$F$108,H69) -> 15 | J69: =I69/$I$72 -> 0.51724138
B70: ='BASE DA MATRIZ DE RISCOS'!E78 -> Legal | F70: ='BASE DA MATRIZ DE RISCOS'!K78 -> BAIXO IMPACTO | H70: MÉDIO IMPACTO | I70: =COUNTIF($F$70:$F$108,H70) -> 7 | J70: =I70/$I$72 -> 0.24137931
B71: ='BASE DA MATRIZ DE RISCOS'!E79 -> Financeiro | C71: Estratégico | D71: =COUNTIF($B$70:$B$98,C71) -> 2 | F71: ='BASE DA MATRIZ DE RISCOS'!K79 -> BAIXO IMPACTO | H71: ALTO IMPACTO | I71: =COUNTIF($F$70:$F$108,H71) -> 7 | J71: =I71/$I$72 -> 0.24137931
B72: ='BASE DA MATRIZ DE RISCOS'!E80 -> Operacional | C72: Financeiro | D72: =COUNTIF($B$70:$B$98,C72) -> 14 | F72: ='BASE DA MATRIZ DE RISCOS'!K80 -> BAIXO IMPACTO | I72: =SUM(I69:I71) -> 29
B73: ='BASE DA MATRIZ DE RISCOS'!E81 -> Operacional | C73: Operacional | D73: =COUNTIF($B$70:$B$98,C73) -> 3 | F73: ='BASE DA MATRIZ DE RISCOS'!K81 -> BAIXO IMPACTO
B74: ='BASE DA MATRIZ DE RISCOS'!E82 -> Financeiro | C74: Legal | D74: =COUNTIF($B$70:$B$98,C74) -> 10 | F74: ='BASE DA MATRIZ DE RISCOS'!K82 -> BAIXO IMPACTO
B75: ='BASE DA MATRIZ DE RISCOS'!E83 -> Financeiro | F75: ='BASE DA MATRIZ DE RISCOS'!K83 -> BAIXO IMPACTO
B76: ='BASE DA MATRIZ DE RISCOS'!E84 -> Legal | F76: ='BASE DA MATRIZ DE RISCOS'!K84 -> ALTO IMPACTO
B77: ='BASE DA MATRIZ DE RISCOS'!E85 -> Legal | F77: ='BASE DA MATRIZ DE RISCOS'!K85 -> MÉDIO IMPACTO
B78: ='BASE DA MATRIZ DE RISCOS'!E86 -> Legal | F78: ='BASE DA MATRIZ DE RISCOS'!K86 -> BAIXO IMPACTO
B79: ='BASE DA MATRIZ DE RISCOS'!E87 -> Estratégico | F79: ='BASE DA MATRIZ DE RISCOS'!K87 -> ALTO IMPACTO
B80: ='BASE DA MATRIZ DE RISCOS'!E88 -> Estratégico | F80: ='BASE DA MATRIZ DE RISCOS'!K88 -> ALTO IMPACTO
B81: ='BASE DA MATRIZ DE RISCOS'!E89 -> Legal | F81: ='BASE DA MATRIZ DE RISCOS'!K89 -> MÉDIO IMPACTO
B82: ='BASE DA MATRIZ DE RISCOS'!E90 -> Financeiro | F82: ='BASE DA MATRIZ DE RISCOS'!K90 -> BAIXO IMPACTO
B83: ='BASE DA MATRIZ DE RISCOS'!E91 -> Financeiro | F83: ='BASE DA MATRIZ DE RISCOS'!K91 -> BAIXO IMPACTO
B84: ='BASE DA MATRIZ DE RISCOS'!E92 -> Financeiro | F84: ='BASE DA MATRIZ DE RISCOS'!K92 -> BAIXO IMPACTO
B85: ='BASE DA MATRIZ DE RISCOS'!E93 -> Financeiro | F85: ='BASE DA MATRIZ DE RISCOS'!K93 -> ALTO IMPACTO
B86: ='BASE DA MATRIZ DE RISCOS'!E94 -> Financeiro | F86: ='BASE DA MATRIZ DE RISCOS'!K94 -> ALTO IMPACTO
... B98: ='BASE DA MATRIZ DE RISCOS'!E106 -> Financeiro | F98: ='BASE DA MATRIZ DE RISCOS'!K106 -> ALTO IMPACTO
B99: ='BASE DA MATRIZ DE RISCOS'!#REF! -> #REF! | F99: ='BASE DA MATRIZ DE RISCOS'!#REF! -> #REF!
B100: ='BASE DA MATRIZ DE RISCOS'!#REF! -> #REF! | F100: ='BASE DA MATRIZ DE RISCOS'!#REF! -> #REF!
B101: ='BASE DA MATRIZ DE RISCOS'!#REF! -> #REF! | F101: ='BASE DA MATRIZ DE RISCOS'!#REF! -> #REF!
B102: ='BASE DA MATRIZ DE RISCOS'!#REF! -> #REF! | F102: ='BASE DA MATRIZ DE RISCOS'!#REF! -> #REF!
B103: ='BASE DA MATRIZ DE RISCOS'!#REF! -> #REF! | F103: ='BASE DA MATRIZ DE RISCOS'!#REF! -> #REF!
B104: ='BASE DA MATRIZ DE RISCOS'!#REF! -> #REF! | F104: ='BASE DA MATRIZ DE RISCOS'!#REF! -> #REF!
B105: ='BASE DA MATRIZ DE RISCOS'!#REF! -> #REF! | F105: ='BASE DA MATRIZ DE RISCOS'!#REF! -> #REF!
B106: ='BASE DA MATRIZ DE RISCOS'!#REF! -> #REF! | F106: ='BASE DA MATRIZ DE RISCOS'!#REF! -> #REF! | K106: Matriz de Exposição ao Risco
B107: ='BASE DA MATRIZ DE RISCOS'!#REF! -> #REF! | F107: ='BASE DA MATRIZ DE RISCOS'!#REF! -> #REF! | K107: ='BASE DA MATRIZ DE RISCOS'!C78 -> [P1] | L107: ='BASE DA MATRIZ DE RISCOS'!I78 -> 48 | M107: =L107/$L$189 -> 0.027777778
B108: ='BASE DA MATRIZ DE RISCOS'!#REF! -> #REF! | F108: ='BASE DA MATRIZ DE RISCOS'!#REF! -> #REF! | K108: ='BASE DA MATRIZ DE RISCOS'!C79 -> [P2] | L108: ='BASE DA MATRIZ DE RISCOS'!I79 -> 45 | M108: =L108/$L$189 -> 0.026041667
B109: ='BASE DA MATRIZ DE RISCOS'!#REF! -> #REF! | F109: ='BASE DA MATRIZ DE RISCOS'!#REF! -> #REF! | K109: ='BASE DA MATRIZ DE RISCOS'!C80 -> [P3] | L109: ='BASE DA MATRIZ DE RISCOS'!I80 -> 24 | M109: =L109/$L$189 -> 0.013888889
B110: ='BASE DA MATRIZ DE RISCOS'!#REF! -> #REF! | F110: ='BASE DA MATRIZ DE RISCOS'!#REF! -> #REF! | K110: ='BASE DA MATRIZ DE RISCOS'!C81 -> [P4] | L110: ='BASE DA MATRIZ DE RISCOS'!I81 -> 40 | M110: =L110/$L$189 -> 0.023148148
B111: ='BASE DA MATRIZ DE RISCOS'!#REF! -> #REF! | F111: ='BASE DA MATRIZ DE RISCOS'!#REF! -> #REF! | K111: ='BASE DA MATRIZ DE RISCOS'!C82 -> [P5] | L111: ='BASE DA MATRIZ DE RISCOS'!I82 -> 12 | M111: =L111/$L$189 -> 0.0069444444
B112: ='BASE DA MATRIZ DE RISCOS'!#REF! -> #REF! | F112: ='BASE DA MATRIZ DE RISCOS'!#REF! -> #REF! | K112: ='BASE DA MATRIZ DE RISCOS'!C83 -> [P6] | L112: ='BASE DA MATRIZ DE RISCOS'!I83 -> 20 | M112: =L112/$L$189 -> 0.011574074
B113: ='BASE DA MATRIZ DE RISCOS'!E107 -> 0 | F113: ='BASE DA MATRIZ DE RISCOS'!K107 -> 0 | K113: ='BASE DA MATRIZ DE RISCOS'!C84 -> [P7] | L113: ='BASE DA MATRIZ DE RISCOS'!I84 -> 125 | M113: =L113/$L$189 -> 0.072337963
B114: ='BASE DA MATRIZ DE RISCOS'!E108 -> 0 | F114: ='BASE DA MATRIZ DE RISCOS'!K108 -> 0 | K114: ='BASE DA MATRIZ DE RISCOS'!C85 -> [P8] | L114: ='BASE DA MATRIZ DE RISCOS'!I85 -> 60 | M114: =L114/$L$189 -> 0.034722222
B115: ='BASE DA MATRIZ DE RISCOS'!E109 -> 0 | F115: ='BASE DA MATRIZ DE RISCOS'!K109 -> 0 | K115: ='BASE DA MATRIZ DE RISCOS'!C86 -> [P9] | L115: ='BASE DA MATRIZ DE RISCOS'!I86 -> 45 | M115: =L115/$L$189 -> 0.026041667
B116: ='BASE DA MATRIZ DE RISCOS'!E110 -> 0 | F116: ='BASE DA MATRIZ DE RISCOS'!K110 -> 0 | K116: ='BASE DA MATRIZ DE RISCOS'!C87 -> [P10] | L116: ='BASE DA MATRIZ DE RISCOS'!I87 -> 125 | M116: =L116/$L$189 -> 0.072337963
B117: ='BASE DA MATRIZ DE RISCOS'!E111 -> 0 | F117: ='BASE DA MATRIZ DE RISCOS'!K111 -> 0 | K117: ='BASE DA MATRIZ DE RISCOS'!C88 -> [P11] | L117: ='BASE DA MATRIZ DE RISCOS'!I88 -> 100 | M117: =L117/$L$189 -> 0.05787037
B118: ='BASE DA MATRIZ DE RISCOS'!E112 -> 0 | F118: ='BASE DA MATRIZ DE RISCOS'!K112 -> 0 | K118: ='BASE DA MATRIZ DE RISCOS'!C89 -> [P12] | L118: ='BASE DA MATRIZ DE RISCOS'!I89 -> 64 | M118: =L118/$L$189 -> 0.037037037
B119: ='BASE DA MATRIZ DE RISCOS'!E113 -> 0 | F119: ='BASE DA MATRIZ DE RISCOS'!K113 -> 0 | K119: ='BASE DA MATRIZ DE RISCOS'!C90 -> [P13] | L119: ='BASE DA MATRIZ DE RISCOS'!I90 -> 36 | M119: =L119/$L$189 -> 0.020833333
B120: ='BASE DA MATRIZ DE RISCOS'!E114 -> 0 | F120: ='BASE DA MATRIZ DE RISCOS'!K114 -> 0 | K120: ='BASE DA MATRIZ DE RISCOS'!C91 -> [P14] | L120: ='BASE DA MATRIZ DE RISCOS'!I91 -> 48 | M120: =L120/$L$189 -> 0.027777778
B121: ='BASE DA MATRIZ DE RISCOS'!E115 -> 0 | F121: ='BASE DA MATRIZ DE RISCOS'!K115 -> 0 | K121: ='BASE DA MATRIZ DE RISCOS'!C92 -> [P15] | L121: ='BASE DA MATRIZ DE RISCOS'!I92 -> 36 | M121: =L121/$L$189 -> 0.020833333
B122: ='BASE DA MATRIZ DE RISCOS'!E116 -> 0 | F122: ='BASE DA MATRIZ DE RISCOS'!K116 -> 0 | K122: ='BASE DA MATRIZ DE RISCOS'!C93 -> [P16] | L122: ='BASE DA MATRIZ DE RISCOS'!I93 -> 125 | M122: =L122/$L$189 -> 0.072337963
B123: ='BASE DA MATRIZ DE RISCOS'!E117 -> 0 | F123: ='BASE DA MATRIZ DE RISCOS'!K117 -> 0 | K123: ='BASE DA MATRIZ DE RISCOS'!C94 -> [P17] | L123: ='BASE DA MATRIZ DE RISCOS'!I94 -> 125 | M123: =L123/$L$189 -> 0.072337963
B124: ='BASE DA MATRIZ DE RISCOS'!E118 -> 0 | F124: ='BASE DA MATRIZ DE RISCOS'!K118 -> 0 | K124: ='BASE DA MATRIZ DE RISCOS'!C95 -> [P18] | L124: ='BASE DA MATRIZ DE RISCOS'!I95 -> 60 | M124: =L124/$L$189 -> 0.034722222
... B136: ='BASE DA MATRIZ DE RISCOS'!E130 -> 0 | F136: ='BASE DA MATRIZ DE RISCOS'!K130 -> 0 | K136: ='BASE DA MATRIZ DE RISCOS'!C107 -> 0 | L136: ='BASE DA MATRIZ DE RISCOS'!I107 -> 0 | M136: =L136/$L$189 -> 0
B137: ='BASE DA MATRIZ DE RISCOS'!E131 -> 0 | F137: ='BASE DA MATRIZ DE RISCOS'!K131 -> 0 | K137: ='BASE DA MATRIZ DE RISCOS'!C108 -> 0 | L137: ='BASE DA MATRIZ DE RISCOS'!I108 -> 0 | M137: =L137/$L$189 -> 0 | R137: Exposição | S137: Porcentagem | U137: Matriz de Exposição ao Risco | V137: Baixo | W137: Médio | X137: Alto
B138: ='BASE DA MATRIZ DE RISCOS'!E132 -> 0 | F138: ='BASE DA MATRIZ DE RISCOS'!K132 -> 0 | K138: ='BASE DA MATRIZ DE RISCOS'!C109 -> 0 | L138: ='BASE DA MATRIZ DE RISCOS'!I109 -> 0 | M138: =L138/$L$189 -> 0 | R138: 16 | S138: =R138/$R$170 -> 0.012769354 | U138: [P1] | V138: =IF(R138<=50,S138,"") -> 0.012769354 | W138: =IF(AND(R138>50,R138<75),S138,"") | X138: =IF(R138>=75,S138,"")
B139: ='BASE DA MATRIZ DE RISCOS'!E133 -> 0 | F139: ='BASE DA MATRIZ DE RISCOS'!K133 -> 0 | K139: ='BASE DA MATRIZ DE RISCOS'!C110 -> 0 | L139: ='BASE DA MATRIZ DE RISCOS'!I110 -> 0 | M139: =L139/$L$189 -> 0 | R139: 20 | S139: =R139/$R$170 -> 0.015961692 | U139: ='BASE DA MATRIZ DE RISCOS'!C79 -> [P2] | V139: =IF(R139<=50,S139,"") -> 0.015961692 | W139: =IF(AND(R139>50,R139<75),S139,"") | X139: =IF(R139>=75,S139,"")
B140: ='BASE DA MATRIZ DE RISCOS'!E134 -> 0 | F140: ='BASE DA MATRIZ DE RISCOS'!K134 -> 0 | K140: ='BASE DA MATRIZ DE RISCOS'!C111 -> 0 | L140: ='BASE DA MATRIZ DE RISCOS'!I111 -> 0 | M140: =L140/$L$189 -> 0 | R140: 16 | S140: =R140/$R$170 -> 0.012769354 | U140: ='BASE DA MATRIZ DE RISCOS'!C80 -> [P3] | V140: =IF(R140<=50,S140,"") -> 0.012769354 | W140: =IF(AND(R140>50,R140<75),S140,"") | X140: =IF(R140>=75,S140,"")
R141: 16 | S141: =R141/$R$170 -> 0.012769354 | U141: ='BASE DA MATRIZ DE RISCOS'!C81 -> [P4] | V141: =IF(R141<=50,S141,"") -> 0.012769354
R142: 9 | S142: =R142/$R$170 -> 0.0071827614 | U142: ='BASE DA MATRIZ DE RISCOS'!C82 -> [P5] | V142: =IF(R142<=50,S142,"") -> 0.0071827614
R143: 30 | S143: =R143/$R$170 -> 0.023942538 | U143: ='BASE DA MATRIZ DE RISCOS'!C83 -> [P6] | V143: =IF(R143<=50,S143,"") -> 0.023942538
R144: 3 | S144: =R144/$R$170 -> 0.0023942538 | U144: ='BASE DA MATRIZ DE RISCOS'!C84 -> [P7] | V144: =IF(R144<=50,S144,"") -> 0.0023942538
R145: 32 | S145: =R145/$R$170 -> 0.025538707 | U145: ='BASE DA MATRIZ DE RISCOS'!C85 -> [P8] | V145: =IF(R145<=50,S145,"") -> 0.025538707
R146: 125 | S146: =R146/$R$170 -> 0.099760575 | U146: ='BASE DA MATRIZ DE RISCOS'!C86 -> [P9] | V146: =IF(R146<=50,S146,"")
R147: 40 | S147: =R147/$R$170 -> 0.031923384 | U147: ='BASE DA MATRIZ DE RISCOS'!C87 -> [P10] | V147: =IF(R147<=50,S147,"") -> 0.031923384
R148: 30 | S148: =R148/$R$170 -> 0.023942538 | U148: ='BASE DA MATRIZ DE RISCOS'!C88 -> [P11] | V148: =IF(R148<=50,S148,"") -> 0.023942538
B149: ='BASE DA MATRIZ DE RISCOS'!E135 -> 0 | F149: ='BASE DA MATRIZ DE RISCOS'!K141 -> 0 | K149: ='BASE DA MATRIZ DE RISCOS'!C112 -> 0 | L149: ='BASE DA MATRIZ DE RISCOS'!I112 -> 0 | M149: =L149/$L$189 -> 0 | R149: 40 | S149: =R149/$R$170 -> 0.031923384 | U149: ='BASE DA MATRIZ DE RISCOS'!C89 -> [P12] | V149: =IF(R149<=50,S149,"") -> 0.031923384 | W149: =IF(AND(R149>50,R149<75),S149,"") | X149: =IF(R149>=75,S149,"")
B150: ='BASE DA MATRIZ DE RISCOS'!E136 -> 0 | K150: ='BASE DA MATRIZ DE RISCOS'!C113 -> 0 | L150: ='BASE DA MATRIZ DE RISCOS'!I113 -> 0 | M150: =L150/$L$189 -> 0 | R150: 40 | S150: =R150/$R$170 -> 0.031923384 | U150: ='BASE DA MATRIZ DE RISCOS'!C90 -> [P13] | V150: =IF(R150<=50,S150,"") -> 0.031923384 | W150: =IF(AND(R150>50,R150<75),S150,"") | X150: =IF(R150>=75,S150,"")
B151: ='BASE DA MATRIZ DE RISCOS'!E137 -> 0 | K151: ='BASE DA MATRIZ DE RISCOS'!C114 -> 0 | L151: ='BASE DA MATRIZ DE RISCOS'!I114 -> 0 | M151: =L151/$L$189 -> 0 | R151: 12 | S151: =R151/$R$170 -> 0.0095770152 | U151: ='BASE DA MATRIZ DE RISCOS'!C91 -> [P14] | V151: =IF(R151<=50,S151,"") -> 0.0095770152 | W151: =IF(AND(R151>50,R151<75),S151,"") | X151: =IF(R151>=75,S151,"")
B152: ='BASE DA MATRIZ DE RISCOS'!E138 -> 0 | K152: ='BASE DA MATRIZ DE RISCOS'!C115 -> 0 | L152: ='BASE DA MATRIZ DE RISCOS'!I115 -> 0 | M152: =L152/$L$189 -> 0 | R152: 16 | S152: =R152/$R$170 -> 0.012769354 | U152: ='BASE DA MATRIZ DE RISCOS'!C92 -> [P15] | V152: =IF(R152<=50,S152,"") -> 0.012769354 | W152: =IF(AND(R152>50,R152<75),S152,"") | X152: =IF(R152>=75,S152,"")
B153: ='BASE DA MATRIZ DE RISCOS'!E139 -> 0 | K153: ='BASE DA MATRIZ DE RISCOS'!C116 -> 0 | L153: ='BASE DA MATRIZ DE RISCOS'!I116 -> 0 | M153: =L153/$L$189 -> 0 | R153: 48 | S153: =R153/$R$170 -> 0.038308061 | U153: ='BASE DA MATRIZ DE RISCOS'!C93 -> [P16] | V153: =IF(R153<=50,S153,"") -> 0.038308061 | W153: =IF(AND(R153>50,R153<75),S153,"") | X153: =IF(R153>=75,S153,"")
B154: ='BASE DA MATRIZ DE RISCOS'!E140 -> 0 | K154: ='BASE DA MATRIZ DE RISCOS'!C117 -> 0 | L154: ='BASE DA MATRIZ DE RISCOS'!I117 -> 0 | M154: =L154/$L$189 -> 0 | R154: 60 | S154: =R154/$R$170 -> 0.047885076 | U154: ='BASE DA MATRIZ DE RISCOS'!C94 -> [P17] | V154: =IF(R154<=50,S154,"") | W154: =IF(AND(R154>50,R154<75),S154,"") -> 0.047885076 | X154: =IF(R154>=75,S154,"")
B155: ='BASE DA MATRIZ DE RISCOS'!E141 -> 0 | K155: ='BASE DA MATRIZ DE RISCOS'!C118 -> 0 | L155: ='BASE DA MATRIZ DE RISCOS'!I118 -> 0 | M155: =L155/$L$189 -> 0 | R155: 36 | S155: =R155/$R$170 -> 0.028731045 | U155: ='BASE DA MATRIZ DE RISCOS'!C95 -> [P18] | V155: =IF(R155<=50,S155,"") -> 0.028731045 | W155: =IF(AND(R155>50,R155<75),S155,"") | X155: =IF(R155>=75,S155,"")
B156: ='BASE DA MATRIZ DE RISCOS'!E142 -> 0 | K156: ='BASE DA MATRIZ DE RISCOS'!C119 -> 0 | L156: ='BASE DA MATRIZ DE RISCOS'!I119 -> 0 | M156: =L156/$L$189 -> 0 | R156: 48 | S156: =R156/$R$170 -> 0.038308061 | U156: ='BASE DA MATRIZ DE RISCOS'!C96 -> [P19] | V156: =IF(R156<=50,S156,"") -> 0.038308061 | W156: =IF(AND(R156>50,R156<75),S156,"") | X156: =IF(R156>=75,S156,"")
B157: ='BASE DA MATRIZ DE RISCOS'!E143 -> 0 | K157: ='BASE DA MATRIZ DE RISCOS'!C120 -> 0 | L157: ='BASE DA MATRIZ DE RISCOS'!I120 -> 0 | M157: =L157/$L$189 -> 0 | R157: 40 | S157: =R157/$R$170 -> 0.031923384 | U157: ='BASE DA MATRIZ DE RISCOS'!C97 -> [P20] | V157: =IF(R157<=50,S157,"") -> 0.031923384 | W157: =IF(AND(R157>50,R157<75),S157,"") | X157: =IF(R157>=75,S157,"")
B158: ='BASE DA MATRIZ DE RISCOS'!E144 -> 0 | K158: ='BASE DA MATRIZ DE RISCOS'!C121 -> 0 | L158: ='BASE DA MATRIZ DE RISCOS'!I121 -> 0 | M158: =L158/$L$189 -> 0 | R158: 40 | S158: =R158/$R$170 -> 0.031923384 | U158: ='BASE DA MATRIZ DE RISCOS'!C98 -> [P21] | V158: =IF(R158<=50,S158,"") -> 0.031923384 | W158: =IF(AND(R158>50,R158<75),S158,"") | X158: =IF(R158>=75,S158,"")
B159: ='BASE DA MATRIZ DE RISCOS'!E145 -> 0 | K159: ='BASE DA MATRIZ DE RISCOS'!C122 -> 0 | L159: ='BASE DA MATRIZ DE RISCOS'!I122 -> 0 | M159: =L159/$L$189 -> 0 | R159: 100 | S159: =R159/$R$170 -> 0.07980846 | U159: ='BASE DA MATRIZ DE RISCOS'!C99 -> [P22] | V159: =IF(R159<=50,S159,"") | W159: =IF(AND(R159>50,R159<75),S159,"") | X159: =IF(R159>=75,S159,"") -> 0.07980846
B160: ='BASE DA MATRIZ DE RISCOS'!E146 -> 0 | K160: ='BASE DA MATRIZ DE RISCOS'!C123 -> 0 | L160: ='BASE DA MATRIZ DE RISCOS'!I123 -> 0 | M160: =L160/$L$189 -> 0 | R160: 100 | S160: =R160/$R$170 -> 0.07980846 | U160: ='BASE DA MATRIZ DE RISCOS'!C100 -> [P23] | V160: =IF(R160<=50,S160,"") | W160: =IF(AND(R160>50,R160<75),S160,"") | X160: =IF(R160>=75,S160,"") -> 0.07980846
B161: ='BASE DA MATRIZ DE RISCOS'!E147 -> 0 | K161: ='BASE DA MATRIZ DE RISCOS'!C124 -> 0 | L161: ='BASE DA MATRIZ DE RISCOS'!I124 -> 0 | M161: =L161/$L$189 -> 0 | R161: 40 | S161: =R161/$R$170 -> 0.031923384 | U161: ='BASE DA MATRIZ DE RISCOS'!C101 -> [P24] | V161: =IF(R161<=50,S161,"") -> 0.031923384 | W161: =IF(AND(R161>50,R161<75),S161,"") | X161: =IF(R161>=75,S161,"")
... B165: ='BASE DA MATRIZ DE RISCOS'!E151 -> 0 | K165: ='BASE DA MATRIZ DE RISCOS'!C128 -> 0 | L165: ='BASE DA MATRIZ DE RISCOS'!I128 -> 0 | M165: =L165/$L$189 -> 0 | R165: 12 | S165: =R165/$R$170 -> 0.0095770152 | U165: ='BASE DA MATRIZ DE RISCOS'!C105 -> [P28] | V165: =IF(R165<=50,S165,"") -> 0.0095770152 | W165: =IF(AND(R165>50,R165<75),S165,"") | X165: =IF(R165>=75,S165,"")
B166: ='BASE DA MATRIZ DE RISCOS'!E152 -> 0 | K166: ='BASE DA MATRIZ DE RISCOS'!C129 -> 0 | L166: ='BASE DA MATRIZ DE RISCOS'!I129 -> 0 | M166: =L166/$L$189 -> 0 | R166: 100 | S166: =R166/$R$170 -> 0.07980846 | U166: ='BASE DA MATRIZ DE RISCOS'!C106 -> [P29] | V166: =IF(R166<=50,S166,"") | W166: =IF(AND(R166>50,R166<75),S166,"") | X166: =IF(R166>=75,S166,"") -> 0.07980846 | AV166: 239.99
B167: ='BASE DA MATRIZ DE RISCOS'!E153 -> 0 | K167: ='BASE DA MATRIZ DE RISCOS'!C130 -> 0 | L167: ='BASE DA MATRIZ DE RISCOS'!I130 -> 0 | M167: =L167/$L$189 -> 0 | X167: =IF(R167>=75,S167,"") | AV167: 5
B168: ='BASE DA MATRIZ DE RISCOS'!E154 -> 0 | K168: ='BASE DA MATRIZ DE RISCOS'!C131 -> 0 | L168: ='BASE DA MATRIZ DE RISCOS'!I131 -> 0 | M168: =L168/$L$189 -> 0 | X168: =IF(R168>=75,S168,"") | AV168: 19.2
K169: ='BASE DA MATRIZ DE RISCOS'!C138 -> 0 | L169: ='BASE DA MATRIZ DE RISCOS'!I138 -> 0 | M169: =L169/$L$189 -> 0
K170: ='BASE DA MATRIZ DE RISCOS'!C139 -> 0 | L170: ='BASE DA MATRIZ DE RISCOS'!I139 -> 0 | M170: =L170/$L$189 -> 0 | R170: =SUM(R138:R169) -> 1253 | AV170: =SUM(AV166:AV169) -> 264.19
K171: ='BASE DA MATRIZ DE RISCOS'!C140 -> 0 | L171: ='BASE DA MATRIZ DE RISCOS'!I140 -> 0 | M171: =L171/$L$189 -> 0
K172: ='BASE DA MATRIZ DE RISCOS'!C141 -> 0 | L172: ='BASE DA MATRIZ DE RISCOS'!I141 -> 0 | M172: =L172/$L$189 -> 0
K173: ='BASE DA MATRIZ DE RISCOS'!C142 -> 0 | L173: ='BASE DA MATRIZ DE RISCOS'!I142 -> 0 | M173: =L173/$L$189 -> 0
K174: ='BASE DA MATRIZ DE RISCOS'!C143 -> 0 | L174: ='BASE DA MATRIZ DE RISCOS'!I143 -> 0 | M174: =L174/$L$189 -> 0
K175: ='BASE DA MATRIZ DE RISCOS'!C144 -> 0 | L175: ='BASE DA MATRIZ DE RISCOS'!I144 -> 0 | M175: =L175/$L$189 -> 0
K176: ='BASE DA MATRIZ DE RISCOS'!C145 -> 0 | L176: ='BASE DA MATRIZ DE RISCOS'!I145 -> 0 | M176: =L176/$L$189 -> 0
K177: ='BASE DA MATRIZ DE RISCOS'!C146 -> 0 | L177: ='BASE DA MATRIZ DE RISCOS'!I146 -> 0 | M177: =L177/$L$189 -> 0
K178: ='BASE DA MATRIZ DE RISCOS'!C147 -> 0 | L178: ='BASE DA MATRIZ DE RISCOS'!I147 -> 0 | M178: =L178/$L$189 -> 0
K179: ='BASE DA MATRIZ DE RISCOS'!C148 -> 0 | L179: ='BASE DA MATRIZ DE RISCOS'!I148 -> 0 | M179: =L179/$L$189 -> 0
K180: ='BASE DA MATRIZ DE RISCOS'!C149 -> 0 | L180: ='BASE DA MATRIZ DE RISCOS'!I149 -> 0 | M180: =L180/$L$189 -> 0
K181: ='BASE DA MATRIZ DE RISCOS'!C150 -> 0 | L181: ='BASE DA MATRIZ DE RISCOS'!I150 -> 0 | M181: =L181/$L$189 -> 0
K182: ='BASE DA MATRIZ DE RISCOS'!C151 -> 0 | L182: ='BASE DA MATRIZ DE RISCOS'!I151 -> 0 | M182: =L182/$L$189 -> 0
... K187: ='BASE DA MATRIZ DE RISCOS'!C156 -> 0 | L187: ='BASE DA MATRIZ DE RISCOS'!I156 -> 0 | M187: =L187/$L$189 -> 0
L189: =SUM(L107:L188) -> 1728

Sheet P1
B2: Pontos de Controle
B3: Item | C3: Descrição
B4: Impacto | C4: =IF(C12>=75,"ALTO IMPACTO",IF(C12<=50,"BAIXO IMPACTO","MÉDIO IMPACTO")) -> BAIXO IMPACTO | E4: <<<<<< Automático conforme Metodologia e baseado no grau de exposição
B5: Status | C5: =IFERROR(VLOOKUP(C6,'RESUMO DE PONTOS'!$C$9:$M$64,11,),"") -> • 08/11/2022 • Novo ■ Vorcon Auditoria & Consultoria
B6: Código | C6: [P1]
B7: Título | C7: =VLOOKUP(C6,'BASE DA MATRIZ DE RISCOS'!$C$78:$D$202,2,) -> Pagamento sem documento fiscal
B8: Tipo | C8: =VLOOKUP(C6,'BASE DA MATRIZ DE RISCOS'!$C$78:$E$202,3,) -> Legal
B9: Tipo | C9: =VLOOKUP(C6,'BASE DA MATRIZ DE RISCOS'!$C$78:$H$202,4,) -> 3 | E9: <<<<<< Automático - Valores de 1 a 5 conforme metodologia
B10: Probabilidade | C10: =VLOOKUP(C6,'BASE DA MATRIZ DE RISCOS'!$C$78:$H$202,5,) -> 4 | E10: <<<<<< Valores de 1 a 5 conforme metodologia
B11: Impacto | C11: =VLOOKUP(C6,'BASE DA MATRIZ DE RISCOS'!$C$78:$H$202,6,) -> 2 | E11: <<<<<< Valores de 1 a 5 conforme metodologia
B12: Exposição | C12: =C9*C10*C11 -> 24 | E12: <<<<<< Calculado
B13: Testes/Áreas | C13: =VLOOKUP(C6,'BASE DA MATRIZ DE RISCOS'!$C$78:$J$202,8,) -> Voucher documental | E13: <<<<<< Automático - conforme Matriz de Risco
B14: Descrição | C14: =VLOOKUP(C$6,'RESUMO DE PONTOS'!$C$9:$H$64,3,) -> Verificamos que ocorreram gastos sem a respectiva emissão de documento fiscal pelos fornecedores e/ou prestadores de serviços.
B15: Riscos e Implicações | C15: =IFERROR(VLOOKUP(C$6,'RESUMO DE PONTOS'!$C$9:$H$64,4,),"") -> Pagamentos sem os respectivos documentos fiscais dos fornecedores/prestadores de serviços não são permitidos pela legislação brasileira, assim como Convenção e Regimento Interno do Condomínio. Dessa forma, o mesmo pode ser multado e/ou sofrer outras penalidades impostas pelo fisco.
B16: Impacto Financeiro | C16: =IFERROR(VLOOKUP(C$6,'RESUMO DE PONTOS'!$C$9:$H$64,5,),"") -> 17679.82
B17: Recomendações | C17: =IFERROR(VLOOKUP(C$6,'RESUMO DE PONTOS'!$C$9:$H$64,6,),"") -> Sugerimos que seja solicitado aos respectivos fornecedores/ prestadores de serviços a nota fiscal pelo fornecimento de material ou de prestação de serviço.
B18: Comentários da Administração | C18: Resposta da Administração sobre o ponto identificado e sobre as ações de melhoria sugeridas e, eventualmente, esclarecimento das prioridades recomendadas.
B19: Ações a serem Implementadas pela Administração | C19: Ações definidas pela Administração para resolução do ponto identificado.
B20: Data Limite para Resolução do Ponto Identificado | C20: Prazo estipulado pela Administração para que o ponto identificado deixe de existir.

Sheet P2
B2: Pontos de Controle
B3: Item | C3: Descrição
B4: Impacto | C4: =IF(C12>=75,"ALTO IMPACTO",IF(C12<=50,"BAIXO IMPACTO","MÉDIO IMPACTO")) -> BAIXO IMPACTO | E4: <<<<<< Automático conforme Metodologia e baseado no grau de exposição
B5: Status | C5: =IFERROR(VLOOKUP(C6,'RESUMO DE PONTOS'!$C$9:$M$64,11,),"") -> • 08/11/2022 • Novo ■ Vorcon Auditoria & Consultoria
B6: Código | C6: [P2] | E6: <<<<<< Lista Suspensa (Selecionar)
B7: Título | C7: =VLOOKUP(C6,'BASE DA MATRIZ DE RISCOS'!$C$78:$D$202,2,) -> Pagamentos realizados sem os respectivos comprovantes de pagamento anexados
B8: Tipo | C8: =VLOOKUP(C6,'BASE DA MATRIZ DE RISCOS'!$C$78:$E$202,3,) -> Financeiro | E8: <<<<<< Lista Suspensa (Selecionar)
B9: Tipo | C9: =VLOOKUP(C6,'BASE DA MATRIZ DE RISCOS'!$C$78:$H$202,4,) -> 5 | E9: <<<<<< Automático - Valores de 1 a 5 conforme metodologia
B10: Probabilidade | C10: =VLOOKUP(C6,'BASE DA MATRIZ DE RISCOS'!$C$78:$H$202,5,) -> 3 | E10: <<<<<< Valores de 1 a 5 conforme metodologia
B11: Impacto | C11: =VLOOKUP(C6,'BASE DA MATRIZ DE RISCOS'!$C$78:$H$202,6,) -> 1 | E11: <<<<<< Valores de 1 a 5 conforme metodologia
B12: Exposição | C12: =C9*C10*C11 -> 15 | E12: <<<<<< Calculado
B13: Testes/Áreas | C13: =VLOOKUP(C6,'BASE DA MATRIZ DE RISCOS'!$C$78:$J$202,8,) -> Voucher documental | E13: <<<<<< Automático - conforme Matriz de Risco
B14: Descrição | C14: =VLOOKUP(C$6,'RESUMO DE PONTOS'!$C$9:$H$64,3,) -> Constatamos que alguns pagamentos foram realizados sem que fossem anexados os respectivos comprovantes de pagamentos ou documentos equivalentes dando a respectiva quitação.
B15: Riscos e Implicações | C15: =IFERROR(VLOOKUP(C$6,'RESUMO DE PONTOS'!$C$9:$H$64,4,),"") -> Possibilidade de pagamento duplicado dos valores, ou caso haja a solicitação dos comprovantes de pagamentos o Condomínio não os possua.
B16: Impacto Financeiro | C16: =IFERROR(VLOOKUP(C$6,'RESUMO DE PONTOS'!$C$9:$H$64,5,),"") -> 1558.24
B17: Recomendações | C17: =IFERROR(VLOOKUP(C$6,'RESUMO DE PONTOS'!$C$9:$H$64,6,),"") -> Sugerimos que sejam criados controles para que os comprovantes de pagamentos estejam anexados com seus respectivos documentos.
B18: Comentários da Administração | C18: Resposta da Administração sobre o ponto identificado e sobre as ações de melhoria sugeridas e, eventualmente, esclarecimento das prioridades recomendadas.
B19: Ações a serem Implementadas pela Administração | C19: Ações definidas pela Administração para resolução do ponto identificado.
B20: Data Limite para Resolução do Ponto Identificado | C20: Prazo estipulado pela Administração para que o ponto identificado deixe de existir.

Sheet P3
B2: Pontos de Controle
B3: Item | C3: Descrição
B4: Impacto | C4: =IF(C12>=75,"ALTO IMPACTO",IF(C12<=50,"BAIXO IMPACTO","MÉDIO IMPACTO")) -> BAIXO IMPACTO | E4: <<<<<< Automático conforme Metodologia e baseado no grau de exposição
B5: Status | C5: =IFERROR(VLOOKUP(C6,'RESUMO DE PONTOS'!$C$9:$M$64,11,),"") -> • 08/11/2022 • Novo ■ Vorcon Auditoria & Consultoria
B6: Código | C6: [P3] | E6: <<<<<< Lista Suspensa (Selecionar)
B7: Título | C7: Negligência na gestão dos Documentos que compõe os Demonstrativos
B8: Tipo | C8: =VLOOKUP(C6,'BASE DA MATRIZ DE RISCOS'!$C$78:$E$202,3,) -> Operacional | E8: <<<<<< Lista Suspensa (Selecionar)
B9: Tipo | C9: =VLOOKUP(C6,'BASE DA MATRIZ DE RISCOS'!$C$78:$H$202,4,) -> 4 | E9: <<<<<< Automático - Valores de 1 a 5 conforme metodologia
B10: Probabilidade | C10: =VLOOKUP(C6,'BASE DA MATRIZ DE RISCOS'!$C$78:$H$202,5,) -> 3 | E10: <<<<<< Valores de 1 a 5 conforme metodologia
B11: Impacto | C11: =VLOOKUP(C6,'BASE DA MATRIZ DE RISCOS'!$C$78:$H$202,6,) -> 1 | E11: <<<<<< Valores de 1 a 5 conforme metodologia
B12: Exposição | C12: =C9*C10*C11 -> 12 | E12: <<<<<< Calculado
B13: Testes/Áreas | C13: =VLOOKUP(C6,'BASE DA MATRIZ DE RISCOS'!$C$78:$J$202,8,) -> Voucher documental | E13: <<<<<< Automático - conforme Matriz de Risco
B14: Descrição | C14: =VLOOKUP(C$6,'RESUMO DE PONTOS'!$C$9:$H$64,3,) -> Verificamos que alguns comprovantes não estão sendo arquivados com os cuidados necessários, com isso alguns estão ilegíveis.
B15: Riscos e Implicações | C15: =IFERROR(VLOOKUP(C$6,'RESUMO DE PONTOS'!$C$9:$H$64,4,),"") -> Possível dificuldade e/ou impossibilidade na visualização dos gastos e dúvidas quanto a possíveis consultas no futuro em função do estado dos documentos.
B16: Impacto Financeiro | C16: =IFERROR(VLOOKUP(C$6,'RESUMO DE PONTOS'!$C$9:$H$64,5,),"") -> 118.82
B17: Recomendações | C17: =IFERROR(VLOOKUP(C$6,'RESUMO DE PONTOS'!$C$9:$H$64,6,),"") -> Sugerimos aperfeiçoamento dos controles internos para que no momento do recebimento das documentações sejam retiradas as cópias ou ocorram as digitalizações visando preservar as informações.
B18: Comentários da Administração | C18: Resposta da Administração sobre o ponto identificado e sobre as ações de melhoria sugeridas e, eventualmente, esclarecimento das prioridades recomendadas.
B19: Ações a serem Implementadas pela Administração | C19: Ações definidas pela Administração para resolução do ponto identificado.
B20: Data Limite para Resolução do Ponto Identificado | C20: Prazo estipulado pela Administração para que o ponto identificado deixe de existir.

Sheet P4
B2: Pontos de Controle
B3: Item | C3: Descrição
B4: Impacto | C4: =IF(C12>=75,"ALTO IMPACTO",IF(C12<=50,"BAIXO IMPACTO","MÉDIO IMPACTO")) -> BAIXO IMPACTO | E4: <<<<<< Automático conforme Metodologia e baseado no grau de exposição
B5: Status | C5: =IFERROR(VLOOKUP(C6,'RESUMO DE PONTOS'!$C$9:$M$64,11,),"") -> • 08/11/2022 • Novo ■ Vorcon Auditoria & Consultoria
B6: Código | C6: [P4] | E6: <<<<<< Lista Suspensa (Selecionar)
B7: Título | C7: =VLOOKUP(C6,'BASE DA MATRIZ DE RISCOS'!$C$78:$D$202,2,) -> Conjunto de documentos anexados fora do mês correspondente no Balancete.
B8: Tipo | C8: =VLOOKUP(C6,'BASE DA MATRIZ DE RISCOS'!$C$78:$E$202,3,) -> Operacional | E8: <<<<<< Lista Suspensa (Selecionar)
B9: Tipo | C9: =VLOOKUP(C6,'BASE DA MATRIZ DE RISCOS'!$C$78:$H$202,4,) -> 4 | E9: <<<<<< Automático - Valores de 1 a 5 conforme metodologia
B10: Probabilidade | C10: =VLOOKUP(C6,'BASE DA MATRIZ DE RISCOS'!$C$78:$H$202,5,) -> 1 | E10: <<<<<< Valores de 1 a 5 conforme metodologia
B11: Impacto | C11: =VLOOKUP(C6,'BASE DA MATRIZ DE RISCOS'!$C$78:$H$202,6,) -> 1 | E11: <<<<<< Valores de 1 a 5 conforme metodologia
B12: Exposição | C12: =C9*C10*C11 -> 4 | E12: <<<<<< Calculado
B13: Testes/Áreas | C13: =VLOOKUP(C6,'BASE DA MATRIZ DE RISCOS'!$C$78:$J$202,8,) -> Voucher documental | E13: <<<<<< Automático - conforme Matriz de Risco
B14: Descrição | C14: =VLOOKUP(C$6,'RESUMO DE PONTOS'!$C$9:$H$64,3,) -> Desorganização da documentação suporte dificultam a análise de todas as partes envolvidas.
B15: Riscos e Implicações | C15: Possibilidade de pagamento duplicado dos valores, ou caso haja a solicitação do comprovante de pagamento o Condomínio não os possua.
B16: Impacto Financeiro | C16: =IFERROR(VLOOKUP(C$6,'RESUMO DE PONTOS'!$C$9:$H$64,5,),"") -> 418.07
B17: Recomendações | C17: Sugerimos que sejam criados controles para que os comprovantes de pagamentos estejam anexados ao processo de pagamentos.
B18: Comentários da Administração | C18: Resposta da Administração sobre o ponto identificado e sobre as ações de melhoria sugeridas e, eventualmente, esclarecimento das prioridades recomendadas.
B19: Ações a serem Implementadas pela Administração | C19: Ações definidas pela Administração para resolução do ponto identificado.
B20: Data Limite para Resolução do Ponto Identificado | C20: Prazo estipulado pela Administração para que o ponto identificado deixe de existir.

Sheet P5
B2: Pontos de Controle
B3: Item | C3: Descrição
B4: Impacto | C4: =IF(C12>=75,"ALTO IMPACTO",IF(C12<=50,"BAIXO IMPACTO","MÉDIO IMPACTO")) -> BAIXO IMPACTO | E4: <<<<<< Automático conforme Metodologia e baseado no grau de exposição
B5: Status | C5: =IFERROR(VLOOKUP(C6,'RESUMO DE PONTOS'!$C$9:$M$64,11,),"") -> • 08/11/2022 • Novo ■ Vorcon Auditoria & Consultoria
B6: Código | C6: [P5] | E6: <<<<<< Lista Suspensa (Selecionar)
B7: Título | C7: =VLOOKUP(C6,'BASE DA MATRIZ DE RISCOS'!$C$78:$D$202,2,) -> Informações apresentado fora do mês correspondente na demonstração financeira.
B8: Tipo | C8: =VLOOKUP(C6,'BASE DA MATRIZ DE RISCOS'!$C$78:$E$202,3,) -> Financeiro | E8: <<<<<< Lista Suspensa (Selecionar)
B9: Tipo | C9: =VLOOKUP(C6,'BASE DA MATRIZ DE RISCOS'!$C$78:$H$202,4,) -> 5 | E9: <<<<<< Automático - Valores de 1 a 5 conforme metodologia
B10: Probabilidade | C10: =VLOOKUP(C6,'BASE DA MATRIZ DE RISCOS'!$C$78:$H$202,5,) -> 1 | E10: <<<<<< Valores de 1 a 5 conforme metodologia
B11: Impacto | C11: =VLOOKUP(C6,'BASE DA MATRIZ DE RISCOS'!$C$78:$H$202,6,) -> 1 | E11: <<<<<< Valores de 1 a 5 conforme metodologia
B12: Exposição | C12: =C9*C10*C11 -> 5 | E12: <<<<<< Calculado
B13: Testes/Áreas | C13: =VLOOKUP(C6,'BASE DA MATRIZ DE RISCOS'!$C$78:$J$202,8,) -> Voucher documental | E13: <<<<<< Automático - conforme Matriz de Risco
B14: Descrição | C14: =VLOOKUP(C$6,'RESUMO DE PONTOS'!$C$9:$H$64,3,) -> Verificamos que há desorganização das informações na demonstração financeira que dificultam na análise de todas as partes envolvidas.
B15: Riscos e Implicações | C15: =IFERROR(VLOOKUP(C$6,'RESUMO DE PONTOS'!$C$9:$H$64,4,),"") -> A falta de apresentação de maneira tempestiva das informações financeiras poderá afetar diretamente o controle financeiro do condomínio e o entendimento dos Demonstrativos.
B16: Impacto Financeiro | C16: =IFERROR(VLOOKUP(C$6,'RESUMO DE PONTOS'!$C$9:$H$64,5,),"") -> 418.07
B17: Recomendações | C17: =IFERROR(VLOOKUP(C$6,'RESUMO DE PONTOS'!$C$9:$H$64,6,),"") -> Indicamos que as informações apresentadas nas Demonstrações Financeiras sejam realizadas conforme o período correspondente.
B18: Comentários da Administração | C18: Resposta da Administração sobre o ponto identificado e sobre as ações de melhoria sugeridas e, eventualmente, esclarecimento das prioridades recomendadas.
B19: Ações a serem Implementadas pela Administração | C19: Ações definidas pela Administração para resolução do ponto identificado.
B20: Data Limite para Resolução do Ponto Identificado | C20: Prazo estipulado pela Administração para que o ponto identificado deixe de existir.

Sheet P6
B2: Pontos de Controle
B3: Item | C3: Descrição
B4: Impacto | C4: =IF(C12>=75,"ALTO IMPACTO",IF(C12<=50,"BAIXO IMPACTO","MÉDIO IMPACTO")) -> BAIXO IMPACTO | E4: <<<<<< Automático conforme Metodologia e baseado no grau de exposição
B5: Status | C5: =IFERROR(VLOOKUP(C6,'RESUMO DE PONTOS'!$C$9:$M$64,11,),"") -> • 08/11/2022 • Novo ■ Vorcon Auditoria & Consultoria
B6: Código | C6: [P6] | E6: <<<<<< Lista Suspensa (Selecionar)
B7: Título | C7: =VLOOKUP(C6,'BASE DA MATRIZ DE RISCOS'!$C$78:$D$202,2,) -> Diferenças entre: Valor do comprovante de pagamento X Valor da documentação suporte.
B8: Tipo | C8: =VLOOKUP(C6,'BASE DA MATRIZ DE RISCOS'!$C$78:$E$202,3,) -> Financeiro | E8: <<<<<< Lista Suspensa (Selecionar)
B9: Tipo | C9: =VLOOKUP(C6,'BASE DA MATRIZ DE RISCOS'!$C$78:$H$202,4,) -> 5 | E9: <<<<<< Automático - Valores de 1 a 5 conforme metodologia
B10: Probabilidade | C10: =VLOOKUP(C6,'BASE DA MATRIZ DE RISCOS'!$C$78:$H$202,5,) -> 3 | E10: <<<<<< Valores de 1 a 5 conforme metodologia
B11: Impacto | C11: =VLOOKUP(C6,'BASE DA MATRIZ DE RISCOS'!$C$78:$H$202,6,) -> 1 | E11: <<<<<< Valores de 1 a 5 conforme metodologia
B12: Exposição | C12: =C9*C10*C11 -> 15 | E12: <<<<<< Calculado
B13: Testes/Áreas | C13: =VLOOKUP(C6,'BASE DA MATRIZ DE RISCOS'!$C$78:$J$202,8,) -> Voucher documental | E13: <<<<<< Automático - conforme Matriz de Risco
B14: Descrição | C14: =VLOOKUP(C$6,'RESUMO DE PONTOS'!$C$9:$H$64,3,) -> Verificamos que alguns pagamentos foram realizados após a data de vencimento acarretando em gastos adicionais.
B15: Riscos e Implicações | C15: =IFERROR(VLOOKUP(C$6,'RESUMO DE PONTOS'!$C$9:$H$64,4,),"") -> Possibilidade do condomínio incorrer em gastos desnecessários
B16: Impacto Financeiro | C16: =IFERROR(VLOOKUP(C$6,'RESUMO DE PONTOS'!$C$9:$H$64,5,),"") -> 10.37
B17: Recomendações | C17: =IFERROR(VLOOKUP(C$6,'RESUMO DE PONTOS'!$C$9:$H$64,6,),"") -> Sugerimos que seja elaborado um controle de vencimento das despesas e que sejam efetuados os pagamentos até o vencimento.
B18: Comentários da Administração | C18: Resposta da Administração sobre o ponto identificado e sobre as ações de melhoria sugeridas e, eventualmente, esclarecimento das prioridades recomendadas.
B19: Ações a serem Implementadas pela Administração | C19: Ações definidas pela Administração para resolução do ponto identificado.
B20: Data Limite para Resolução do Ponto Identificado | C20: Prazo estipulado pela Administração para que o ponto identificado deixe de existir.

Sheet P7
B2: Pontos de Controle
B3: Item | C3: Descrição
B4: Impacto | C4: =IF(C12>=75,"ALTO IMPACTO",IF(C12<=50,"BAIXO IMPACTO","MÉDIO IMPACTO")) -> BAIXO IMPACTO | E4: <<<<<< Automático conforme Metodologia e baseado no grau de exposição
B5: Status | C5: =IFERROR(VLOOKUP(C6,'RESUMO DE PONTOS'!$C$9:$M$64,11,),"") -> • 08/11/2022 • Novo ■ Vorcon Auditoria & Consultoria
B6: Código | C6: [P7] | E6: <<<<<< Lista Suspensa (Selecionar)
B7: Título | C7: =VLOOKUP(C6,'BASE DA MATRIZ DE RISCOS'!$C$78:$D$202,2,) -> Pagamentos realizados antes da emissão da nota fiscal.
B8: Tipo | C8: =VLOOKUP(C6,'BASE DA MATRIZ DE RISCOS'!$C$78:$E$202,3,) -> Legal | E8: <<<<<< Lista Suspensa (Selecionar)
B9: Tipo | C9: =VLOOKUP($C$8,'BASE DA MATRIZ DE RISCOS'!$C$30:$E$35,3) -> 5 | E9: <<<<<< Automático - Valores de 1 a 5 conforme metodologia
B10: Probabilidade | C10: =VLOOKUP(C6,'BASE DA MATRIZ DE RISCOS'!$C$78:$H$202,5,) -> 3 | E10: <<<<<< Valores de 1 a 5 conforme metodologia
B11: Impacto | C11: =VLOOKUP(C6,'BASE DA MATRIZ DE RISCOS'!$C$78:$H$202,6,) -> 1 | E11: <<<<<< Valores de 1 a 5 conforme metodologia
B12: Exposição | C12: =C9*C10*C11 -> 15 | E12: <<<<<< Calculado
B13: Testes/Áreas | C13: =VLOOKUP(C6,'BASE DA MATRIZ DE RISCOS'!$C$78:$J$202,8,) -> Voucher documental | E13: <<<<<< Automático - conforme Matriz de Risco
B14: Descrição | C14: =VLOOKUP(C$6,'RESUMO DE PONTOS'!$C$9:$H$64,3,) -> Verificamos que ocorreram pagamentos onde a emissão da documentação fiscal é posterior a data em que a transação bancária foi realizada.
B15: Riscos e Implicações | C15: =IFERROR(VLOOKUP(C$6,'RESUMO DE PONTOS'!$C$9:$H$64,4,),"") -> O pagamento antes da emissão das notas fiscais traz uma vulnerabilidade a respeito do cumprimento das melhores práticas de gestão podendo gerar penalidades tributárias.
B16: Impacto Financeiro | C16: =IFERROR(VLOOKUP(C$6,'RESUMO DE PONTOS'!$C$9:$H$64,5,),"") -> 3563.16
B17: Recomendações | C17: =IFERROR(VLOOKUP(C$6,'RESUMO DE PONTOS'!$C$9:$H$64,6,),"") -> Recomendamos que seja verificada a emissão da nota fiscal antes da realização do pagamento.
B18: Comentários da Administração | C18: Resposta da Administração sobre o ponto identificado e sobre as ações de melhoria sugeridas e, eventualmente, esclarecimento das prioridades recomendadas.
B19: Ações a serem Implementadas pela Administração | C19: Ações definidas pela Administração para resolução do ponto identificado.
B20: Data Limite para Resolução do Ponto Identificado | C20: Prazo estipulado pela Administração para que o ponto identificado deixe de existir.

Sheet P8
B2: Pontos de Controle
B3: Item | C3: Descrição
B4: Impacto | C4: =IF(C12>=75,"ALTO IMPACTO",IF(C12<=50,"BAIXO IMPACTO","MÉDIO IMPACTO")) -> ALTO IMPACTO | E4: <<<<<< Automático conforme Metodologia e baseado no grau de exposição
B5: Status | C5: =IFERROR(VLOOKUP(C6,'RESUMO DE PONTOS'!$C$9:$M$64,11,),"") -> • 08/11/2022 • Novo ■ Vorcon Auditoria & Consultoria
B6: Código | C6: [P8]
B7: Título | C7: =VLOOKUP(C6,'BASE DA MATRIZ DE RISCOS'!$C$78:$D$202,2,) -> Os balancetes sem aprovação dos conselheiros fiscais e do síndico no termo de aprovação.
B8: Tipo | C8: =VLOOKUP(C6,'BASE DA MATRIZ DE RISCOS'!$C$78:$E$202,3,) -> Legal
B9: Tipo | C9: =VLOOKUP($C$8,'BASE DA MATRIZ DE RISCOS'!$C$30:$E$35,3) -> 5 | E9: <<<<<< Automático - Valores de 1 a 5 conforme metodologia
B10: Probabilidade | C10: =VLOOKUP(C6,'BASE DA MATRIZ DE RISCOS'!$C$78:$H$202,5,) -> 5 | E10: <<<<<< Valores de 1 a 5 conforme metodologia
B11: Impacto | C11: =VLOOKUP(C6,'BASE DA MATRIZ DE RISCOS'!$C$78:$H$202,6,) -> 4 | E11: <<<<<< Valores de 1 a 5 conforme metodologia
B12: Exposição | C12: =C9*C10*C11 -> 100 | E12: <<<<<< Calculado
B13: Testes/Áreas | C13: =VLOOKUP(C6,'BASE DA MATRIZ DE RISCOS'!$C$78:$J$202,8,) -> Resumo Convenção | E13: <<<<<< Automático - conforme Matriz de Risco
B14: Descrição | C14: =VLOOKUP(C$6,'RESUMO DE PONTOS'!$C$9:$H$64,3,) -> No período de 03/2021 a 02/2022 não constam as assinaturas do síndico e dos conselheiros fiscais para aprovação dos balancetes. Porém, conforme a Convenção do Subcondomínio Reserva das Plantas na cláusula 4.9.1 - f) "O Síndico de cada Subcondomínio tem as seguintes atribuições [...] rubrica[...] dos livros". Além disso, no item G-4.21-c) "Cada Conselho Fiscal [...] terá as seguintes atribuições: emitir parecer sobre as contas [...] do Síndico do Subcondomínio Residencial [...], conferindo-as, aprovando-as ou rejeitando-as".
B15: Riscos e Implicações | C15: =IFERROR(VLOOKUP(C$6,'RESUMO DE PONTOS'!$C$9:$H$64,4,),"") -> A falta das assinaturas dos conselheiros fiscais nos termos de aprovação dos balancetes indica que as contas do condomínio não foram submetidas ao exame, podendo acarretar a redução do nível de confiança dos demonstrativos e prejudicar a leitura dos usuários.
B16: Impacto Financeiro | C16: =IFERROR(VLOOKUP(C$6,'RESUMO DE PONTOS'!$C$9:$H$64,5,),"") -> NA
B17: Recomendações | C17: =IFERROR(VLOOKUP(C$6,'RESUMO DE PONTOS'!$C$9:$H$64,6,),"") -> Sugerimos que os conselheiros fiscais realizem o exame dos balancetes e caso ocorra a aprovação dos mesmos, confirmem com as suas assinaturas nos termos de aprovação. Mesmo com as demonstrações financeiras sendo auditadas mensalmente, é necessário a validação do conselho fiscal.
B18: Comentários da Administração | C18: Resposta da Administração sobre o ponto identificado e sobre as ações de melhoria sugeridas e, eventualmente, esclarecimento das prioridades recomendadas.
B19: Ações a serem Implementadas pela Administração | C19: Ações definidas pela Administração para resolução do ponto identificado.
B20: Data Limite para Resolução do Ponto Identificado | C20: Prazo estipulado pela Administração para que o ponto identificado deixe de existir.

Sheet P9
B2: Pontos de Controle
B3: Item | C3: Descrição
B4: Impacto | C4: =IF(C12>=75,"ALTO IMPACTO",IF(C12<=50,"BAIXO IMPACTO","MÉDIO IMPACTO")) -> ALTO IMPACTO | E4: <<<<<< Automático conforme Metodologia e baseado no grau de exposição
B5: Status | C5: =IFERROR(VLOOKUP(C6,'RESUMO DE PONTOS'!$C$9:$M$64,11,),"") -> • 08/11/2022 • Novo ■ Vorcon Auditoria & Consultoria
B6: Código | C6: [P9] | E6: <<<<<< Lista Suspensa (Selecionar)
B7: Título | C7: =VLOOKUP(C6,'BASE DA MATRIZ DE RISCOS'!$C$78:$D$202,2,) -> Falta de registro de Ata's em cartório
B8: Tipo | C8: =VLOOKUP(C6,'BASE DA MATRIZ DE RISCOS'!$C$78:$E$202,3,) -> Legal | E8: <<<<<< Lista Suspensa (Selecionar)
B9: Tipo | C9: =VLOOKUP($C$8,'BASE DA MATRIZ DE RISCOS'!$C$30:$E$35,3) -> 5 | E9: <<<<<< Automático - Valores de 1 a 5 conforme metodologia
B10: Probabilidade | C10: =VLOOKUP(C6,'BASE DA MATRIZ DE RISCOS'!$C$78:$H$202,5,) -> 5 | E10: <<<<<< Valores de 1 a 5 conforme metodologia
B11: Impacto | C11: =VLOOKUP(C6,'BASE DA MATRIZ DE RISCOS'!$C$78:$H$202,6,) -> 4 | E11: <<<<<< Valores de 1 a 5 conforme metodologia
B12: Exposição | C12: =C9*C10*C11 -> 100 | E12: <<<<<< Calculado
B13: Testes/Áreas | C13: =VLOOKUP(C6,'BASE DA MATRIZ DE RISCOS'!$C$78:$J$202,8,) -> Resumo Convenção | E13: <<<<<< Automático - conforme Matriz de Risco
B14: Descrição | C14: =VLOOKUP(C$6,'RESUMO DE PONTOS'!$C$9:$H$64,3,) -> Não identificamos o registro em cartório das Ata's: 16/12/2021, 09/09/2021, 14/10/2021, 27/01/2022, 03/02/2022. Conforme a Convenção do Subcondomínio Reserva das Plantas na cláusula 4.9.1 - f) "O Síndico de cada Subcondomínio tem as seguintes atribuições [...] Providenciar abertura, numeração, rubrica e encerramento dos livros, bem como o registro das atas em Cartório de Registro de Títulos e Documentos".
B15: Riscos e Implicações | C15: =IFERROR(VLOOKUP(C$6,'RESUMO DE PONTOS'!$C$9:$H$64,4,),"") -> Possível questionamento dos Condominos quanto a validação das Ata's por falta de registo no cartório.
B16: Impacto Financeiro | C16: =IFERROR(VLOOKUP(C$6,'RESUMO DE PONTOS'!$C$9:$H$64,5,),"") -> NA
B17: Recomendações | C17: =IFERROR(VLOOKUP(C$6,'RESUMO DE PONTOS'!$C$9:$H$64,6,),"") -> Sugerimos que haja registro das Ata's em cartório, conforme convenção.
B18: Comentários da Administração | C18: Resposta da Administração sobre o ponto identificado e sobre as ações de melhoria sugeridas e, eventualmente, esclarecimento das prioridades recomendadas.
B19: Ações a serem Implementadas pela Administração | C19: Ações definidas pela Administração para resolução do ponto identificado.
B20: Data Limite para Resolução do Ponto Identificado | C20: Prazo estipulado pela Administração para que o ponto identificado deixe de existir.

Sheet P10
B2: Pontos de Controle
B3: Item | C3: Descrição
B4: Impacto | C4: =IF(C12>=75,"ALTO IMPACTO",IF(C12<=50,"BAIXO IMPACTO","MÉDIO IMPACTO")) -> ALTO IMPACTO | E4: <<<<<< Automático conforme Metodologia e baseado no grau de exposição
B5: Status | C5: =IFERROR(VLOOKUP(C6,'RESUMO DE PONTOS'!$C$9:$M$64,11,),"") -> • 08/11/2022 • Novo ■ Vorcon Auditoria & Consultoria
B6: Código | C6: [P10] | E6: <<<<<< Lista Suspensa (Selecionar)
B7: Título | C7: =VLOOKUP(C6,'BASE DA MATRIZ DE RISCOS'!$C$78:$D$202,2,) -> Falta relatório de auditoria do período anterior.
B8: Tipo | C8: =VLOOKUP(C6,'BASE DA MATRIZ DE RISCOS'!$C$78:$E$202,3,) -> Estratégico | E8: <<<<<< Lista Suspensa (Selecionar)
B9: Tipo | C9: =VLOOKUP($C$8,'BASE DA MATRIZ DE RISCOS'!$C$30:$E$35,3) -> 4 | E9: <<<<<< Automático - Valores de 1 a 5 conforme metodologia
B10: Probabilidade | C10: =VLOOKUP(C6,'BASE DA MATRIZ DE RISCOS'!$C$78:$H$202,5,) -> 5 | E10: <<<<<< Valores de 1 a 5 conforme metodologia
B11: Impacto | C11: =VLOOKUP(C6,'BASE DA MATRIZ DE RISCOS'!$C$78:$H$202,6,) -> 4 | E11: <<<<<< Valores de 1 a 5 conforme metodologia
B12: Exposição | C12: =C9*C10*C11 -> 80 | E12: <<<<<< Calculado
B13: Testes/Áreas | C13: =VLOOKUP(C6,'BASE DA MATRIZ DE RISCOS'!$C$78:$J$202,8,) -> Follow Up CCI | E13: <<<<<< Automático - conforme Matriz de Risco
B14: Descrição | C14: =VLOOKUP(C$6,'RESUMO DE PONTOS'!$C$9:$H$64,3,) -> Conforme a Convenção do Subcondomínio Reserva das Plantas na cláusula 4.9.1 - h) "O Síndico de cada Subcondomínio tem as seguintes atribuições [...] Contratar, anualmente, empresa de auditoria para fiscalizar as contas do Subcondomínio." Dessa forma, não foi identificado o relatório da auditoria do período que antecedeu a auditoria atual (03/2021 a 02/2022). No entanto, analisamos conforme entendimento com o cliente que o condomínio realizou a auditoria em 2021 e não receberam o relatório.
B15: Riscos e Implicações | C15: =IFERROR(VLOOKUP(C$6,'RESUMO DE PONTOS'!$C$9:$H$64,4,),"") -> A ausência de contratação da auditoria e apresentação do relatório em relação ao período anterior, além de infringir a convenção condomonial, prejudica a transparência na prestação de contas podendo causar danos a situação financeira, econômica, legal e imagem da entidade.
B16: Impacto Financeiro | C16: =IFERROR(VLOOKUP(C$6,'RESUMO DE PONTOS'!$C$9:$H$64,5,),"") -> NA
B17: Recomendações | C17: =IFERROR(VLOOKUP(C$6,'RESUMO DE PONTOS'!$C$9:$H$64,6,),"") -> Recomendamos que a administração sempre realize auditorias preventivas.
B18: Comentários da Administração | C18: Resposta da Administração sobre o ponto identificado e sobre as ações de melhoria sugeridas e, eventualmente, esclarecimento das prioridades recomendadas.
B19: Ações a serem Implementadas pela Administração | C19: Ações definidas pela Administração para resolução do ponto identificado.
B20: Data Limite para Resolução do Ponto Identificado | C20: Prazo estipulado pela Administração para que o ponto identificado deixe de existir.

Sheet P11
B2: Pontos de Controle
B3: Item | C3: Descrição
B4: Impacto | C4: =IF(C12>=75,"ALTO IMPACTO",IF(C12<=50,"BAIXO IMPACTO","MÉDIO IMPACTO")) -> ALTO IMPACTO | E4: <<<<<< Automático conforme Metodologia e baseado no grau de exposição
B5: Status | C5: =IFERROR(VLOOKUP(C6,'RESUMO DE PONTOS'!$C$9:$M$64,11,),"") -> • 08/11/2022 • Novo ■ Vorcon Auditoria & Consultoria
B6: Código | C6: [P11]
B7: Título | C7: =VLOOKUP(C6,'BASE DA MATRIZ DE RISCOS'!$C$78:$D$202,2,) -> Falta de Planejamento Orçamentário Anual
B8: Tipo | C8: =VLOOKUP(C6,'BASE DA MATRIZ DE RISCOS'!$C$78:$E$202,3,) -> Estratégico | E8: <<<<<< Lista Suspensa (Selecionar)
B9: Tipo | C9: =VLOOKUP($C$8,'BASE DA MATRIZ DE RISCOS'!$C$30:$E$35,3) -> 4 | E9: <<<<<< Automático - Valores de 1 a 5 conforme metodologia
B10: Probabilidade | C10: =VLOOKUP(C6,'BASE DA MATRIZ DE RISCOS'!$C$78:$H$202,5,) -> 5 | E10: <<<<<< Valores de 1 a 5 conforme metodologia
B11: Impacto | C11: =VLOOKUP(C6,'BASE DA MATRIZ DE RISCOS'!$C$78:$H$202,6,) -> 5 | E11: <<<<<< Valores de 1 a 5 conforme metodologia
B12: Exposição | C12: =C9*C10*C11 -> 100 | E12: <<<<<< Calculado
B13: Testes/Áreas | C13: =VLOOKUP(C6,'BASE DA MATRIZ DE RISCOS'!$C$78:$J$202,8,) -> Orçado X Realizado | E13: <<<<<< Automático - conforme Matriz de Risco
B14: Descrição | C14: =VLOOKUP(C$6,'RESUMO DE PONTOS'!$C$9:$H$64,3,) -> Conforme a Convenção do Subcondomínio Reserva das Plantas na cláusula 4.36.1 "A assembleia geral ordinária do Condomínio realizar-se-á anualmente [...] outra assembleia geral ordinária do CONDOMÍNIO [Sic], sempre até o final do mês de novembro de cada ano e a ela competirá especificamente fixar o orçamento anual do CONDOMÍNIO para o exercicio social vindouro e a forma de cobrança das respectivas despesas." Dessa forma, não foi identificado o Planejamento Orçamentário para o ano de 2021. Além disso, identificamos nas Atas que o Sr. Marco Ribeiro, demonstrou as prinipais causas do aumento das despesas e informou que o condomíno está lidando com o mesmo planejamento orçamentário há 03 anos e que com a pandemia, todos os produtos e serviços tem sofrido aumentos fora do comum.
B15: Riscos e Implicações | C15: =IFERROR(VLOOKUP(C$6,'RESUMO DE PONTOS'!$C$9:$H$64,4,),"") -> A falta da elaboração do planejamento orçamentário poderá prejudicar o controle das contas condominiais e a prevenção dos gastos desnecerrários ou demasiados.
B16: Impacto Financeiro | C16: =IFERROR(VLOOKUP(C$6,'RESUMO DE PONTOS'!$C$9:$H$64,5,),"") -> NA
B17: Recomendações | C17: =IFERROR(VLOOKUP(C$6,'RESUMO DE PONTOS'!$C$9:$H$64,6,),"") -> Recomendamos que o o planejamento orçamentário ocorra dentro do período previsto em convenção.
B18: Comentários da Administração | C18: Resposta da Administração sobre o ponto identificado e sobre as ações de melhoria sugeridas e, eventualmente, esclarecimento das prioridades recomendadas.
B19: Ações a serem Implementadas pela Administração | C19: Ações definidas pela Administração para resolução do ponto identificado.
B20: Data Limite para Resolução do Ponto Identificado | C20: Prazo estipulado pela Administração para que o ponto identificado deixe de existir.

Sheet P12
B2: Pontos de Controle
B3: Item | C3: Descrição
B4: Impacto | C4: =IF(C12>=75,"ALTO IMPACTO",IF(C12<=50,"BAIXO IMPACTO","MÉDIO IMPACTO")) -> ALTO IMPACTO | E4: <<<<<< Automático conforme Metodologia e baseado no grau de exposição
B5: Status | C5: =IFERROR(VLOOKUP(C6,'RESUMO DE PONTOS'!$C$9:$M$64,11,),"") -> • 08/11/2022 • Novo ■ Vorcon Auditoria & Consultoria
B6: Código | C6: [P12] | E6: <<<<<< Lista Suspensa (Selecionar)
B7: Título | C7: =VLOOKUP(C6,'BASE DA MATRIZ DE RISCOS'!$C$78:$D$202,2,) -> Sistema de medição da água realizado de forma não individualizada
B8: Tipo | C8: =VLOOKUP(C6,'BASE DA MATRIZ DE RISCOS'!$C$78:$E$202,3,) -> Legal | E8: <<<<<< Lista Suspensa (Selecionar)
B9: Tipo | C9: =VLOOKUP($C$8,'BASE DA MATRIZ DE RISCOS'!$C$30:$E$35,3) -> 5 | E9: <<<<<< Automático - Valores de 1 a 5 conforme metodologia
B10: Probabilidade | C10: =VLOOKUP(C6,'BASE DA MATRIZ DE RISCOS'!$C$78:$H$202,5,) -> 5 | E10: <<<<<< Valores de 1 a 5 conforme metodologia
B11: Impacto | C11: =VLOOKUP(C6,'BASE DA MATRIZ DE RISCOS'!$C$78:$H$202,6,) -> 4 | E11: <<<<<< Valores de 1 a 5 conforme metodologia
B12: Exposição | C12: =C9*C10*C11 -> 100 | E12: <<<<<< Calculado
B13: Testes/Áreas | C13: =VLOOKUP(C6,'BASE DA MATRIZ DE RISCOS'!$C$78:$J$202,8,) -> Resumo Convenção | E13: <<<<<< Automático - conforme Matriz de Risco
B14: Descrição | C14: =VLOOKUP(C$6,'RESUMO DE PONTOS'!$C$9:$H$64,3,) -> Segundo a ATA Reunião de Moradores do dia 09/09/2021 o "Sr. Roque Andrade entrou na tratativa da individualização da água e falou sobre os benefícios que isso traria por conta do consumo desigual entre as unidades [...]". Dessa forma, identificamos que o sistema de medição da água não é realizado de forma individualizada, infringindo assim, a cláusula 15.1 - e) da Convenção Condominial.
B15: Riscos e Implicações | C15: =IFERROR(VLOOKUP(C$6,'RESUMO DE PONTOS'!$C$9:$H$64,4,),"") -> A infração em relação a item previsto na Convenção Condominial pode gerar questionamentos, reclamações, impactos em relação a sustentabilidade e prejuizos de ordem legal para o condominio.
B16: Impacto Financeiro | C16: =IFERROR(VLOOKUP(C$6,'RESUMO DE PONTOS'!$C$9:$H$64,5,),"") -> NA
B17: Recomendações | C17: =IFERROR(VLOOKUP(C$6,'RESUMO DE PONTOS'!$C$9:$H$64,6,),"") -> Recomendamos que a administração analise a viabilidade da individualização de medição da água junto aos condominos e profissionais técnicos. Após isso, se for viável planeje a implementação e caso contrário, atualize a convenção para modificar a previsão desse item.
B18: Comentários da Administração | C18: Resposta da Administração sobre o ponto identificado e sobre as ações de melhoria sugeridas e, eventualmente, esclarecimento das prioridades recomendadas.
B19: Ações a serem Implementadas pela Administração | C19: Ações definidas pela Administração para resolução do ponto identificado.
B20: Data Limite para Resolução do Ponto Identificado | C20: Prazo estipulado pela Administração para que o ponto identificado deixe de existir.

Sheet P13
B2: Pontos de Controle
B3: Item | C3: Descrição
B4: Impacto | C4: =IF(C12>=75,"ALTO IMPACTO",IF(C12<=50,"BAIXO IMPACTO","MÉDIO IMPACTO")) -> BAIXO IMPACTO | E4: <<<<<< Automático conforme Metodologia e baseado no grau de exposição
B5: Status | C5: =IFERROR(VLOOKUP(C6,'RESUMO DE PONTOS'!$C$9:$M$64,11,),"")
B6: Código | C6: [P13] | E6: <<<<<< Lista Suspensa (Selecionar)
B7: Título | C7: =VLOOKUP(C6,'BASE DA MATRIZ DE RISCOS'!$C$78:$D$202,2,) -> Valor apresentado no comprovante de pagamento, mas que não consta no extrato bancário
B8: Tipo | C8: =VLOOKUP(C6,'BASE DA MATRIZ DE RISCOS'!$C$78:$E$202,3,) -> Financeiro | E8: <<<<<< Lista Suspensa (Selecionar)
B9: Tipo | C9: =VLOOKUP($C$8,'BASE DA MATRIZ DE RISCOS'!$C$30:$E$35,3) -> 5 | E9: <<<<<< Automático - Valores de 1 a 5 conforme metodologia
B10: Probabilidade | C10: =VLOOKUP(C6,'BASE DA MATRIZ DE RISCOS'!$C$78:$H$202,5,) -> 3 | E10: <<<<<< Valores de 1 a 5 conforme metodologia
B11: Impacto | C11: =VLOOKUP(C6,'BASE DA MATRIZ DE RISCOS'!$C$78:$H$202,6,) -> 3 | E11: <<<<<< Valores de 1 a 5 conforme metodologia
B12: Exposição | C12: =C9*C10*C11 -> 45 | E12: <<<<<< Calculado
B13: Testes/Áreas | C13: =VLOOKUP(C6,'BASE DA MATRIZ DE RISCOS'!$C$78:$J$202,8,) -> Demonstrativo Financeiro + voucher nos extratos | E13: <<<<<< Automático - conforme Matriz de Risco
B14: Descrição | C14: =VLOOKUP(C$6,'RESUMO DE PONTOS'!$C$9:$H$64,3,) -> Identificamos comprovante de pagamento do dia 19/10/2021 informando que foi realizado o pagamento no valor de R$ 1000,00 através da Agência: 4306 e Conta: 130035030. No entanto, essas informações não constam no extrato bancário dessa respectiva conta.
B15: Riscos e Implicações | C15: =IFERROR(VLOOKUP(C$6,'RESUMO DE PONTOS'!$C$9:$H$64,4,),"") -> A divergência de informações entre comprovante de pagamento e o extrato bancário pode indicar erro ou fraude na gestão financeira condominial e impactar nas disponibilidades da entidade.
B16: Impacto Financeiro | C16: =IFERROR(VLOOKUP(C$6,'RESUMO DE PONTOS'!$C$9:$H$64,5,),"") -> 1000
B17: Recomendações | C17: =IFERROR(VLOOKUP(C$6,'RESUMO DE PONTOS'!$C$9:$H$64,6,),"") -> Indicamos que a Administração promova melhorias em seus controles interno tendo como finalidade a apresentação de informações financeiras convergentes com os registros expostos nos extratos bancários.
B18: Comentários da Administração | C18: Resposta da Administração sobre o ponto identificado e sobre as ações de melhoria sugeridas e, eventualmente, esclarecimento das prioridades recomendadas.
B19: Ações a serem Implementadas pela Administração | C19: Ações definidas pela Administração para resolução do ponto identificado.
B20: Data Limite para Resolução do Ponto Identificado | C20: Prazo estipulado pela Administração para que o ponto identificado deixe de existir.

Sheet P14
B2: Pontos de Controle
B3: Item | C3: Descrição
B4: Impacto | C4: =IF(C12>=75,"ALTO IMPACTO",IF(C12<=50,"BAIXO IMPACTO","MÉDIO IMPACTO")) -> ALTO IMPACTO | E4: <<<<<< Automático conforme Metodologia e baseado no grau de exposição
B5: Status | C5: =IFERROR(VLOOKUP(C6,'RESUMO DE PONTOS'!$C$9:$M$64,11,),"") -> • 08/11/2022 • Novo ■ Vorcon Auditoria & Consultoria
B6: Código | C6: [P14] | E6: <<<<<< Lista Suspensa (Selecionar)
B7: Título | C7: =VLOOKUP(C6,'BASE DA MATRIZ DE RISCOS'!$C$78:$D$202,2,) -> Falta de apresentação de extratos bancários
B8: Tipo | C8: =VLOOKUP(C6,'BASE DA MATRIZ DE RISCOS'!$C$78:$E$202,3,) -> Financeiro | E8: <<<<<< Lista Suspensa (Selecionar)
B9: Tipo | C9: =VLOOKUP($C$8,'BASE DA MATRIZ DE RISCOS'!$C$30:$E$35,3) -> 5 | E9: <<<<<< Automático - Valores de 1 a 5 conforme metodologia
B10: Probabilidade | C10: =VLOOKUP(C6,'BASE DA MATRIZ DE RISCOS'!$C$78:$H$202,5,) -> 4 | E10: <<<<<< Valores de 1 a 5 conforme metodologia
B11: Impacto | C11: =VLOOKUP(C6,'BASE DA MATRIZ DE RISCOS'!$C$78:$H$202,6,) -> 4 | E11: <<<<<< Valores de 1 a 5 conforme metodologia
B12: Exposição | C12: =C9*C10*C11 -> 80 | E12: <<<<<< Calculado
B13: Testes/Áreas | C13: =VLOOKUP(C6,'BASE DA MATRIZ DE RISCOS'!$C$78:$J$202,8,) -> Demonstrativo Financeiro + voucher nos extratos | E13: <<<<<< Automático - conforme Matriz de Risco
B14: Descrição | C14: =VLOOKUP(C$6,'RESUMO DE PONTOS'!$C$9:$H$64,3,) -> Verificamos que em alguns meses não foram apresentados à auditoria os extratos do Banco Santander, agência: 4306 e contas: 13.003502-3 / 13.003496-7, além das aplicações financeiras.
B15: Riscos e Implicações | C15: =IFERROR(VLOOKUP(C$6,'RESUMO DE PONTOS'!$C$9:$H$64,4,),"") -> A falta dos extratos bancários prejudica a análise das informações, o entendimento e a validação das entradas e saídas financeiras do condomínio.
B16: Impacto Financeiro | C16: =IFERROR(VLOOKUP(C$6,'RESUMO DE PONTOS'!$C$9:$H$64,5,),"") -> NA
B17: Recomendações | C17: =IFERROR(VLOOKUP(C$6,'RESUMO DE PONTOS'!$C$9:$H$64,6,),"") -> Visando aumentar a transparência na prestação de contas do condomínio, sugerimos à Administração que envie os extratos bancários emitidos diretamente pelas instituições financeiras para que as análises dessas informações se tornem possíveis.
B18: Comentários da Administração | C18: Resposta da Administração sobre o ponto identificado e sobre as ações de melhoria sugeridas e, eventualmente, esclarecimento das prioridades recomendadas.
B19: Ações a serem Implementadas pela Administração | C19: Ações definidas pela Administração para resolução do ponto identificado.
B20: Data Limite para Resolução do Ponto Identificado | C20: Prazo estipulado pela Administração para que o ponto identificado deixe de existir.

Sheet P15
B2: Pontos de Controle
B3: Item | C3: Descrição
B4: Impacto | C4: =IF(C12>=75,"ALTO IMPACTO",IF(C12<=50,"BAIXO IMPACTO","MÉDIO IMPACTO")) -> BAIXO IMPACTO | E4: <<<<<< Automático conforme Metodologia e baseado no grau de exposição
B5: Status | C5: =IFERROR(VLOOKUP(C6,'RESUMO DE PONTOS'!$C$9:$M$64,11,),"") -> • 08/11/2022 • Novo ■ Vorcon Auditoria & Consultoria
B6: Código | C6: [P15] | E6: <<<<<< Lista Suspensa (Selecionar)
B7: Título | C7: =VLOOKUP(C6,'BASE DA MATRIZ DE RISCOS'!$C$78:$D$202,2,) -> Saídas nos extratos não validados com a voucher
B8: Tipo | C8: =VLOOKUP(C6,'BASE DA MATRIZ DE RISCOS'!$C$78:$E$202,3,) -> Financeiro | E8: <<<<<< Lista Suspensa (Selecionar)
B9: Tipo | C9: =VLOOKUP($C$8,'BASE DA MATRIZ DE RISCOS'!$C$30:$E$35,3) -> 5 | E9: <<<<<< Automático - Valores de 1 a 5 conforme metodologia
B10: Probabilidade | C10: =VLOOKUP(C6,'BASE DA MATRIZ DE RISCOS'!$C$78:$H$202,5,) -> 3 | E10: <<<<<< Valores de 1 a 5 conforme metodologia
B11: Impacto | C11: =VLOOKUP(C6,'BASE DA MATRIZ DE RISCOS'!$C$78:$H$202,6,) -> 3 | E11: <<<<<< Valores de 1 a 5 conforme metodologia
B12: Exposição | C12: =C9*C10*C11 -> 45 | E12: <<<<<< Calculado
B13: Testes/Áreas | C13: =VLOOKUP(C6,'BASE DA MATRIZ DE RISCOS'!$C$78:$J$202,8,) -> Demonstrativo Financeiro + voucher nos extratos | E13: <<<<<< Automático - conforme Matriz de Risco
B14: Descrição | C14: =VLOOKUP(C$6,'RESUMO DE PONTOS'!$C$9:$H$64,3,) -> Identificamos no momento do confronto entre os extratos bancários e a Voucher Documental produzida com as informações apresentadas pelo condomínio, a existência de saídas de recursos dos extratos que não constam na Voucher. Diante disso, não ocorre a verificação dos documentos comprobatórios dos respectivos dispêndios realizados pelo condomínio
B15: Riscos e Implicações | C15: =IFERROR(VLOOKUP(C$6,'RESUMO DE PONTOS'!$C$9:$H$64,4,),"") -> As saídas de recursos dos extratos sem a validação da Voucher Documental poderão prejudicar a transparência e afetar a prestação de contas, dando oportunidade de os valores não serem utilizados para fins que geram benefícios econômicos ao condomínio.
B16: Impacto Financeiro | C16: =IFERROR(VLOOKUP(C$6,'RESUMO DE PONTOS'!$C$9:$H$64,5,),"") -> 2117.99
B17: Recomendações | C17: =IFERROR(VLOOKUP(C$6,'RESUMO DE PONTOS'!$C$9:$H$64,6,),"") -> Indicamos ao Conselho Fiscal a estruturação de procedimentos de controles internos que garantam destinação adequada dos recursos condominiais sendo apresentados todos os documentos comprobatórios da realização de suas despesas e validados por uma auditoria contínua.
B18: Comentários da Administração | C18: Resposta da Administração sobre o ponto identificado e sobre as ações de melhoria sugeridas e, eventualmente, esclarecimento das prioridades recomendadas.
B19: Ações a serem Implementadas pela Administração | C19: Ações definidas pela Administração para resolução do ponto identificado.
B20: Data Limite para Resolução do Ponto Identificado | C20: Prazo estipulado pela Administração para que o ponto identificado deixe de existir.

Sheet P16
B2: Pontos de Controle
B3: Item | C3: Descrição
B4: Impacto | C4: =IF(C12>=75,"ALTO IMPACTO",IF(C12<=50,"BAIXO IMPACTO","MÉDIO IMPACTO")) -> MÉDIO IMPACTO | E4: <<<<<< Automático conforme Metodologia e baseado no grau de exposição
B5: Status | C5: =IFERROR(VLOOKUP(C6,'RESUMO DE PONTOS'!$C$9:$M$64,11,),"") -> • 08/11/2022 • Novo ■ Vorcon Auditoria & Consultoria
B6: Código | C6: [P16] | E6: <<<<<< Lista Suspensa (Selecionar)
B7: Título | C7: =VLOOKUP(C6,'BASE DA MATRIZ DE RISCOS'!$C$78:$D$202,2,) -> Apresentação incompleta de extrato bancário
B8: Tipo | C8: =VLOOKUP(C6,'BASE DA MATRIZ DE RISCOS'!$C$78:$E$202,3,) -> Financeiro | E8: <<<<<< Lista Suspensa (Selecionar)
B9: Tipo | C9: =VLOOKUP($C$8,'BASE DA MATRIZ DE RISCOS'!$C$30:$E$35,3) -> 5 | E9: <<<<<< Automático - Valores de 1 a 5 conforme metodologia
B10: Probabilidade | C10: =VLOOKUP(C6,'BASE DA MATRIZ DE RISCOS'!$C$78:$H$202,5,) -> 3 | E10: <<<<<< Valores de 1 a 5 conforme metodologia
B11: Impacto | C11: =VLOOKUP(C6,'BASE DA MATRIZ DE RISCOS'!$C$78:$H$202,6,) -> 4 | E11: <<<<<< Valores de 1 a 5 conforme metodologia
B12: Exposição | C12: =C9*C10*C11 -> 60 | E12: <<<<<< Calculado
B13: Testes/Áreas | C13: =VLOOKUP(C6,'BASE DA MATRIZ DE RISCOS'!$C$78:$J$202,8,) -> Demonstrativo Financeiro + voucher nos extratos | E13: <<<<<< Automático - conforme Matriz de Risco
B14: Descrição | C14: =VLOOKUP(C$6,'RESUMO DE PONTOS'!$C$9:$H$64,3,) -> Recebemos o extrato do Banco Santander, agência: 4306 e conta: 13.003503-0 referente ao mês 02/2022 de forma incompleta, impossibilitando assim, a conferência de todas as suas informações.
B15: Riscos e Implicações | C15: =IFERROR(VLOOKUP(C$6,'RESUMO DE PONTOS'!$C$9:$H$64,4,),"") -> A entrega de extrato realizada de forma incompleta impede a análise, o entendimento e a validação das entradas e saídas financeiras, reduzindo assim, a transparência nas prestação de contas do condomínio.
B16: Impacto Financeiro | C16: =IFERROR(VLOOKUP(C$6,'RESUMO DE PONTOS'!$C$9:$H$64,5,),"") -> NA
B17: Recomendações | C17: =IFERROR(VLOOKUP(C$6,'RESUMO DE PONTOS'!$C$9:$H$64,6,),"") -> Recomendamos à Administração que envie os extratos bancários emitidos diretamente pelas instituições financeiras contemplando todas as informações do período solicitado.
B18: Comentários da Administração | C18: Resposta da Administração sobre o ponto identificado e sobre as ações de melhoria sugeridas e, eventualmente, esclarecimento das prioridades recomendadas.
B19: Ações a serem Implementadas pela Administração | C19: Ações definidas pela Administração para resolução do ponto identificado.
B20: Data Limite para Resolução do Ponto Identificado | C20: Prazo estipulado pela Administração para que o ponto identificado deixe de existir.

Sheet P17
B2: Pontos de Controle
B3: Item | C3: Descrição
B4: Impacto | C4: =IF(C12>=75,"ALTO IMPACTO",IF(C12<=50,"BAIXO IMPACTO","MÉDIO IMPACTO")) -> BAIXO IMPACTO | E4: <<<<<< Automático conforme Metodologia e baseado no grau de exposição
B5: Status | C5: =IFERROR(VLOOKUP(C6,'RESUMO DE PONTOS'!$C$9:$M$64,11,),"") -> • 08/11/2022 • Novo ■ Vorcon Auditoria & Consultoria
B6: Código | C6: [P17] | E6: <<<<<< Lista Suspensa (Selecionar)
B7: Título | C7: =VLOOKUP(C6,'BASE DA MATRIZ DE RISCOS'!$C$78:$D$202,2,) -> Diferenças entre os saldos dos Demonstrativos Financeiros de Receitas e Despesas em relação a Demonstração dos Saldos Financeiros.
B8: Tipo | C8: =VLOOKUP(C6,'BASE DA MATRIZ DE RISCOS'!$C$78:$E$202,3,) -> Financeiro | E8: <<<<<< Lista Suspensa (Selecionar)
B9: Tipo | C9: =VLOOKUP($C$8,'BASE DA MATRIZ DE RISCOS'!$C$30:$E$35,3) -> 5 | E9: <<<<<< Automático - Valores de 1 a 5 conforme metodologia
B10: Probabilidade | C10: =VLOOKUP(C6,'BASE DA MATRIZ DE RISCOS'!$C$78:$H$202,5,) -> 2 | E10: <<<<<< Valores de 1 a 5 conforme metodologia
B11: Impacto | C11: =VLOOKUP(C6,'BASE DA MATRIZ DE RISCOS'!$C$78:$H$202,6,) -> 2 | E11: <<<<<< Valores de 1 a 5 conforme metodologia
B12: Exposição | C12: =C9*C10*C11 -> 20 | E12: <<<<<< Calculado
B13: Testes/Áreas | C13: =VLOOKUP(C6,'BASE DA MATRIZ DE RISCOS'!$C$78:$J$202,8,) -> Conciliação Bancária + Elaboração dos quadros dos Demonstrativos Financeiros | E13: <<<<<< Automático - conforme Matriz de Risco
B14: Descrição | C14: =VLOOKUP(C$6,'RESUMO DE PONTOS'!$C$9:$H$64,3,) -> Verificamos os saldos finais dos demonstrativos financeiros de receitas e despesas (DF) e confrontamos com os valores finais dos demonstrativos dos saldos financeiros (DSF), nos quais foram identificadas divergências.
B15: Riscos e Implicações | C15: =IFERROR(VLOOKUP(C$6,'RESUMO DE PONTOS'!$C$9:$H$64,4,),"") -> A apresentação dos saldos divergentes nos demonstrativos financeiros de receita e despesas, poderá prejudicar a transparência e afetar a prestação de contas comprometendo a interpretação dos usuários das informações financeiras do condomínio.
B16: Impacto Financeiro | C16: =IFERROR(VLOOKUP(C$6,'RESUMO DE PONTOS'!$C$9:$H$64,5,),"") -> 109
B17: Recomendações | C17: =IFERROR(VLOOKUP(C$6,'RESUMO DE PONTOS'!$C$9:$H$64,6,),"") -> Recomendamos que os demonstrativos dos saldos financeiros assim como os demonstrativo de receita e despesas sejam revisados para reduzir os riscos de divergências.
B18: Comentários da Administração | C18: Resposta da Administração sobre o ponto identificado e sobre as ações de melhoria sugeridas e, eventualmente, esclarecimento das prioridades recomendadas.
B19: Ações a serem Implementadas pela Administração | C19: Ações definidas pela Administração para resolução do ponto identificado.
B20: Data Limite para Resolução do Ponto Identificado | C20: Prazo estipulado pela Administração para que o ponto identificado deixe de existir.

Sheet P18
B2: Pontos de Controle
B3: Item | C3: Descrição
B4: Impacto | C4: =IF(C12>=75,"ALTO IMPACTO",IF(C12<=50,"BAIXO IMPACTO","MÉDIO IMPACTO")) -> BAIXO IMPACTO | E4: <<<<<< Automático conforme Metodologia e baseado no grau de exposição
B5: Status | C5: =IFERROR(VLOOKUP(C6,'RESUMO DE PONTOS'!$C$9:$M$64,11,),"") -> • 08/11/2022 • Novo ■ Vorcon Auditoria & Consultoria
B6: Código | C6: [P18] | E6: <<<<<< Lista Suspensa (Selecionar)
B7: Título | C7: =VLOOKUP(C6,'BASE DA MATRIZ DE RISCOS'!$C$78:$D$202,2,) -> Ausência de apresentação de mapa de cotação
B8: Tipo | C8: =VLOOKUP(C6,'BASE DA MATRIZ DE RISCOS'!$C$78:$E$202,3,) -> Operacional | E8: <<<<<< Lista Suspensa (Selecionar)
B9: Tipo | C9: =VLOOKUP($C$8,'BASE DA MATRIZ DE RISCOS'!$C$30:$E$36,3) -> 3 | E9: <<<<<< Automático - Valores de 1 a 5 conforme metodologia
B10: Probabilidade | C10: =VLOOKUP(C6,'BASE DA MATRIZ DE RISCOS'!$C$78:$H$202,5,) -> 4 | E10: <<<<<< Valores de 1 a 5 conforme metodologia
B11: Impacto | C11: =VLOOKUP(C6,'BASE DA MATRIZ DE RISCOS'!$C$78:$H$202,6,) -> 3 | E11: <<<<<< Valores de 1 a 5 conforme metodologia
B12: Exposição | C12: =C9*C10*C11 -> 36 | E12: <<<<<< Calculado
B13: Testes/Áreas | C13: =VLOOKUP(C6,'BASE DA MATRIZ DE RISCOS'!$C$78:$J$202,8,) -> Voucher documental | E13: <<<<<< Automático - conforme Matriz de Risco
B14: Descrição | C14: =VLOOKUP(C$6,'RESUMO DE PONTOS'!$C$9:$H$64,3,) -> Verificamos que algumas compras realizadas não estavam sendo efetuado o mapa de cotação.
B15: Riscos e Implicações | C15: =IFERROR(VLOOKUP(C$6,'RESUMO DE PONTOS'!$C$9:$H$64,4,),"") -> A falta da cotação mínima de 3 orçamentos poderá prejudicar o condomínio através de aquisições de bens e/ou serviços de baixa qualidade, com fornecedores sem conhecimento ou respaldo técnico e entregas diferente do escopo esperado.
B16: Impacto Financeiro | C16: =IFERROR(VLOOKUP(C$6,'RESUMO DE PONTOS'!$C$9:$H$64,5,),"") -> NA
B17: Recomendações | C17: =IFERROR(VLOOKUP(C$6,'RESUMO DE PONTOS'!$C$9:$H$64,6,),"") -> Recomendamos a administração que seja realizado mapa de orçamento no mínimo de 3 cotações para as aquisições dos bens ou serviços do condomínio.
B18: Comentários da Administração | C18: Resposta da Administração sobre o ponto identificado e sobre as ações de melhoria sugeridas e, eventualmente, esclarecimento das prioridades recomendadas.
B19: Ações a serem Implementadas pela Administração | C19: Ações definidas pela Administração para resolução do ponto identificado.
B20: Data Limite para Resolução do Ponto Identificado | C20: Prazo estipulado pela Administração para que o ponto identificado deixe de existir.

Sheet P19
B2: Pontos de Controle
B3: Item | C3: Descrição
B4: Impacto | C4: =IF(C12>=75,"ALTO IMPACTO",IF(C12<=50,"BAIXO IMPACTO","MÉDIO IMPACTO")) -> MÉDIO IMPACTO | E4: <<<<<< Automático conforme Metodologia e baseado no grau de exposição
B5: Status | C5: =IFERROR(VLOOKUP(C6,'RESUMO DE PONTOS'!$C$9:$M$64,11,),"") -> • 08/11/2022 • Novo ■ Vorcon Auditoria & Consultoria
B6: Código | C6: [P19] | E6: <<<<<< Lista Suspensa (Selecionar)
B7: Título | C7: =VLOOKUP(C6,'BASE DA MATRIZ DE RISCOS'!$C$78:$D$202,2,) -> Ausência de inventário dos ativos imobilizados
B8: Tipo | C8: =VLOOKUP(C6,'BASE DA MATRIZ DE RISCOS'!$C$78:$E$202,3,) -> Financeiro | E8: <<<<<< Lista Suspensa (Selecionar)
B9: Tipo | C9: =VLOOKUP($C$8,'BASE DA MATRIZ DE RISCOS'!$C$30:$E$36,3) -> 5 | E9: <<<<<< Automático - Valores de 1 a 5 conforme metodologia
B10: Probabilidade | C10: =VLOOKUP(C6,'BASE DA MATRIZ DE RISCOS'!$C$78:$H$202,5,) -> 4 | E10: <<<<<< Valores de 1 a 5 conforme metodologia
B11: Impacto | C11: =VLOOKUP(C6,'BASE DA MATRIZ DE RISCOS'!$C$78:$H$202,6,) -> 3 | E11: <<<<<< Valores de 1 a 5 conforme metodologia
B12: Exposição | C12: =C9*C10*C11 -> 60 | E12: <<<<<< Calculado
B13: Testes/Áreas | C13: =VLOOKUP(C6,'BASE DA MATRIZ DE RISCOS'!$C$78:$J$202,8,) -> Inspeção estatística dos itens do Imobilizado | E13: <<<<<< Automático - conforme Matriz de Risco
B14: Descrição | C14: =VLOOKUP(C$6,'RESUMO DE PONTOS'!$C$9:$H$64,3,) -> Não identificamos o controle patrimonial dos ativos imobilizados para atualização do saldo em decorrência dos bens adquiridos, obsoletos e/ou perdidos para realização da baixa, assim como as depreciações.
B15: Riscos e Implicações | C15: =IFERROR(VLOOKUP(C$6,'RESUMO DE PONTOS'!$C$9:$H$64,4,),"") -> A ausência do controle patrimonial do condomínio poderá impactar em possíveis perdas ou desvios do ativo imobilizado.
B16: Impacto Financeiro | C16: =IFERROR(VLOOKUP(C$6,'RESUMO DE PONTOS'!$C$9:$H$64,5,),"") -> NA
B17: Recomendações | C17: =IFERROR(VLOOKUP(C$6,'RESUMO DE PONTOS'!$C$9:$H$64,6,),"") -> Sugerimos que à Administração do condomínio busque realizar o inventário dos ativos imobilizados anualmente.
B18: Comentários da Administração | C18: Resposta da Administração sobre o ponto identificado e sobre as ações de melhoria sugeridas e, eventualmente, esclarecimento das prioridades recomendadas.
B19: Ações a serem Implementadas pela Administração | C19: Ações definidas pela Administração para resolução do ponto identificado.
B20: Data Limite para Resolução do Ponto Identificado | C20: Prazo estipulado pela Administração para que o ponto identificado deixe de existir.

Sheet P20
B2: Pontos de Controle
B3: Item | C3: Descrição
B4: Impacto | C4: =IF(C12>=75,"ALTO IMPACTO",IF(C12<=50,"BAIXO IMPACTO","MÉDIO IMPACTO")) -> BAIXO IMPACTO | E4: <<<<<< Automático conforme Metodologia e baseado no grau de exposição
B5: Status | C5: =IFERROR(VLOOKUP(C6,'RESUMO DE PONTOS'!$C$9:$M$64,11,),"")
B6: Código | C6: [P20] | E6: <<<<<< Lista Suspensa (Selecionar)
B7: Título | C7: =VLOOKUP(C6,'BASE DA MATRIZ DE RISCOS'!$C$78:$D$202,2,) -> Inexistência de valor estimado dos honorários advocatícios
B8: Tipo | C8: =VLOOKUP(C6,'BASE DA MATRIZ DE RISCOS'!$C$78:$E$202,3,) -> Financeiro | E8: <<<<<< Lista Suspensa (Selecionar)
B9: Tipo | C9: =VLOOKUP($C$8,'BASE DA MATRIZ DE RISCOS'!$C$30:$E$36,3) -> 5 | E9: <<<<<< Automático - Valores de 1 a 5 conforme metodologia
B10: Probabilidade | C10: =VLOOKUP(C6,'BASE DA MATRIZ DE RISCOS'!$C$78:$H$202,5,) -> 3 | E10: <<<<<< Valores de 1 a 5 conforme metodologia
B11: Impacto | C11: =VLOOKUP(C6,'BASE DA MATRIZ DE RISCOS'!$C$78:$H$202,6,) -> 1 | E11: <<<<<< Valores de 1 a 5 conforme metodologia
B12: Exposição | C12: =C9*C10*C11 -> 15 | E12: <<<<<< Calculado
B13: Testes/Áreas | C13: =VLOOKUP(C6,'BASE DA MATRIZ DE RISCOS'!$C$78:$J$202,8,) -> Teste de Contingência | E13: <<<<<< Automático - conforme Matriz de Risco
B14: Descrição | C14: =VLOOKUP(C$6,'RESUMO DE PONTOS'!$C$9:$H$64,3,) -> Não identificamos o valor estimado da expectativa de exito nos casos de processos onde o condomínio esteja como polo ativo ou passivo para período de 03/2021 até 02/2022
B15: Riscos e Implicações | C15: =IFERROR(VLOOKUP(C$6,'RESUMO DE PONTOS'!$C$9:$H$64,4,),"") -> 0
B16: Impacto Financeiro | C16: =IFERROR(VLOOKUP(C$6,'RESUMO DE PONTOS'!$C$9:$H$64,5,),"") -> N/A
B17: Recomendações | C17: =IFERROR(VLOOKUP(C$6,'RESUMO DE PONTOS'!$C$9:$H$64,6,),"") -> 0
B18: Comentários da Administração | C18: Resposta da Administração sobre o ponto identificado e sobre as ações de melhoria sugeridas e, eventualmente, esclarecimento das prioridades recomendadas.
B19: Ações a serem Implementadas pela Administração | C19: Ações definidas pela Administração para resolução do ponto identificado.
B20: Data Limite para Resolução do Ponto Identificado | C20: Prazo estipulado pela Administração para que o ponto identificado deixe de existir.

Sheet P21
B2: Pontos de Controle
B3: Item | C3: Descrição
B4: Impacto | C4: =IF(C12>=75,"ALTO IMPACTO",IF(C12<=50,"BAIXO IMPACTO","MÉDIO IMPACTO")) -> ALTO IMPACTO | E4: <<<<<< Automático conforme Metodologia e baseado no grau de exposição
B5: Status | C5: =IFERROR(VLOOKUP(C6,'RESUMO DE PONTOS'!$C$9:$M$64,11,),"") -> • 08/11/2022 • Novo ■ Vorcon Auditoria & Consultoria
B6: Código | C6: [P21] | E6: <<<<<< Lista Suspensa (Selecionar)
B7: Título | C7: =VLOOKUP(C6,'BASE DA MATRIZ DE RISCOS'!$C$78:$D$202,2,) -> Perda Possível de Causa Judicial
B8: Tipo | C8: =VLOOKUP(C6,'BASE DA MATRIZ DE RISCOS'!$C$78:$E$202,3,) -> Legal | E8: <<<<<< Lista Suspensa (Selecionar)
B9: Tipo | C9: =VLOOKUP($C$8,'BASE DA MATRIZ DE RISCOS'!$C$30:$E$35,3) -> 5 | E9: <<<<<< Automático - Valores de 1 a 5 conforme metodologia
B10: Probabilidade | C10: =VLOOKUP(C6,'BASE DA MATRIZ DE RISCOS'!$C$78:$H$202,5,) -> 5 | E10: <<<<<< Valores de 1 a 5 conforme metodologia
B11: Impacto | C11: =VLOOKUP(C6,'BASE DA MATRIZ DE RISCOS'!$C$78:$H$202,6,) -> 4 | E11: <<<<<< Valores de 1 a 5 conforme metodologia
B12: Exposição | C12: =C9*C10*C11 -> 100 | E12: <<<<<< Calculado
B13: Testes/Áreas | C13: =VLOOKUP(C6,'BASE DA MATRIZ DE RISCOS'!$C$78:$J$202,8,) -> Teste de Contingência | E13: <<<<<< Automático - conforme Matriz de Risco
B14: Descrição | C14: =VLOOKUP(C$6,'RESUMO DE PONTOS'!$C$9:$H$64,3,) -> Identificamos no período de 28 de fevereiro 2022 a perda possível de R$ 406.946,20. Salientamos que a Perda Possível é aquela que o condomínio tem ou não uma obrigação presente legal como resultado de evento passado que haverá uma saída de recursos para liquidar essa obrigação.
B15: Riscos e Implicações | C15: =IFERROR(VLOOKUP(C$6,'RESUMO DE PONTOS'!$C$9:$H$64,4,),"") -> 0
B16: Impacto Financeiro | C16: =IFERROR(VLOOKUP(C$6,'RESUMO DE PONTOS'!$C$9:$H$64,5,),"") -> 396946.2
B17: Recomendações | C17: =IFERROR(VLOOKUP(C$6,'RESUMO DE PONTOS'!$C$9:$H$64,6,),"") -> 0
B18: Comentários da Administração | C18: Resposta da Administração sobre o ponto identificado e sobre as ações de melhoria sugeridas e, eventualmente, esclarecimento das prioridades recomendadas.
