Workbook
Name _Hlk102822595: 'BASE DE PONTOS V+'!#REF!
Name _Hlk102822605: 'BASE DE PONTOS V+'!#REF!
Name _Hlk44932008: 'Matriz de Risco'!$C$9
Name _Hlk44932008: 'RESUMO DE PONTOS'!#REF!
Name _Hlk44932008: 'RESUMO DE PONTOS Original'!$C$8
Name _Hlk44932282: 'Matriz de Risco'!$C$13
Name _Hlk44933547: 'Matriz de Risco'!$C$17
Name _Hlk44933737: 'Matriz de Risco'!$C$18
Name _Toc54348655: 'BASE DA MATRIZ DE RISCOS'!$C$19
Name _Toc54348656: 'BASE DA MATRIZ DE RISCOS'!$C$20
Name _Toc54348657: 'BASE DA MATRIZ DE RISCOS'!$C$37
Name _Toc54348658: 'BASE DA MATRIZ DE RISCOS'!$C$46
Name _Toc54348659: 'BASE DA MATRIZ DE RISCOS'!$C$75
Name _Toc54348660: 'BASE DA MATRIZ DE RISCOS'!$C$76
Name _Toc54348662: 'BASE DA MATRIZ DE RISCOS'!$C$127
Name _Toc70060767: TESTES!#REF!
Name _Toc70060768: TESTES!#REF!
Name _Toc70060769: TESTES!#REF!
Name _Toc70060770: TESTES!#REF!
Name _Toc70060771: TESTES!#REF!
Name _Toc70060772: TESTES!#REF!
Name _Toc70060773: TESTES!#REF!
Name _Toc70060774: TESTES!#REF!
Name _Toc70060775: TESTES!#REF!
Name _Toc70060776: TESTES!#REF!
Name _Toc70060777: TESTES!#REF!
Name _Toc70060778: TESTES!#REF!
Name _Toc70060779: TESTES!#REF!
Name _Toc70060780: TESTES!#REF!
Name _Toc70060781: TESTES!#REF!
Name _Toc70060782: TESTES!#REF!
Name _Toc70060783: TESTES!#REF!
Name _Toc70060784: TESTES!#REF!
Name _Toc70060785: TESTES!#REF!
Name _Toc70060786: TESTES!#REF!
Name _Toc70060787: TESTES!#REF!
Name _Toc70060788: TESTES!#REF!
Name _Toc70060789: TESTES!#REF!
Name _Toc70060790: TESTES!#REF!
Name _Toc70060791: TESTES!#REF!
Name _Toc70060792: TESTES!#REF!
Name _Toc70060793: TESTES!#REF!
Name _Toc70060794: TESTES!#REF!
Name _Toc70060795: TESTES!#REF!
Name _Toc70060796: TESTES!#REF!
Name _Toc70060797: TESTES!#REF!
Name _Toc70060798: TESTES!#REF!
Name _Toc70060799: TESTES!#REF!
Name _Toc70060800: TESTES!#REF!
Name _Toc70060801: TESTES!#REF!
Name _Toc70060802: TESTES!#REF!
Name _Toc70060803: TESTES!#REF!
Name _Toc70060804: TESTES!#REF!
Name _Toc70060805: TESTES!#REF!
Name _Toc70060806: TESTES!#REF!
Name _Toc70060807: TESTES!#REF!
Name _Toc70060808: TESTES!#REF!
Name _Toc70060809: TESTES!#REF!
Name _Toc70060810: TESTES!#REF!
Name _Toc70060811: TESTES!#REF!

Sheet TESTES
B2: Condomínio Mar de Itapuã
B3: Testes e Procedimentos da Auditoira Condominial
B4: Data base: 01/01/2021 à 31/12/2021
B6: Etapas | C6: Análise do Contrato - Auditoria conforme a NBC TA 800 | D6: Responsável | E6: Código Vorcon | F6: Cliente | G6: Testes e Procedimentos de Auditoria realizados | H6: Código do Teste | I6: Status testes | J6: Responsável | K6: Pedido de análise | L6: Descrição no Pedido de Análise | M6: Status pedido de análise | N6: Observações | P6: Simbolo | Q6: Tipo | R6: Conclusão
B7: Planejamento | E7: 01.1.1 | F7: CRP | G7: Confirmação de Independência | H7: 01.1.1 - CRP - Confirmação de Independência | I7: a | J7: Isaias | K7: N/A | M7: x | P7: a | Q7: OK | R7: =COUNTIFS(I7:I54,"a")/COUNTA(H7:H54) -> 0.41666667
B8: Planejamento | E8: 01.1.2 | F8: CRP | G8: Pedido de Análise | H8: 01.1.2 - CRP - Pedido de Análise | I8: a | J8: Isaias | K8: N/A | M8: x | P8: x | Q8: Não Aplicável | R8: =COUNTIFS(I7:I54,"x")/COUNTA(H7:H54) -> 0.27083333
B9: Planejamento | E9: 01.1.3 | F9: CRP | G9: Entrevista para entendimento dos controles internos do condomínio (Inquiries) | H9: 01.1.3 - CRP - Entrevista para entendimento dos controles internos do condomínio | I9: a | J9: Isaias | K9: N/A | M9: x | P9: r | Q9: Pendente | R9: =COUNTIFS(I7:I54,"")/COUNTA(H7:H54) -> 0.10416667
B10: Planejamento | E10: 01.1.4 | F10: CRP | G10: Cálculo da Materialidade | H10: 01.1.4 - CRP - Cálculo da Materialidade | I10: a | J10: Isaias | K10: Demonstrativos Financeiros - Relatório (01/01/2019 à 31/12/2021) | M10: a | P10: q | Q10: Em Andamento | R10: =COUNTIFS(I9:I56,"q")/COUNTA(H9:H56) -> 0.02173913
B11: Planejamento | E11: 01.1.5 | F11: CRP | G11: Follow Up CCI | H11: 01.1.5 - CRP - Follow Up CCI | I11: a | J11: Renata | K11: Relatório de auditoria anterior (2018) | M11: a
B12: Preparação | E12: 01.1.6 | F12: CRP | G12: Voucher documental | H12: 01.1.6 - CRP - Voucher documental | I12: a | J12: Time Vorcon | K12: Balancetes 100% | M12: a
B13: Preparação | E13: 01.1.7 | F13: CRP | G13: Constituição e operação do Condomínio | H13: 01.1.7 - CRP - Constituição e operação do Condomínio | I13: a | J13: David | K13: Convenção + Regimento Interno | M13: a
B14: Preparação | E14: 01.1.8 | F14: CRP | G14: Resumo Regimento | H14: 01.1.8 - CRP - Resumo Regimento | I14: a | J14: Renata | K14: Regimento Interno | M14: a
B15: Preparação | E15: 01.1.9 | F15: CRP | G15: Resumo Convenção | H15: 01.1.9 - CRP - Resumo Convenção | I15: a | J15: Renata | K15: Convenção | M15: a
B16: Preparação | E16: 01.1.10 | F16: CRP | G16: Resumo do Manual de Obrigações Trabalhistas | H16: 01.1.10 - CRP - Resumo do Manual de Obrigações Trabalhistas | I16: x | J16: - | K16: N/A | M16: x
B17: Preparação | E17: 01.1.11 | F17: CRP | G17: Resumo do Manual Operacional de Receitas | H17: 01.1.11 - CRP - Resumo do Manual Operacional de Receitas | I17: x | J17: - | K17: N/A | M17: x
B18: Preparação | E18: 01.1.12 | F18: CRP | G18: Resumo do Manual de Contratação | H18: 01.1.12 - CRP - Resumo do Manual de Contratação | I18: x | J18: - | K18: N/A | M18: x
B19: Preparação | E19: 01.1.13 | F19: CRP | G19: Carta de Representação de Atas | H19: 01.1.13 - CRP - Carta de Representação de Atas | I19: a | J19: Isaias | K19: N/A | M19: a
B20: Preparação | E20: 01.1.14 | F20: CRP | G20: Resumo Atas | H20: 01.1.14 - CRP - Resumo Atas | I20: a | J20: Renata | K20: Assinatura da Carta de Representação de Atas | M20: a
B21: Preparação | E21: 01.1.15 | F21: CRP | G21: Teste de voucher (inspeção das guias e confronto dos saldos demonstrativos) | H21: 01.1.15 - CRP - Teste de voucher (inspeção das guias e confronto dos saldos demonstrativos) | I21: r | J21: Isaias | K21: Balancetes 100% | M21: a
B22: Preparação | E22: 01.1.16 | F22: CRP | G22: Consolidação dos saldos dos demonstrativos financeiro + Voucher Documental | H22: 01.1.16 - CRP - Consolidação dos saldos dos demonstrativos financeiro + Voucher Documental | I22: a | J22: Time Vorcon | K22: Demonstrativo Financeiros + Balancetes | M22: a
B23: Execução | E23: 01.1.17 | F23: CRP | G23: Emitir Cartas de Circularização aos Bancos | H23: 01.1.17 - CRP - Emitir Cartas de Circularização aos Bancos | I23: x | K23: N/A | M23: x
B24: Execução | E24: 01.1.18 | F24: CRP | G24: Carta de Representação de Instituições Financeiras | H24: 01.1.18 - CRP - Carta de Representação de Instituições Financeiras | I24: a | J24: Isaias | K24: N/A | M24: a
B25: Execução | E25: 01.1.19 | F25: CRP | G25: Validação da Carta de Representação de Instituições Financeiras | H25: 01.1.19 - CRP - Validação da Carta de Representação de Instituições Financeiras | I25: r | J25: Renata | K25: Assinatura da Carta de Representação de Instituição Financeira | M25: a
B26: Execução | E26: 01.1.20 | F26: CRP | G26: Demonstrativo Financeiro + voucher nos extratos | H26: 01.1.20 - CRP - Demonstrativo Financeiro + voucher nos extratos | I26: q | J26: Isaias | K26: Demonstrativo Financeiros + Extratos | M26: a
B27: Execução | E27: 01.1.21 | F27: CRP | G27: Conciliação Bancária + Elaboração dos quadros dos Demonstrativos Financeiros | H27: 01.1.21 - CRP - Conciliação Bancária + Elaboração dos quadros dos Demonstrativos Financeiros | I27: a | J27: Isaias | K27: Demonstrativo Financeiros + Extratos + Balancetes | M27: a
B28: Execução | E28: 01.1.22 | F28: CRP | G28: Orçado X Realizado | H28: 01.1.22 - CRP - Orçado X Realizado | I28: x | J28: - | K28: Planejamento Orçamentário + Orçado x Realizado | M28: x
B29: Execução | E29: 01.1.23 | F29: CRP | G29: Revisão analitica de demonstrativos | H29: 01.1.23 - CRP - Revisão analitica de demonstrativos | I29: a | J29: Renata | K29: Demonstrativos Financeiros | M29: a
B30: Execução | E30: 01.1.23.1 | F30: CRP | G30: Revisão do Fundo de Reserva | H30: 01.1.23.1 - CRP - Revisão do Fundo de Reserva | I30: r | J30: Isaias | K30: Relatório Analítico do Fundo de Reserva (Está nos Extratos) | M30: a
B31: Execução | E31: 01.1.24 | F31: CRP | G31: Walkthrough de Receita | H31: 01.1.24 - CRP - Walkthrough de Receita | I31: x | J31: - | K31: N/A | M31: x
B32: Execução | E32: 01.1.25 | F32: CRP | G32: TOD + TOE de Receita | H32: 01.1.25 - CRP - TOD + TOE de Receita | I32: x | J32: - | K32: N/A | M32: x
B33: Execução | E33: 01.1.26 | F33: CRP | G33: Validação de Inadimplentes | H33: 01.1.26 - CRP - Validação de Inadimplentes | I33: a | J33: Isaias | K33: Inadimplentes | M33: a
B34: Execução | E34: 01.1.27 | F34: CRP | G34: Seguros | H34: 01.1.27 - CRP - Seguros | I34: r | J34: David | K34: Seguros | M34: a
B35: Execução | E35: 01.1.28 | F35: CRP | G35: Carta de Representação de Prestadores de Serviços (Detalhar os principais) | H35: 01.1.28 - CRP - Carta de Representação de Prestadores de Serviços (Detalhar os principais) | I35: a | J35: Isaias | K35: N/A | M35: x
... B49: Execução | E49: 01.1.42 | F49: CRP | G49: Teste de Contingências + Circularização de assessor jurídico | H49: 01.1.42 - CRP - Teste de Contingências + Circularização de assessor jurídico | I49: r | J49: Renata | K49: Controle auxiliar da Provisões para Contingências (Analítico) + Assinatura da Carta de Representação de Assessores Jurídicos | M49: x
B50: Revisão | E50: 01.1.43 | F50: CRP | G50: Consolidação de pontos (baseado no novo modelo com matriz de risco.) | H50: 01.1.43 - CRP - Consolidação de pontos (baseado no novo modelo com matriz de risco.) | K50: N/A | M50: x
B51: Revisão | E51: 01.1.44 | F51: CRP | G51: Carta de Representação da Administração | H51: 01.1.44 - CRP - Carta de Representação da Administração | J51: Renata
B52: Revisão | E52: 01.1.45 | F52: CRP | G52: Minuta da Auditoria NBC TA 800 | H52: 01.1.45 - CRP - Minuta da Auditoria NBC TA 800 | J52: Isaias
B53: Revisão | E53: 01.1.46 | F53: CRP | G53: Minuta da Apresentação da Auditoria NBC TA 800 | H53: 01.1.46 - CRP - Minuta da Apresentação da Auditoria NBC TA 800 | J53: Isaias
B54: Revisão | E54: 01.1.47 | F54: CRP | G54: Relatório Final da Auditoria NBC TA 800 | H54: 01.1.47 - CRP - Relatório Final da Auditoria NBC TA 800 | J54: Isaias

Sheet OPNIÃO
B1: Condomínios
B2: APROVA | C2: RELATÓRIO COM OPINIÃO SEM RESSALVA | D2: O relatório sem ressalva é emitido quando o auditor está convencido sobre todos os aspectos relevantes dos assuntos tratados no item 4 deste Pronunciamento. O relatório do auditor independente deve expressar essa convicção de forma clara e objetiva. | E2: O relatório sem ressalva implica afirmação de que, em tendo havido alterações em princípios contábeis ou no método de sua aplicação, o fato e os efeitos dele decorrentes foram adequadamente determinados e revelados nas demonstrações contábeis e/ou nas notas explicativas. | F2: O auditor não deve emitir um relatório sem ressalva quando existirem quaisquer das circunstâncias seguintes, que, na sua opinião, tenham efeitos relevantes para as demonstrações contábeis.
B3: APROVA COM RESSALVA | C3: RELATÓRIO COM OPINIÃO COM RESSALVA | D3: O relatório com ressalva é emitido quando o auditor conclui que o efeito de qualquer discordância ou restrição na extensão de um trabalho não é de tal magnitude que requeira relatório adverso ou abstenção de opinião. | E3: O relatório com ressalva deve obedecer ao modelo do relatório sem ressalva, com a utilização das expressões "exceto por", "exceto quanto" ou "com exceção de", referindo-se aos efeitos do assunto objeto da ressalva. Não é aceitável nenhuma outra expressão na redação desse tipo de relatório.
B4: Não APROVA | C4: RELATÓRIO COM OPINIÃO ADVERSO | D4: O auditor deve emitir relatório adverso quando verificar que as demonstrações contábeis estão incorretas ou incompletas, em tal magnitude que impossibilite a emissão do relatório com ressalvas. | E4: Assim, relatório adverso é o que exprime a opinião de que as demonstrações contábeis não representam adequadamente a posição patrimonial e financeira, nem o resultado das operações, e/ou as mutações do patrimônio líquido, e/ou as origens e aplicações de recursos de acordo com os Princípios Fundamentais de Contabilidade. | F4: O auditor deve, portanto, emitir relatório adverso quando verificar efeitos que, em sua opinião, comprometam em tal magnitude das demonstrações contábeis examinadas a ponto de não ser suficiente a simples ressalva no relatório. Nessas circunstâncias, uma ressalva não é considerada apropriada, uma vez que o auditor possui informações suficientes para declarar que as demonstrações contábeis não estão adequadamente apresentadas.
B5: Não APROVA | C5: RELATÓRIO COM ABSTENÇÃO DE OPINIÃO | D5: O relatório com abstenção de opinião é emitido quando houver uma limitação significativa na extensão de seus exames que impossibilite o auditor expressar opinião sobre as demonstrações contábeis por não ter obtido comprovação suficiente para fundamentá-la. Abstenção de opinião por limitação da extensão | E5: Nos casos de limitações significativas, o auditor deve, no parágrafo da extensão, indicar claramente os procedimentos omitidos e suas circunstâncias ou fazer uma referência a um parágrafo intermediário específico do relatório que descreva tal limitação. Em quaisquer desses casos, em parágrafo final do relatório, o auditor deve mencionar claramente que o exame não foi suficiente para permitir emissão de opinião sobre as demonstrações contábeis tomadas em conjunto. A abstenção de opinião não elimina a responsabilidade do auditor em mencionar, no relatório, qualquer desvio relevante que possa influenciar a decisão do usuário dessas informações.
C7: Análise: Quando houver distorção relevante ou não identificação de evidências de que as demonstrações não apresentam distorções relevantes, o auditor deverá modificar sua opinião, entre: opinião com ressalva, adversa ou com abstenção de opinião.
C9: Nessas ocasiões, deve-se atentar para as seguintes palavras-chave:
C11: RELEVANTE + NÃO GENERALIZADA (com ou sem evidências): Opinião com ressalva;
C12: RELEVANTE + GENERALIZADA (com evidência): Opinião Adversa;
C13: RELEVANTE + GENERALIZADA (sem evidência): Abstenção de Opinião.
C15: Tipos de Opinião do Auditor
C17: 1. Opinião com ressalva
C19: O auditor deve expressar uma “Opinião com ressalva” quando:
C21: ele, tendo obtido evidência de auditoria apropriada e suficiente, conclui que as distorções, individualmente ou em conjunto, são relevantes, mas Não Generalizadas nas demonstrações contábeis; ou
C22: não é possível para ele obter evidência apropriada e suficiente de auditoria para fundamentar sua opinião, mas ele conclui que os possíveis efeitos de distorções não detectadas sobre as demonstrações contábeis, se houver, poderiam ser relevantes, MAS NÃO GENERALIZADOS.
C24: 2. Opinião adversa
C26: O auditor deve expressar uma “Opinião adversa” quando, tendo obtido evidência de auditoria apropriada e suficiente, conclui que as distorções, individualmente ou em conjunto, são RELEVANTES E GENERALIZADAS para as demonstrações contábeis.
... C30: O auditor deve se abster de expressar uma opinião quando não consegue obter evidência de auditoria apropriada e suficiente para fundamentar sua opinião e ele concluir que os possíveis efeitos de distorções não detectadas sobre as demonstrações contábeis, se houver, poderiam ser relevantes e generalizados.
D32: Natureza do assunto que gerou a modificação | E32: Julgamento do auditor sobre a disseminação de forma generalizada dos efeitos ou possíveis efeitos sobre as DFs
E33: Não Generalizado | F33: Generalizado
D34: DFs apresentam Distorsões Relevantes | E34: Opinião com Ressalva | F34: Opinião Adversa
D35: Impossibilidade de se Obter Evidência de Auditoria Apropriada e Suficiente | E35: Opinião com Ressalva | F35: Abstenção de Opinião

Sheet VELOCIMETRO
E1: =SUM(E2:E4) -> 0.5
D2: Não Aprova | E2: =50%-E3-E4 -> 0.125 | F2: =E2/$E$1 -> 0.25
D3: Aprova c/Ressalva | E3: 0.125 | F3: =E3/$E$1 -> 0.25
D4: Aprova | E4: 0.25 | F4: =E4/$E$1 -> 0.5
E5: 0.5
E6: Aprova | G6: Aprova c/ Ressalva | I6: Não Aprova | K6: Não Aprova
D7: Total de Pontos de baixo Impacto | E7: 0 | F7: =K23 -> 0.15384615 | G7: 2 | H7: =G7/$G$10 -> 0.14285714 | I7: 15 | J7: =I7/$I$10 -> 0.6 | K7: 15 | L7: =K7/$K$10 -> 0.42857143
D8: Ponteiro | E8: 5 | F8: 0.01 | G8: 5 | H8: =G8/$G$10 -> 0.35714286 | I8: 5 | J8: =I8/$I$10 -> 0.2 | K8: 10 | L8: =K8/$K$10 -> 0.28571429
D9: Total de Pontos de alto Impacto | E9: 15 | F9: =K21 -> 0.61538462 | G9: 7 | H9: =G9/$G$10 -> 0.5 | I9: 5 | J9: =I9/$I$10 -> 0.2 | K9: 10 | L9: =K9/$K$10 -> 0.28571429
E10: =SUM(E7:E9) -> 20 | F10: =SUM(F7:F9) -> 0.77923077 | G10: =SUM(G7:G9) -> 14 | H10: =SUM(H7:H9) -> 1 | I10: =SUM(I7:I9) -> 25 | J10: =SUM(J7:J9) -> 1 | K10: =SUM(K7:K9) -> 35 | L10: =SUM(L7:L9) -> 1
D12: 0% - 50% | E12: Se, pelo menos 75% dos pontos forem de baixo impacto e não houver nenhum ponto de Alto impacto crítico o bastante para reprovar as contas
D13: 51% - 75% | E13: Se a maioria dos pontos forem de Média e Baixo Impacto e houverem pouco s pontos de alto impacto ( pelo menos 75% forem de pontos de médio e baixo impacto e nos pontos de alto impacto não haver nenhum ponto crítico o bastante para reprovar as contas.
D14: 75% - 90% | E14: Se a maioria dos pontos forem de alto Impacto e houverem poucos pontos de baixo e médio impacto ( pelo menos 75% forem de pontos de alto impacto e nos pontos de alto impacto não haver nenhum ponto crítico o bastante para reprovar as contas.
D15: Crítico ( 100% ) | E15: Se houver algum ponto crítico o bastante que a auditoria julgue que seja impactante o suficiente para não permitir a aprovação das contas ou haja limitação de escopo que não permita que a auditoria seja realizada.
E20: Ponto | F20: Tipo | G20: Quantidade
E21: P01 | F21: ALTO | G21: 1 | I21: Alto | J21: =SUMIF($F$21:$F$46,$I21,$G$21:$G$46) -> 8 | K21: =J21/$J$24 -> 0.61538462
E22: P02 | F22: ALTO | G22: 1 | I22: Médio | J22: =SUMIF($F$21:$F$46,$I22,$G$21:$G$46) -> 3 | K22: =J22/$J$24 -> 0.23076923
E23: P03 | F23: ALTO | G23: 1 | I23: Baixo | J23: =SUMIF($F$21:$F$46,$I23,$G$21:$G$46) -> 2 | K23: =J23/$J$24 -> 0.15384615
E24: P04 | F24: ALTO | G24: 1 | J24: =SUM(J21:J23) -> 13 | K24: =SUM(K21:K23) -> 1
E25: P05 | F25: ALTO | G25: 1
E26: P06 | F26: ALTO | G26: 1
E27: P07 | F27: MÉDIO | G27: 1
E28: P08 | F28: BAIXO | G28: 1
E29: P09 | F29: ALTO | G29: 1
E30: P10 | F30: ALTO | G30: 1
E31: P11 | F31: BAIXO | G31: 1
E32: P12 | F32: MÉDIO | G32: 1
E33: P13 | F33: MÉDIO | G33: 1
E34: P14 | G34: 1
E35: P15 | G35: 1
E36: P16
E37: P17
E38: P18
E39: P19
E40: P20
E41: P21
E42: P22
E43: P23
E44: P24
E45: P25
E46: P26
B47: x | C47: x | D47: x | E47: x | F47: x | G47: x | H47: x | I47: x

Sheet BASE DE PONTOS V+
B2: Condomínio Mar de Itapuã
B3: BASE DE PONTOS V+
B4: Data base: 12/2021
B6: 2 | C6: 2 | H6: 7 | I6: 8 | J6: 8 | K6: 8 | M6: 8
B7: V+ | C7: Descrição Resumida | D7: Descrição | E7: Impacto Financeiro | F7: Riscos e Impactos | G7: Recomendação | H7: Tipo | I7: Tipo de Teste | J7: Julgamento | K7: Tipo de Teste | M7: Tipo de Teste
B8: V01 | C8: Pagamento sem nota fiscal | D8: Verificamos que ocorreram gastos sem a respectiva emissão de nota fiscal pelos fornecedores e prestadores de serviços. | E8: 47819.88 | F8: Pagamento sem os respectivos Fornecedores/Prestadores de serviços não é permitido pela legislação brasileira assim como Convenção e Regimento Interno do Condomínio podendo ser multado e/ou sofrer outras penalidades impostas pelo fisco. | G8: Sugerimos que seja solicitado aos respectivos Fornecedores/ Prestadores de serviços ou fornecedores a nota fiscal pelo fornecimento de material ou de prestação de serviço. | H8: Legal | I8: Voucher Documental | J8: Alto Impacto | L8: • 31/12/2021 • Recorrente ■ Vorcon Auditoria & Consultoria ■ 24/06/2022
B9: V02 | C9: Diferenças entre: Favorecido do documento X Beneficiário do pagamento | D9: O fornecedor apresentado no comprovante de pagamento não é o mesmo da Nota Fiscal. | E9: 516.77 | F9: Pagamentos realizados a fornecedores diferentes do da Nota Fiscal pode evidenciar pagamentos indevidos ou mesmo situações que levem a riscos de fraude. | G9: Sugerimos que seja solicitado aos respectivos prestadores de serviço ou fornecedores a nota fiscal pelo fornecimento de material ou de prestação de serviços. | H9: Legal | I9: Voucher Documental | J9: Baixo Impacto | L9: • 31/12/2021 • Recorrente ■ Vorcon Auditoria & Consultoria ■ 24/06/2022
B10: V03 | C10: Pagamentos realizados sem os respectivos comprovantes de pagamento anexados | D10: Verificamos que alguns pagamentos foram realizados sem que fossem anexados os respectivos comprovantes de pagamentos ou documentos equivalentes dando a respectiva quitação. | E10: 23309.37 | F10: Pagamento duplicado dos valores, ou caso haja a solicitação do comprovante de pagamento o Condomínio não os possua | G10: Sugerimos que sejam criados processos para que os comprovantes de pagamentos estejam anexados ao processo de pagamentos | H10: Financeiro | I10: Voucher Documental | J10: Alto Impacto | L10: • 31/12/2021 • Recorrente ■ Vorcon Auditoria & Consultoria ■ 24/06/2022
B11: V04 | C11: Negligência na gestão dos Documentos que compõe os Demonstrativos | D11: Verificamos que alguns comprovantes não estão sendo arquivados com os cuidados necessários, com isso alguns estão ilegíveis. | E11: 1087.39 | F11: Dificuldade na visualização dos gastos e impossibilidade e dúvidas quanto a possíveis consultas no futuro em função do estado dos documentos. | G11: Sugerimos que sejam criados processos para que os comprovantes sejam de responsabilidade do financeiro tirar cópia ou digitalizá-los assim que os receber. | H11: Operacional | I11: Voucher Documental | J11: Baixo Impacto | L11: • 31/12/2021 • Recorrente ■ Vorcon Auditoria & Consultoria ■ 24/06/2022
B12: V05 | C12: Pagamento de tarifa bancária. | D12: Verificamos que ocorreram pagamento de fornecedores e prestadores de serviços por meio de transferência bancária. | E12: 88.4 | F12: Pagamento de encargos financeiros que deveriam ser de responsabilidade dos Fornecedores/Prestadores de serviços | G12: Sugerimos que seja solicitado boleto para pagamento de todos os Fornecedores/Prestadores de serviços e em caso de negativa o valor dos encargos financeiros deve ser subtraído do pagamento. | H12: Financeiro | I12: Voucher Documental | J12: Baixo Impacto | L12: • 31/12/2021 • Recorrente ■ Vorcon Auditoria & Consultoria ■ 24/06/2022
B13: V06 | C13: Diferenças entre: Valor do comprovante de pagamento X Valor da documentação suporte. | D13: Verificamos que há diferença entre os valores apresentados, não justificada por parcelamento ou multa. | E13: 333.3 | F13: Possibilidade de pagamentos realizados com valores incorretos. | G13: Sugerimos que os pagamentos sejam realizados com os valores que constam no documento auxiliar. | H13: Financeiro | I13: Voucher Documental | J13: Baixo Impacto | L13: • 31/12/2021 • Recorrente ■ Vorcon Auditoria & Consultoria ■ 24/06/2022
B14: V07 | C14: Acesso a Convenção do Condomínio | D14: Verificamos que o Condomínio não possui site, o ideal seria ter um site e disponibiliar o requimento Regimento nele. | E14: N/A | F14: As melhores práticas de gestão sugerem que as informações do Condomínio estejam de fácil acesso para qualquer condômino. | G14: Sugerimos que o Condomínio contate a sua equipe de TI e verifique a possibilidade de criar um site do Condomínio e disponibilizar a convenção | H14: Operacional | I14: Resumo da Convenção | J14: Baixo Impacto | L14: • 31/12/2021 • Recorrente ■ Vorcon Auditoria & Consultoria ■ 24/06/2022
B15: V08 | C15: Os balancetes sem aprovação dos conselheiros fiscais no termo de aprovação. | D15: Nos meses 01/2021 à 12/2021 não constam as assinaturas dos conselheiros fiscais e do síndico para aprovação dos balancetes. | E15: N/A | F15: A falta das assinaturas dos conselheiros fiscais nos termos de aprovação dos balancetes indica que as contas do condomínio não foram submetidas ao exame, acarretando a redução do nível de confiança dos demonstrativos e podendo prejudicar a leitura dos usuários. | G15: Sugerimos que os conselheiros fiscais realizem o exame dos balancetes e caso ocorra a aprovação dos mesmos, confirmem com as suas assinaturas nos termos de aprovação. Mesmo com as demonstrações financeiras sendo auditadas mensalmente, é necessário a validação do conselho fiscal. | H15: Operacional | I15: Resumo da Convenção | J15: Baixo Impacto | L15: • 31/12/2021 • Novo ■ Vorcon Auditoria & Consultoria ■ 24/06/2022
B16: V09 | C16: Impacto com os inadimplentes | D16: Verificamos que a inadimplência na data base de 31/12/2021 foi equivalente a R$ 23.053,25 atualizados com multas, juros e correção. | E16: 23053.25 | F16: O alto índice de inadimplência condominial impacta inicialmente o orçamento do condomínio. Assim, é preciso compensar de alguma forma o déficit orçamentário para que as obrigações condominiais sejam cumpridas. Como alternativas para essas compensações, podem ser ajustados os valores das taxas condominiais, utilizados os seus fundos de reserva ou criadas taxas extras, gerado assim, prejuízos aos condomínios adimplentes e a toda estrutura financeira condominial. Ademais, ocorre as implicações de ordem interpessoal para que ocorra a regularização dos valores, o que em casos mais graves necessita de cobrança judicial, gerando outros gastos com honorários advocatícios e custas judiciais. | G16: Indicamos à administração ações preventivas que tenham como objetivo a redução das despesas condominiais, o fortalecimento do fundo de reserva e a cobrança de maneira assertiva dos inadimplentes. Além disso, devem ser buscadas alternativas analisando a relação de custos e benefícios para solução desse problema, como por exemplo, a utilização dos serviços de uma garantidora de condomínio. | H16: Financeiro | I16: Inadimplentes | J16: Médio Impacto | L16: • 31/12/2021 • Recorrente ■ Vorcon Auditoria & Consultoria ■ 24/06/2022
B17: V10 | C17: Ausência de Inventário dos ativos imobilizados | D17: Não foi possível identificar o controle patrimonial dos ativos imobilizados do condomínio. | E17: N/A | F17: A ausência do controle patrimonial, o condomínio poderá impactar em possíveis perdas ou desvios do ativo imobilizado. | G17: Sugerimos à Administração do condomínio que busque realizar o inventário dos ativos imobilizados anualmente. | H17: Financeiro | I17: Ativo imobilizado | J17: Alto Impacto | L17: • 31/12/2021 • Recorrente ■ Vorcon Auditoria & Consultoria ■ 24/06/2022
B18: V11 | C18: Inexistência de informações para emissão da certidão de FGTS na Caixa econômica Federal. | D18: Ao realizar a consulta do Certificado de Regularidade Do FGTS, obtivemos a seguinte resposta: "As informações disponíveis não são suficientes para a comprovação automática da regularidade do empregador perante o FGTS. Solicitamos acessar o portal Conectividade Social, mediante certificado ICP, para verificar possíveis impedimentos ou comparecer a uma das Agências da CAIXA". Com esclarecimentos adicionais no endereçamento. | E18: N/A | F18: A inexistência dos dados para emissão da certidão junto ao Caixa, poderá resultar no agravamento do acompanhamento das certidões. | G18: Sugerimos que a administração entre no portal Conectividade Social da Caixa e faça o entendimento de quais dados estão faltando para verificar possíveis impedimentos. | H18: Legal | I18: Certidão | J18: Alto Impacto | L18: • 31/12/2021 • Recorrente ■ Vorcon Auditoria & Consultoria ■ 24/06/2022
B19: V12 | C19: Capacidade de arrecadação inferior aos gastos. | D19: As receitas do meses 02, 04, 07, 09, 10 e 12/2021 não estão sendo suficiente para cobrir as despesas, acarretando em um défict no total nesses meses de - R$ 235.528,38 | E19: -235528.38 | F19: Com as despesas elevadas, o condomínio não consegue arcar com 100% das suas obrigações afetando o fluxo de caixa do financeiro, e ao mesmo tempo não consegue atingir um valor médio ou alto para o fundo de reserva para um futuro inesperado. | G19: Recomendamos ao Conselho Fiscal e a Administração condominial que verifique novas ações a realizar para redução das despesas mitigando ou solucionando o problema. | H19: Estratégico | I19: Demonstrativo de Receita e Despesas | J19: Alto Impacto | L19: • 31/12/2021 • Recorrente ■ Vorcon Auditoria & Consultoria ■ 24/06/2022
B20: V13 | C20: Envio de Boleto Fraudado | D20: Identificamos que o Condomínio enviou um possível boleto fraudado para a Condômina Jussara Barros da Unidade 2801 B no Mês 01/2021 na qual realizou o pagamento. O condomínio necessitou realizar a baixa do valor pago da condômina resultando em prejuízo financeiro de R$ 919,14. | E20: 919.14 | F20: A falta de processo da análise do controle interno das contas a pagar sobre a verificação dos envios dos boletos recebidos pelo Advogado, poderá acarretar em envios de boletos errôneos e gerar prejuízos ao condomínio e a toda estrutura financeira condominial. | G20: Recomendamos a Administração do Condomíonio verifique ações de controles internos para verificação dos boletos enviados aos clientes. | H20: Operacional | I20: Demonstrativo de Receita e Despesas | J20: Baixo Impacto | L20: • 31/12/2021 • Novo ■ Vorcon Auditoria & Consultoria ■ 24/06/2022
B21: V14 | C21: Débito automático referente ao bloqueio judicial | D21: Identificamos nos extratos e nas despesas operacionais que houve o débito automático de de R$ 1.045,19 no mês 8/2021 e de R$ 420,069 no mês 09/2021 referente ao bloqueio judicial. | E21: 1465.259 | F21: Os gastos com bloqueios judiciais geram possíveis prejuízos ao condomínio e a toda estrutura financeira condominial. | G21: Sugerimos a Administração do Condomínio que mantenha o monitoramento constante dos processos financeiros e judicial acompanhando os processos em andamento. | H21: Legal | I21: Extratos | J21: Médio Impacto | L21: • 31/12/2021 • Novo ■ Vorcon Auditoria & Consultoria ■ 24/06/2022
B22: V15 | C22: Saldo bloqueado Custódia de Caução. | D22: Identificamos que durante os meses 09, 10, 11 e 12/2021 o condomínio está em opção custodia caução no valor R$ 4.889,37 nas contas, Bradesco e Caixa Econômica devido a cancelamento do acesso ao conta CEF não foi possível atualizar o saldo das contas. | E22: 4889.37 | F22: Devido ao bloqueio do saldo da conta CEF, não foi possível atualizar o saldo das contas nos meses 09, 10, 11 e 12/2021 podendo afetar diretamente o fluxo de caixa e o controle do financeiro do condomínio. | G22: Sugerimos que a administração entre em contato com a Caixa Econômica Federal e verificar os possíveis impedimentos. | H22: Financeiro | I22: Demonstrativo de Receita e Despesas | J22: Baixo Impacto | L22: • 31/12/2021 • Novo ■ Vorcon Auditoria & Consultoria ■ 24/06/2022
B23: V16 | C23: Não há classificação de expectativa de ganho para algumas causas ativas e de perda para as passivas. | D23: Não há classificação de expectativa de ganho para algumas causas ativas e de perda para as passivas. | E23: 22000 | F23: Verificamos os relatórios de contingências de 2021 e não identificamos quais expectativas de ganho ou perda no contrato. • Passivas – montante de R$ 22.000,00 | G23: Recomendamos que o jurídico do condomínio forneça informações relativa a estimativa de perda ou ganhos dos processos ativos. | H23: Legal | I23: Contigência | J23: Alto Impacto | L23: • 31/12/2021 • Novo ■ Vorcon Auditoria & Consultoria ■ 24/06/2022
B24: V17 | C24: Perda de Causa Judicial | D24: Indentificamos que durante o período de 2021 que há perda de causa judicial de R$ 10.477,17 referente ao n° 0101419-55.2017.8.05.0001 de TICIANA CARNEIRO DA ROCHA PRATA MONTEIRO X TRIBECA, e R$ 29.000,00 referente ao n° 0164073-44.2018.8.05.0001 de RAFAEL CALDAS LOPES X TRIBECA, totalizando em uma perda de R$ 39.477,17 | E24: =29000+10477.17 -> 39477.17 | F24: Devido a perda das causas judicais podendo afetar diretamente o fluxo de caixa e o controle do financeiro do condomínio. | G24: Recomendamos ações preventivas nas melhorias no controle interno para que as causas judiciais não sejam abertas contra o condomínio. | H24: Legal | I24: Contigência | J24: Alto Impacto | L24: • 31/12/2021 • Novo ■ Vorcon Auditoria & Consultoria ■ 24/06/2022

Sheet Matriz de Risco
B6: BASE DA MATRIZ
B7: [P01] | C7: Não foi estabelecida a confiança nos controles que estão implementados no Condomínio Le Parc Residential Resort. | D7: Alto Impacto | E7: Operação Administrativa do Condomínio
B8: [P02] | C8: Ausência de manual de normas e procedimentos | D8: Alto Impacto | E8: Manual de normas e procedimentos
B9: [P03] | C9: Diferenças entre: Favorecido do documento X Beneficiário do pagamento | D9: Alto Impacto | E9: Inspeção Documental - Gastos
B10: [P04] | C10: Pagamentos realizados sem os respectivos comprovantes de pagamento anexados | D10: Alto Impacto | E10: Inspeção Documental - Gastos
B11: [P05] | C11: Diferenças entre: Valor do comprovante de pagamento X Valor da documentação suporte. | D11: Alto Impacto | E11: Inspeção Documental - Gastos
B12: [P06] | C12: Inexistência de rotina de inventário físico do ativo imobilizado. | D12: Alto Impacto | E12: Imobilizado
B13: [P07] | C13: Definição de vida útil do ativo imobilizado | D13: Médio Impacto | E13: Imobilizado
B14: [P08] | C14: Páginas não numeradas ou numeradas de forma incorreta. | D14: Baixo Impacto | E14: Controle Interno
B15: [P09] | C15: Registro da Convenção do Condomínio Le Parc Residential Resort em cartório. | D15: Alto Impacto | E15: Convenção
B16: [P10] | C16: Registro do Regimento do Condomínio Le Parc Residential Resort em cartório. | D16: Alto Impacto | E16: Regimento do Condomínio
B17: [P11] | C17: Não há classificação de expectativa de ganho para algumas causas ativas e de perda para as passivas. | D17: Baixo Impacto | E17: Contingências
B18: [P12] | C18: Inexistência de padronização dos relatórios mensais de contingência | D18: Médio Impacto | E18: Contingências
B19: [P13] | C19: Relatório de encaminhamento aos órgãos de proteção ao crédito. | D19: Médio Impacto | E19: Contingências

Sheet RESUMO DE PONTOS Original
F3: Avaliação da soma das NFs Identificadas | I3: Leilane ajustar | J3: JULGAMENTO PROFISSIONAL | L3: Utilizar essa estrutura no Status
B4: 1 | C4: 2 | D4: 3 | E4: 4 | F4: 5 | G4: 6 | H4: 7 | I4: 8 | J4: 9 | K4: Status | L4: Estrutura
B5: Ponto | C5: Descrição Resumida | D5: Descrição do Ponto | E5: Riscos e Implicações | F5: Impacto Financeiro | G5: Recomendações | H5: Tipo | I5: Tipo de Teste
B6: [P1] | C6: Pagamento sem nota fiscal | D6: Verificamos que ocorreram gastos sem a respectiva emissão de nota fiscal pelos fornecedores e prestadores de serviços. | E6: Pagamento sem os respectivos Fornecedores/ Prestadores de serviços não é permitido pela legislação brasileira assim como Convenção e Regimento Interno do Condomínio. | F6: N/A | G6: Sugerimos que seja solicitado aos respectivos Fornecedores/ Prestadores de serviços ou fornecedores a nota fiscal pelo fornecimento de material ou de prestação de serviços. | H6: Estratégico | I6: Operação Administrativa do Condomínio | J6: MÉDIO IMPACTO | K6: • 31/12/2020 • Recorrente ■ Vorcon Auditoria & Consultoria ■ 22 de abril de 2021 | L6: • [Data base do relatório] • Ponto Novo ou Recorrente??? ■ Empresa que Identificou o Ponto ■ 22 de abril de 2021 [Data do relatório]
B7: [P2] | C7: Diferenças entre: Favorecido do documento X Beneficiário do pagamento | D7: O fornecedor apresentado no comprovante de pagamento não é o mesmo da Nota Fiscal. | E7: Pagamento sem as respectivas notas fiscais não é permitido pela legislação brasileira assim como Convenção e Regimento Interno do Condomínio. | F7: N/A | G7: Sugerimos que seja solicitado aos respectivos prestadores de serviço ou fornecedores a nota fiscal pelo fornecimento de material ou de prestação de serviços. | H7: Operacional | I7: Manual de normas e procedimentos | J7: BAIXO IMPACTO | K7: • 31/12/2020 ■ Vorcon Auditoria & Consultoria ■ 22 de abril de 2021
B8: [P3] | C8: Pagamentos realizados sem os respectivos comprovantes de pagamento anexados | D8: Verificamos que alguns pagamentos foram realizados sem que fossem anexados os respectivos comprovantes de pagamentos ou documentos equivalentes dando a respectiva quitação. | E8: Pagamento duplicado dos valores, ou caso haja a solicitação do comprovante de pagamento o Condomínio não os possua. | F8: N/A | G8: Sugerimos que sejam criados processos para que os comprovantes de pagamentos estejam anexados ao processo de pagamentos. | H8: Operacional | I8: Inspeção Documental - Gastos | J8: ALTO IMPACTO | K8: • 31/12/2020 ■ Vorcon Auditoria & Consultoria ■ 22 de abril de 2021
B9: [P4] | C9: Pagamento de impostos sem identificação do prestador de serviços | D9: Não identificamos documentação suporte que indique a origem dos impostos e os respectivos prestadores de serviço. | E9: Possíveis pagamentos duplicado dos valores, ou caso haja a solicitação do comprovante de pagamento o Condomínio não os possua | F9: N/A | G9: Sugerimos que sejam criados processos para que todos os documentos estejam anexados ao processo de prestação de contas no demonstrativo financeiros. | H9: Operacional | I9: Inspeção Documental - Receitas | J9: MÉDIO IMPACTO | K9: • 31/12/2020 ■ Vorcon Auditoria & Consultoria ■ 22 de abril de 2021
B10: [P5] | C10: Conjunto de documentos sem apresentação de mapa de orçamentos. | D10: Verificamos que muitas das compras realizadas não estavam anexados os mapas de orçamento. | E10: Agindo dessa forma, não estão em conformidade com as normas do estatuto vigente do condomínio. | F10: N/A | G10: Seja realizada a conferência na pré-compra, se estão observando as normas do mapa do orçamento | H10: Estratégico | I10: Imobilizado | J10: BAIXO IMPACTO | K10: • 31/12/2020 ■ Vorcon Auditoria & Consultoria ■ 22 de abril de 2021
B11: [P6] | C11: Inexistência de tempestividade na prestação de contas do fundo fixo | D11: Verificamos que o fundo fixo do Condomínio, por diversas vezes, possui valores retirados onde existe a prestação de contas nos meses não referentes. | E11: Não sendo apresentadas tempestivamentes as apresentações das contas do fundo fixo, afetará diretamente o fluxo de caixa e o controle do fundo fixo do condomínio. | F11: N/A | G11: Seja elaborada uma periodicidade fixa para apresentação das contas do fundo fixo, e que seja realizado as prestações dos períodos correspondentes as despesas. | H11: Operacional | I11: Controle Interno | J11: ALTO IMPACTO | K11: • 31/12/2020 ■ Vorcon Auditoria & Consultoria ■ 22 de abril de 2021
B12: [P7] | C12: Inconsistência na apresentação da atividade da empresa | D12: O serviço/produto adquirido não condiz com a atividade econômica apresentada no CNPJ da empresa. | E12: Afeta diretamente nos cálculos de retenções de impostos do condomínio, se a empresa prestadora de serviço siga a legislação que não à apresentada. | F12: N/A | G12: Criação de um passo a passo na empresa contratada na intenção de verificar a sua atividade perante a forma de tributação. | H12: Estratégico | I12: Regimento | J12: MÉDIO IMPACTO | K12: • 31/12/2020 ■ Vorcon Auditoria & Consultoria ■ 22 de abril de 2021
B13: [P8] | C13: Negligência na gestão dos Documentos que compõe os Demonstrativos | D13: Verificamos que alguns comprovantes não estão sendo arquivados com os cuidados necessários, com isso alguns estão ilegíveis. | E13: Dificuldade na visualização dos gastos e impossibilidade e dúvidas quanto a possíveis consultas no futuro em função do estado dos documentos. | F13: N/A | G13: Sugerimos que sejam criados processos para que os comprovantes sejam de responsabilidade de quem incorre no gasto sendo de responsabilidade do financeiro tirar cópia dos comprovantes ou digitaliza-los assim que os receber. | H13: Operacional | I13: 02.1.2 STC - Voucher documental | J13: BAIXO IMPACTO | K13: • 31/12/2020 • Recorrente ■ Vorcon Auditoria & Consultoria ■ 22 de abril de 2021
B14: [P9] | C14: Conjunto de documentos sem composição clara do valor pago | D14: Verificamos que existe apresentação de despesa sem os respectivos comprovantes de pagamentos. | E14: Pagamento sem os respectivos comprovante de pagamento não é permitido pela Convenção e Regimento Interno do Condomínio. | F14: N/A | G14: Criação de um passo a passo para verificação nos comprovantes de pagamentos das despesas do condomínios. | H14: Operacional | I14: Inspeção Documental - Gastos | J14: ALTO IMPACTO | K14: • 31/12/2020 ■ Vorcon Auditoria & Consultoria ■ 22 de abril de 2021
B15: [P10] | C15: Páginas não numeradas ou numeradas de forma incorreta | D15: Verificamos que algumas páginas do Demonstrativo Financeiro não estão sendo numeradas ou não seguem uma ordem sequencial. | E15: Falhas na padronização implica em perda de eficiência na conferência das prestações de contas. | F15: N/A | G15: Sugerimos que seja criada rotina de revisão da padronização dos Demonstrativos Financeiros mensais, pois isso mitigará possivéis falhas. | H15: Operacional | I15: 02.1.2 STC - Voucher documental | J15: MÉDIO IMPACTO | K15: • 31/12/2020 • Recorrente ■ Vorcon Auditoria & Consultoria ■ 22 de abril de 2021
B16: [P11] | C16: Pagamento de tarifa bancária. | D16: Verificamos que ocorreram pagamento de fornecedores e prestadores de serviços por meio de transferência bancária. | E16: Pagamento de encargos financeiros que deveriam ser de responsabilidade dos Fornecedores/Prestadores de serviços. | F16: N/A | G16: Sugerimos que seja solicitado boleto para pagamento de todos os Fornecedores/Prestadores de serviços e em caso de negativa o valor dos encargos financeiros deve ser subtraído do pagamento. | H16: Financeiro | I16: Inspeção Documental - Gastos | J16: BAIXO IMPACTO | K16: • 31/12/2020 • Recorrente ■ Vorcon Auditoria & Consultoria ■ 22 de abril de 2021
B17: [P12] | C17: Conjunto de documentos anexados fora do mês correspondente. | D17: Desorganização da documentação suporte dificultam a análise de todas as partes envolvidas. | E17: Não sendo apresentadas tempestivamentes as apresentações das contas, afetará diretamente o fluxo de caixa e o controle do financeiro do condomínio. | F17: N/A | G17: Seja elaborada uma periodicidade fixa para apresentação das despesas, e que seja realizado as prestações dos períodos correspondentes as despesas. | H17: Operacional | I17: Inspeção Documental - Gastos | J17: ALTO IMPACTO | K17: • 31/12/2020 ■ Vorcon Auditoria & Consultoria ■ 22 de abril de 2021
B18: [P13] | C18: Conjunto de documentos anexados no balancete sem o mesmo constarem nos demonstrativos financeiros mensais de gastos. | D18: Ausência de transparência na prestação de contas e aumento do risco de pagamentos indevidos. | E18: A apresentação no balancetes sem os respectivos comprovantes do demonstrativos financeiros não é permitido pela legislação brasileira e pela Convenção e Regimento Interno do Condomínio. | F18: N/A | G18: Seja elaborada uma periodicidade fixa para apresentação dos respectivos comprovantes nos balancetes e que seja realizado as prestações dos períodos correspondentes as despesas. | H18: Operacional | I18: Inspeção Documental - Gastos | J18: MÉDIO IMPACTO | K18: • 31/12/2020 ■ Vorcon Auditoria & Consultoria ■ 22 de abril de 2021
... B30: [P28] | C30: Fornecedores citados na resposta de circulação indevidamente | D30: Em resposta na carta de circularização foram citados os seguintes fornecedores: Grupo Contínua - 07.536.483/0001-92, Ecowash - 11.877.873/0001-01, Elemidia - 03.616.039/0001-26, Izar Park - 18.021.222/0001-56, Posto Mataripe - 13.578.265/0001-13, LA Construções - 20.726.309/0001-70, Softdados - 17.869.823/0001-50, Grupo Solução - 23.105.423/0001-71 e Coopcicla - 01.397.759/0001-12, contudo não houveram pagamentos no período em que a auditoria está sendo realizada, informação confirmada posteriormente pela Administração. | E30: Dificuldade quanto ao rastreamentos dos contratos e incerteza quanto a informação apresentada. | F30: N/A | G30: Recomendamos que sejam tomadas as medidas necessárias para que haja um padrão sobre apresentação das informações do contrato e sejam apresentadas conforme solicitado. | H30: Operacional | I30: 02.2.9 STC - Validação da carta de representação de contratos | J30: BAIXO IMPACTO | K30: • 31/12/2020 • Recorrente ■ Vorcon Auditoria & Consultoria ■ 22 de abril de 2021
B31: [P29] | C31: Não há controle de recolhimento do FGTS das empresas terceirizadas | D31: Não nos foi encaminhado um controle de recolhimento a respeito do recolhimento do FGTS dos funcionários que trabalham de forma terceirizada no condomínio. Esse controle é necessário tendo em vista que o condomínio é subsidiariamente responsável pelos recolhimentos tributários e trabalhistas assim como legisla a Súmula 331, IV, do TST | E31: Recolhimento do FGTS sobre os funcinonarios contratados de forma terceirizados. | F31: 1086628.7 | G31: Recomendamos ter um controle de recolhimentos dos funcionários contratados de forma terceirizado. | H31: Operacional | I31: 02.3.3 STC - Recalculo individual de Colaboradores (Validar quantidade com o gestor do projeto) | J31: ALTO IMPACTO | K31: • 31/12/2020 • Novo ■ Vorcon Auditoria & Consultoria ■ 22 de abril de 2021
B32: [P30] | C32: Inexistência de atualização dos Relatórios Jurídicos | D32: Solicitamos a Administração os relatórios jurídicos para o período do trabalho realizado, contudo após a relaização dos testes verificamos que os relatórios disponibilizados apesar de serem de meses diferentes não possuem diferença. Dessa forma há dúvidas se os mesmos estão sendo atualizados ou não. | E32: Possível risco de informações desatualizadas que podem gerar saídas de caixa não programadas para o Condomínio. | F32: N/A | G32: Sugerimso que os relatórios sejam atualizados mensalmente com a expectativa real do valores e ações. Conforme atualização dos processos. | H32: Financeiro | I32: Contingências | J32: BAIXO IMPACTO | K32: • 31/12/2020 • Novo ■ Vorcon Auditoria & Consultoria ■ 22 de abril de 2021
B33: [P31] | C33: Inexistência de expectativa de Ganho e Perda para os Relatórios Jurídicos. | D33: Os relatórios jurídicos apresentados pela Administração não possuem a expectativa de perda ou ganho dos mesmos, conforme prática usual dos assesores jurídicos. | E33: A inêxistência da classificação quanto a possiveis perdas faz com que a Adiministração não possa planejar possiveis saídas de caixas futuras, e além disso tal prática não contempla as melhores práticas de mercado. | F33: N/A | G33: Sugiro que a Administração solicite aos seus Assessores jurídicos que mensalmente os relatórios sejam classificados tanto para perda ou para ganho como: Remota: Prognóstico de perda deve ser menos do que 25% Possível: Prognóstico de perda desde que o risco não seja remoto Provável: Prognóstico de perda deve ser mais do que 50% | H33: Financeiro | I33: 02.3.6 STC - Validação da Carta de Representação de Assessores Jurídicos | J33: BAIXO IMPACTO | K33: • 31/12/2020 • Novo ■ Vorcon Auditoria & Consultoria ■ 22 de abril de 2021
B34: [P32] | C34: Inexistência de politica de acompanhamento das principais certidões. | D34: A Administração não possui como rotina o acompanhamento das principais certidões: Municipal; Estaduas; Federal e; Serviço de proteção de Crédito. | E34: A inexistência do acompanhamento de forma preventiva das certidões pode vir a gerar desembolsados não esperados assim como possíveis bloqueios que podem vir a afetar a rotina do Condomínio. | F34: N/A | G34: Sugerimos que a Administração avalie adicionar em sua rotina, pelo menos trimestral, a emissão dessas certidões como forma de mitigar possíveis problemas. | H34: Legal | I34: 02.3.4 STC - Certidões | J34: MÉDIO IMPACTO | K34: • 31/12/2020 • Novo ■ Vorcon Auditoria & Consultoria ■ 22 de abril de 2021
B35: [P33] | C35: Limitação de escopo | D35: A administração não possui acompanhamento para a rotina de cobrança feita aos condominos inadimplentes | E35: A não entrega de documentos ou evidencias solicitadas impedem que processos possam ser avaliados no decorrer da auditoria | F35: N/A | G35: Se faz necessário que a administração do condominio possua uma rotina ou sistema de cobrança de inadimplentes | H35: Operacional | I35: 02.2.5 STC - Walkthrough de Receita | J35: MÉDIO IMPACTO | K35: • 31/12/2020 • Recorrente ■ Vorcon Auditoria & Consultoria ■ 22 de abril de 2021

Sheet RESUMO DE PONTOS
B3: Condomínio Parque Tropical | E3: Materialidade | F3: 141950 | G3: Total da Receita
B4: RESUMO DE PONTOS | E4: PM | F4: 95800 | G4: 4731498.7
B5: Data base: 01/01/2019 à 31/12/2021 | E5: AMPT | F5: 7100 | M5: ATUALIZAR
G6: Avaliação da soma das NFs Identificadas
B7: COD | C7: 1 | D7: 2 | E7: 3 | F7: 4 | G7: 5 | H7: 6 | I7: 7 | J7: 8 | L7: 9 | M7: Status | N7: Perdas/Impacto
B8: Código | C8: Ponto | D8: Descrição Resumida | E8: Descrição do Ponto | F8: Riscos e Implicações | G8: Impacto Financeiro | H8: Recomendações | I8: Tipo | J8: Tipo de Teste | K8: Tipo de Teste | L8: Julgamento Profissional
B9: V01 | C9: [P1] | D9: =_xlfn.XLOOKUP($B9,'BASE DE PONTOS V+'!$B:$B,'BASE DE PONTOS V+'!$C:$C) -> Pagamento sem nota fiscal | E9: =_xlfn.XLOOKUP($B9,'BASE DE PONTOS V+'!$B:$B,'BASE DE PONTOS V+'!$D:$D) -> Verificamos que ocorreram gastos sem a respectiva emissão de nota fiscal pelos fornecedores e prestadores de serviços. | F9: =_xlfn.XLOOKUP($B9,'BASE DE PONTOS V+'!$B:$B,'BASE DE PONTOS V+'!$F:$F) -> Pagamento sem os respectivos Fornecedores/Prestadores de serviços não é permitido pela legislação brasileira assim como Convenção e Regimento Interno do Condomínio podendo ser multado e/ou sofrer outras penalidades impostas pelo fisco. | G9: =_xlfn.XLOOKUP(B9,'BASE DE PONTOS V+'!B:B,'BASE DE PONTOS V+'!E:E) -> 47819.88 | H9: =_xlfn.XLOOKUP($B9,'BASE DE PONTOS V+'!$B:$B,'BASE DE PONTOS V+'!$G:$G) -> Sugerimos que seja solicitado aos respectivos Fornecedores/ Prestadores de serviços ou fornecedores a nota fiscal pelo fornecimento de material ou de prestação de serviço. | I9: =_xlfn.XLOOKUP($B9,'BASE DE PONTOS V+'!$B:$B,'BASE DE PONTOS V+'!$H:$H) -> Legal | J9: =_xlfn.XLOOKUP($B9,'BASE DE PONTOS V+'!$B:$B,'BASE DE PONTOS V+'!$I:$I) -> Voucher Documental | K9: =_xlfn.XLOOKUP($B9,'BASE DE PONTOS V+'!$B:$B,'BASE DE PONTOS V+'!$M:$M) -> 0 | L9: =_xlfn.XLOOKUP(B9,'BASE DE PONTOS V+'!B:B,'BASE DE PONTOS V+'!J:J) -> Alto Impacto | M9: =_xlfn.XLOOKUP(D9,'BASE DE PONTOS V+'!C:C,'BASE DE PONTOS V+'!L:L) -> • 31/12/2021 • Recorrente ■ Vorcon Auditoria & Consultoria ■ 24/06/2022 | N9: =IF(B9="","",IFERROR(IF(I9="Financeiro",VLOOKUP(G9,'BASE DA MATRIZ DE RISCOS'!$O$58:$Q$62,3,1),"Avaliar por julgameto"),"1")) -> Avaliar por julgameto
B10: V03 | C10: [P2] | D10: =_xlfn.XLOOKUP($B10,'BASE DE PONTOS V+'!$B:$B,'BASE DE PONTOS V+'!$C:$C) -> Pagamentos realizados sem os respectivos comprovantes de pagamento anexados | E10: =_xlfn.XLOOKUP($B10,'BASE DE PONTOS V+'!$B:$B,'BASE DE PONTOS V+'!$D:$D) -> Verificamos que alguns pagamentos foram realizados sem que fossem anexados os respectivos comprovantes de pagamentos ou documentos equivalentes dando a respectiva quitação. | F10: =_xlfn.XLOOKUP($B10,'BASE DE PONTOS V+'!$B:$B,'BASE DE PONTOS V+'!$F:$F) -> Pagamento duplicado dos valores, ou caso haja a solicitação do comprovante de pagamento o Condomínio não os possua | G10: =_xlfn.XLOOKUP(B10,'BASE DE PONTOS V+'!B:B,'BASE DE PONTOS V+'!E:E) -> 23309.37 | H10: =_xlfn.XLOOKUP($B10,'BASE DE PONTOS V+'!$B:$B,'BASE DE PONTOS V+'!$G:$G) -> Sugerimos que sejam criados processos para que os comprovantes de pagamentos estejam anexados ao processo de pagamentos | I10: =_xlfn.XLOOKUP($B10,'BASE DE PONTOS V+'!$B:$B,'BASE DE PONTOS V+'!$H:$H) -> Financeiro | J10: =_xlfn.XLOOKUP($B10,'BASE DE PONTOS V+'!$B:$B,'BASE DE PONTOS V+'!$I:$I) -> Voucher Documental | K10: =_xlfn.XLOOKUP($B10,'BASE DE PONTOS V+'!$B:$B,'BASE DE PONTOS V+'!$M:$M) -> 0 | L10: =_xlfn.XLOOKUP(B10,'BASE DE PONTOS V+'!B:B,'BASE DE PONTOS V+'!J:J) -> Alto Impacto | M10: =_xlfn.XLOOKUP(D10,'BASE DE PONTOS V+'!C:C,'BASE DE PONTOS V+'!L:L) -> • 31/12/2021 • Recorrente ■ Vorcon Auditoria & Consultoria ■ 24/06/2022 | N10: =IF(B10="","",IFERROR(IF(I10="Financeiro",VLOOKUP(G10,'BASE DA MATRIZ DE RISCOS'!$O$58:$Q$62,3,1),"Avaliar por julgameto"),"1")) -> 2
B11: V04 | C11: [P3] | D11: =_xlfn.XLOOKUP($B11,'BASE DE PONTOS V+'!$B:$B,'BASE DE PONTOS V+'!$C:$C) -> Negligência na gestão dos Documentos que compõe os Demonstrativos | E11: =_xlfn.XLOOKUP($B11,'BASE DE PONTOS V+'!$B:$B,'BASE DE PONTOS V+'!$D:$D) -> Verificamos que alguns comprovantes não estão sendo arquivados com os cuidados necessários, com isso alguns estão ilegíveis. | F11: =_xlfn.XLOOKUP($B11,'BASE DE PONTOS V+'!$B:$B,'BASE DE PONTOS V+'!$F:$F) -> Dificuldade na visualização dos gastos e impossibilidade e dúvidas quanto a possíveis consultas no futuro em função do estado dos documentos. | G11: =_xlfn.XLOOKUP(B11,'BASE DE PONTOS V+'!B:B,'BASE DE PONTOS V+'!E:E) -> 1087.39 | H11: =_xlfn.XLOOKUP($B11,'BASE DE PONTOS V+'!$B:$B,'BASE DE PONTOS V+'!$G:$G) -> Sugerimos que sejam criados processos para que os comprovantes sejam de responsabilidade do financeiro tirar cópia ou digitalizá-los assim que os receber. | I11: =_xlfn.XLOOKUP($B11,'BASE DE PONTOS V+'!$B:$B,'BASE DE PONTOS V+'!$H:$H) -> Operacional | J11: =_xlfn.XLOOKUP($B11,'BASE DE PONTOS V+'!$B:$B,'BASE DE PONTOS V+'!$I:$I) -> Voucher Documental | K11: =_xlfn.XLOOKUP($B11,'BASE DE PONTOS V+'!$B:$B,'BASE DE PONTOS V+'!$M:$M) -> 0 | L11: =_xlfn.XLOOKUP(B11,'BASE DE PONTOS V+'!B:B,'BASE DE PONTOS V+'!J:J) -> Baixo Impacto | M11: =_xlfn.XLOOKUP(D11,'BASE DE PONTOS V+'!C:C,'BASE DE PONTOS V+'!L:L) -> • 31/12/2021 • Recorrente ■ Vorcon Auditoria & Consultoria ■ 24/06/2022 | N11: =IF(B11="","",IFERROR(IF(I11="Financeiro",VLOOKUP(G11,'BASE DA MATRIZ DE RISCOS'!$O$58:$Q$62,3,1),"Avaliar por julgameto"),"1")) -> Avaliar por julgameto
B12: V05 | C12: [P4] | D12: =_xlfn.XLOOKUP($B12,'BASE DE PONTOS V+'!$B:$B,'BASE DE PONTOS V+'!$C:$C) -> Pagamento de tarifa bancária. | E12: =_xlfn.XLOOKUP($B12,'BASE DE PONTOS V+'!$B:$B,'BASE DE PONTOS V+'!$D:$D) -> Verificamos que ocorreram pagamento de fornecedores e prestadores de serviços por meio de transferência bancária. | F12: =_xlfn.XLOOKUP($B12,'BASE DE PONTOS V+'!$B:$B,'BASE DE PONTOS V+'!$F:$F) -> Pagamento de encargos financeiros que deveriam ser de responsabilidade dos Fornecedores/Prestadores de serviços | G12: =_xlfn.XLOOKUP(B12,'BASE DE PONTOS V+'!B:B,'BASE DE PONTOS V+'!E:E) -> 88.4 | H12: =_xlfn.XLOOKUP($B12,'BASE DE PONTOS V+'!$B:$B,'BASE DE PONTOS V+'!$G:$G) -> Sugerimos que seja solicitado boleto para pagamento de todos os Fornecedores/Prestadores de serviços e em caso de negativa o valor dos encargos financeiros deve ser subtraído do pagamento. | I12: =_xlfn.XLOOKUP($B12,'BASE DE PONTOS V+'!$B:$B,'BASE DE PONTOS V+'!$H:$H) -> Financeiro | J12: =_xlfn.XLOOKUP($B12,'BASE DE PONTOS V+'!$B:$B,'BASE DE PONTOS V+'!$I:$I) -> Voucher Documental | K12: =_xlfn.XLOOKUP($B12,'BASE DE PONTOS V+'!$B:$B,'BASE DE PONTOS V+'!$M:$M) -> 0 | L12: =_xlfn.XLOOKUP(B12,'BASE DE PONTOS V+'!B:B,'BASE DE PONTOS V+'!J:J) -> Baixo Impacto | M12: =_xlfn.XLOOKUP(D12,'BASE DE PONTOS V+'!C:C,'BASE DE PONTOS V+'!L:L) -> • 31/12/2021 • Recorrente ■ Vorcon Auditoria & Consultoria ■ 24/06/2022 | N12: =IF(B12="","",IFERROR(IF(I12="Financeiro",VLOOKUP(G12,'BASE DA MATRIZ DE RISCOS'!$O$58:$Q$62,3,1),"Avaliar por julgameto"),"1")) -> 1
B13: V06 | C13: [P5] | D13: =_xlfn.XLOOKUP($B13,'BASE DE PONTOS V+'!$B:$B,'BASE DE PONTOS V+'!$C:$C) -> Diferenças entre: Valor do comprovante de pagamento X Valor da documentação suporte. | E13: =_xlfn.XLOOKUP($B13,'BASE DE PONTOS V+'!$B:$B,'BASE DE PONTOS V+'!$D:$D) -> Verificamos que há diferença entre os valores apresentados, não justificada por parcelamento ou multa. | F13: =_xlfn.XLOOKUP($B13,'BASE DE PONTOS V+'!$B:$B,'BASE DE PONTOS V+'!$F:$F) -> Possibilidade de pagamentos realizados com valores incorretos. | G13: =_xlfn.XLOOKUP(B13,'BASE DE PONTOS V+'!B:B,'BASE DE PONTOS V+'!E:E) -> 333.3 | H13: =_xlfn.XLOOKUP($B13,'BASE DE PONTOS V+'!$B:$B,'BASE DE PONTOS V+'!$G:$G) -> Sugerimos que os pagamentos sejam realizados com os valores que constam no documento auxiliar. | I13: =_xlfn.XLOOKUP($B13,'BASE DE PONTOS V+'!$B:$B,'BASE DE PONTOS V+'!$H:$H) -> Financeiro | J13: =_xlfn.XLOOKUP($B13,'BASE DE PONTOS V+'!$B:$B,'BASE DE PONTOS V+'!$I:$I) -> Voucher Documental | K13: =_xlfn.XLOOKUP($B13,'BASE DE PONTOS V+'!$B:$B,'BASE DE PONTOS V+'!$M:$M) -> 0 | L13: =_xlfn.XLOOKUP(B13,'BASE DE PONTOS V+'!B:B,'BASE DE PONTOS V+'!J:J) -> Baixo Impacto | M13: =_xlfn.XLOOKUP(D13,'BASE DE PONTOS V+'!C:C,'BASE DE PONTOS V+'!L:L) -> • 31/12/2021 • Recorrente ■ Vorcon Auditoria & Consultoria ■ 24/06/2022 | N13: =IF(B13="","",IFERROR(IF(I13="Financeiro",VLOOKUP(G13,'BASE DA MATRIZ DE RISCOS'!$O$58:$Q$62,3,1),"Avaliar por julgameto"),"1")) -> 1
B14: V07 | C14: [P6] | D14: =_xlfn.XLOOKUP($B14,'BASE DE PONTOS V+'!$B:$B,'BASE DE PONTOS V+'!$C:$C) -> Acesso a Convenção do Condomínio | E14: =_xlfn.XLOOKUP($B14,'BASE DE PONTOS V+'!$B:$B,'BASE DE PONTOS V+'!$D:$D) -> Verificamos que o Condomínio não possui site, o ideal seria ter um site e disponibiliar o requimento Regimento nele. | F14: =_xlfn.XLOOKUP($B14,'BASE DE PONTOS V+'!$B:$B,'BASE DE PONTOS V+'!$F:$F) -> As melhores práticas de gestão sugerem que as informações do Condomínio estejam de fácil acesso para qualquer condômino. | G14: =_xlfn.XLOOKUP(B14,'BASE DE PONTOS V+'!B:B,'BASE DE PONTOS V+'!E:E) -> N/A | H14: =_xlfn.XLOOKUP($B14,'BASE DE PONTOS V+'!$B:$B,'BASE DE PONTOS V+'!$G:$G) -> Sugerimos que o Condomínio contate a sua equipe de TI e verifique a possibilidade de criar um site do Condomínio e disponibilizar a convenção | I14: =_xlfn.XLOOKUP($B14,'BASE DE PONTOS V+'!$B:$B,'BASE DE PONTOS V+'!$H:$H) -> Operacional | J14: =_xlfn.XLOOKUP($B14,'BASE DE PONTOS V+'!$B:$B,'BASE DE PONTOS V+'!$I:$I) -> Resumo da Convenção | K14: =_xlfn.XLOOKUP($B14,'BASE DE PONTOS V+'!$B:$B,'BASE DE PONTOS V+'!$M:$M) -> 0 | L14: =_xlfn.XLOOKUP(B14,'BASE DE PONTOS V+'!B:B,'BASE DE PONTOS V+'!J:J) -> Baixo Impacto | M14: =_xlfn.XLOOKUP(D14,'BASE DE PONTOS V+'!C:C,'BASE DE PONTOS V+'!L:L) -> • 31/12/2021 • Recorrente ■ Vorcon Auditoria & Consultoria ■ 24/06/2022 | N14: =IF(B14="","",IFERROR(IF(I14="Financeiro",VLOOKUP(G14,'BASE DA MATRIZ DE RISCOS'!$O$58:$Q$62,3,1),"Avaliar por julgameto"),"1")) -> Avaliar por julgameto
B15: V08 | C15: [P7] | D15: =_xlfn.XLOOKUP($B15,'BASE DE PONTOS V+'!$B:$B,'BASE DE PONTOS V+'!$C:$C) -> Os balancetes sem aprovação dos conselheiros fiscais no termo de aprovação. | E15: =_xlfn.XLOOKUP($B15,'BASE DE PONTOS V+'!$B:$B,'BASE DE PONTOS V+'!$D:$D) -> Nos meses 01/2021 à 12/2021 não constam as assinaturas dos conselheiros fiscais e do síndico para aprovação dos balancetes. | F15: =_xlfn.XLOOKUP($B15,'BASE DE PONTOS V+'!$B:$B,'BASE DE PONTOS V+'!$F:$F) -> A falta das assinaturas dos conselheiros fiscais nos termos de aprovação dos balancetes indica que as contas do condomínio não foram submetidas ao exame, acarretando a redução do nível de confiança dos demonstrativos e podendo prejudicar a leitura dos usuários. | G15: =_xlfn.XLOOKUP(B15,'BASE DE PONTOS V+'!B:B,'BASE DE PONTOS V+'!E:E) -> N/A | H15: =_xlfn.XLOOKUP($B15,'BASE DE PONTOS V+'!$B:$B,'BASE DE PONTOS V+'!$G:$G) -> Sugerimos que os conselheiros fiscais realizem o exame dos balancetes e caso ocorra a aprovação dos mesmos, confirmem com as suas assinaturas nos termos de aprovação. Mesmo com as demonstrações financeiras sendo auditadas mensalmente, é necessário a validação do conselho fiscal. | I15: =_xlfn.XLOOKUP($B15,'BASE DE PONTOS V+'!$B:$B,'BASE DE PONTOS V+'!$H:$H) -> Operacional | J15: =_xlfn.XLOOKUP($B15,'BASE DE PONTOS V+'!$B:$B,'BASE DE PONTOS V+'!$I:$I) -> Resumo da Convenção | K15: =_xlfn.XLOOKUP($B15,'BASE DE PONTOS V+'!$B:$B,'BASE DE PONTOS V+'!$M:$M) -> 0 | L15: =_xlfn.XLOOKUP(B15,'BASE DE PONTOS V+'!B:B,'BASE DE PONTOS V+'!J:J) -> Baixo Impacto | M15: =_xlfn.XLOOKUP(D15,'BASE DE PONTOS V+'!C:C,'BASE DE PONTOS V+'!L:L) -> • 31/12/2021 • Novo ■ Vorcon Auditoria & Consultoria ■ 24/06/2022 | N15: =IF(B15="","",IFERROR(IF(I15="Financeiro",VLOOKUP(G15,'BASE DA MATRIZ DE RISCOS'!$O$58:$Q$62,3,1),"Avaliar por julgameto"),"1")) -> Avaliar por julgameto
B16: V09 | C16: [P8] | D16: =_xlfn.XLOOKUP($B16,'BASE DE PONTOS V+'!$B:$B,'BASE DE PONTOS V+'!$C:$C) -> Impacto com os inadimplentes | E16: =_xlfn.XLOOKUP($B16,'BASE DE PONTOS V+'!$B:$B,'BASE DE PONTOS V+'!$D:$D) -> Verificamos que a inadimplência na data base de 31/12/2021 foi equivalente a R$ 23.053,25 atualizados com multas, juros e correção. | F16: =_xlfn.XLOOKUP($B16,'BASE DE PONTOS V+'!$B:$B,'BASE DE PONTOS V+'!$F:$F) -> O alto índice de inadimplência condominial impacta inicialmente o orçamento do condomínio. Assim, é preciso compensar de alguma forma o déficit orçamentário para que as obrigações condominiais sejam cumpridas. Como alternativas para essas compensações, podem ser ajustados os valores das taxas condominiais, utilizados os seus fundos de reserva ou criadas taxas extras, gerado assim, prejuízos aos condomínios adimplentes e a toda estrutura financeira condominial. Ademais, ocorre as implicações de ordem interpessoal para que ocorra a regularização dos valores, o que em casos mais graves necessita de cobrança judicial, gerando outros gastos com honorários advocatícios e custas judiciais. | G16: =_xlfn.XLOOKUP(B16,'BASE DE PONTOS V+'!B:B,'BASE DE PONTOS V+'!E:E) -> 23053.25 | H16: =_xlfn.XLOOKUP($B16,'BASE DE PONTOS V+'!$B:$B,'BASE DE PONTOS V+'!$G:$G) -> Indicamos à administração ações preventivas que tenham como objetivo a redução das despesas condominiais, o fortalecimento do fundo de reserva e a cobrança de maneira assertiva dos inadimplentes. Além disso, devem ser buscadas alternativas analisando a relação de custos e benefícios para solução desse problema, como por exemplo, a utilização dos serviços de uma garantidora de condomínio. | I16: =_xlfn.XLOOKUP($B16,'BASE DE PONTOS V+'!$B:$B,'BASE DE PONTOS V+'!$H:$H) -> Financeiro | J16: =_xlfn.XLOOKUP($B16,'BASE DE PONTOS V+'!$B:$B,'BASE DE PONTOS V+'!$I:$I) -> Inadimplentes | K16: =_xlfn.XLOOKUP($B16,'BASE DE PONTOS V+'!$B:$B,'BASE DE PONTOS V+'!$M:$M) -> 0 | L16: =_xlfn.XLOOKUP(B16,'BASE DE PONTOS V+'!B:B,'BASE DE PONTOS V+'!J:J) -> Médio Impacto | M16: =_xlfn.XLOOKUP(D16,'BASE DE PONTOS V+'!C:C,'BASE DE PONTOS V+'!L:L) -> • 31/12/2021 • Recorrente ■ Vorcon Auditoria & Consultoria ■ 24/06/2022 | N16: =IF(B16="","",IFERROR(IF(I16="Financeiro",VLOOKUP(G16,'BASE DA MATRIZ DE RISCOS'!$O$58:$Q$62,3,1),"Avaliar por julgameto"),"1")) -> 2
B17: V10 | C17: [P9] | D17: =_xlfn.XLOOKUP($B17,'BASE DE PONTOS V+'!$B:$B,'BASE DE PONTOS V+'!$C:$C) -> Ausência de Inventário dos ativos imobilizados | E17: =_xlfn.XLOOKUP($B17,'BASE DE PONTOS V+'!$B:$B,'BASE DE PONTOS V+'!$D:$D) -> Não foi possível identificar o controle patrimonial dos ativos imobilizados do condomínio. | F17: =_xlfn.XLOOKUP($B17,'BASE DE PONTOS V+'!$B:$B,'BASE DE PONTOS V+'!$F:$F) -> A ausência do controle patrimonial, o condomínio poderá impactar em possíveis perdas ou desvios do ativo imobilizado. | G17: =_xlfn.XLOOKUP(B17,'BASE DE PONTOS V+'!B:B,'BASE DE PONTOS V+'!E:E) -> N/A | H17: =_xlfn.XLOOKUP($B17,'BASE DE PONTOS V+'!$B:$B,'BASE DE PONTOS V+'!$G:$G) -> Sugerimos à Administração do condomínio que busque realizar o inventário dos ativos imobilizados anualmente. | I17: =_xlfn.XLOOKUP($B17,'BASE DE PONTOS V+'!$B:$B,'BASE DE PONTOS V+'!$H:$H) -> Financeiro | J17: =_xlfn.XLOOKUP($B17,'BASE DE PONTOS V+'!$B:$B,'BASE DE PONTOS V+'!$I:$I) -> Ativo imobilizado | K17: =_xlfn.XLOOKUP($B17,'BASE DE PONTOS V+'!$B:$B,'BASE DE PONTOS V+'!$M:$M) -> 0 | L17: =_xlfn.XLOOKUP(B17,'BASE DE PONTOS V+'!B:B,'BASE DE PONTOS V+'!J:J) -> Alto Impacto | M17: =_xlfn.XLOOKUP(D17,'BASE DE PONTOS V+'!C:C,'BASE DE PONTOS V+'!L:L) -> • 31/12/2021 • Recorrente ■ Vorcon Auditoria & Consultoria ■ 24/06/2022 | N17: =IF(B17="","",IFERROR(IF(I17="Financeiro",VLOOKUP(G17,'BASE DA MATRIZ DE RISCOS'!$O$58:$Q$62,3,1),"Avaliar por julgameto"),"1")) -> 1
B18: V11 | C18: [P10] | D18: =_xlfn.XLOOKUP($B18,'BASE DE PONTOS V+'!$B:$B,'BASE DE PONTOS V+'!$C:$C) -> Inexistência de informações para emissão da certidão de FGTS na Caixa econômica Federal. | E18: =_xlfn.XLOOKUP($B18,'BASE DE PONTOS V+'!$B:$B,'BASE DE PONTOS V+'!$D:$D) -> Ao realizar a consulta do Certificado de Regularidade Do FGTS, obtivemos a seguinte resposta: "As informações disponíveis não são suficientes para a comprovação automática da regularidade do empregador perante o FGTS. Solicitamos acessar o portal Conectividade Social, mediante certificado ICP, para verificar possíveis impedimentos ou comparecer a uma das Agências da CAIXA". Com esclarecimentos adicionais no endereçamento. | F18: =_xlfn.XLOOKUP($B18,'BASE DE PONTOS V+'!$B:$B,'BASE DE PONTOS V+'!$F:$F) -> A inexistência dos dados para emissão da certidão junto ao Caixa, poderá resultar no agravamento do acompanhamento das certidões. | G18: =_xlfn.XLOOKUP(B18,'BASE DE PONTOS V+'!B:B,'BASE DE PONTOS V+'!E:E) -> N/A | H18: =_xlfn.XLOOKUP($B18,'BASE DE PONTOS V+'!$B:$B,'BASE DE PONTOS V+'!$G:$G) -> Sugerimos que a administração entre no portal Conectividade Social da Caixa e faça o entendimento de quais dados estão faltando para verificar possíveis impedimentos. | I18: =_xlfn.XLOOKUP($B18,'BASE DE PONTOS V+'!$B:$B,'BASE DE PONTOS V+'!$H:$H) -> Legal | J18: =_xlfn.XLOOKUP($B18,'BASE DE PONTOS V+'!$B:$B,'BASE DE PONTOS V+'!$I:$I) -> Certidão | K18: =_xlfn.XLOOKUP($B18,'BASE DE PONTOS V+'!$B:$B,'BASE DE PONTOS V+'!$M:$M) -> 0 | L18: =_xlfn.XLOOKUP(B18,'BASE DE PONTOS V+'!B:B,'BASE DE PONTOS V+'!J:J) -> Alto Impacto | M18: =_xlfn.XLOOKUP(D18,'BASE DE PONTOS V+'!C:C,'BASE DE PONTOS V+'!L:L) -> • 31/12/2021 • Recorrente ■ Vorcon Auditoria & Consultoria ■ 24/06/2022 | N18: =IF(B18="","",IFERROR(IF(I18="Financeiro",VLOOKUP(G18,'BASE DA MATRIZ DE RISCOS'!$O$58:$Q$62,3,1),"Avaliar por julgameto"),"1")) -> Avaliar por julgameto
B19: V12 | C19: [P11] | D19: =_xlfn.XLOOKUP($B19,'BASE DE PONTOS V+'!$B:$B,'BASE DE PONTOS V+'!$C:$C) -> Capacidade de arrecadação inferior aos gastos. | E19: =_xlfn.XLOOKUP($B19,'BASE DE PONTOS V+'!$B:$B,'BASE DE PONTOS V+'!$D:$D) -> As receitas do meses 02, 04, 07, 09, 10 e 12/2021 não estão sendo suficiente para cobrir as despesas, acarretando em um défict no total nesses meses de - R$ 235.528,38 | F19: =_xlfn.XLOOKUP($B19,'BASE DE PONTOS V+'!$B:$B,'BASE DE PONTOS V+'!$F:$F) -> Com as despesas elevadas, o condomínio não consegue arcar com 100% das suas obrigações afetando o fluxo de caixa do financeiro, e ao mesmo tempo não consegue atingir um valor médio ou alto para o fundo de reserva para um futuro inesperado. | G19: =_xlfn.XLOOKUP(B19,'BASE DE PONTOS V+'!B:B,'BASE DE PONTOS V+'!E:E) -> -235528.38 | H19: =_xlfn.XLOOKUP($B19,'BASE DE PONTOS V+'!$B:$B,'BASE DE PONTOS V+'!$G:$G) -> Recomendamos ao Conselho Fiscal e a Administração condominial que verifique novas ações a realizar para redução das despesas mitigando ou solucionando o problema. | I19: =_xlfn.XLOOKUP($B19,'BASE DE PONTOS V+'!$B:$B,'BASE DE PONTOS V+'!$H:$H) -> Estratégico | J19: =_xlfn.XLOOKUP($B19,'BASE DE PONTOS V+'!$B:$B,'BASE DE PONTOS V+'!$I:$I) -> Demonstrativo de Receita e Despesas | K19: =_xlfn.XLOOKUP($B19,'BASE DE PONTOS V+'!$B:$B,'BASE DE PONTOS V+'!$M:$M) -> 0 | L19: =_xlfn.XLOOKUP(B19,'BASE DE PONTOS V+'!B:B,'BASE DE PONTOS V+'!J:J) -> Alto Impacto | M19: =_xlfn.XLOOKUP(D19,'BASE DE PONTOS V+'!C:C,'BASE DE PONTOS V+'!L:L) -> • 31/12/2021 • Recorrente ■ Vorcon Auditoria & Consultoria ■ 24/06/2022 | N19: =IF(B19="","",IFERROR(IF(I19="Financeiro",VLOOKUP(G19,'BASE DA MATRIZ DE RISCOS'!$O$58:$Q$62,3,1),"Avaliar por julgameto"),"1")) -> Avaliar por julgameto
B20: V13 | C20: [P12] | D20: =_xlfn.XLOOKUP($B20,'BASE DE PONTOS V+'!$B:$B,'BASE DE PONTOS V+'!$C:$C) -> Envio de Boleto Fraudado | E20: =_xlfn.XLOOKUP($B20,'BASE DE PONTOS V+'!$B:$B,'BASE DE PONTOS V+'!$D:$D) -> Identificamos que o Condomínio enviou um possível boleto fraudado para a Condômina Jussara Barros da Unidade 2801 B no Mês 01/2021 na qual realizou o pagamento. O condomínio necessitou realizar a baixa do valor pago da condômina resultando em prejuízo financeiro de R$ 919,14. | F20: =_xlfn.XLOOKUP($B20,'BASE DE PONTOS V+'!$B:$B,'BASE DE PONTOS V+'!$F:$F) -> A falta de processo da análise do controle interno das contas a pagar sobre a verificação dos envios dos boletos recebidos pelo Advogado, poderá acarretar em envios de boletos errôneos e gerar prejuízos ao condomínio e a toda estrutura financeira condominial. | G20: =_xlfn.XLOOKUP(B20,'BASE DE PONTOS V+'!B:B,'BASE DE PONTOS V+'!E:E) -> 919.14 | H20: =_xlfn.XLOOKUP($B20,'BASE DE PONTOS V+'!$B:$B,'BASE DE PONTOS V+'!$G:$G) -> Recomendamos a Administração do Condomíonio verifique ações de controles internos para verificação dos boletos enviados aos clientes. | I20: =_xlfn.XLOOKUP($B20,'BASE DE PONTOS V+'!$B:$B,'BASE DE PONTOS V+'!$H:$H) -> Operacional | J20: =_xlfn.XLOOKUP($B20,'BASE DE PONTOS V+'!$B:$B,'BASE DE PONTOS V+'!$I:$I) -> Demonstrativo de Receita e Despesas | K20: =_xlfn.XLOOKUP($B20,'BASE DE PONTOS V+'!$B:$B,'BASE DE PONTOS V+'!$M:$M) -> 0 | L20: =_xlfn.XLOOKUP(B20,'BASE DE PONTOS V+'!B:B,'BASE DE PONTOS V+'!J:J) -> Baixo Impacto | M20: =_xlfn.XLOOKUP(D20,'BASE DE PONTOS V+'!C:C,'BASE DE PONTOS V+'!L:L) -> • 31/12/2021 • Novo ■ Vorcon Auditoria & Consultoria ■ 24/06/2022 | N20: =IF(B20="","",IFERROR(IF(I20="Financeiro",VLOOKUP(G20,'BASE DA MATRIZ DE RISCOS'!$O$58:$Q$62,3,1),"Avaliar por julgameto"),"1")) -> Avaliar por julgameto
... B24: V17 | C24: [P16] | D24: =_xlfn.XLOOKUP($B24,'BASE DE PONTOS V+'!$B:$B,'BASE DE PONTOS V+'!$C:$C) -> Perda de Causa Judicial | E24: =_xlfn.XLOOKUP($B24,'BASE DE PONTOS V+'!$B:$B,'BASE DE PONTOS V+'!$D:$D) -> Indentificamos que durante o período de 2021 que há perda de causa judicial de R$ 10.477,17 referente ao n° 0101419-55.2017.8.05.0001 de TICIANA CARNEIRO DA ROCHA PRATA MONTEIRO X TRIBECA, e R$ 29.000,00 referente ao n° 0164073-44.2018.8.05.0001 de RAFAEL CALDAS LOPES X TRIBECA, totalizando em uma perda de R$ 39.477,17 | F24: =_xlfn.XLOOKUP($B24,'BASE DE PONTOS V+'!$B:$B,'BASE DE PONTOS V+'!$F:$F) -> Devido a perda das causas judicais podendo afetar diretamente o fluxo de caixa e o controle do financeiro do condomínio. | G24: =_xlfn.XLOOKUP(B24,'BASE DE PONTOS V+'!B:B,'BASE DE PONTOS V+'!E:E) -> 39477.17 | H24: =_xlfn.XLOOKUP($B24,'BASE DE PONTOS V+'!$B:$B,'BASE DE PONTOS V+'!$G:$G) -> Recomendamos ações preventivas nas melhorias no controle interno para que as causas judiciais não sejam abertas contra o condomínio. | I24: =_xlfn.XLOOKUP($B24,'BASE DE PONTOS V+'!$B:$B,'BASE DE PONTOS V+'!$H:$H) -> Legal | J24: =_xlfn.XLOOKUP($B24,'BASE DE PONTOS V+'!$B:$B,'BASE DE PONTOS V+'!$I:$I) -> Contigência | K24: =_xlfn.XLOOKUP($B24,'BASE DE PONTOS V+'!$B:$B,'BASE DE PONTOS V+'!$M:$M) -> 0 | L24: =_xlfn.XLOOKUP(B24,'BASE DE PONTOS V+'!B:B,'BASE DE PONTOS V+'!J:J) -> Alto Impacto | M24: =_xlfn.XLOOKUP(D24,'BASE DE PONTOS V+'!C:C,'BASE DE PONTOS V+'!L:L) -> • 31/12/2021 • Novo ■ Vorcon Auditoria & Consultoria ■ 24/06/2022 | N24: =IF(B24="","",IFERROR(IF(I24="Financeiro",VLOOKUP(G24,'BASE DA MATRIZ DE RISCOS'!$O$58:$Q$62,3,1),"Avaliar por julgameto"),"1")) -> Avaliar por julgameto
C25: [P17] | D25: =_xlfn.XLOOKUP($B25,'BASE DE PONTOS V+'!$B:$B,'BASE DE PONTOS V+'!$C:$C) -> 0 | E25: =_xlfn.XLOOKUP($B25,'BASE DE PONTOS V+'!$B:$B,'BASE DE PONTOS V+'!$D:$D) -> 0 | F25: =_xlfn.XLOOKUP($B25,'BASE DE PONTOS V+'!$B:$B,'BASE DE PONTOS V+'!$F:$F) -> 0 | G25: =_xlfn.XLOOKUP(B25,'BASE DE PONTOS V+'!B:B,'BASE DE PONTOS V+'!E:E) -> 0 | H25: =_xlfn.XLOOKUP($B25,'BASE DE PONTOS V+'!$B:$B,'BASE DE PONTOS V+'!$G:$G) -> 0 | I25: =_xlfn.XLOOKUP($B25,'BASE DE PONTOS V+'!$B:$B,'BASE DE PONTOS V+'!$H:$H) -> 0 | J25: =_xlfn.XLOOKUP($B25,'BASE DE PONTOS V+'!$B:$B,'BASE DE PONTOS V+'!$I:$I) -> 0 | K25: =_xlfn.XLOOKUP($B25,'BASE DE PONTOS V+'!$B:$B,'BASE DE PONTOS V+'!$M:$M) -> 0 | L25: =_xlfn.XLOOKUP(B25,'BASE DE PONTOS V+'!B:B,'BASE DE PONTOS V+'!J:J) -> 0 | M25: =_xlfn.XLOOKUP(D25,'BASE DE PONTOS V+'!C:C,'BASE DE PONTOS V+'!L:L) -> #N/A | N25: =IF(B25="","",IFERROR(IF(I25="Financeiro",VLOOKUP(G25,'BASE DA MATRIZ DE RISCOS'!$O$58:$Q$62,3,1),"Avaliar por julgameto"),"1"))
C26: [P18] | D26: =_xlfn.XLOOKUP($B26,'BASE DE PONTOS V+'!$B:$B,'BASE DE PONTOS V+'!$C:$C) -> 0 | E26: =_xlfn.XLOOKUP($B26,'BASE DE PONTOS V+'!$B:$B,'BASE DE PONTOS V+'!$D:$D) -> 0 | F26: =_xlfn.XLOOKUP($B26,'BASE DE PONTOS V+'!$B:$B,'BASE DE PONTOS V+'!$F:$F) -> 0 | G26: =_xlfn.XLOOKUP(B26,'BASE DE PONTOS V+'!B:B,'BASE DE PONTOS V+'!E:E) -> 0 | H26: =_xlfn.XLOOKUP($B26,'BASE DE PONTOS V+'!$B:$B,'BASE DE PONTOS V+'!$G:$G) -> 0 | I26: =_xlfn.XLOOKUP($B26,'BASE DE PONTOS V+'!$B:$B,'BASE DE PONTOS V+'!$H:$H) -> 0 | J26: =_xlfn.XLOOKUP($B26,'BASE DE PONTOS V+'!$B:$B,'BASE DE PONTOS V+'!$I:$I) -> 0 | K26: =_xlfn.XLOOKUP($B26,'BASE DE PONTOS V+'!$B:$B,'BASE DE PONTOS V+'!$M:$M) -> 0 | L26: =_xlfn.XLOOKUP(B26,'BASE DE PONTOS V+'!B:B,'BASE DE PONTOS V+'!J:J) -> 0 | M26: =_xlfn.XLOOKUP(D26,'BASE DE PONTOS V+'!C:C,'BASE DE PONTOS V+'!L:L) -> #N/A | N26: =IF(B26="","",IFERROR(IF(I26="Financeiro",VLOOKUP(G26,'BASE DA MATRIZ DE RISCOS'!$O$58:$Q$62,3,1),"Avaliar por julgameto"),"1"))
C27: [P19] | D27: =_xlfn.XLOOKUP($B27,'BASE DE PONTOS V+'!$B:$B,'BASE DE PONTOS V+'!$C:$C) -> 0 | E27: =_xlfn.XLOOKUP($B27,'BASE DE PONTOS V+'!$B:$B,'BASE DE PONTOS V+'!$D:$D) -> 0 | F27: =_xlfn.XLOOKUP($B27,'BASE DE PONTOS V+'!$B:$B,'BASE DE PONTOS V+'!$F:$F) -> 0 | G27: =_xlfn.XLOOKUP(B27,'BASE DE PONTOS V+'!B:B,'BASE DE PONTOS V+'!E:E) -> 0 | H27: =_xlfn.XLOOKUP($B27,'BASE DE PONTOS V+'!$B:$B,'BASE DE PONTOS V+'!$G:$G) -> 0 | I27: =_xlfn.XLOOKUP($B27,'BASE DE PONTOS V+'!$B:$B,'BASE DE PONTOS V+'!$H:$H) -> 0 | J27: =_xlfn.XLOOKUP($B27,'BASE DE PONTOS V+'!$B:$B,'BASE DE PONTOS V+'!$I:$I) -> 0 | K27: =_xlfn.XLOOKUP($B27,'BASE DE PONTOS V+'!$B:$B,'BASE DE PONTOS V+'!$M:$M) -> 0 | L27: =_xlfn.XLOOKUP(B27,'BASE DE PONTOS V+'!B:B,'BASE DE PONTOS V+'!J:J) -> 0 | M27: =_xlfn.XLOOKUP(D27,'BASE DE PONTOS V+'!C:C,'BASE DE PONTOS V+'!L:L) -> #N/A | N27: =IF(B27="","",IFERROR(IF(I27="Financeiro",VLOOKUP(G27,'BASE DA MATRIZ DE RISCOS'!$O$58:$Q$62,3,1),"Avaliar por julgameto"),"1"))
C28: [P20] | D28: =_xlfn.XLOOKUP($B28,'BASE DE PONTOS V+'!$B:$B,'BASE DE PONTOS V+'!$C:$C) -> 0 | E28: =_xlfn.XLOOKUP($B28,'BASE DE PONTOS V+'!$B:$B,'BASE DE PONTOS V+'!$D:$D) -> 0 | F28: =_xlfn.XLOOKUP($B28,'BASE DE PONTOS V+'!$B:$B,'BASE DE PONTOS V+'!$F:$F) -> 0 | G28: =_xlfn.XLOOKUP(B28,'BASE DE PONTOS V+'!B:B,'BASE DE PONTOS V+'!E:E) -> 0 | H28: =_xlfn.XLOOKUP($B28,'BASE DE PONTOS V+'!$B:$B,'BASE DE PONTOS V+'!$G:$G) -> 0 | I28: =_xlfn.XLOOKUP($B28,'BASE DE PONTOS V+'!$B:$B,'BASE DE PONTOS V+'!$H:$H) -> 0 | J28: =_xlfn.XLOOKUP($B28,'BASE DE PONTOS V+'!$B:$B,'BASE DE PONTOS V+'!$I:$I) -> 0 | K28: =_xlfn.XLOOKUP($B28,'BASE DE PONTOS V+'!$B:$B,'BASE DE PONTOS V+'!$M:$M) -> 0 | L28: =_xlfn.XLOOKUP(B28,'BASE DE PONTOS V+'!B:B,'BASE DE PONTOS V+'!J:J) -> 0 | M28: =_xlfn.XLOOKUP(D28,'BASE DE PONTOS V+'!C:C,'BASE DE PONTOS V+'!L:L) -> #N/A | N28: =IF(B28="","",IFERROR(IF(I28="Financeiro",VLOOKUP(G28,'BASE DA MATRIZ DE RISCOS'!$O$58:$Q$62,3,1),"Avaliar por julgameto"),"1"))
C29: [P21] | D29: =_xlfn.XLOOKUP($B29,'BASE DE PONTOS V+'!$B:$B,'BASE DE PONTOS V+'!$C:$C) -> 0 | E29: =_xlfn.XLOOKUP($B29,'BASE DE PONTOS V+'!$B:$B,'BASE DE PONTOS V+'!$D:$D) -> 0 | F29: =_xlfn.XLOOKUP($B29,'BASE DE PONTOS V+'!$B:$B,'BASE DE PONTOS V+'!$F:$F) -> 0 | G29: =_xlfn.XLOOKUP(B29,'BASE DE PONTOS V+'!B:B,'BASE DE PONTOS V+'!E:E) -> 0 | H29: =_xlfn.XLOOKUP($B29,'BASE DE PONTOS V+'!$B:$B,'BASE DE PONTOS V+'!$G:$G) -> 0 | I29: =_xlfn.XLOOKUP($B29,'BASE DE PONTOS V+'!$B:$B,'BASE DE PONTOS V+'!$H:$H) -> 0 | J29: =_xlfn.XLOOKUP($B29,'BASE DE PONTOS V+'!$B:$B,'BASE DE PONTOS V+'!$I:$I) -> 0 | K29: =_xlfn.XLOOKUP($B29,'BASE DE PONTOS V+'!$B:$B,'BASE DE PONTOS V+'!$M:$M) -> 0 | L29: =_xlfn.XLOOKUP(B29,'BASE DE PONTOS V+'!B:B,'BASE DE PONTOS V+'!J:J) -> 0 | M29: =_xlfn.XLOOKUP(D29,'BASE DE PONTOS V+'!C:C,'BASE DE PONTOS V+'!L:L) -> #N/A | N29: =IF(B29="","",IFERROR(IF(I29="Financeiro",VLOOKUP(G29,'BASE DA MATRIZ DE RISCOS'!$O$58:$Q$62,3,1),"Avaliar por julgameto"),"1"))
C30: [P22] | D30: =_xlfn.XLOOKUP($B30,'BASE DE PONTOS V+'!$B:$B,'BASE DE PONTOS V+'!$C:$C) -> 0 | E30: =_xlfn.XLOOKUP($B30,'BASE DE PONTOS V+'!$B:$B,'BASE DE PONTOS V+'!$D:$D) -> 0 | F30: =_xlfn.XLOOKUP($B30,'BASE DE PONTOS V+'!$B:$B,'BASE DE PONTOS V+'!$F:$F) -> 0 | G30: =_xlfn.XLOOKUP(B30,'BASE DE PONTOS V+'!B:B,'BASE DE PONTOS V+'!E:E) -> 0 | H30: =_xlfn.XLOOKUP($B30,'BASE DE PONTOS V+'!$B:$B,'BASE DE PONTOS V+'!$G:$G) -> 0 | I30: =_xlfn.XLOOKUP($B30,'BASE DE PONTOS V+'!$B:$B,'BASE DE PONTOS V+'!$H:$H) -> 0 | J30: =_xlfn.XLOOKUP($B30,'BASE DE PONTOS V+'!$B:$B,'BASE DE PONTOS V+'!$I:$I) -> 0 | K30: =_xlfn.XLOOKUP($B30,'BASE DE PONTOS V+'!$B:$B,'BASE DE PONTOS V+'!$M:$M) -> 0 | L30: =_xlfn.XLOOKUP(B30,'BASE DE PONTOS V+'!B:B,'BASE DE PONTOS V+'!J:J) -> 0 | M30: =_xlfn.XLOOKUP(D30,'BASE DE PONTOS V+'!C:C,'BASE DE PONTOS V+'!L:L) -> #N/A | N30: =IF(B30="","",IFERROR(IF(I30="Financeiro",VLOOKUP(G30,'BASE DA MATRIZ DE RISCOS'!$O$58:$Q$62,3,1),"Avaliar por julgameto"),"1"))
C31: [P23] | D31: =_xlfn.XLOOKUP($B31,'BASE DE PONTOS V+'!$B:$B,'BASE DE PONTOS V+'!$C:$C) -> 0 | E31: =_xlfn.XLOOKUP($B31,'BASE DE PONTOS V+'!$B:$B,'BASE DE PONTOS V+'!$D:$D) -> 0 | F31: =_xlfn.XLOOKUP($B31,'BASE DE PONTOS V+'!$B:$B,'BASE DE PONTOS V+'!$F:$F) -> 0 | G31: =_xlfn.XLOOKUP(B31,'BASE DE PONTOS V+'!B:B,'BASE DE PONTOS V+'!E:E) -> 0 | H31: =_xlfn.XLOOKUP($B31,'BASE DE PONTOS V+'!$B:$B,'BASE DE PONTOS V+'!$G:$G) -> 0 | I31: =_xlfn.XLOOKUP($B31,'BASE DE PONTOS V+'!$B:$B,'BASE DE PONTOS V+'!$H:$H) -> 0 | J31: =_xlfn.XLOOKUP($B31,'BASE DE PONTOS V+'!$B:$B,'BASE DE PONTOS V+'!$I:$I) -> 0 | K31: =_xlfn.XLOOKUP($B31,'BASE DE PONTOS V+'!$B:$B,'BASE DE PONTOS V+'!$M:$M) -> 0 | L31: =_xlfn.XLOOKUP(B31,'BASE DE PONTOS V+'!B:B,'BASE DE PONTOS V+'!J:J) -> 0 | M31: =_xlfn.XLOOKUP(D31,'BASE DE PONTOS V+'!C:C,'BASE DE PONTOS V+'!L:L) -> #N/A | N31: =IF(B31="","",IFERROR(IF(I31="Financeiro",VLOOKUP(G31,'BASE DA MATRIZ DE RISCOS'!$O$58:$Q$62,3,1),"Avaliar por julgameto"),"1"))
C32: [P24] | D32: =_xlfn.XLOOKUP($B32,'BASE DE PONTOS V+'!$B:$B,'BASE DE PONTOS V+'!$C:$C) -> 0 | E32: =_xlfn.XLOOKUP($B32,'BASE DE PONTOS V+'!$B:$B,'BASE DE PONTOS V+'!$D:$D) -> 0 | F32: =_xlfn.XLOOKUP($B32,'BASE DE PONTOS V+'!$B:$B,'BASE DE PONTOS V+'!$F:$F) -> 0 | G32: =_xlfn.XLOOKUP(B32,'BASE DE PONTOS V+'!B:B,'BASE DE PONTOS V+'!E:E) -> 0 | H32: =_xlfn.XLOOKUP($B32,'BASE DE PONTOS V+'!$B:$B,'BASE DE PONTOS V+'!$G:$G) -> 0 | I32: =_xlfn.XLOOKUP($B32,'BASE DE PONTOS V+'!$B:$B,'BASE DE PONTOS V+'!$H:$H) -> 0 | J32: =_xlfn.XLOOKUP($B32,'BASE DE PONTOS V+'!$B:$B,'BASE DE PONTOS V+'!$I:$I) -> 0 | K32: =_xlfn.XLOOKUP($B32,'BASE DE PONTOS V+'!$B:$B,'BASE DE PONTOS V+'!$M:$M) -> 0 | L32: =_xlfn.XLOOKUP(B32,'BASE DE PONTOS V+'!B:B,'BASE DE PONTOS V+'!J:J) -> 0 | M32: =_xlfn.XLOOKUP(D32,'BASE DE PONTOS V+'!C:C,'BASE DE PONTOS V+'!L:L) -> #N/A | N32: =IF(B32="","",IFERROR(IF(I32="Financeiro",VLOOKUP(G32,'BASE DA MATRIZ DE RISCOS'!$O$58:$Q$62,3,1),"Avaliar por julgameto"),"1"))
C33: [P25] | D33: =_xlfn.XLOOKUP($B33,'BASE DE PONTOS V+'!$B:$B,'BASE DE PONTOS V+'!$C:$C) -> 0 | E33: =_xlfn.XLOOKUP($B33,'BASE DE PONTOS V+'!$B:$B,'BASE DE PONTOS V+'!$D:$D) -> 0 | F33: =_xlfn.XLOOKUP($B33,'BASE DE PONTOS V+'!$B:$B,'BASE DE PONTOS V+'!$F:$F) -> 0 | G33: =_xlfn.XLOOKUP(B33,'BASE DE PONTOS V+'!B:B,'BASE DE PONTOS V+'!E:E) -> 0 | H33: =_xlfn.XLOOKUP($B33,'BASE DE PONTOS V+'!$B:$B,'BASE DE PONTOS V+'!$G:$G) -> 0 | I33: =_xlfn.XLOOKUP($B33,'BASE DE PONTOS V+'!$B:$B,'BASE DE PONTOS V+'!$H:$H) -> 0 | J33: =_xlfn.XLOOKUP($B33,'BASE DE PONTOS V+'!$B:$B,'BASE DE PONTOS V+'!$I:$I) -> 0 | K33: =_xlfn.XLOOKUP($B33,'BASE DE PONTOS V+'!$B:$B,'BASE DE PONTOS V+'!$M:$M) -> 0 | L33: =_xlfn.XLOOKUP(B33,'BASE DE PONTOS V+'!B:B,'BASE DE PONTOS V+'!J:J) -> 0 | M33: =_xlfn.XLOOKUP(D33,'BASE DE PONTOS V+'!C:C,'BASE DE PONTOS V+'!L:L) -> #N/A | N33: =IF(B33="","",IFERROR(IF(I33="Financeiro",VLOOKUP(G33,'BASE DA MATRIZ DE RISCOS'!$O$58:$Q$62,3,1),"Avaliar por julgameto"),"1"))
C34: [P26] | D34: =_xlfn.XLOOKUP($B34,'BASE DE PONTOS V+'!$B:$B,'BASE DE PONTOS V+'!$C:$C) -> 0 | E34: =_xlfn.XLOOKUP($B34,'BASE DE PONTOS V+'!$B:$B,'BASE DE PONTOS V+'!$D:$D) -> 0 | F34: =_xlfn.XLOOKUP($B34,'BASE DE PONTOS V+'!$B:$B,'BASE DE PONTOS V+'!$F:$F) -> 0 | G34: =_xlfn.XLOOKUP(B34,'BASE DE PONTOS V+'!B:B,'BASE DE PONTOS V+'!E:E) -> 0 | H34: =_xlfn.XLOOKUP($B34,'BASE DE PONTOS V+'!$B:$B,'BASE DE PONTOS V+'!$G:$G) -> 0 | I34: =_xlfn.XLOOKUP($B34,'BASE DE PONTOS V+'!$B:$B,'BASE DE PONTOS V+'!$H:$H) -> 0 | J34: =_xlfn.XLOOKUP($B34,'BASE DE PONTOS V+'!$B:$B,'BASE DE PONTOS V+'!$I:$I) -> 0 | K34: =_xlfn.XLOOKUP($B34,'BASE DE PONTOS V+'!$B:$B,'BASE DE PONTOS V+'!$M:$M) -> 0 | L34: =_xlfn.XLOOKUP(B34,'BASE DE PONTOS V+'!B:B,'BASE DE PONTOS V+'!J:J) -> 0 | M34: =_xlfn.XLOOKUP(D34,'BASE DE PONTOS V+'!C:C,'BASE DE PONTOS V+'!L:L) -> #N/A | N34: =IF(B34="","",IFERROR(IF(I34="Financeiro",VLOOKUP(G34,'BASE DA MATRIZ DE RISCOS'!$O$58:$Q$62,3,1),"Avaliar por julgameto"),"1"))
C35: [P27] | D35: =_xlfn.XLOOKUP($B35,'BASE DE PONTOS V+'!$B:$B,'BASE DE PONTOS V+'!$C:$C) -> 0 | E35: =_xlfn.XLOOKUP($B35,'BASE DE PONTOS V+'!$B:$B,'BASE DE PONTOS V+'!$D:$D) -> 0 | F35: =_xlfn.XLOOKUP($B35,'BASE DE PONTOS V+'!$B:$B,'BASE DE PONTOS V+'!$F:$F) -> 0 | G35: =_xlfn.XLOOKUP(B35,'BASE DE PONTOS V+'!B:B,'BASE DE PONTOS V+'!E:E) -> 0 | H35: =_xlfn.XLOOKUP($B35,'BASE DE PONTOS V+'!$B:$B,'BASE DE PONTOS V+'!$G:$G) -> 0 | I35: =_xlfn.XLOOKUP($B35,'BASE DE PONTOS V+'!$B:$B,'BASE DE PONTOS V+'!$H:$H) -> 0 | J35: =_xlfn.XLOOKUP($B35,'BASE DE PONTOS V+'!$B:$B,'BASE DE PONTOS V+'!$I:$I) -> 0 | K35: =_xlfn.XLOOKUP($B35,'BASE DE PONTOS V+'!$B:$B,'BASE DE PONTOS V+'!$M:$M) -> 0 | L35: =_xlfn.XLOOKUP(B35,'BASE DE PONTOS V+'!B:B,'BASE DE PONTOS V+'!J:J) -> 0 | M35: =_xlfn.XLOOKUP(D35,'BASE DE PONTOS V+'!C:C,'BASE DE PONTOS V+'!L:L) -> #N/A | N35: =IF(B35="","",IFERROR(IF(I35="Financeiro",VLOOKUP(G35,'BASE DA MATRIZ DE RISCOS'!$O$58:$Q$62,3,1),"Avaliar por julgameto"),"1"))
C36: [P28] | D36: =_xlfn.XLOOKUP($B36,'BASE DE PONTOS V+'!$B:$B,'BASE DE PONTOS V+'!$C:$C) -> 0 | E36: =_xlfn.XLOOKUP($B36,'BASE DE PONTOS V+'!$B:$B,'BASE DE PONTOS V+'!$D:$D) -> 0 | F36: =_xlfn.XLOOKUP($B36,'BASE DE PONTOS V+'!$B:$B,'BASE DE PONTOS V+'!$F:$F) -> 0 | G36: =_xlfn.XLOOKUP(B36,'BASE DE PONTOS V+'!B:B,'BASE DE PONTOS V+'!E:E) -> 0 | H36: =_xlfn.XLOOKUP($B36,'BASE DE PONTOS V+'!$B:$B,'BASE DE PONTOS V+'!$G:$G) -> 0 | I36: =_xlfn.XLOOKUP($B36,'BASE DE PONTOS V+'!$B:$B,'BASE DE PONTOS V+'!$H:$H) -> 0 | J36: =_xlfn.XLOOKUP($B36,'BASE DE PONTOS V+'!$B:$B,'BASE DE PONTOS V+'!$I:$I) -> 0 | K36: =_xlfn.XLOOKUP($B36,'BASE DE PONTOS V+'!$B:$B,'BASE DE PONTOS V+'!$M:$M) -> 0 | L36: =_xlfn.XLOOKUP(B36,'BASE DE PONTOS V+'!B:B,'BASE DE PONTOS V+'!J:J) -> 0 | M36: =_xlfn.XLOOKUP(D36,'BASE DE PONTOS V+'!C:C,'BASE DE PONTOS V+'!L:L) -> #N/A | N36: =IF(B36="","",IFERROR(IF(I36="Financeiro",VLOOKUP(G36,'BASE DA MATRIZ DE RISCOS'!$O$58:$Q$62,3,1),"Avaliar por julgameto"),"1"))
... C38: [P30] | D38: =_xlfn.XLOOKUP($B38,'BASE DE PONTOS V+'!$B:$B,'BASE DE PONTOS V+'!$C:$C) -> 0 | E38: =_xlfn.XLOOKUP($B38,'BASE DE PONTOS V+'!$B:$B,'BASE DE PONTOS V+'!$D:$D) -> 0 | F38: =_xlfn.XLOOKUP($B38,'BASE DE PONTOS V+'!$B:$B,'BASE DE PONTOS V+'!$F:$F) -> 0 | G38: =_xlfn.XLOOKUP(B38,'BASE DE PONTOS V+'!B:B,'BASE DE PONTOS V+'!E:E) -> 0 | H38: =_xlfn.XLOOKUP($B38,'BASE DE PONTOS V+'!$B:$B,'BASE DE PONTOS V+'!$G:$G) -> 0 | I38: =_xlfn.XLOOKUP($B38,'BASE DE PONTOS V+'!$B:$B,'BASE DE PONTOS V+'!$H:$H) -> 0 | J38: =_xlfn.XLOOKUP($B38,'BASE DE PONTOS V+'!$B:$B,'BASE DE PONTOS V+'!$I:$I) -> 0 | K38: =_xlfn.XLOOKUP($B38,'BASE DE PONTOS V+'!$B:$B,'BASE DE PONTOS V+'!$M:$M) -> 0 | L38: =_xlfn.XLOOKUP(B38,'BASE DE PONTOS V+'!B:B,'BASE DE PONTOS V+'!J:J) -> 0 | M38: =_xlfn.XLOOKUP(D38,'BASE DE PONTOS V+'!C:C,'BASE DE PONTOS V+'!L:L) -> #N/A | N38: =IF(B38="","",IFERROR(IF(I38="Financeiro",VLOOKUP(G38,'BASE DA MATRIZ DE RISCOS'!$O$58:$Q$62,3,1),"Avaliar por julgameto"),"1"))
M39: =_xlfn.XLOOKUP(D39,'BASE DE PONTOS V+'!C:C,'BASE DE PONTOS V+'!L:L) -> 0 | N39: =IF(B39="","",IFERROR(IF(I39="Financeiro",VLOOKUP(G39,'BASE DA MATRIZ DE RISCOS'!$O$58:$Q$62,3,1),"Avaliar por julgameto"),"1"))
M40: =_xlfn.XLOOKUP(D40,'BASE DE PONTOS V+'!C:C,'BASE DE PONTOS V+'!L:L) -> 0 | N40: =IF(B40="","",IFERROR(IF(I40="Financeiro",VLOOKUP(G40,'BASE DA MATRIZ DE RISCOS'!$O$58:$Q$62,3,1),"Avaliar por julgameto"),"1"))
M41: =_xlfn.XLOOKUP(D41,'BASE DE PONTOS V+'!C:C,'BASE DE PONTOS V+'!L:L) -> 0 | N41: =IF(B41="","",IFERROR(IF(I41="Financeiro",VLOOKUP(G41,'BASE DA MATRIZ DE RISCOS'!$O$58:$Q$62,3,1),"Avaliar por julgameto"),"1"))
M42: =_xlfn.XLOOKUP(D42,'BASE DE PONTOS V+'!C:C,'BASE DE PONTOS V+'!L:L) -> 0 | N42: =IF(B42="","",IFERROR(IF(I42="Financeiro",VLOOKUP(G42,'BASE DA MATRIZ DE RISCOS'!$O$58:$Q$62,3,1),"Avaliar por julgameto"),"1"))
M43: =_xlfn.XLOOKUP(D43,'BASE DE PONTOS V+'!C:C,'BASE DE PONTOS V+'!L:L) -> 0 | N43: =IF(B43="","",IFERROR(IF(I43="Financeiro",VLOOKUP(G43,'BASE DA MATRIZ DE RISCOS'!$O$58:$Q$62,3,1),"Avaliar por julgameto"),"1"))

Sheet FREQ. X PONTOS
A1: Ponto V+ | B1: Pontos | C1: Ponto de forma resumida | D1: Descrição do ponto: | F1: Ponto | G1: Total | H1: Probabilidade | I1: Frequência | J1: Peso
B2: P01 | C2: Pagamento sem nota fiscal | D2: Verificamos que ocorreram gastos sem a respectiva emissão de nota fiscal pelos fornecedores e prestadores de serviços. | F2: P01 | G2: 35 | H2: 0.61403509 | I2: Muito frequente | J2: 5
B3: P02 | C3: Diferenças entre: Favorecido do documento X Beneficiário do pagamento | D3: O fornecedor apresentado no comprovante de pagamento não é o mesmo da Nota Fiscal. | F3: P02 | G3: 0
B4: P03 | C4: Pagamentos realizados sem os respectivos comprovantes de pagamento anexados | D4: Verificamos que alguns pagamentos foram realizados sem que fossem anexados os respectivos comprovantes de pagamentos ou documentos equivalentes dando a respectiva quitação. | F4: P03 | G4: 9 | H4: 0.15789474 | I4: Eventual | J4: 3
B5: P04 | C5: Pagamento de impostos sem identificação do prestador de serviços | D5: Não identificamos documentação suporte que indique a origem dos impostos e os respectivos prestadores de serviço. | F5: P04 | G5: 0
B6: P05 | C6: Ausência de apresentação de mapa de orçamentos | D6: Verificamos que muitas das compras realizadas não estavam anexados os mapas de orçamento. | F6: P05 | G6: 0
B7: P06 | C7: Inexistência de tempestividade na prestação de contas do fundo fixo | D7: Verificamos que o fundo fixo do Condomínio, por diversas vezes, possui valores retirados onde existe a prestação de contas nos meses não referentes. | F7: P06 | G7: 0
B8: P07 | C8: Inconsistência na apresentação da atividade da empresa | D8: O serviço/produto adquirido não condiz com a atividade econômica apresentada no CNPJ da empresa. | F8: P07 | G8: 0
B9: P08 | C9: Negligência na gestão dos Documentos que compõe os Demonstrativos | D9: Verificamos que alguns comprovantes não estão sendo arquivados com os cuidados necessários, com isso alguns estão ilegíveis. | F9: P08 | G9: 4 | H9: 0.070175439 | I9: Raro | J9: 2
B10: P09 | C10: Conjunto de documentos sem composição clara do valor pago | D10: Verificamos que algumas páginas do Demonstrativo Financeiro não estão sendo numeradas ou não seguem uma ordem sequencial. | F10: P09 | G10: 0
B11: P10 | C11: Páginas não numeradas ou numeradas de forma incorreta | D11: Verificamos que algumas páginas do Demonstrativo Financeiro não estão sendo numeradas ou não seguem uma ordem sequencial. | F11: P10 | G11: 0
B12: P11 | C12: Pagamento de tarifa bancária. | D12: Verificamos que ocorreram pagamento de fornecedores e prestadores de serviços por meio de transferência bancária. | F12: P11 | G12: 8 | H12: 0.14035088 | I12: Eventual | J12: 3
B13: P12 | C13: Conjunto de documentos anexados fora do mês correspondente. | D13: Desorganização da documentação suporte dificultam a análise de todas as partes envolvidas. | F13: P12 | G13: 0
B14: P13 | C14: Conjunto de documentos anexados no balancete sem o mesmo constarem nos demonstrativos financeiros mensais de gastos. | D14: Ausência de transparência na prestação de contas e aumento do risco de pagamentos indevidos. | F14: P13 | G14: 0
B15: P14 | C15: Diferenças entre: Valor do comprovante de pagamento X Valor da documentação suporte. | D15: Verificamos que há diferença entre os valores apresentados,não justificada por parcelamento ou multa. | F15: P14 | G15: 1 | H15: 0.01754386 | I15: Raríssimo | J15: 1
B16: P15 | C16: Pagamento realizado em duplicidade. | D16: Verificamos a existência de saidas no extrato duplicadas e pagamentos de despesas já encerradas. | F16: P15 | G16: 0
B17: P16 | C17: Pagamento realizados após data de vencimento com incidência de multa e juros. | D17: Verificamos que alguns pagamentos foram realizados após a data de vencimento acarretando em gastos adicionais. | F17: P16 | G17: 0
B18: P17 | C18: Pagamentos realizados antes da emissão da nota fiscal. | D18: Verificamos que ocorreram pagamentos com documentação fiscal com emissão posterior a data em que a transação bancária foi realizada. | F18: P17 | G18: 0
B19: P18 | C19: Informações apresentado fora do mês correspondente na demonstração financeira. | D19: Verificamos que há desorganização das informações na demonstração financeira que dificultam na análise de todas as partes envolvidas. | F19: P18 | G19: 0
F20: 0 | G20: 0
G26: 57 | H26: 1

Sheet Lista Suspensa
C3: TESTES | H3: Legenda
C4: 02.1.1 - CRA - Follow Up CCI | H4: a | I4: Feito
C5: 02.1.2 - CRA - Confirmação de Independência | H5: r | I5: Pendente
C6: 02.1.3 - CRA - Cálculo da Materialidade | H6: s | I6: Dúvida
C7: 02.1.4 - CRA - Planejamento dos testes e das contas Significativas conforme MATERIALIDADE | H7: x | I7: Ponto de escopo
C8: 02.1.5 - CRA - Voucher documental
C9: 02.1.6 - CRA - Voucher documental + voucher nos extratos
C10: 02.1.7 - CRA - Teste de voucher (inspeção das guias e confronto dos saldos demonstrativos)
C11: 02.1.8 - CRA - Consolidação dos saldos
C12: 02.1.9 - CRA - Resumo Regimento
C13: 02.1.10 - CRA - Resumo Convenção
C14: 02.1.11 - CRA - Carta de Representação de Atas
C15: 02.1.12 - CRA - Resumo Atas
C16: 02.1.13 - CRA - Analise do resumo de atas e verificação das despesas aprovadas
C17: 02.1.14 - CRA - Seguros
C18: 02.1.15 - CRA - Orçado X Realizado
C19: 02.1.16 - CRA - Revisão analitica de demonstrativos
... C62: 02.4.9 - CRA - Relatório Final da Apresentação da Auditoria

Sheet BASE DA MATRIZ DE RISCOS
C2: Item | D2: Descrição
C3: Impacto | D3: ALTO IMPACTO
C4: Status | D4: Explicação se é um ponto novo ou recorrente e quem identificou o ponto e/ou quando.
C5: Código | D5: [PX] Representa a numeração sequencial do Ponto de Controle;
C6: Título | D6: Explicação sintética e ideia central do Ponto de Controle;
C7: Tipo | D7: Cada Ponto de Controle é enquadrado em um tipo que implicará em um peso para o cálculo da exposição a risco;
C8: Probabilidade | D8: Frequência associada ao procedimento levantado no Ponto de Controle;
C9: Impacto | D9: Mensuração do impacto causado em cada ocasião de acontecimento do Ponto de Controle;
C10: Exposição | D10: Exposição = (PesoTipo*Probabilidade*Impacto);
C11: Setor | D11: A área da Empresa a qual o Ponto de Controle implica;
C12: Descrição | D12: Detalhamento conceitual do Ponto de Contole;
C13: Riscos e Implicações | D13: Consequências da não resolução do Ponto de Controle; usada também como base de mensuração para o Impacto;
... C17: Data Limite para Resolução do Ponto Identificado | D17: Prazo estipulado pela Administração do Condomínio Le Parc Residential Resort para que o ponto identificado deixe de existir.
C19: Critérios e Classificações dos Pontos de Controle
C20: Tipos de Pontos de Controle
C21: Tipo | D21: Descrição | E21: Peso
C22: Estratégico | D22: Inerentes às ações de longo prazo que visam a perpetuidade e transparência das operações; | E22: 4
C23: Financeiro | D23: Quando se tem risco de impacto financerio e/ou contingências financeiras evidentes; | E23: 5
C24: Operacional | D24: Riscos quanto a procedimentos executados no dia a dia para a prestação dos serviços; | E24: 4
C25: Legal | D25: Relativos a riscos e impactos jurídicos; | E25: 3
C26: Tecnologia | D26: Relativos a integração de sistema e LGPD; | E26: 3
C27: Imagem | D27: Referente a riscos de provável perda de credibilidade e desgaste da instituição. | E27: 3
C29: Tipo | D29: Descrição | E29: Peso | F29: Tipo | G29: Tipo | H29: % | I29: Tipo
C30: Estratégico | D30: Inerentes às ações de longo prazo que visam a perpetuidade e transparência das operações; | E30: 4 | F30: Estratégico | G30: Estratégico | H30: =I30/$J$36 -> 0.0625 | I30: =COUNTIFS($E$78:$E$109,$C30) -> 1
C31: Financeiro | D31: Quando se tem risco de impacto financerio e/ou contingências financeiras evidentes; | E31: 5 | F31: Financeiro | G31: Financeiro | H31: =I31/$J$36 -> 0.375 | I31: =COUNTIFS($E$78:$E$109,$C31) -> 6
C32: Operacional | D32: Riscos quanto a procedimentos executados no dia a dia para a prestação dos serviços; | E32: 4 | F32: Operacional | G32: Operacional | H32: =I32/$J$36 -> 0.25 | I32: =COUNTIFS($E$78:$E$109,$C32) -> 4
C33: Legal | D33: Relativos a riscos e impactos jurídicos; | E33: 3 | F33: Legal | G33: Legal | H33: =I33/$J$36 -> 0.3125 | I33: =COUNTIFS($E$78:$E$109,$C33) -> 5
C34: Tecnologia | D34: Relativos a integração de sistema e LGPD; | E34: 3 | F34: Tecnologia | G34: Tecnologia | H34: =I34/$J$36 -> 0 | I34: =COUNTIFS($E$78:$E$109,$C34) -> 0
C35: Imagem | D35: Referente a riscos de provável perda de credibilidade e desgaste da instituição. | E35: 3 | F35: Imagem | G35: Imagem | H35: =I35/$J$36 -> 0 | I35: =COUNTIFS($E$78:$E$109,$C35) -> 0
I36: =SUM(H30:H35) -> 1 | J36: =SUM(I30:I35) -> 16
C37: Probabilidade dos Pontos de Controle
C38: Probabilidade | D38: Frequencia | E38: Peso
C39: Muito frequente | D39: Frequencia de pontos incidentes em mais de 30% dos itens analisados | E39: 5
C40: Frequente | D40: Frequencia de pontos incidentes entre 20% e 30% analisados | E40: 4
C41: Eventual | D41: Frequencia de pontos incidentes entre 10% e 20% analisados | E41: 3
C42: Raro | D42: Frequencia de pontos incidentes entre 5% e 10% analisados | E42: 2
C43: Raríssimo | D43: Frequencia de pontos incidentes menor de 5% | E43: 1
C44: WP – Work Papers (Papéis de Trabalho)
C46: Impacto dos Pontos de Controle
J47: ='RESUMO DE PONTOS'!E3 -> Materialidade | K47: ='RESUMO DE PONTOS'!F3 -> 141950 | L47: =K47/$H$49 -> 0.030001065
F48: Impacto Faturamento | H48: ='RESUMO DE PONTOS'!G3 -> Total da Receita | J48: ='RESUMO DE PONTOS'!E4 -> PM | K48: ='RESUMO DE PONTOS'!F4 -> 95800 | L48: =K48/$H$49 -> 0.020247284
C49: Impacto | D49: Mensuração | E49: Peso | H49: ='RESUMO DE PONTOS'!G4 -> 4731498.7 | J49: ='RESUMO DE PONTOS'!E5 -> AMPT | K49: ='RESUMO DE PONTOS'!F5 -> 7100 | L49: =K49/$H$49 -> 0.0015005816
C50: Perdas graves | D50: - Impactos financeiros diretos superiores a M ( Materiality); | E50: 5 | F50: =G54+0.0000001% -> 0.030001066 | H50: =$H$49*F50 -> 141950 | I50: 10000000 | J50: 5
D51: - Riscos quanto a perpetuidade da operação;
D52: - Riscos críticos operacionais ligados à prestação do serviço;
D53: - Risco de morte/invalidez/doenças.
C54: Perdas grandes | D54: - Impactos financeiros diretos do PM até a M; | E54: 4 | F54: =G60+0.0000001% -> 0.020247285 | G54: =L47 -> 0.030001065 | H54: =$H$49*F54 -> 95800.005 | I54: =$H$49*G54 -> 141950 | J54: 4
D55: - Necessidade de contingências de 5;00% ou mais do faturamento;
D56: - Riscos operacionais ligados à prestação do serviço;
D57: - Riscos críticos gerenciais;
D58: - Riscos críticos de imagem; | O58: =H70 -> 0 | P58: =I70 -> 7100 | Q58: 1
D59: - Riscos críticos de clima organizacional. | O59: =H66 -> 7100.0473 | P59: =I66 -> 71850 | Q59: 2
C60: Perdas médias | D60: - Impactos financeiros diretos de até 75% do PM até o PM; | E60: 3 | F60: =G66+0.000001% -> 0.015185473 | G60: =L48 -> 0.020247284 | H60: =$H$49*F60-0.01 -> 71850.037 | I60: =$H$49*G60-0.01 -> 95799.99 | J60: 3 | O60: =H60 -> 71850.037 | P60: =I60 -> 95799.99 | Q60: 3
D61: - Necessidade de contingências de 1;00% a 4;99% do faturamento; | O61: =H54 -> 95800.005 | P61: =I54 -> 141950 | Q61: 4
D62: - Riscos leves operacionais ligados à prestação do serviço; | O62: =H50 -> 141950 | P62: =I50 -> 10000000 | Q62: 5
D63: - Riscos gerenciais. | O63: =H49 -> 4731498.7
D64: - Riscos de clima organizacional
D65: - Riscos de imagem.
C66: Perdas moderadas | D66: - Impactos financeiros diretos de entre o nosso AMPT e 75% do PM | E66: 2 | F66: =L49+0.000001% -> 0.0015005916 | G66: =L48*75% -> 0.015185463 | H66: =$H$49*F66 -> 7100.0473 | I66: =$H$49*G66 -> 71850 | J66: 2
D67: - Riscos leves gerenciais;
D68: - Riscos leves de imagem;
D69: - Riscos leves de clima organizacional
C70: Perdas pequenas | D70: - Impactos financeiros diretos de até o nosso AMPT; | E70: 1 | F70: 0 | G70: =L49 -> 0.0015005816 | H70: =$H$49*F70 -> 0 | I70: =$H$49*G70 -> 7100 | J70: 1
D71: - Falhas técnicas e/ou humanas em procedimentos que não irão impactar diretamente a qualidade dos dados.
C75: 3 – Pontos de Controle | M75: PRIORIDADE
C76: Sumário de Pontos | D76: Fórmula | E76: Fórmula | F76: Fórmula | G76: Avaliar | H76: Avaliar | I76: Fórmula | J76: Fórmula | K76: Fórmula | M76: Avaliação
A77: Link | C77: Ponto de Controle | D77: Título | E77: Tipo | F77: Tipo | G77: Probabilidade | H77: Perdas/ Impacto | I77: Exposição | J77: Setor | K77: Classificação por Pontuação | M77: Classificação Por Julgamento
A78: [P1] | C78: ='RESUMO DE PONTOS'!C9 -> [P1] | D78: =IFERROR(VLOOKUP(C78,'RESUMO DE PONTOS'!$C$9:$D$38,2,),"") -> Pagamento sem nota fiscal | E78: =IFERROR(VLOOKUP($C78,'RESUMO DE PONTOS'!$C$9:$L$38,7,),"") -> Legal | F78: =VLOOKUP(E78,$C$30:$E$35,3,) -> 3 | G78: =_xlfn.XLOOKUP(D78,'FREQ. X PONTOS'!C:C,'FREQ. X PONTOS'!J:J) -> 5 | H78: 2 | I78: =F78*G78*H78 -> 30 | J78: =IFERROR(VLOOKUP(C78,'RESUMO DE PONTOS'!$C$9:$J$38,8,),"") -> Voucher Documental | K78: =IF(I78>=75,"ALTO IMPACTO",IF(I78<=50,"BAIXO IMPACTO","MÉDIO IMPACTO")) -> BAIXO IMPACTO | M78: =_xlfn.XLOOKUP(C78,'RESUMO DE PONTOS'!C:C,'RESUMO DE PONTOS'!L:L) -> Alto Impacto | N78: =C78 -> [P1] | O78: =I78 -> 30
A79: [P2] | C79: ='RESUMO DE PONTOS'!C10 -> [P2] | D79: =IFERROR(VLOOKUP(C79,'RESUMO DE PONTOS'!$C$9:$D$38,2,),"") -> Pagamentos realizados sem os respectivos comprovantes de pagamento anexados | E79: =IFERROR(VLOOKUP($C79,'RESUMO DE PONTOS'!$C$9:$L$38,7,),"") -> Financeiro | F79: =VLOOKUP(E79,$C$30:$E$35,3,) -> 5 | G79: 3 | H79: 2 | I79: =F79*G79*H79 -> 30 | J79: =IFERROR(VLOOKUP(C79,'RESUMO DE PONTOS'!$C$9:$J$38,8,),"") -> Voucher Documental | K79: =IF(I79>=75,"ALTO IMPACTO",IF(I79<=50,"BAIXO IMPACTO","MÉDIO IMPACTO")) -> BAIXO IMPACTO | M79: =_xlfn.XLOOKUP(C79,'RESUMO DE PONTOS'!C:C,'RESUMO DE PONTOS'!L:L) -> Alto Impacto | N79: =C79 -> [P2] | O79: =I79 -> 30
A80: [P3] | C80: ='RESUMO DE PONTOS'!C11 -> [P3] | D80: =IFERROR(VLOOKUP(C80,'RESUMO DE PONTOS'!$C$9:$D$38,2,),"") -> Negligência na gestão dos Documentos que compõe os Demonstrativos | E80: =IFERROR(VLOOKUP($C80,'RESUMO DE PONTOS'!$C$9:$L$38,7,),"") -> Operacional | F80: =VLOOKUP(E80,$C$30:$E$35,3,) -> 4 | G80: 2 | H80: 1 | I80: =F80*G80*H80 -> 8 | J80: =IFERROR(VLOOKUP(C80,'RESUMO DE PONTOS'!$C$9:$J$38,8,),"") -> Voucher Documental | K80: =IF(I80>=75,"ALTO IMPACTO",IF(I80<=50,"BAIXO IMPACTO","MÉDIO IMPACTO")) -> BAIXO IMPACTO | M80: =_xlfn.XLOOKUP(C80,'RESUMO DE PONTOS'!C:C,'RESUMO DE PONTOS'!L:L) -> Baixo Impacto | N80: =C80 -> [P3] | O80: =I80 -> 8
A81: [P4] | C81: ='RESUMO DE PONTOS'!C12 -> [P4] | D81: =IFERROR(VLOOKUP(C81,'RESUMO DE PONTOS'!$C$9:$D$38,2,),"") -> Pagamento de tarifa bancária. | E81: =IFERROR(VLOOKUP($C81,'RESUMO DE PONTOS'!$C$9:$L$38,7,),"") -> Financeiro | F81: =VLOOKUP(E81,$C$30:$E$35,3,) -> 5 | G81: 3 | H81: 1 | I81: =F81*G81*H81 -> 15 | J81: =IFERROR(VLOOKUP(C81,'RESUMO DE PONTOS'!$C$9:$J$38,8,),"") -> Voucher Documental | K81: =IF(I81>=75,"ALTO IMPACTO",IF(I81<=50,"BAIXO IMPACTO","MÉDIO IMPACTO")) -> BAIXO IMPACTO | M81: =_xlfn.XLOOKUP(C81,'RESUMO DE PONTOS'!C:C,'RESUMO DE PONTOS'!L:L) -> Baixo Impacto | N81: =C81 -> [P4] | O81: =I81 -> 15
C82: ='RESUMO DE PONTOS'!C13 -> [P5] | D82: =IFERROR(VLOOKUP(C82,'RESUMO DE PONTOS'!$C$9:$D$38,2,),"") -> Diferenças entre: Valor do comprovante de pagamento X Valor da documentação suporte. | E82: =IFERROR(VLOOKUP($C82,'RESUMO DE PONTOS'!$C$9:$L$38,7,),"") -> Financeiro | F82: =VLOOKUP(E82,$C$30:$E$35,3,) -> 5 | G82: 1 | H82: 1 | I82: =F82*G82*H82 -> 5 | J82: =IFERROR(VLOOKUP(C82,'RESUMO DE PONTOS'!$C$9:$J$38,8,),"") -> Voucher Documental | K82: =IF(I82>=75,"ALTO IMPACTO",IF(I82<=50,"BAIXO IMPACTO","MÉDIO IMPACTO")) -> BAIXO IMPACTO | M82: =_xlfn.XLOOKUP(C82,'RESUMO DE PONTOS'!C:C,'RESUMO DE PONTOS'!L:L) -> Baixo Impacto | N82: =C82 -> [P5] | O82: =I82 -> 5
C83: ='RESUMO DE PONTOS'!C14 -> [P6] | D83: =IFERROR(VLOOKUP(C83,'RESUMO DE PONTOS'!$C$9:$D$38,2,),"") -> Acesso a Convenção do Condomínio | E83: =IFERROR(VLOOKUP($C83,'RESUMO DE PONTOS'!$C$9:$L$38,7,),"") -> Operacional | F83: =VLOOKUP(E83,$C$30:$E$35,3,) -> 4 | G83: 1 | H83: 1 | I83: =F83*G83*H83 -> 4 | J83: =IFERROR(VLOOKUP(C83,'RESUMO DE PONTOS'!$C$9:$J$38,8,),"") -> Resumo da Convenção | K83: =IF(I83>=75,"ALTO IMPACTO",IF(I83<=50,"BAIXO IMPACTO","MÉDIO IMPACTO")) -> BAIXO IMPACTO | M83: =_xlfn.XLOOKUP(C83,'RESUMO DE PONTOS'!C:C,'RESUMO DE PONTOS'!L:L) -> Baixo Impacto | N83: =C83 -> [P6] | O83: =I83 -> 4
C84: ='RESUMO DE PONTOS'!C15 -> [P7] | D84: =IFERROR(VLOOKUP(C84,'RESUMO DE PONTOS'!$C$9:$D$38,2,),"") -> Os balancetes sem aprovação dos conselheiros fiscais no termo de aprovação. | E84: =IFERROR(VLOOKUP($C84,'RESUMO DE PONTOS'!$C$9:$L$38,7,),"") -> Operacional | F84: =VLOOKUP(E84,$C$30:$E$35,3,) -> 4 | G84: 5 | H84: 3 | I84: =F84*G84*H84 -> 60 | J84: =IFERROR(VLOOKUP(C84,'RESUMO DE PONTOS'!$C$9:$J$38,8,),"") -> Resumo da Convenção | K84: =IF(I84>=75,"ALTO IMPACTO",IF(I84<=50,"BAIXO IMPACTO","MÉDIO IMPACTO")) -> MÉDIO IMPACTO | M84: =_xlfn.XLOOKUP(C84,'RESUMO DE PONTOS'!C:C,'RESUMO DE PONTOS'!L:L) -> Baixo Impacto | N84: =C84 -> [P7] | O84: =I84 -> 60
C85: ='RESUMO DE PONTOS'!C16 -> [P8] | D85: =IFERROR(VLOOKUP(C85,'RESUMO DE PONTOS'!$C$9:$D$38,2,),"") -> Impacto com os inadimplentes | E85: =IFERROR(VLOOKUP($C85,'RESUMO DE PONTOS'!$C$9:$L$38,7,),"") -> Financeiro | F85: =VLOOKUP(E85,$C$30:$E$35,3,) -> 5 | G85: 4 | H85: 2 | I85: =F85*G85*H85 -> 40 | J85: =IFERROR(VLOOKUP(C85,'RESUMO DE PONTOS'!$C$9:$J$38,8,),"") -> Inadimplentes | K85: =IF(I85>=75,"ALTO IMPACTO",IF(I85<=50,"BAIXO IMPACTO","MÉDIO IMPACTO")) -> BAIXO IMPACTO | M85: =_xlfn.XLOOKUP(C85,'RESUMO DE PONTOS'!C:C,'RESUMO DE PONTOS'!L:L) -> Médio Impacto | N85: =C85 -> [P8] | O85: =I85 -> 40
C86: ='RESUMO DE PONTOS'!C17 -> [P9] | D86: =IFERROR(VLOOKUP(C86,'RESUMO DE PONTOS'!$C$9:$D$38,2,),"") -> Ausência de Inventário dos ativos imobilizados | E86: =IFERROR(VLOOKUP($C86,'RESUMO DE PONTOS'!$C$9:$L$38,7,),"") -> Financeiro | F86: =VLOOKUP(E86,$C$30:$E$35,3,) -> 5 | G86: 4 | H86: 4 | I86: =F86*G86*H86 -> 80 | J86: =IFERROR(VLOOKUP(C86,'RESUMO DE PONTOS'!$C$9:$J$38,8,),"") -> Ativo imobilizado | K86: =IF(I86>=75,"ALTO IMPACTO",IF(I86<=50,"BAIXO IMPACTO","MÉDIO IMPACTO")) -> ALTO IMPACTO | M86: =_xlfn.XLOOKUP(C86,'RESUMO DE PONTOS'!C:C,'RESUMO DE PONTOS'!L:L) -> Alto Impacto | N86: =C86 -> [P9] | O86: =I86 -> 80
C87: ='RESUMO DE PONTOS'!C18 -> [P10] | D87: =IFERROR(VLOOKUP(C87,'RESUMO DE PONTOS'!$C$9:$D$38,2,),"") -> Inexistência de informações para emissão da certidão de FGTS na Caixa econômica Federal. | E87: =IFERROR(VLOOKUP($C87,'RESUMO DE PONTOS'!$C$9:$L$38,7,),"") -> Legal | F87: =VLOOKUP(E87,$C$30:$E$35,3,) -> 3 | G87: 4 | H87: 4 | I87: =F87*G87*H87 -> 48 | J87: =IFERROR(VLOOKUP(C87,'RESUMO DE PONTOS'!$C$9:$J$38,8,),"") -> Certidão | K87: =IF(I87>=75,"ALTO IMPACTO",IF(I87<=50,"BAIXO IMPACTO","MÉDIO IMPACTO")) -> BAIXO IMPACTO | M87: =_xlfn.XLOOKUP(C87,'RESUMO DE PONTOS'!C:C,'RESUMO DE PONTOS'!L:L) -> Alto Impacto | N87: =C87 -> [P10] | O87: =I87 -> 48
C88: ='RESUMO DE PONTOS'!C19 -> [P11] | D88: =IFERROR(VLOOKUP(C88,'RESUMO DE PONTOS'!$C$9:$D$38,2,),"") -> Capacidade de arrecadação inferior aos gastos. | E88: =IFERROR(VLOOKUP($C88,'RESUMO DE PONTOS'!$C$9:$L$38,7,),"") -> Estratégico | F88: =VLOOKUP(E88,$C$30:$E$35,3,) -> 4 | G88: 5 | H88: 5 | I88: =F88*G88*H88 -> 100 | J88: =IFERROR(VLOOKUP(C88,'RESUMO DE PONTOS'!$C$9:$J$38,8,),"") -> Demonstrativo de Receita e Despesas | K88: =IF(I88>=75,"ALTO IMPACTO",IF(I88<=50,"BAIXO IMPACTO","MÉDIO IMPACTO")) -> ALTO IMPACTO | M88: =_xlfn.XLOOKUP(C88,'RESUMO DE PONTOS'!C:C,'RESUMO DE PONTOS'!L:L) -> Alto Impacto | N88: =C88 -> [P11] | O88: =I88 -> 100
C89: ='RESUMO DE PONTOS'!C20 -> [P12] | D89: =IFERROR(VLOOKUP(C89,'RESUMO DE PONTOS'!$C$9:$D$38,2,),"") -> Envio de Boleto Fraudado | E89: =IFERROR(VLOOKUP($C89,'RESUMO DE PONTOS'!$C$9:$L$38,7,),"") -> Operacional | F89: =VLOOKUP(E89,$C$30:$E$35,3,) -> 4 | G89: 1 | H89: 1 | I89: =F89*G89*H89 -> 4 | J89: =IFERROR(VLOOKUP(C89,'RESUMO DE PONTOS'!$C$9:$J$38,8,),"") -> Demonstrativo de Receita e Despesas | K89: =IF(I89>=75,"ALTO IMPACTO",IF(I89<=50,"BAIXO IMPACTO","MÉDIO IMPACTO")) -> BAIXO IMPACTO | M89: =_xlfn.XLOOKUP(C89,'RESUMO DE PONTOS'!C:C,'RESUMO DE PONTOS'!L:L) -> Baixo Impacto | N89: =C89 -> [P12] | O89: =I89 -> 4
C90: ='RESUMO DE PONTOS'!C21 -> [P13] | D90: =IFERROR(VLOOKUP(C90,'RESUMO DE PONTOS'!$C$9:$D$38,2,),"") -> Débito automático referente ao bloqueio judicial | E90: =IFERROR(VLOOKUP($C90,'RESUMO DE PONTOS'!$C$9:$L$38,7,),"") -> Legal | F90: =VLOOKUP(E90,$C$30:$E$35,3,) -> 3 | G90: 3 | H90: 1 | I90: =F90*G90*H90 -> 9 | J90: =IFERROR(VLOOKUP(C90,'RESUMO DE PONTOS'!$C$9:$J$38,8,),"") -> Extratos | K90: =IF(I90>=75,"ALTO IMPACTO",IF(I90<=50,"BAIXO IMPACTO","MÉDIO IMPACTO")) -> BAIXO IMPACTO | M90: =_xlfn.XLOOKUP(C90,'RESUMO DE PONTOS'!C:C,'RESUMO DE PONTOS'!L:L) -> Médio Impacto | N90: =C90 -> [P13] | O90: =I90 -> 9
C91: ='RESUMO DE PONTOS'!C22 -> [P14] | D91: =IFERROR(VLOOKUP(C91,'RESUMO DE PONTOS'!$C$9:$D$38,2,),"") -> Saldo bloqueado Custódia de Caução. | E91: =IFERROR(VLOOKUP($C91,'RESUMO DE PONTOS'!$C$9:$L$38,7,),"") -> Financeiro | F91: =VLOOKUP(E91,$C$30:$E$35,3,) -> 5 | G91: 5 | H91: 1 | I91: =F91*G91*H91 -> 25 | J91: =IFERROR(VLOOKUP(C91,'RESUMO DE PONTOS'!$C$9:$J$38,8,),"") -> Demonstrativo de Receita e Despesas | K91: =IF(I91>=75,"ALTO IMPACTO",IF(I91<=50,"BAIXO IMPACTO","MÉDIO IMPACTO")) -> BAIXO IMPACTO | M91: =_xlfn.XLOOKUP(C91,'RESUMO DE PONTOS'!C:C,'RESUMO DE PONTOS'!L:L) -> Baixo Impacto | N91: =C91 -> [P14] | O91: =I91 -> 25
C92: ='RESUMO DE PONTOS'!C23 -> [P15] | D92: =IFERROR(VLOOKUP(C92,'RESUMO DE PONTOS'!$C$9:$D$38,2,),"") -> Não há classificação de expectativa de ganho para algumas causas ativas e de perda para as passivas. | E92: =IFERROR(VLOOKUP($C92,'RESUMO DE PONTOS'!$C$9:$L$38,7,),"") -> Legal | F92: =VLOOKUP(E92,$C$30:$E$35,3,) -> 3 | G92: 3 | H92: 2 | I92: =F92*G92*H92 -> 18 | J92: =IFERROR(VLOOKUP(C92,'RESUMO DE PONTOS'!$C$9:$J$38,8,),"") -> Contigência | K92: =IF(I92>=75,"ALTO IMPACTO",IF(I92<=50,"BAIXO IMPACTO","MÉDIO IMPACTO")) -> BAIXO IMPACTO | M92: =_xlfn.XLOOKUP(C92,'RESUMO DE PONTOS'!C:C,'RESUMO DE PONTOS'!L:L) -> Alto Impacto | N92: =C92 -> [P15] | O92: =I92 -> 18
C93: ='RESUMO DE PONTOS'!C24 -> [P16] | D93: =IFERROR(VLOOKUP(C93,'RESUMO DE PONTOS'!$C$9:$D$38,2,),"") -> Perda de Causa Judicial | E93: =IFERROR(VLOOKUP($C93,'RESUMO DE PONTOS'!$C$9:$L$38,7,),"") -> Legal | F93: =VLOOKUP(E93,$C$30:$E$35,3,) -> 3 | G93: 4 | H93: 2 | I93: =F93*G93*H93 -> 24 | J93: =IFERROR(VLOOKUP(C93,'RESUMO DE PONTOS'!$C$9:$J$38,8,),"") -> Contigência | K93: =IF(I93>=75,"ALTO IMPACTO",IF(I93<=50,"BAIXO IMPACTO","MÉDIO IMPACTO")) -> BAIXO IMPACTO | M93: =_xlfn.XLOOKUP(C93,'RESUMO DE PONTOS'!C:C,'RESUMO DE PONTOS'!L:L) -> Alto Impacto | N93: =C93 -> [P16] | O93: =I93 -> 24
J110: =IFERROR(VLOOKUP(C110,'RESUMO DE PONTOS'!$C$9:$J$38,8,),"")

Sheet GRÁFICOS
H69: BAIXO IMPACTO | I69: =COUNTIF($F$70:$F$100,H69) -> 13 | J69: =I69/$I$72 -> 0.8125
B70: ='BASE DA MATRIZ DE RISCOS'!E78 -> Legal | F70: ='BASE DA MATRIZ DE RISCOS'!K78 -> BAIXO IMPACTO | H70: MÉDIO IMPACTO | I70: =COUNTIF($F$70:$F$100,H70) -> 1 | J70: =I70/$I$72 -> 0.0625
B71: ='BASE DA MATRIZ DE RISCOS'!E79 -> Financeiro | C71: Estratégico | D71: =COUNTIF($B$70:$B$98,C71) -> 1 | F71: ='BASE DA MATRIZ DE RISCOS'!K79 -> BAIXO IMPACTO | H71: ALTO IMPACTO | I71: =COUNTIF($F$70:$F$100,H71) -> 2 | J71: =I71/$I$72 -> 0.125
B72: ='BASE DA MATRIZ DE RISCOS'!E80 -> Operacional | C72: Financeiro | D72: =COUNTIF($B$70:$B$98,C72) -> 6 | F72: ='BASE DA MATRIZ DE RISCOS'!K80 -> BAIXO IMPACTO | I72: =SUM(I69:I71) -> 16
B73: ='BASE DA MATRIZ DE RISCOS'!E81 -> Financeiro | C73: Operacional | D73: =COUNTIF($B$70:$B$98,C73) -> 4 | F73: ='BASE DA MATRIZ DE RISCOS'!K81 -> BAIXO IMPACTO
B74: ='BASE DA MATRIZ DE RISCOS'!E82 -> Financeiro | C74: Legal | D74: =COUNTIF($B$70:$B$98,C74) -> 5 | F74: ='BASE DA MATRIZ DE RISCOS'!K82 -> BAIXO IMPACTO
B75: ='BASE DA MATRIZ DE RISCOS'!E83 -> Operacional | F75: ='BASE DA MATRIZ DE RISCOS'!K83 -> BAIXO IMPACTO
B76: ='BASE DA MATRIZ DE RISCOS'!E84 -> Operacional | F76: ='BASE DA MATRIZ DE RISCOS'!K84 -> MÉDIO IMPACTO
B77: ='BASE DA MATRIZ DE RISCOS'!E85 -> Financeiro | F77: ='BASE DA MATRIZ DE RISCOS'!K85 -> BAIXO IMPACTO
B78: ='BASE DA MATRIZ DE RISCOS'!E86 -> Financeiro | F78: ='BASE DA MATRIZ DE RISCOS'!K86 -> ALTO IMPACTO
B79: ='BASE DA MATRIZ DE RISCOS'!E87 -> Legal | F79: ='BASE DA MATRIZ DE RISCOS'!K87 -> BAIXO IMPACTO
B80: ='BASE DA MATRIZ DE RISCOS'!E88 -> Estratégico | F80: ='BASE DA MATRIZ DE RISCOS'!K88 -> ALTO IMPACTO
B81: ='BASE DA MATRIZ DE RISCOS'!E89 -> Operacional | F81: ='BASE DA MATRIZ DE RISCOS'!K89 -> BAIXO IMPACTO
B82: ='BASE DA MATRIZ DE RISCOS'!E90 -> Legal | F82: ='BASE DA MATRIZ DE RISCOS'!K90 -> BAIXO IMPACTO
B83: ='BASE DA MATRIZ DE RISCOS'!E91 -> Financeiro | F83: ='BASE DA MATRIZ DE RISCOS'!K91 -> BAIXO IMPACTO
B84: ='BASE DA MATRIZ DE RISCOS'!E92 -> Legal | F84: ='BASE DA MATRIZ DE RISCOS'!K92 -> BAIXO IMPACTO
B85: ='BASE DA MATRIZ DE RISCOS'!E93 -> Legal | F85: ='BASE DA MATRIZ DE RISCOS'!K93 -> BAIXO IMPACTO
B86: ='BASE DA MATRIZ DE RISCOS'!E94 -> 0 | F86: ='BASE DA MATRIZ DE RISCOS'!K94 -> 0
... B141: ='BASE DA MATRIZ DE RISCOS'!E149 -> 0 | F141: ='BASE DA MATRIZ DE RISCOS'!K149 -> 0

Sheet P1
B2: Pontos de Controle
B3: Item | C3: Descrição
B4: Impacto | C4: =IF(C12>=75,"ALTO IMPACTO",IF(C12<=50,"BAIXO IMPACTO","MÉDIO IMPACTO")) -> BAIXO IMPACTO | E4: <<<<<< Automático conforme Metodologia e baseado no grau de exposição
B5: Status | C5: =IFERROR(VLOOKUP(C6,'RESUMO DE PONTOS'!$C$9:$M$58,11,),"") -> • 31/12/2021 • Recorrente ■ Vorcon Auditoria & Consultoria ■ 24/06/2022
B6: Código | C6: [P1]
B7: Título | C7: =VLOOKUP(C6,'BASE DA MATRIZ DE RISCOS'!$C$78:$D$210,2,) -> Pagamento sem nota fiscal
B8: Tipo | C8: =VLOOKUP(C6,'BASE DA MATRIZ DE RISCOS'!$C$78:$E$210,3,) -> Legal
B9: Tipo | C9: =VLOOKUP(C6,'BASE DA MATRIZ DE RISCOS'!$C$78:$H$210,4,) -> 3 | E9: <<<<<< Automático - Valores de 1 a 5 conforme metodologia
B10: Probabilidade | C10: =VLOOKUP(C6,'BASE DA MATRIZ DE RISCOS'!$C$78:$H$210,5,) -> 5 | E10: <<<<<< Valores de 1 a 5 conforme metodologia
B11: Impacto | C11: =VLOOKUP(C6,'BASE DA MATRIZ DE RISCOS'!$C$78:$H$210,6,) -> 2 | E11: <<<<<< Valores de 1 a 5 conforme metodologia
B12: Exposição | C12: =C9*C10*C11 -> 30 | E12: <<<<<< Calculado
B13: Testes/Áreas | C13: =VLOOKUP(C6,'BASE DA MATRIZ DE RISCOS'!$C$78:$J$210,8,) -> Voucher Documental | E13: <<<<<< Automático - conforme Matriz de Risco
B14: Descrição | C14: =VLOOKUP(C$6,'RESUMO DE PONTOS'!$C$9:$H$58,3,) -> Verificamos que ocorreram gastos sem a respectiva emissão de nota fiscal pelos fornecedores e prestadores de serviços.
B15: Riscos e Implicações | C15: =IFERROR(VLOOKUP(C$6,'RESUMO DE PONTOS'!$C$9:$H$58,4,),"") -> Pagamento sem os respectivos Fornecedores/Prestadores de serviços não é permitido pela legislação brasileira assim como Convenção e Regimento Interno do Condomínio podendo ser multado e/ou sofrer outras penalidades impostas pelo fisco.
B16: Impacto Financeiro | C16: =IFERROR(VLOOKUP(C$6,'RESUMO DE PONTOS'!$C$9:$H$58,5,),"") -> 47819.88
B17: Recomendações | C17: =IFERROR(VLOOKUP(C$6,'RESUMO DE PONTOS'!$C$9:$H$58,6,),"") -> Sugerimos que seja solicitado aos respectivos Fornecedores/ Prestadores de serviços ou fornecedores a nota fiscal pelo fornecimento de material ou de prestação de serviço.
B18: Comentários da Administração | C18: Resposta da Administração sobre o ponto identificado e sobre as ações de melhoria sugeridas e, eventualmente, esclarecimento das prioridades recomendadas.
B19: Ações a serem Implementadas pela Administração | C19: Ações definidas pela Administração para resolução do ponto identificado.
B20: Data Limite para Resolução do Ponto Identificado | C20: Prazo estipulado pela Administração para que o ponto identificado deixe de existir.

Sheet P2
B2: Pontos de Controle
B3: Item | C3: Descrição
B4: Impacto | C4: =IF(C12>=75,"ALTO IMPACTO",IF(C12<=50,"BAIXO IMPACTO","MÉDIO IMPACTO")) -> BAIXO IMPACTO | E4: <<<<<< Automático conforme Metodologia e baseado no grau de exposição
B5: Status | C5: =IFERROR(VLOOKUP(C6,'RESUMO DE PONTOS'!$C$9:$M$58,11,),"") -> • 31/12/2021 • Recorrente ■ Vorcon Auditoria & Consultoria ■ 24/06/2022
B6: Código | C6: [P2] | E6: <<<<<< Lista Suspensa (Selecionar)
B7: Título | C7: =VLOOKUP(C6,'BASE DA MATRIZ DE RISCOS'!$C$78:$D$210,2,) -> Pagamentos realizados sem os respectivos comprovantes de pagamento anexados
B8: Tipo | C8: =VLOOKUP(C6,'BASE DA MATRIZ DE RISCOS'!$C$78:$E$210,3,) -> Financeiro | E8: <<<<<< Lista Suspensa (Selecionar)
B9: Tipo | C9: =VLOOKUP(C6,'BASE DA MATRIZ DE RISCOS'!$C$78:$H$210,4,) -> 5 | E9: <<<<<< Automático - Valores de 1 a 5 conforme metodologia
B10: Probabilidade | C10: =VLOOKUP(C6,'BASE DA MATRIZ DE RISCOS'!$C$78:$H$210,5,) -> 3 | E10: <<<<<< Valores de 1 a 5 conforme metodologia
B11: Impacto | C11: =VLOOKUP(C6,'BASE DA MATRIZ DE RISCOS'!$C$78:$H$210,6,) -> 2 | E11: <<<<<< Valores de 1 a 5 conforme metodologia
B12: Exposição | C12: =C9*C10*C11 -> 30 | E12: <<<<<< Calculado
B13: Testes/Áreas | C13: =VLOOKUP(C6,'BASE DA MATRIZ DE RISCOS'!$C$78:$J$210,8,) -> Voucher Documental | E13: <<<<<< Automático - conforme Matriz de Risco
B14: Descrição | C14: =VLOOKUP(C$6,'RESUMO DE PONTOS'!$C$9:$H$58,3,) -> Verificamos que alguns pagamentos foram realizados sem que fossem anexados os respectivos comprovantes de pagamentos ou documentos equivalentes dando a respectiva quitação.
B15: Riscos e Implicações | C15: =IFERROR(VLOOKUP(C$6,'RESUMO DE PONTOS'!$C$9:$H$58,4,),"") -> Pagamento duplicado dos valores, ou caso haja a solicitação do comprovante de pagamento o Condomínio não os possua
B16: Impacto Financeiro | C16: =IFERROR(VLOOKUP(C$6,'RESUMO DE PONTOS'!$C$9:$H$58,5,),"") -> 23309.37
B17: Recomendações | C17: =IFERROR(VLOOKUP(C$6,'RESUMO DE PONTOS'!$C$9:$H$58,6,),"") -> Sugerimos que sejam criados processos para que os comprovantes de pagamentos estejam anexados ao processo de pagamentos
B18: Comentários da Administração | C18: Resposta da Administração sobre o ponto identificado e sobre as ações de melhoria sugeridas e, eventualmente, esclarecimento das prioridades recomendadas.
B19: Ações a serem Implementadas pela Administração | C19: Ações definidas pela Administração para resolução do ponto identificado.
B20: Data Limite para Resolução do Ponto Identificado | C20: Prazo estipulado pela Administração para que o ponto identificado deixe de existir.

Sheet P3
B2: Pontos de Controle
B3: Item | C3: Descrição
B4: Impacto | C4: =IF(C12>=75,"ALTO IMPACTO",IF(C12<=50,"BAIXO IMPACTO","MÉDIO IMPACTO")) -> BAIXO IMPACTO | E4: <<<<<< Automático conforme Metodologia e baseado no grau de exposição
B5: Status | C5: =IFERROR(VLOOKUP(C6,'RESUMO DE PONTOS'!$C$9:$M$58,11,),"") -> • 31/12/2021 • Recorrente ■ Vorcon Auditoria & Consultoria ■ 24/06/2022
B6: Código | C6: [P3] | E6: <<<<<< Lista Suspensa (Selecionar)
B7: Título | C7: =VLOOKUP(C6,'BASE DA MATRIZ DE RISCOS'!$C$78:$D$210,2,) -> Negligência na gestão dos Documentos que compõe os Demonstrativos
B8: Tipo | C8: =VLOOKUP(C6,'BASE DA MATRIZ DE RISCOS'!$C$78:$E$210,3,) -> Operacional | E8: <<<<<< Lista Suspensa (Selecionar)
B9: Tipo | C9: =VLOOKUP(C6,'BASE DA MATRIZ DE RISCOS'!$C$78:$H$210,4,) -> 4 | E9: <<<<<< Automático - Valores de 1 a 5 conforme metodologia
B10: Probabilidade | C10: =VLOOKUP(C6,'BASE DA MATRIZ DE RISCOS'!$C$78:$H$210,5,) -> 2 | E10: <<<<<< Valores de 1 a 5 conforme metodologia
B11: Impacto | C11: =VLOOKUP(C6,'BASE DA MATRIZ DE RISCOS'!$C$78:$H$210,6,) -> 1 | E11: <<<<<< Valores de 1 a 5 conforme metodologia
B12: Exposição | C12: =C9*C10*C11 -> 8 | E12: <<<<<< Calculado
B13: Testes/Áreas | C13: =VLOOKUP(C6,'BASE DA MATRIZ DE RISCOS'!$C$78:$J$210,8,) -> Voucher Documental | E13: <<<<<< Automático - conforme Matriz de Risco
B14: Descrição | C14: =VLOOKUP(C$6,'RESUMO DE PONTOS'!$C$9:$H$58,3,) -> Verificamos que alguns comprovantes não estão sendo arquivados com os cuidados necessários, com isso alguns estão ilegíveis. | L14: =72000 -> 72000
B15: Riscos e Implicações | C15: =IFERROR(VLOOKUP(C$6,'RESUMO DE PONTOS'!$C$9:$H$58,4,),"") -> Dificuldade na visualização dos gastos e impossibilidade e dúvidas quanto a possíveis consultas no futuro em função do estado dos documentos. | L15: =L14*19% -> 13680
B16: Impacto Financeiro | C16: =IFERROR(VLOOKUP(C$6,'RESUMO DE PONTOS'!$C$9:$H$58,5,),"") -> 1087.39 | L16: =L14-L15 -> 58320
B17: Recomendações | C17: =IFERROR(VLOOKUP(C$6,'RESUMO DE PONTOS'!$C$9:$H$58,6,),"") -> Sugerimos que sejam criados processos para que os comprovantes sejam de responsabilidade do financeiro tirar cópia ou digitalizá-los assim que os receber.
B18: Comentários da Administração | C18: Resposta da Administração sobre o ponto identificado e sobre as ações de melhoria sugeridas e, eventualmente, esclarecimento das prioridades recomendadas.
B19: Ações a serem Implementadas pela Administração | C19: Ações definidas pela Administração para resolução do ponto identificado.
B20: Data Limite para Resolução do Ponto Identificado | C20: Prazo estipulado pela Administração para que o ponto identificado deixe de existir.

Sheet P4
B2: Pontos de Controle
B3: Item | C3: Descrição
B4: Impacto | C4: =IF(C12>=75,"ALTO IMPACTO",IF(C12<=50,"BAIXO IMPACTO","MÉDIO IMPACTO")) -> BAIXO IMPACTO | E4: <<<<<< Automático conforme Metodologia e baseado no grau de exposição
B5: Status | C5: =IFERROR(VLOOKUP(C6,'RESUMO DE PONTOS'!$C$9:$M$58,11,),"") -> • 31/12/2021 • Recorrente ■ Vorcon Auditoria & Consultoria ■ 24/06/2022
B6: Código | C6: [P4] | E6: <<<<<< Lista Suspensa (Selecionar)
B7: Título | C7: =VLOOKUP(C6,'BASE DA MATRIZ DE RISCOS'!$C$78:$D$210,2,) -> Pagamento de tarifa bancária.
B8: Tipo | C8: =VLOOKUP(C6,'BASE DA MATRIZ DE RISCOS'!$C$78:$E$210,3,) -> Financeiro | E8: <<<<<< Lista Suspensa (Selecionar)
B9: Tipo | C9: =VLOOKUP(C6,'BASE DA MATRIZ DE RISCOS'!$C$78:$H$210,4,) -> 5 | E9: <<<<<< Automático - Valores de 1 a 5 conforme metodologia
B10: Probabilidade | C10: =VLOOKUP(C6,'BASE DA MATRIZ DE RISCOS'!$C$78:$H$210,5,) -> 3 | E10: <<<<<< Valores de 1 a 5 conforme metodologia
B11: Impacto | C11: =VLOOKUP(C6,'BASE DA MATRIZ DE RISCOS'!$C$78:$H$210,6,) -> 1 | E11: <<<<<< Valores de 1 a 5 conforme metodologia
B12: Exposição | C12: =C9*C10*C11 -> 15 | E12: <<<<<< Calculado
B13: Testes/Áreas | C13: =VLOOKUP(C6,'BASE DA MATRIZ DE RISCOS'!$C$78:$J$210,8,) -> Voucher Documental | E13: <<<<<< Automático - conforme Matriz de Risco
B14: Descrição | C14: =VLOOKUP(C$6,'RESUMO DE PONTOS'!$C$9:$H$58,3,) -> Verificamos que ocorreram pagamento de fornecedores e prestadores de serviços por meio de transferência bancária.
B15: Riscos e Implicações | C15: =IFERROR(VLOOKUP(C$6,'RESUMO DE PONTOS'!$C$9:$H$58,4,),"") -> Pagamento de encargos financeiros que deveriam ser de responsabilidade dos Fornecedores/Prestadores de serviços
B16: Impacto Financeiro | C16: =IFERROR(VLOOKUP(C$6,'RESUMO DE PONTOS'!$C$9:$H$58,5,),"") -> 88.4
B17: Recomendações | C17: =IFERROR(VLOOKUP(C$6,'RESUMO DE PONTOS'!$C$9:$H$58,6,),"") -> Sugerimos que seja solicitado boleto para pagamento de todos os Fornecedores/Prestadores de serviços e em caso de negativa o valor dos encargos financeiros deve ser subtraído do pagamento.
B18: Comentários da Administração | C18: Resposta da Administração sobre o ponto identificado e sobre as ações de melhoria sugeridas e, eventualmente, esclarecimento das prioridades recomendadas.
B19: Ações a serem Implementadas pela Administração | C19: Ações definidas pela Administração para resolução do ponto identificado.
B20: Data Limite para Resolução do Ponto Identificado | C20: Prazo estipulado pela Administração para que o ponto identificado deixe de existir.

Sheet P5
B2: Pontos de Controle
B3: Item | C3: Descrição
B4: Impacto | C4: =IF(C12>=75,"ALTO IMPACTO",IF(C12<=50,"BAIXO IMPACTO","MÉDIO IMPACTO")) -> BAIXO IMPACTO | E4: <<<<<< Automático conforme Metodologia e baseado no grau de exposição
B5: Status | C5: =IFERROR(VLOOKUP(C6,'RESUMO DE PONTOS'!$C$9:$M$58,11,),"") -> • 31/12/2021 • Recorrente ■ Vorcon Auditoria & Consultoria ■ 24/06/2022
B6: Código | C6: [P5] | E6: <<<<<< Lista Suspensa (Selecionar)
B7: Título | C7: =VLOOKUP(C6,'BASE DA MATRIZ DE RISCOS'!$C$78:$D$210,2,) -> Diferenças entre: Valor do comprovante de pagamento X Valor da documentação suporte.
B8: Tipo | C8: =VLOOKUP(C6,'BASE DA MATRIZ DE RISCOS'!$C$78:$E$210,3,) -> Financeiro | E8: <<<<<< Lista Suspensa (Selecionar)
B9: Tipo | C9: =VLOOKUP(C6,'BASE DA MATRIZ DE RISCOS'!$C$78:$H$210,4,) -> 5 | E9: <<<<<< Automático - Valores de 1 a 5 conforme metodologia
B10: Probabilidade | C10: =VLOOKUP(C6,'BASE DA MATRIZ DE RISCOS'!$C$78:$H$210,5,) -> 1 | E10: <<<<<< Valores de 1 a 5 conforme metodologia
B11: Impacto | C11: =VLOOKUP(C6,'BASE DA MATRIZ DE RISCOS'!$C$78:$H$210,6,) -> 1 | E11: <<<<<< Valores de 1 a 5 conforme metodologia
B12: Exposição | C12: =C9*C10*C11 -> 5 | E12: <<<<<< Calculado
B13: Testes/Áreas | C13: =VLOOKUP(C6,'BASE DA MATRIZ DE RISCOS'!$C$78:$J$210,8,) -> Voucher Documental | E13: <<<<<< Automático - conforme Matriz de Risco
B14: Descrição | C14: =VLOOKUP(C$6,'RESUMO DE PONTOS'!$C$9:$H$58,3,) -> Verificamos que há diferença entre os valores apresentados, não justificada por parcelamento ou multa.
B15: Riscos e Implicações | C15: =IFERROR(VLOOKUP(C$6,'RESUMO DE PONTOS'!$C$9:$H$58,4,),"") -> Possibilidade de pagamentos realizados com valores incorretos.
B16: Impacto Financeiro | C16: =IFERROR(VLOOKUP(C$6,'RESUMO DE PONTOS'!$C$9:$H$58,5,),"") -> 333.3
B17: Recomendações | C17: =IFERROR(VLOOKUP(C$6,'RESUMO DE PONTOS'!$C$9:$H$58,6,),"") -> Sugerimos que os pagamentos sejam realizados com os valores que constam no documento auxiliar.
B18: Comentários da Administração | C18: Resposta da Administração sobre o ponto identificado e sobre as ações de melhoria sugeridas e, eventualmente, esclarecimento das prioridades recomendadas.
B19: Ações a serem Implementadas pela Administração | C19: Ações definidas pela Administração para resolução do ponto identificado.
B20: Data Limite para Resolução do Ponto Identificado | C20: Prazo estipulado pela Administração para que o ponto identificado deixe de existir.

Sheet P6
B2: Pontos de Controle
B3: Item | C3: Descrição
B4: Impacto | C4: =IF(C12>=75,"ALTO IMPACTO",IF(C12<=50,"BAIXO IMPACTO","MÉDIO IMPACTO")) -> BAIXO IMPACTO | E4: <<<<<< Automático conforme Metodologia e baseado no grau de exposição
B5: Status | C5: =IFERROR(VLOOKUP(C6,'RESUMO DE PONTOS'!$C$9:$M$58,11,),"") -> • 31/12/2021 • Recorrente ■ Vorcon Auditoria & Consultoria ■ 24/06/2022
B6: Código | C6: [P6] | E6: <<<<<< Lista Suspensa (Selecionar)
B7: Título | C7: =VLOOKUP(C6,'BASE DA MATRIZ DE RISCOS'!$C$78:$D$210,2,) -> Acesso a Convenção do Condomínio
B8: Tipo | C8: =VLOOKUP(C6,'BASE DA MATRIZ DE RISCOS'!$C$78:$E$210,3,) -> Operacional | E8: <<<<<< Lista Suspensa (Selecionar)
B9: Tipo | C9: =VLOOKUP(C6,'BASE DA MATRIZ DE RISCOS'!$C$78:$H$210,4,) -> 4 | E9: <<<<<< Automático - Valores de 1 a 5 conforme metodologia
B10: Probabilidade | C10: =VLOOKUP(C6,'BASE DA MATRIZ DE RISCOS'!$C$78:$H$210,5,) -> 1 | E10: <<<<<< Valores de 1 a 5 conforme metodologia
B11: Impacto | C11: =VLOOKUP(C6,'BASE DA MATRIZ DE RISCOS'!$C$78:$H$210,6,) -> 1 | E11: <<<<<< Valores de 1 a 5 conforme metodologia
B12: Exposição | C12: =C9*C10*C11 -> 4 | E12: <<<<<< Calculado
B13: Testes/Áreas | C13: =VLOOKUP(C6,'BASE DA MATRIZ DE RISCOS'!$C$78:$J$210,8,) -> Resumo da Convenção | E13: <<<<<< Automático - conforme Matriz de Risco
B14: Descrição | C14: =VLOOKUP(C$6,'RESUMO DE PONTOS'!$C$9:$H$58,3,) -> Verificamos que o Condomínio não possui site, o ideal seria ter um site e disponibiliar o requimento Regimento nele.
B15: Riscos e Implicações | C15: =IFERROR(VLOOKUP(C$6,'RESUMO DE PONTOS'!$C$9:$H$58,4,),"") -> As melhores práticas de gestão sugerem que as informações do Condomínio estejam de fácil acesso para qualquer condômino.
B16: Impacto Financeiro | C16: =IFERROR(VLOOKUP(C$6,'RESUMO DE PONTOS'!$C$9:$H$58,5,),"") -> N/A
B17: Recomendações | C17: =IFERROR(VLOOKUP(C$6,'RESUMO DE PONTOS'!$C$9:$H$58,6,),"") -> Sugerimos que o Condomínio contate a sua equipe de TI e verifique a possibilidade de criar um site do Condomínio e disponibilizar a convenção
B18: Comentários da Administração | C18: Resposta da Administração sobre o ponto identificado e sobre as ações de melhoria sugeridas e, eventualmente, esclarecimento das prioridades recomendadas.
B19: Ações a serem Implementadas pela Administração | C19: Ações definidas pela Administração para resolução do ponto identificado.
B20: Data Limite para Resolução do Ponto Identificado | C20: Prazo estipulado pela Administração para que o ponto identificado deixe de existir.

Sheet P7
B2: Pontos de Controle
B3: Item | C3: Descrição
B4: Impacto | C4: =IF(C12>=75,"ALTO IMPACTO",IF(C12<=50,"BAIXO IMPACTO","MÉDIO IMPACTO")) -> MÉDIO IMPACTO | E4: <<<<<< Automático conforme Metodologia e baseado no grau de exposição
B5: Status | C5: =IFERROR(VLOOKUP(C6,'RESUMO DE PONTOS'!$C$9:$M$58,11,),"") -> • 31/12/2021 • Novo ■ Vorcon Auditoria & Consultoria ■ 24/06/2022
B6: Código | C6: [P7] | E6: <<<<<< Lista Suspensa (Selecionar)
B7: Título | C7: =VLOOKUP(C6,'BASE DA MATRIZ DE RISCOS'!$C$78:$D$210,2,) -> Os balancetes sem aprovação dos conselheiros fiscais no termo de aprovação.
B8: Tipo | C8: =VLOOKUP(C6,'BASE DA MATRIZ DE RISCOS'!$C$78:$E$210,3,) -> Operacional | E8: <<<<<< Lista Suspensa (Selecionar)
B9: Tipo | C9: =VLOOKUP($C$8,'BASE DA MATRIZ DE RISCOS'!$C$30:$E$35,3) -> 4 | E9: <<<<<< Automático - Valores de 1 a 5 conforme metodologia
B10: Probabilidade | C10: =VLOOKUP(C6,'BASE DA MATRIZ DE RISCOS'!$C$78:$H$210,5,) -> 5 | E10: <<<<<< Valores de 1 a 5 conforme metodologia
B11: Impacto | C11: =VLOOKUP(C6,'BASE DA MATRIZ DE RISCOS'!$C$78:$H$210,6,) -> 3 | E11: <<<<<< Valores de 1 a 5 conforme metodologia
B12: Exposição | C12: =C9*C10*C11 -> 60 | E12: <<<<<< Calculado
B13: Testes/Áreas | C13: =VLOOKUP(C6,'BASE DA MATRIZ DE RISCOS'!$C$78:$J$210,8,) -> Resumo da Convenção | E13: <<<<<< Automático - conforme Matriz de Risco
B14: Descrição | C14: =VLOOKUP(C$6,'RESUMO DE PONTOS'!$C$9:$H$58,3,) -> Nos meses 01/2021 à 12/2021 não constam as assinaturas dos conselheiros fiscais e do síndico para aprovação dos balancetes.
B15: Riscos e Implicações | C15: =IFERROR(VLOOKUP(C$6,'RESUMO DE PONTOS'!$C$9:$H$58,4,),"") -> A falta das assinaturas dos conselheiros fiscais nos termos de aprovação dos balancetes indica que as contas do condomínio não foram submetidas ao exame, acarretando a redução do nível de confiança dos demonstrativos e podendo prejudicar a leitura dos usuários.
B16: Impacto Financeiro | C16: =IFERROR(VLOOKUP(C$6,'RESUMO DE PONTOS'!$C$9:$H$58,5,),"") -> N/A
B17: Recomendações | C17: =IFERROR(VLOOKUP(C$6,'RESUMO DE PONTOS'!$C$9:$H$58,6,),"") -> Sugerimos que os conselheiros fiscais realizem o exame dos balancetes e caso ocorra a aprovação dos mesmos, confirmem com as suas assinaturas nos termos de aprovação. Mesmo com as demonstrações financeiras sendo auditadas mensalmente, é necessário a validação do conselho fiscal.
B18: Comentários da Administração | C18: Resposta da Administração sobre o ponto identificado e sobre as ações de melhoria sugeridas e, eventualmente, esclarecimento das prioridades recomendadas.
B19: Ações a serem Implementadas pela Administração | C19: Ações definidas pela Administração para resolução do ponto identificado.
B20: Data Limite para Resolução do Ponto Identificado | C20: Prazo estipulado pela Administração para que o ponto identificado deixe de existir.

Sheet P8
B2: Pontos de Controle
B3: Item | C3: Descrição
B4: Impacto | C4: =IF(C12>=75,"ALTO IMPACTO",IF(C12<=50,"BAIXO IMPACTO","MÉDIO IMPACTO")) -> BAIXO IMPACTO | E4: <<<<<< Automático conforme Metodologia e baseado no grau de exposição
B5: Status | C5: =IFERROR(VLOOKUP(C6,'RESUMO DE PONTOS'!$C$9:$M$58,11,),"") -> • 31/12/2021 • Recorrente ■ Vorcon Auditoria & Consultoria ■ 24/06/2022
B6: Código | C6: [P8]
B7: Título | C7: =VLOOKUP(C6,'BASE DA MATRIZ DE RISCOS'!$C$78:$D$210,2,) -> Impacto com os inadimplentes
B8: Tipo | C8: =VLOOKUP(C6,'BASE DA MATRIZ DE RISCOS'!$C$78:$E$210,3,) -> Financeiro
B9: Tipo | C9: =VLOOKUP($C$8,'BASE DA MATRIZ DE RISCOS'!$C$30:$E$35,3) -> 5 | E9: <<<<<< Automático - Valores de 1 a 5 conforme metodologia
B10: Probabilidade | C10: =VLOOKUP(C6,'BASE DA MATRIZ DE RISCOS'!$C$78:$H$210,5,) -> 4 | E10: <<<<<< Valores de 1 a 5 conforme metodologia
B11: Impacto | C11: =VLOOKUP(C6,'BASE DA MATRIZ DE RISCOS'!$C$78:$H$210,6,) -> 2 | E11: <<<<<< Valores de 1 a 5 conforme metodologia
B12: Exposição | C12: =C9*C10*C11 -> 40 | E12: <<<<<< Calculado
B13: Testes/Áreas | C13: =VLOOKUP(C6,'BASE DA MATRIZ DE RISCOS'!$C$78:$J$210,8,) -> Inadimplentes | E13: <<<<<< Automático - conforme Matriz de Risco
B14: Descrição | C14: =VLOOKUP(C$6,'RESUMO DE PONTOS'!$C$9:$H$58,3,) -> Verificamos que a inadimplência na data base de 31/12/2021 foi equivalente a R$ 23.053,25 atualizados com multas, juros e correção.
B15: Riscos e Implicações | C15: =IFERROR(VLOOKUP(C$6,'RESUMO DE PONTOS'!$C$9:$H$58,4,),"") -> O alto índice de inadimplência condominial impacta inicialmente o orçamento do condomínio. Assim, é preciso compensar de alguma forma o déficit orçamentário para que as obrigações condominiais sejam cumpridas. Como alternativas para essas compensações, podem ser ajustados os valores das taxas condominiais, utilizados os seus fundos de reserva ou criadas taxas extras, gerado assim, prejuízos aos condomínios adimplentes e a toda estrutura financeira condominial. Ademais, ocorre as implicações de ordem interpessoal para que ocorra a regularização dos valores, o que em casos mais graves necessita de cobrança judicial, gerando outros gastos com honorários advocatícios e custas judiciais.
B16: Impacto Financeiro | C16: =IFERROR(VLOOKUP(C$6,'RESUMO DE PONTOS'!$C$9:$H$58,5,),"") -> 23053.25
B17: Recomendações | C17: =IFERROR(VLOOKUP(C$6,'RESUMO DE PONTOS'!$C$9:$H$58,6,),"") -> Indicamos à administração ações preventivas que tenham como objetivo a redução das despesas condominiais, o fortalecimento do fundo de reserva e a cobrança de maneira assertiva dos inadimplentes. Além disso, devem ser buscadas alternativas analisando a relação de custos e benefícios para solução desse problema, como por exemplo, a utilização dos serviços de uma garantidora de condomínio.
B18: Comentários da Administração | C18: Resposta da Administração sobre o ponto identificado e sobre as ações de melhoria sugeridas e, eventualmente, esclarecimento das prioridades recomendadas.
B19: Ações a serem Implementadas pela Administração | C19: Ações definidas pela Administração para resolução do ponto identificado.
B20: Data Limite para Resolução do Ponto Identificado | C20: Prazo estipulado pela Administração para que o ponto identificado deixe de existir.

Sheet P9
B2: Pontos de Controle
B3: Item | C3: Descrição
B4: Impacto | C4: =IF(C12>=75,"ALTO IMPACTO",IF(C12<=50,"BAIXO IMPACTO","MÉDIO IMPACTO")) -> ALTO IMPACTO | E4: <<<<<< Automático conforme Metodologia e baseado no grau de exposição
B5: Status | C5: =IFERROR(VLOOKUP(C6,'RESUMO DE PONTOS'!$C$9:$M$58,11,),"") -> • 31/12/2021 • Recorrente ■ Vorcon Auditoria & Consultoria ■ 24/06/2022
B6: Código | C6: [P9] | E6: <<<<<< Lista Suspensa (Selecionar)
B7: Título | C7: =VLOOKUP(C6,'BASE DA MATRIZ DE RISCOS'!$C$78:$D$210,2,) -> Ausência de Inventário dos ativos imobilizados
B8: Tipo | C8: =VLOOKUP(C6,'BASE DA MATRIZ DE RISCOS'!$C$78:$E$210,3,) -> Financeiro | E8: <<<<<< Lista Suspensa (Selecionar)
B9: Tipo | C9: =VLOOKUP($C$8,'BASE DA MATRIZ DE RISCOS'!$C$30:$E$35,3) -> 5 | E9: <<<<<< Automático - Valores de 1 a 5 conforme metodologia
B10: Probabilidade | C10: =VLOOKUP(C6,'BASE DA MATRIZ DE RISCOS'!$C$78:$H$210,5,) -> 4 | E10: <<<<<< Valores de 1 a 5 conforme metodologia
B11: Impacto | C11: =VLOOKUP(C6,'BASE DA MATRIZ DE RISCOS'!$C$78:$H$210,6,) -> 4 | E11: <<<<<< Valores de 1 a 5 conforme metodologia
B12: Exposição | C12: =C9*C10*C11 -> 80 | E12: <<<<<< Calculado
B13: Testes/Áreas | C13: =VLOOKUP(C6,'BASE DA MATRIZ DE RISCOS'!$C$78:$J$210,8,) -> Ativo imobilizado | E13: <<<<<< Automático - conforme Matriz de Risco
B14: Descrição | C14: =VLOOKUP(C$6,'RESUMO DE PONTOS'!$C$9:$H$58,3,) -> Não foi possível identificar o controle patrimonial dos ativos imobilizados do condomínio.
B15: Riscos e Implicações | C15: =IFERROR(VLOOKUP(C$6,'RESUMO DE PONTOS'!$C$9:$H$58,4,),"") -> A ausência do controle patrimonial, o condomínio poderá impactar em possíveis perdas ou desvios do ativo imobilizado.
B16: Impacto Financeiro | C16: =IFERROR(VLOOKUP(C$6,'RESUMO DE PONTOS'!$C$9:$H$58,5,),"") -> N/A
B17: Recomendações | C17: =IFERROR(VLOOKUP(C$6,'RESUMO DE PONTOS'!$C$9:$H$58,6,),"") -> Sugerimos à Administração do condomínio que busque realizar o inventário dos ativos imobilizados anualmente.
B18: Comentários da Administração | C18: Resposta da Administração sobre o ponto identificado e sobre as ações de melhoria sugeridas e, eventualmente, esclarecimento das prioridades recomendadas.
B19: Ações a serem Implementadas pela Administração | C19: Ações definidas pela Administração para resolução do ponto identificado.
B20: Data Limite para Resolução do Ponto Identificado | C20: Prazo estipulado pela Administração para que o ponto identificado deixe de existir.

Sheet P10
B2: Pontos de Controle
B3: Item | C3: Descrição
B4: Impacto | C4: =IF(C12>=75,"ALTO IMPACTO",IF(C12<=50,"BAIXO IMPACTO","MÉDIO IMPACTO")) -> ALTO IMPACTO | E4: <<<<<< Automático conforme Metodologia e baseado no grau de exposição
B5: Status | C5: =IFERROR(VLOOKUP(C6,'RESUMO DE PONTOS'!$C$9:$M$58,11,),"") -> • 31/12/2021 • Recorrente ■ Vorcon Auditoria & Consultoria ■ 24/06/2022
B6: Código | C6: [P10] | E6: <<<<<< Lista Suspensa (Selecionar)
B7: Título | C7: =VLOOKUP(C6,'BASE DA MATRIZ DE RISCOS'!$C$78:$D$210,2,) -> Inexistência de informações para emissão da certidão de FGTS na Caixa econômica Federal.
B8: Tipo | C8: =VLOOKUP(C6,'BASE DA MATRIZ DE RISCOS'!$C$78:$E$210,3,) -> Legal | E8: <<<<<< Lista Suspensa (Selecionar)
B9: Tipo | C9: =VLOOKUP($C$8,'BASE DA MATRIZ DE RISCOS'!$C$30:$E$35,3) -> 5 | E9: <<<<<< Automático - Valores de 1 a 5 conforme metodologia
B10: Probabilidade | C10: =VLOOKUP(C6,'BASE DA MATRIZ DE RISCOS'!$C$78:$H$210,5,) -> 4 | E10: <<<<<< Valores de 1 a 5 conforme metodologia
B11: Impacto | C11: =VLOOKUP(C6,'BASE DA MATRIZ DE RISCOS'!$C$78:$H$210,6,) -> 4 | E11: <<<<<< Valores de 1 a 5 conforme metodologia
B12: Exposição | C12: =C9*C10*C11 -> 80 | E12: <<<<<< Calculado
B13: Testes/Áreas | C13: =VLOOKUP(C6,'BASE DA MATRIZ DE RISCOS'!$C$78:$J$210,8,) -> Certidão | E13: <<<<<< Automático - conforme Matriz de Risco
B14: Descrição | C14: =VLOOKUP(C$6,'RESUMO DE PONTOS'!$C$9:$H$58,3,) -> Ao realizar a consulta do Certificado de Regularidade Do FGTS, obtivemos a seguinte resposta: "As informações disponíveis não são suficientes para a comprovação automática da regularidade do empregador perante o FGTS. Solicitamos acessar o portal Conectividade Social, mediante certificado ICP, para verificar possíveis impedimentos ou comparecer a uma das Agências da CAIXA". Com esclarecimentos adicionais no endereçamento.
B15: Riscos e Implicações | C15: =IFERROR(VLOOKUP(C$6,'RESUMO DE PONTOS'!$C$9:$H$58,4,),"") -> A inexistência dos dados para emissão da certidão junto ao Caixa, poderá resultar no agravamento do acompanhamento das certidões.
B16: Impacto Financeiro | C16: =IFERROR(VLOOKUP(C$6,'RESUMO DE PONTOS'!$C$9:$H$58,5,),"") -> N/A
B17: Recomendações | C17: =IFERROR(VLOOKUP(C$6,'RESUMO DE PONTOS'!$C$9:$H$58,6,),"") -> Sugerimos que a administração entre no portal Conectividade Social da Caixa e faça o entendimento de quais dados estão faltando para verificar possíveis impedimentos.
B18: Comentários da Administração | C18: Resposta da Administração sobre o ponto identificado e sobre as ações de melhoria sugeridas e, eventualmente, esclarecimento das prioridades recomendadas.
B19: Ações a serem Implementadas pela Administração | C19: Ações definidas pela Administração para resolução do ponto identificado.
B20: Data Limite para Resolução do Ponto Identificado | C20: Prazo estipulado pela Administração para que o ponto identificado deixe de existir.

Sheet P11
B2: Pontos de Controle
B3: Item | C3: Descrição
B4: Impacto | C4: =IF(C12>=75,"ALTO IMPACTO",IF(C12<=50,"BAIXO IMPACTO","MÉDIO IMPACTO")) -> ALTO IMPACTO | E4: <<<<<< Automático conforme Metodologia e baseado no grau de exposição
B5: Status | C5: =IFERROR(VLOOKUP(C6,'RESUMO DE PONTOS'!$C$9:$M$58,11,),"") -> • 31/12/2021 • Recorrente ■ Vorcon Auditoria & Consultoria ■ 24/06/2022
B6: Código | C6: [P11]
B7: Título | C7: =VLOOKUP(C6,'BASE DA MATRIZ DE RISCOS'!$C$78:$D$210,2,) -> Capacidade de arrecadação inferior aos gastos.
B8: Tipo | C8: =VLOOKUP(C6,'BASE DA MATRIZ DE RISCOS'!$C$78:$E$210,3,) -> Estratégico | E8: <<<<<< Lista Suspensa (Selecionar)
B9: Tipo | C9: =VLOOKUP($C$8,'BASE DA MATRIZ DE RISCOS'!$C$30:$E$35,3) -> 4 | E9: <<<<<< Automático - Valores de 1 a 5 conforme metodologia
B10: Probabilidade | C10: =VLOOKUP(C6,'BASE DA MATRIZ DE RISCOS'!$C$78:$H$210,5,) -> 5 | E10: <<<<<< Valores de 1 a 5 conforme metodologia
B11: Impacto | C11: =VLOOKUP(C6,'BASE DA MATRIZ DE RISCOS'!$C$78:$H$210,6,) -> 5 | E11: <<<<<< Valores de 1 a 5 conforme metodologia
B12: Exposição | C12: =C9*C10*C11 -> 100 | E12: <<<<<< Calculado
B13: Testes/Áreas | C13: =VLOOKUP(C6,'BASE DA MATRIZ DE RISCOS'!$C$78:$J$210,8,) -> Demonstrativo de Receita e Despesas | E13: <<<<<< Automático - conforme Matriz de Risco
B14: Descrição | C14: =VLOOKUP(C$6,'RESUMO DE PONTOS'!$C$9:$H$58,3,) -> As receitas do meses 02, 04, 07, 09, 10 e 12/2021 não estão sendo suficiente para cobrir as despesas, acarretando em um défict no total nesses meses de - R$ 235.528,38
B15: Riscos e Implicações | C15: =IFERROR(VLOOKUP(C$6,'RESUMO DE PONTOS'!$C$9:$H$58,4,),"") -> Com as despesas elevadas, o condomínio não consegue arcar com 100% das suas obrigações afetando o fluxo de caixa do financeiro, e ao mesmo tempo não consegue atingir um valor médio ou alto para o fundo de reserva para um futuro inesperado.
B16: Impacto Financeiro | C16: =IFERROR(VLOOKUP(C$6,'RESUMO DE PONTOS'!$C$9:$H$58,5,),"") -> -235528.38
B17: Recomendações | C17: =IFERROR(VLOOKUP(C$6,'RESUMO DE PONTOS'!$C$9:$H$58,6,),"") -> Recomendamos ao Conselho Fiscal e a Administração condominial que verifique novas ações a realizar para redução das despesas mitigando ou solucionando o problema.
B18: Comentários da Administração | C18: Resposta da Administração sobre o ponto identificado e sobre as ações de melhoria sugeridas e, eventualmente, esclarecimento das prioridades recomendadas.
B19: Ações a serem Implementadas pela Administração | C19: Ações definidas pela Administração para resolução do ponto identificado.
B20: Data Limite para Resolução do Ponto Identificado | C20: Prazo estipulado pela Administração para que o ponto identificado deixe de existir.

Sheet P12
B2: Pontos de Controle
B3: Item | C3: Descrição
B4: Impacto | C4: =IF(C12>=75,"ALTO IMPACTO",IF(C12<=50,"BAIXO IMPACTO","MÉDIO IMPACTO")) -> BAIXO IMPACTO | E4: <<<<<< Automático conforme Metodologia e baseado no grau de exposição
B5: Status | C5: =IFERROR(VLOOKUP(C6,'RESUMO DE PONTOS'!$C$9:$M$58,11,),"") -> • 31/12/2021 • Novo ■ Vorcon Auditoria & Consultoria ■ 24/06/2022
B6: Código | C6: [P12] | E6: <<<<<< Lista Suspensa (Selecionar)
B7: Título | C7: =VLOOKUP(C6,'BASE DA MATRIZ DE RISCOS'!$C$78:$D$210,2,) -> Envio de Boleto Fraudado
B8: Tipo | C8: =VLOOKUP(C6,'BASE DA MATRIZ DE RISCOS'!$C$78:$E$210,3,) -> Operacional | E8: <<<<<< Lista Suspensa (Selecionar)
B9: Tipo | C9: =VLOOKUP($C$8,'BASE DA MATRIZ DE RISCOS'!$C$30:$E$35,3) -> 4 | E9: <<<<<< Automático - Valores de 1 a 5 conforme metodologia
B10: Probabilidade | C10: =VLOOKUP(C6,'BASE DA MATRIZ DE RISCOS'!$C$78:$H$210,5,) -> 1 | E10: <<<<<< Valores de 1 a 5 conforme metodologia
B11: Impacto | C11: =VLOOKUP(C6,'BASE DA MATRIZ DE RISCOS'!$C$78:$H$210,6,) -> 1 | E11: <<<<<< Valores de 1 a 5 conforme metodologia
B12: Exposição | C12: =C9*C10*C11 -> 4 | E12: <<<<<< Calculado
B13: Testes/Áreas | C13: =VLOOKUP(C6,'BASE DA MATRIZ DE RISCOS'!$C$78:$J$210,8,) -> Demonstrativo de Receita e Despesas | E13: <<<<<< Automático - conforme Matriz de Risco
B14: Descrição | C14: =VLOOKUP(C$6,'RESUMO DE PONTOS'!$C$9:$H$58,3,) -> Identificamos que o Condomínio enviou um possível boleto fraudado para a Condômina Jussara Barros da Unidade 2801 B no Mês 01/2021 na qual realizou o pagamento. O condomínio necessitou realizar a baixa do valor pago da condômina resultando em prejuízo financeiro de R$ 919,14.
B15: Riscos e Implicações | C15: =IFERROR(VLOOKUP(C$6,'RESUMO DE PONTOS'!$C$9:$H$58,4,),"") -> A falta de processo da análise do controle interno das contas a pagar sobre a verificação dos envios dos boletos recebidos pelo Advogado, poderá acarretar em envios de boletos errôneos e gerar prejuízos ao condomínio e a toda estrutura financeira condominial.
B16: Impacto Financeiro | C16: =IFERROR(VLOOKUP(C$6,'RESUMO DE PONTOS'!$C$9:$H$58,5,),"") -> 919.14
B17: Recomendações | C17: =IFERROR(VLOOKUP(C$6,'RESUMO DE PONTOS'!$C$9:$H$58,6,),"") -> Recomendamos a Administração do Condomíonio verifique ações de controles internos para verificação dos boletos enviados aos clientes.
B18: Comentários da Administração | C18: Resposta da Administração sobre o ponto identificado e sobre as ações de melhoria sugeridas e, eventualmente, esclarecimento das prioridades recomendadas.
B19: Ações a serem Implementadas pela Administração | C19: Ações definidas pela Administração para resolução do ponto identificado.
B20: Data Limite para Resolução do Ponto Identificado | C20: Prazo estipulado pela Administração para que o ponto identificado deixe de existir.

Sheet P13
B2: Pontos de Controle
B3: Item | C3: Descrição
B4: Impacto | C4: =IF(C12>=75,"ALTO IMPACTO",IF(C12<=50,"BAIXO IMPACTO","MÉDIO IMPACTO")) -> BAIXO IMPACTO | E4: <<<<<< Automático conforme Metodologia e baseado no grau de exposição
B5: Status | C5: =IFERROR(VLOOKUP(C6,'RESUMO DE PONTOS'!$C$9:$M$58,11,),"") -> • 31/12/2021 • Novo ■ Vorcon Auditoria & Consultoria ■ 24/06/2022
B6: Código | C6: [P13] | E6: <<<<<< Lista Suspensa (Selecionar)
B7: Título | C7: =VLOOKUP(C6,'BASE DA MATRIZ DE RISCOS'!$C$78:$D$210,2,) -> Débito automático referente ao bloqueio judicial
B8: Tipo | C8: =VLOOKUP(C6,'BASE DA MATRIZ DE RISCOS'!$C$78:$E$210,3,) -> Legal | E8: <<<<<< Lista Suspensa (Selecionar)
B9: Tipo | C9: =VLOOKUP($C$8,'BASE DA MATRIZ DE RISCOS'!$C$30:$E$35,3) -> 5 | E9: <<<<<< Automático - Valores de 1 a 5 conforme metodologia
B10: Probabilidade | C10: =VLOOKUP(C6,'BASE DA MATRIZ DE RISCOS'!$C$78:$H$210,5,) -> 3 | E10: <<<<<< Valores de 1 a 5 conforme metodologia
B11: Impacto | C11: =VLOOKUP(C6,'BASE DA MATRIZ DE RISCOS'!$C$78:$H$210,6,) -> 1 | E11: <<<<<< Valores de 1 a 5 conforme metodologia
B12: Exposição | C12: =C9*C10*C11 -> 15 | E12: <<<<<< Calculado
B13: Testes/Áreas | C13: =VLOOKUP(C6,'BASE DA MATRIZ DE RISCOS'!$C$78:$J$210,8,) -> Extratos | E13: <<<<<< Automático - conforme Matriz de Risco
B14: Descrição | C14: =VLOOKUP(C$6,'RESUMO DE PONTOS'!$C$9:$H$58,3,) -> Identificamos nos extratos e nas despesas operacionais que houve o débito automático de de R$ 1.045,19 no mês 8/2021 e de R$ 420,069 no mês 09/2021 referente ao bloqueio judicial.
B15: Riscos e Implicações | C15: =IFERROR(VLOOKUP(C$6,'RESUMO DE PONTOS'!$C$9:$H$58,4,),"") -> Os gastos com bloqueios judiciais geram possíveis prejuízos ao condomínio e a toda estrutura financeira condominial.
B16: Impacto Financeiro | C16: =IFERROR(VLOOKUP(C$6,'RESUMO DE PONTOS'!$C$9:$H$58,5,),"") -> 1465.259
B17: Recomendações | C17: =IFERROR(VLOOKUP(C$6,'RESUMO DE PONTOS'!$C$9:$H$58,6,),"") -> Sugerimos a Administração do Condomínio que mantenha o monitoramento constante dos processos financeiros e judicial acompanhando os processos em andamento.
B18: Comentários da Administração | C18: Resposta da Administração sobre o ponto identificado e sobre as ações de melhoria sugeridas e, eventualmente, esclarecimento das prioridades recomendadas.
B19: Ações a serem Implementadas pela Administração | C19: Ações definidas pela Administração para resolução do ponto identificado.
B20: Data Limite para Resolução do Ponto Identificado | C20: Prazo estipulado pela Administração para que o ponto identificado deixe de existir.

Sheet P14
B2: Pontos de Controle
B3: Item | C3: Descrição
B4: Impacto | C4: =IF(C12>=75,"ALTO IMPACTO",IF(C12<=50,"BAIXO IMPACTO","MÉDIO IMPACTO")) -> BAIXO IMPACTO | E4: <<<<<< Automático conforme Metodologia e baseado no grau de exposição
B5: Status | C5: =IFERROR(VLOOKUP(C6,'RESUMO DE PONTOS'!$C$9:$M$58,11,),"") -> • 31/12/2021 • Novo ■ Vorcon Auditoria & Consultoria ■ 24/06/2022
B6: Código | C6: [P14] | E6: <<<<<< Lista Suspensa (Selecionar)
B7: Título | C7: =VLOOKUP(C6,'BASE DA MATRIZ DE RISCOS'!$C$78:$D$210,2,) -> Saldo bloqueado Custódia de Caução.
B8: Tipo | C8: =VLOOKUP(C6,'BASE DA MATRIZ DE RISCOS'!$C$78:$E$210,3,) -> Financeiro | E8: <<<<<< Lista Suspensa (Selecionar)
B9: Tipo | C9: =VLOOKUP($C$8,'BASE DA MATRIZ DE RISCOS'!$C$30:$E$35,3) -> 5 | E9: <<<<<< Automático - Valores de 1 a 5 conforme metodologia
B10: Probabilidade | C10: =VLOOKUP(C6,'BASE DA MATRIZ DE RISCOS'!$C$78:$H$210,5,) -> 5 | E10: <<<<<< Valores de 1 a 5 conforme metodologia
B11: Impacto | C11: =VLOOKUP(C6,'BASE DA MATRIZ DE RISCOS'!$C$78:$H$210,6,) -> 1 | E11: <<<<<< Valores de 1 a 5 conforme metodologia
B12: Exposição | C12: =C9*C10*C11 -> 25 | E12: <<<<<< Calculado
B13: Testes/Áreas | C13: =VLOOKUP(C6,'BASE DA MATRIZ DE RISCOS'!$C$78:$J$210,8,) -> Demonstrativo de Receita e Despesas | E13: <<<<<< Automático - conforme Matriz de Risco
B14: Descrição | C14: =VLOOKUP(C$6,'RESUMO DE PONTOS'!$C$9:$H$58,3,) -> Identificamos que durante os meses 09, 10, 11 e 12/2021 o condomínio está em opção custodia caução no valor R$ 4.889,37 nas contas, Bradesco e Caixa Econômica devido a cancelamento do acesso ao conta CEF não foi possível atualizar o saldo das contas.
B15: Riscos e Implicações | C15: =IFERROR(VLOOKUP(C$6,'RESUMO DE PONTOS'!$C$9:$H$58,4,),"") -> Devido ao bloqueio do saldo da conta CEF, não foi possível atualizar o saldo das contas nos meses 09, 10, 11 e 12/2021 podendo afetar diretamente o fluxo de caixa e o controle do financeiro do condomínio.
B16: Impacto Financeiro | C16: =IFERROR(VLOOKUP(C$6,'RESUMO DE PONTOS'!$C$9:$H$58,5,),"") -> 4889.37
B17: Recomendações | C17: =IFERROR(VLOOKUP(C$6,'RESUMO DE PONTOS'!$C$9:$H$58,6,),"") -> Sugerimos que a administração entre em contato com a Caixa Econômica Federal e verificar os possíveis impedimentos.
B18: Comentários da Administração | C18: Resposta da Administração sobre o ponto identificado e sobre as ações de melhoria sugeridas e, eventualmente, esclarecimento das prioridades recomendadas.
B19: Ações a serem Implementadas pela Administração | C19: Ações definidas pela Administração para resolução do ponto identificado.
B20: Data Limite para Resolução do Ponto Identificado | C20: Prazo estipulado pela Administração para que o ponto identificado deixe de existir.

Sheet P15
B2: Pontos de Controle
B3: Item | C3: Descrição
B4: Impacto | C4: =IF(C12>=75,"ALTO IMPACTO",IF(C12<=50,"BAIXO IMPACTO","MÉDIO IMPACTO")) -> BAIXO IMPACTO | E4: <<<<<< Automático conforme Metodologia e baseado no grau de exposição
B5: Status | C5: =IFERROR(VLOOKUP(C6,'RESUMO DE PONTOS'!$C$9:$M$58,11,),"") -> • 31/12/2021 • Novo ■ Vorcon Auditoria & Consultoria ■ 24/06/2022
B6: Código | C6: [P15] | E6: <<<<<< Lista Suspensa (Selecionar)
B7: Título | C7: =VLOOKUP(C6,'BASE DA MATRIZ DE RISCOS'!$C$78:$D$210,2,) -> Não há classificação de expectativa de ganho para algumas causas ativas e de perda para as passivas.
B8: Tipo | C8: =VLOOKUP(C6,'BASE DA MATRIZ DE RISCOS'!$C$78:$E$210,3,) -> Legal | E8: <<<<<< Lista Suspensa (Selecionar)
B9: Tipo | C9: =VLOOKUP($C$8,'BASE DA MATRIZ DE RISCOS'!$C$30:$E$35,3) -> 5 | E9: <<<<<< Automático - Valores de 1 a 5 conforme metodologia
B10: Probabilidade | C10: =VLOOKUP(C6,'BASE DA MATRIZ DE RISCOS'!$C$78:$H$210,5,) -> 3 | E10: <<<<<< Valores de 1 a 5 conforme metodologia
B11: Impacto | C11: =VLOOKUP(C6,'BASE DA MATRIZ DE RISCOS'!$C$78:$H$210,6,) -> 2 | E11: <<<<<< Valores de 1 a 5 conforme metodologia
B12: Exposição | C12: =C9*C10*C11 -> 30 | E12: <<<<<< Calculado
B13: Testes/Áreas | C13: =VLOOKUP(C6,'BASE DA MATRIZ DE RISCOS'!$C$78:$J$210,8,) -> Contigência | E13: <<<<<< Automático - conforme Matriz de Risco
B14: Descrição | C14: =VLOOKUP(C$6,'RESUMO DE PONTOS'!$C$9:$H$58,3,) -> Não há classificação de expectativa de ganho para algumas causas ativas e de perda para as passivas.
B15: Riscos e Implicações | C15: =IFERROR(VLOOKUP(C$6,'RESUMO DE PONTOS'!$C$9:$H$58,4,),"") -> Verificamos os relatórios de contingências de 2021 e não identificamos quais expectativas de ganho ou perda no contrato. • Passivas – montante de R$ 22.000,00
B16: Impacto Financeiro | C16: =IFERROR(VLOOKUP(C$6,'RESUMO DE PONTOS'!$C$9:$H$58,5,),"") -> 22000
B17: Recomendações | C17: =IFERROR(VLOOKUP(C$6,'RESUMO DE PONTOS'!$C$9:$H$58,6,),"") -> Recomendamos que o jurídico do condomínio forneça informações relativa a estimativa de perda ou ganhos dos processos ativos.
B18: Comentários da Administração | C18: Resposta da Administração sobre o ponto identificado e sobre as ações de melhoria sugeridas e, eventualmente, esclarecimento das prioridades recomendadas.
B19: Ações a serem Implementadas pela Administração | C19: Ações definidas pela Administração para resolução do ponto identificado.
B20: Data Limite para Resolução do Ponto Identificado | C20: Prazo estipulado pela Administração para que o ponto identificado deixe de existir.

Sheet P16
B2: Pontos de Controle
B3: Item | C3: Descrição
B4: Impacto | C4: =IF(C12>=75,"ALTO IMPACTO",IF(C12<=50,"BAIXO IMPACTO","MÉDIO IMPACTO")) -> BAIXO IMPACTO | E4: <<<<<< Automático conforme Metodologia e baseado no grau de exposição
B5: Status | C5: =IFERROR(VLOOKUP(C6,'RESUMO DE PONTOS'!$C$9:$M$58,10,),"") -> Alto Impacto
B6: Código | C6: [P16] | E6: <<<<<< Lista Suspensa (Selecionar)
B7: Título | C7: =VLOOKUP(C6,'BASE DA MATRIZ DE RISCOS'!$C$78:$D$210,2,) -> Perda de Causa Judicial
B8: Tipo | C8: =VLOOKUP(C6,'BASE DA MATRIZ DE RISCOS'!$C$78:$E$210,3,) -> Legal | E8: <<<<<< Lista Suspensa (Selecionar)
B9: Tipo | C9: =VLOOKUP($C$8,'BASE DA MATRIZ DE RISCOS'!$C$30:$E$35,3) -> 5 | E9: <<<<<< Automático - Valores de 1 a 5 conforme metodologia
B10: Probabilidade | C10: =VLOOKUP(C6,'BASE DA MATRIZ DE RISCOS'!$C$78:$H$210,5,) -> 4 | E10: <<<<<< Valores de 1 a 5 conforme metodologia
B11: Impacto | C11: =VLOOKUP(C6,'BASE DA MATRIZ DE RISCOS'!$C$78:$H$210,6,) -> 2 | E11: <<<<<< Valores de 1 a 5 conforme metodologia
B12: Exposição | C12: =C9*C10*C11 -> 40 | E12: <<<<<< Calculado
B13: Testes/Áreas | C13: =VLOOKUP(C6,'BASE DA MATRIZ DE RISCOS'!$C$78:$J$210,8,) -> Contigência | E13: <<<<<< Automático - conforme Matriz de Risco
B14: Descrição | C14: =VLOOKUP(C$6,'RESUMO DE PONTOS'!$C$9:$H$58,3,) -> Indentificamos que durante o período de 2021 que há perda de causa judicial de R$ 10.477,17 referente ao n° 0101419-55.2017.8.05.0001 de TICIANA CARNEIRO DA ROCHA PRATA MONTEIRO X TRIBECA, e R$ 29.000,00 referente ao n° 0164073-44.2018.8.05.0001 de RAFAEL CALDAS LOPES X TRIBECA, totalizando em uma perda de R$ 39.477,17
B15: Riscos e Implicações | C15: =IFERROR(VLOOKUP(C$6,'RESUMO DE PONTOS'!$C$9:$H$58,4,),"") -> Devido a perda das causas judicais podendo afetar diretamente o fluxo de caixa e o controle do financeiro do condomínio.
B16: Impacto Financeiro | C16: =IFERROR(VLOOKUP(C$6,'RESUMO DE PONTOS'!$C$9:$H$58,5,),"") -> 39477.17
B17: Recomendações | C17: =IFERROR(VLOOKUP(C$6,'RESUMO DE PONTOS'!$C$9:$H$58,6,),"") -> Recomendamos ações preventivas nas melhorias no controle interno para que as causas judiciais não sejam abertas contra o condomínio.
B18: Comentários da Administração | C18: Resposta da Administração sobre o ponto identificado e sobre as ações de melhoria sugeridas e, eventualmente, esclarecimento das prioridades recomendadas.
B19: Ações a serem Implementadas pela Administração | C19: Ações definidas pela Administração para resolução do ponto identificado.
B20: Data Limite para Resolução do Ponto Identificado | C20: Prazo estipulado pela Administração para que o ponto identificado deixe de existir.

Sheet P17
B2: Pontos de Controle
B3: Item | C3: Descrição
B4: Impacto | C4: =IF(C12>=75,"ALTO IMPACTO",IF(C12<=50,"BAIXO IMPACTO","MÉDIO IMPACTO")) -> #N/A | E4: <<<<<< Automático conforme Metodologia e baseado no grau de exposição
B5: Status | C5: =IFERROR(VLOOKUP(C6,'RESUMO DE PONTOS'!$C$9:$M$58,10,),"") -> 0
B6: Código | C6: [P17] | E6: <<<<<< Lista Suspensa (Selecionar)
B7: Título | C7: =VLOOKUP(C6,'BASE DA MATRIZ DE RISCOS'!$C$78:$D$210,2,) -> #N/A
B8: Tipo | C8: =VLOOKUP(C6,'BASE DA MATRIZ DE RISCOS'!$C$78:$E$210,3,) -> #N/A | E8: <<<<<< Lista Suspensa (Selecionar)
B9: Tipo | C9: =VLOOKUP($C$8,'BASE DA MATRIZ DE RISCOS'!$C$30:$E$35,3) -> #N/A | E9: <<<<<< Automático - Valores de 1 a 5 conforme metodologia
B10: Probabilidade | C10: =VLOOKUP(C6,'BASE DA MATRIZ DE RISCOS'!$C$78:$H$210,5,) -> #N/A | E10: <<<<<< Valores de 1 a 5 conforme metodologia
B11: Impacto | C11: =VLOOKUP(C6,'BASE DA MATRIZ DE RISCOS'!$C$78:$H$210,6,) -> #N/A | E11: <<<<<< Valores de 1 a 5 conforme metodologia
B12: Exposição | C12: =C9*C10*C11 -> #N/A | E12: <<<<<< Calculado
B13: Testes/Áreas | C13: =VLOOKUP(C6,'BASE DA MATRIZ DE RISCOS'!$C$78:$J$210,8,) -> #N/A | E13: <<<<<< Automático - conforme Matriz de Risco
B14: Descrição | C14: =VLOOKUP(C$6,'RESUMO DE PONTOS'!$C$9:$H$58,3,) -> 0
B15: Riscos e Implicações | C15: =IFERROR(VLOOKUP(C$6,'RESUMO DE PONTOS'!$C$9:$H$58,4,),"") -> 0
B16: Impacto Financeiro | C16: =IFERROR(VLOOKUP(C$6,'RESUMO DE PONTOS'!$C$9:$H$58,5,),"") -> 0
B17: Recomendações | C17: =IFERROR(VLOOKUP(C$6,'RESUMO DE PONTOS'!$C$9:$H$58,6,),"") -> 0
B18: Comentários da Administração | C18: Resposta da Administração sobre o ponto identificado e sobre as ações de melhoria sugeridas e, eventualmente, esclarecimento das prioridades recomendadas.
B19: Ações a serem Implementadas pela Administração | C19: Ações definidas pela Administração para resolução do ponto identificado.
B20: Data Limite para Resolução do Ponto Identificado | C20: Prazo estipulado pela Administração para que o ponto identificado deixe de existir.

Sheet P18
B2: Pontos de Controle
B3: Item | C3: Descrição
B4: Impacto | C4: =IF(C12>=75,"ALTO IMPACTO",IF(C12<=50,"BAIXO IMPACTO","MÉDIO IMPACTO")) -> #N/A | E4: <<<<<< Automático conforme Metodologia e baseado no grau de exposição
B5: Status | C5: =IFERROR(VLOOKUP(C6,'RESUMO DE PONTOS'!$C$9:$M$58,10,),"") -> 0
B6: Código | C6: [P18] | E6: <<<<<< Lista Suspensa (Selecionar)
B7: Título | C7: =VLOOKUP(C6,'BASE DA MATRIZ DE RISCOS'!$C$78:$D$210,2,) -> #N/A
B8: Tipo | C8: =VLOOKUP(C6,'BASE DA MATRIZ DE RISCOS'!$C$78:$E$210,3,) -> #N/A | E8: <<<<<< Lista Suspensa (Selecionar)
B9: Tipo | C9: =VLOOKUP($C$8,'BASE DA MATRIZ DE RISCOS'!$C$30:$E$36,3) -> #N/A | E9: <<<<<< Automático - Valores de 1 a 5 conforme metodologia
B10: Probabilidade | C10: =VLOOKUP(C6,'BASE DA MATRIZ DE RISCOS'!$C$78:$H$210,5,) -> #N/A | E10: <<<<<< Valores de 1 a 5 conforme metodologia
B11: Impacto | C11: =VLOOKUP(C6,'BASE DA MATRIZ DE RISCOS'!$C$78:$H$210,6,) -> #N/A | E11: <<<<<< Valores de 1 a 5 conforme metodologia
B12: Exposição | C12: =C9*C10*C11 -> #N/A | E12: <<<<<< Calculado
B13: Testes/Áreas | C13: =VLOOKUP(C6,'BASE DA MATRIZ DE RISCOS'!$C$78:$J$210,8,) -> #N/A | E13: <<<<<< Automático - conforme Matriz de Risco
B14: Descrição | C14: =VLOOKUP(C$6,'RESUMO DE PONTOS'!$C$9:$H$58,3,) -> 0
B15: Riscos e Implicações | C15: =IFERROR(VLOOKUP(C$6,'RESUMO DE PONTOS'!$C$9:$H$58,4,),"") -> 0
B16: Impacto Financeiro | C16: =IFERROR(VLOOKUP(C$6,'RESUMO DE PONTOS'!$C$9:$H$58,5,),"") -> 0
B17: Recomendações | C17: =IFERROR(VLOOKUP(C$6,'RESUMO DE PONTOS'!$C$9:$H$58,6,),"") -> 0
B18: Comentários da Administração | C18: Resposta da Administração sobre o ponto identificado e sobre as ações de melhoria sugeridas e, eventualmente, esclarecimento das prioridades recomendadas.
B19: Ações a serem Implementadas pela Administração | C19: Ações definidas pela Administração para resolução do ponto identificado.
B20: Data Limite para Resolução do Ponto Identificado | C20: Prazo estipulado pela Administração para que o ponto identificado deixe de existir.

Sheet P19
B2: Pontos de Controle
B3: Item | C3: Descrição
B4: Impacto | C4: =IF(C12>=75,"ALTO IMPACTO",IF(C12<=50,"BAIXO IMPACTO","MÉDIO IMPACTO")) -> #N/A | E4: <<<<<< Automático conforme Metodologia e baseado no grau de exposição
B5: Status | C5: =IFERROR(VLOOKUP(C6,'RESUMO DE PONTOS'!$C$9:$M$58,10,),"") -> 0
B6: Código | C6: [P19] | E6: <<<<<< Lista Suspensa (Selecionar)
B7: Título | C7: =VLOOKUP(C6,'BASE DA MATRIZ DE RISCOS'!$C$78:$D$210,2,) -> #N/A
B8: Tipo | C8: =VLOOKUP(C6,'BASE DA MATRIZ DE RISCOS'!$C$78:$E$210,3,) -> #N/A | E8: <<<<<< Lista Suspensa (Selecionar)
B9: Tipo | C9: =VLOOKUP($C$8,'BASE DA MATRIZ DE RISCOS'!$C$30:$E$36,3) -> #N/A | E9: <<<<<< Automático - Valores de 1 a 5 conforme metodologia
B10: Probabilidade | C10: =VLOOKUP(C6,'BASE DA MATRIZ DE RISCOS'!$C$78:$H$210,5,) -> #N/A | E10: <<<<<< Valores de 1 a 5 conforme metodologia
B11: Impacto | C11: =VLOOKUP(C6,'BASE DA MATRIZ DE RISCOS'!$C$78:$H$210,6,) -> #N/A | E11: <<<<<< Valores de 1 a 5 conforme metodologia
B12: Exposição | C12: =C9*C10*C11 -> #N/A | E12: <<<<<< Calculado
B13: Testes/Áreas | C13: =VLOOKUP(C6,'BASE DA MATRIZ DE RISCOS'!$C$78:$J$210,8,) -> #N/A | E13: <<<<<< Automático - conforme Matriz de Risco
B14: Descrição | C14: =VLOOKUP(C$6,'RESUMO DE PONTOS'!$C$9:$H$58,3,) -> 0
B15: Riscos e Implicações | C15: =IFERROR(VLOOKUP(C$6,'RESUMO DE PONTOS'!$C$9:$H$58,4,),"") -> 0
B16: Impacto Financeiro | C16: =IFERROR(VLOOKUP(C$6,'RESUMO DE PONTOS'!$C$9:$H$58,5,),"") -> 0
B17: Recomendações | C17: =IFERROR(VLOOKUP(C$6,'RESUMO DE PONTOS'!$C$9:$H$58,6,),"") -> 0
B18: Comentários da Administração | C18: Resposta da Administração sobre o ponto identificado e sobre as ações de melhoria sugeridas e, eventualmente, esclarecimento das prioridades recomendadas.
B19: Ações a serem Implementadas pela Administração | C19: Ações definidas pela Administração para resolução do ponto identificado.
B20: Data Limite para Resolução do Ponto Identificado | C20: Prazo estipulado pela Administração para que o ponto identificado deixe de existir.

Sheet P20
B2: Pontos de Controle
B3: Item | C3: Descrição
B4: Impacto | C4: =IF(C12>=75,"ALTO IMPACTO",IF(C12<=50,"BAIXO IMPACTO","MÉDIO IMPACTO")) -> #N/A | E4: <<<<<< Automático conforme Metodologia e baseado no grau de exposição
B5: Status | C5: =IFERROR(VLOOKUP(C6,'RESUMO DE PONTOS'!$C$9:$M$58,10,),"") -> 0
B6: Código | C6: [P20] | E6: <<<<<< Lista Suspensa (Selecionar)
B7: Título | C7: =VLOOKUP(C6,'BASE DA MATRIZ DE RISCOS'!$C$78:$D$210,2,) -> #N/A
B8: Tipo | C8: =VLOOKUP(C6,'BASE DA MATRIZ DE RISCOS'!$C$78:$E$210,3,) -> #N/A | E8: <<<<<< Lista Suspensa (Selecionar)
B9: Tipo | C9: =VLOOKUP($C$8,'BASE DA MATRIZ DE RISCOS'!$C$30:$E$36,3) -> #N/A | E9: <<<<<< Automático - Valores de 1 a 5 conforme metodologia
B10: Probabilidade | C10: =VLOOKUP(C6,'BASE DA MATRIZ DE RISCOS'!$C$78:$H$210,5,) -> #N/A | E10: <<<<<< Valores de 1 a 5 conforme metodologia
B11: Impacto | C11: =VLOOKUP(C6,'BASE DA MATRIZ DE RISCOS'!$C$78:$H$210,6,) -> #N/A | E11: <<<<<< Valores de 1 a 5 conforme metodologia
B12: Exposição | C12: =C9*C10*C11 -> #N/A | E12: <<<<<< Calculado
B13: Testes/Áreas | C13: =VLOOKUP(C6,'BASE DA MATRIZ DE RISCOS'!$C$78:$J$210,8,) -> #N/A | E13: <<<<<< Automático - conforme Matriz de Risco
B14: Descrição | C14: =VLOOKUP(C$6,'RESUMO DE PONTOS'!$C$9:$H$58,3,) -> 0
B15: Riscos e Implicações | C15: =IFERROR(VLOOKUP(C$6,'RESUMO DE PONTOS'!$C$9:$H$58,4,),"") -> 0
B16: Impacto Financeiro | C16: =IFERROR(VLOOKUP(C$6,'RESUMO DE PONTOS'!$C$9:$H$58,5,),"") -> 0
B17: Recomendações | C17: =IFERROR(VLOOKUP(C$6,'RESUMO DE PONTOS'!$C$9:$H$58,6,),"") -> 0
B18: Comentários da Administração | C18: Resposta da Administração sobre o ponto identificado e sobre as ações de melhoria sugeridas e, eventualmente, esclarecimento das prioridades recomendadas.
B19: Ações a serem Implementadas pela Administração | C19: Ações definidas pela Administração para resolução do ponto identificado.
B20: Data Limite para Resolução do Ponto Identificado | C20: Prazo estipulado pela Administração para que o ponto identificado deixe de existir.

Sheet P21
B2: Pontos de Controle
B3: Item | C3: Descrição
B4: Impacto | C4: =IF(C12>=75,"ALTO IMPACTO",IF(C12<=50,"BAIXO IMPACTO","MÉDIO IMPACTO")) -> #N/A | E4: <<<<<< Automático conforme Metodologia e baseado no grau de exposição
B5: Status | C5: =IFERROR(VLOOKUP(C6,'RESUMO DE PONTOS'!$C$9:$M$58,10,),"") -> 0
B6: Código | C6: [P21] | E6: <<<<<< Lista Suspensa (Selecionar)
B7: Título | C7: =VLOOKUP(C6,'BASE DA MATRIZ DE RISCOS'!$C$78:$D$210,2,) -> #N/A
B8: Tipo | C8: =VLOOKUP(C6,'BASE DA MATRIZ DE RISCOS'!$C$78:$E$210,3,) -> #N/A | E8: <<<<<< Lista Suspensa (Selecionar)
B9: Tipo | C9: =VLOOKUP($C$8,'BASE DA MATRIZ DE RISCOS'!$C$30:$E$35,3) -> #N/A | E9: <<<<<< Automático - Valores de 1 a 5 conforme metodologia
B10: Probabilidade | C10: =VLOOKUP(C6,'BASE DA MATRIZ DE RISCOS'!$C$78:$H$210,5,) -> #N/A | E10: <<<<<< Valores de 1 a 5 conforme metodologia
B11: Impacto | C11: =VLOOKUP(C6,'BASE DA MATRIZ DE RISCOS'!$C$78:$H$210,6,) -> #N/A | E11: <<<<<< Valores de 1 a 5 conforme metodologia
B12: Exposição | C12: =C9*C10*C11 -> #N/A | E12: <<<<<< Calculado
B13: Testes/Áreas | C13: =VLOOKUP(C6,'BASE DA MATRIZ DE RISCOS'!$C$78:$J$210,8,) -> #N/A | E13: <<<<<< Automático - conforme Matriz de Risco
B14: Descrição | C14: =VLOOKUP(C$6,'RESUMO DE PONTOS'!$C$9:$H$58,3,) -> 0
B15: Riscos e Implicações | C15: =IFERROR(VLOOKUP(C$6,'RESUMO DE PONTOS'!$C$9:$H$58,4,),"") -> 0
B16: Impacto Financeiro | C16: =IFERROR(VLOOKUP(C$6,'RESUMO DE PONTOS'!$C$9:$H$58,5,),"") -> 0
B17: Recomendações | C17: =IFERROR(VLOOKUP(C$6,'RESUMO DE PONTOS'!$C$9:$H$58,6,),"") -> 0
B18: Comentários da Administração | C18: Resposta da Administração sobre o ponto identificado e sobre as ações de melhoria sugeridas e, eventualmente, esclarecimento das prioridades recomendadas.
B19: Ações a serem Implementadas pela Administração | C19: Ações definidas pela Administração para resolução do ponto identificado.
B20: Data Limite para Resolução do Ponto Identificado | C20: Prazo estipulado pela Administração para que o ponto identificado deixe de existir.

Sheet P22
B2: Pontos de Controle
B3: Item | C3: Descrição
B4: Impacto | C4: =IF(C12>=75,"ALTO IMPACTO",IF(C12<=50,"BAIXO IMPACTO","MÉDIO IMPACTO")) -> #N/A | E4: <<<<<< Automático conforme Metodologia e baseado no grau de exposição
B5: Status | C5: =IFERROR(VLOOKUP(C6,'RESUMO DE PONTOS'!$C$9:$M$58,10,),"") -> 0
B6: Código | C6: [P22] | E6: <<<<<< Lista Suspensa (Selecionar)
B7: Título | C7: =VLOOKUP(C6,'BASE DA MATRIZ DE RISCOS'!$C$78:$D$210,2,) -> #N/A
B8: Tipo | C8: =VLOOKUP(C6,'BASE DA MATRIZ DE RISCOS'!$C$78:$E$210,3,) -> #N/A | E8: <<<<<< Lista Suspensa (Selecionar)
B9: Tipo | C9: =VLOOKUP($C$8,'BASE DA MATRIZ DE RISCOS'!$C$30:$E$35,3) -> #N/A | E9: <<<<<< Automático - Valores de 1 a 5 conforme metodologia
B10: Probabilidade | C10: =VLOOKUP(C6,'BASE DA MATRIZ DE RISCOS'!$C$78:$H$210,5,) -> #N/A | E10: <<<<<< Valores de 1 a 5 conforme metodologia
B11: Impacto | C11: =VLOOKUP(C6,'BASE DA MATRIZ DE RISCOS'!$C$78:$H$210,6,) -> #N/A | E11: <<<<<< Valores de 1 a 5 conforme metodologia
B12: Exposição | C12: =C9*C10*C11 -> #N/A | E12: <<<<<< Calculado
B13: Testes/Áreas | C13: =VLOOKUP(C6,'BASE DA MATRIZ DE RISCOS'!$C$78:$J$210,8,) -> #N/A | E13: <<<<<< Automático - conforme Matriz de Risco
B14: Descrição | C14: =VLOOKUP(C$6,'RESUMO DE PONTOS'!$C$9:$H$58,3,) -> 0
B15: Riscos e Implicações | C15: =IFERROR(VLOOKUP(C$6,'RESUMO DE PONTOS'!$C$9:$H$58,4,),"") -> 0
B16: Impacto Financeiro | C16: =IFERROR(VLOOKUP(C$6,'RESUMO DE PONTOS'!$C$9:$H$58,5,),"") -> 0
B17: Recomendações | C17: =IFERROR(VLOOKUP(C$6,'RESUMO DE PONTOS'!$C$9:$H$58,6,),"") -> 0
B18: Comentários da Administração | C18: Resposta da Administração sobre o ponto identificado e sobre as ações de melhoria sugeridas e, eventualmente, esclarecimento das prioridades recomendadas.
B19: Ações a serem Implementadas pela Administração | C19: Ações definidas pela Administração para resolução do ponto identificado.
B20: Data Limite para Resolução do Ponto Identificado | C20: Prazo estipulado pela Administração para que o ponto identificado deixe de existir.

Sheet P23
B2: Pontos de Controle
B3: Item | C3: Descrição
B4: Impacto | C4: =IF(C12>=75,"ALTO IMPACTO",IF(C12<=50,"BAIXO IMPACTO","MÉDIO IMPACTO")) -> #N/A | E4: <<<<<< Automático conforme Metodologia e baseado no grau de exposição
B5: Status | C5: =IFERROR(VLOOKUP(C6,'RESUMO DE PONTOS'!$C$9:$M$58,10,),"") -> 0
B6: Código | C6: [P23] | E6: <<<<<< Lista Suspensa (Selecionar)
B7: Título | C7: =VLOOKUP(C6,'BASE DA MATRIZ DE RISCOS'!$C$78:$D$210,2,) -> #N/A
B8: Tipo | C8: =VLOOKUP(C6,'BASE DA MATRIZ DE RISCOS'!$C$78:$E$210,3,) -> #N/A | E8: <<<<<< Lista Suspensa (Selecionar)
B9: Tipo | C9: =VLOOKUP($C$8,'BASE DA MATRIZ DE RISCOS'!$C$30:$E$36,3) -> #N/A | E9: <<<<<< Automático - Valores de 1 a 5 conforme metodologia
B10: Probabilidade | C10: =VLOOKUP(C6,'BASE DA MATRIZ DE RISCOS'!$C$78:$H$210,5,) -> #N/A | E10: <<<<<< Valores de 1 a 5 conforme metodologia
B11: Impacto | C11: =VLOOKUP(C6,'BASE DA MATRIZ DE RISCOS'!$C$78:$H$210,6,) -> #N/A | E11: <<<<<< Valores de 1 a 5 conforme metodologia
B12: Exposição | C12: =C9*C10*C11 -> #N/A | E12: <<<<<< Calculado
B13: Testes/Áreas | C13: =VLOOKUP(C6,'BASE DA MATRIZ DE RISCOS'!$C$78:$J$210,8,) -> #N/A | E13: <<<<<< Automático - conforme Matriz de Risco
B14: Descrição | C14: =VLOOKUP(C$6,'RESUMO DE PONTOS'!$C$9:$H$58,3,) -> 0
B15: Riscos e Implicações | C15: =IFERROR(VLOOKUP(C$6,'RESUMO DE PONTOS'!$C$9:$H$58,4,),"") -> 0
B16: Impacto Financeiro | C16: =IFERROR(VLOOKUP(C$6,'RESUMO DE PONTOS'!$C$9:$H$58,5,),"") -> 0
B17: Recomendações | C17: =IFERROR(VLOOKUP(C$6,'RESUMO DE PONTOS'!$C$9:$H$58,6,),"") -> 0
B18: Comentários da Administração | C18: Resposta da Administração sobre o ponto identificado e sobre as ações de melhoria sugeridas e, eventualmente, esclarecimento das prioridades recomendadas.
B19: Ações a serem Implementadas pela Administração | C19: Ações definidas pela Administração para resolução do ponto identificado.
B20: Data Limite para Resolução do Ponto Identificado | C20: Prazo estipulado pela Administração para que o ponto identificado deixe de existir.

Sheet P24
B2: Pontos de Controle
B3: Item | C3: Descrição
B4: Impacto | C4: =IF(C12>=75,"ALTO IMPACTO",IF(C12<=50,"BAIXO IMPACTO","MÉDIO IMPACTO")) -> #N/A | E4: <<<<<< Automático conforme Metodologia e baseado no grau de exposição
B5: Status | C5: =IFERROR(VLOOKUP(C6,'RESUMO DE PONTOS'!$C$9:$M$47,10,),"") -> 0
B6: Código | C6: [P24] | E6: <<<<<< Lista Suspensa (Selecionar)
B7: Título | C7: =VLOOKUP(C6,'BASE DA MATRIZ DE RISCOS'!$C$78:$D$109,2,) -> #N/A
B8: Tipo | C8: =VLOOKUP(C6,'BASE DA MATRIZ DE RISCOS'!$C$78:$E$109,3,) -> #N/A | E8: <<<<<< Lista Suspensa (Selecionar)
B9: Tipo | C9: =VLOOKUP($C$8,'BASE DA MATRIZ DE RISCOS'!$C$30:$E$36,3) -> #N/A | E9: <<<<<< Automático - Valores de 1 a 5 conforme metodologia
B10: Probabilidade | C10: =VLOOKUP(C6,'BASE DA MATRIZ DE RISCOS'!$C$78:$H$109,5,) -> #N/A | E10: <<<<<< Valores de 1 a 5 conforme metodologia
B11: Impacto | C11: =VLOOKUP(C6,'BASE DA MATRIZ DE RISCOS'!$C$78:$H$109,6,) -> #N/A | E11: <<<<<< Valores de 1 a 5 conforme metodologia
B12: Exposição | C12: =C9*C10*C11 -> #N/A | E12: <<<<<< Calculado
B13: Testes/Áreas | C13: =VLOOKUP(C6,'BASE DA MATRIZ DE RISCOS'!$C$78:$J$109,8,) -> #N/A | E13: <<<<<< Automático - conforme Matriz de Risco
B14: Descrição | C14: =VLOOKUP(C$6,'RESUMO DE PONTOS'!$C$9:$H$47,3,) -> 0
B15: Riscos e Implicações | C15: =IFERROR(VLOOKUP(C$6,'RESUMO DE PONTOS'!$C$9:$H$47,4,),"") -> 0
B16: Impacto Financeiro | C16: =IFERROR(VLOOKUP(C$6,'RESUMO DE PONTOS'!$C$9:$H$47,5,),"") -> 0
B17: Recomendações | C17: =IFERROR(VLOOKUP(C$6,'RESUMO DE PONTOS'!$C$9:$H$47,6,),"") -> 0
B18: Comentários da Administração | C18: Resposta da Administração sobre o ponto identificado e sobre as ações de melhoria sugeridas e, eventualmente, esclarecimento das prioridades recomendadas.
B19: Ações a serem Implementadas pela Administração | C19: Ações definidas pela Administração para resolução do ponto identificado.
B20: Data Limite para Resolução do Ponto Identificado | C20: Prazo estipulado pela Administração para que o ponto identificado deixe de existir.

Sheet P25
B2: Pontos de Controle
B3: Item | C3: Descrição
B4: Impacto | C4: =IF(C12>=75,"ALTO IMPACTO",IF(C12<=50,"BAIXO IMPACTO","MÉDIO IMPACTO")) -> #N/A | E4: <<<<<< Automático conforme Metodologia e baseado no grau de exposição
B5: Status | C5: =IFERROR(VLOOKUP(C6,'RESUMO DE PONTOS'!$C$9:$M$47,10,),"") -> 0
B6: Código | C6: [P25] | E6: <<<<<< Lista Suspensa (Selecionar)
B7: Título | C7: =VLOOKUP(C6,'BASE DA MATRIZ DE RISCOS'!$C$78:$D$109,2,) -> #N/A
B8: Tipo | C8: Legal | E8: <<<<<< Lista Suspensa (Selecionar)
B9: Tipo | C9: =VLOOKUP($C$8,'BASE DA MATRIZ DE RISCOS'!$C$30:$E$36,3) -> 3 | E9: <<<<<< Automático - Valores de 1 a 5 conforme metodologia
B10: Probabilidade | C10: =VLOOKUP(C6,'BASE DA MATRIZ DE RISCOS'!$C$78:$H$109,5,) -> #N/A | E10: <<<<<< Valores de 1 a 5 conforme metodologia
B11: Impacto | C11: =VLOOKUP(C6,'BASE DA MATRIZ DE RISCOS'!$C$78:$H$109,6,) -> #N/A | E11: <<<<<< Valores de 1 a 5 conforme metodologia
B12: Exposição | C12: =C9*C10*C11 -> #N/A | E12: <<<<<< Calculado
B13: Testes/Áreas | C13: =VLOOKUP(C6,'BASE DA MATRIZ DE RISCOS'!$C$78:$J$109,8,) -> #N/A | E13: <<<<<< Automático - conforme Matriz de Risco
B14: Descrição | C14: =VLOOKUP(C$6,'RESUMO DE PONTOS'!$C$9:$H$47,3,) -> 0
B15: Riscos e Implicações | C15: =IFERROR(VLOOKUP(C$6,'RESUMO DE PONTOS'!$C$9:$H$47,4,),"") -> 0
B16: Impacto Financeiro | C16: =IFERROR(VLOOKUP(C$6,'RESUMO DE PONTOS'!$C$9:$H$47,5,),"") -> 0
B17: Recomendações | C17: =IFERROR(VLOOKUP(C$6,'RESUMO DE PONTOS'!$C$9:$H$47,6,),"") -> 0
B18: Comentários da Administração | C18: Resposta da Administração sobre o ponto identificado e sobre as ações de melhoria sugeridas e, eventualmente, esclarecimento das prioridades recomendadas.
B19: Ações a serem Implementadas pela Administração | C19: Ações definidas pela Administração para resolução do ponto identificado.
B20: Data Limite para Resolução do Ponto Identificado | C20: Prazo estipulado pela Administração para que o ponto identificado deixe de existir.

Sheet P26
B2: Pontos de Controle
B3: Item | C3: Descrição
B4: Impacto | C4: =IF(C12>=75,"ALTO IMPACTO",IF(C12<=50,"BAIXO IMPACTO","MÉDIO IMPACTO")) -> #N/A | E4: <<<<<< Automático conforme Metodologia e baseado no grau de exposição
B5: Status | C5: =IFERROR(VLOOKUP(C6,'RESUMO DE PONTOS'!$C$9:$M$47,10,),"") -> 0
B6: Código | C6: [P26] | E6: <<<<<< Lista Suspensa (Selecionar)
B7: Título | C7: =VLOOKUP(C6,'BASE DA MATRIZ DE RISCOS'!$C$78:$D$109,2,) -> #N/A
B8: Tipo | C8: =VLOOKUP(C6,'BASE DA MATRIZ DE RISCOS'!$C$78:$E$109,3,) -> #N/A | E8: <<<<<< Lista Suspensa (Selecionar)
B9: Tipo | C9: =VLOOKUP($C$8,'BASE DA MATRIZ DE RISCOS'!$C$30:$E$36,3) -> #N/A | E9: <<<<<< Automático - Valores de 1 a 5 conforme metodologia
B10: Probabilidade | C10: =VLOOKUP(C6,'BASE DA MATRIZ DE RISCOS'!$C$78:$H$109,5,) -> #N/A | E10: <<<<<< Valores de 1 a 5 conforme metodologia
B11: Impacto | C11: =VLOOKUP(C6,'BASE DA MATRIZ DE RISCOS'!$C$78:$H$109,6,) -> #N/A | E11: <<<<<< Valores de 1 a 5 conforme metodologia
B12: Exposição | C12: =C9*C10*C11 -> #N/A | E12: <<<<<< Calculado
B13: Testes/Áreas | C13: =VLOOKUP(C6,'BASE DA MATRIZ DE RISCOS'!$C$78:$J$109,8,) -> #N/A | E13: <<<<<< Automático - conforme Matriz de Risco
B14: Descrição | C14: =VLOOKUP(C$6,'RESUMO DE PONTOS'!$C$9:$H$47,3,) -> 0
B15: Riscos e Implicações | C15: =IFERROR(VLOOKUP(C$6,'RESUMO DE PONTOS'!$C$9:$H$47,4,),"") -> 0
B16: Impacto Financeiro | C16: =IFERROR(VLOOKUP(C$6,'RESUMO DE PONTOS'!$C$9:$H$47,5,),"") -> 0
B17: Recomendações | C17: =IFERROR(VLOOKUP(C$6,'RESUMO DE PONTOS'!$C$9:$H$47,6,),"") -> 0
B18: Comentários da Administração | C18: Resposta da Administração sobre o ponto identificado e sobre as ações de melhoria sugeridas e, eventualmente, esclarecimento das prioridades recomendadas.
B19: Ações a serem Implementadas pela Administração | C19: Ações definidas pela Administração para resolução do ponto identificado.
B20: Data Limite para Resolução do Ponto Identificado | C20: Prazo estipulado pela Administração para que o ponto identificado deixe de existir.

Sheet P27
B2: Pontos de Controle
B3: Item | C3: Descrição
B4: Impacto | C4: =IF(C12>=75,"ALTO IMPACTO",IF(C12<=50,"BAIXO IMPACTO","MÉDIO IMPACTO")) -> #N/A | E4: <<<<<< Automático conforme Metodologia e baseado no grau de exposição
B5: Status | C5: =IFERROR(VLOOKUP(C6,'RESUMO DE PONTOS'!$C$9:$M$47,10,),"") -> 0
B6: Código | C6: [P27] | E6: <<<<<< Lista Suspensa (Selecionar)
B7: Título | C7: =VLOOKUP(C6,'BASE DA MATRIZ DE RISCOS'!$C$78:$D$109,2,) -> #N/A
B8: Tipo | C8: Legal | E8: <<<<<< Lista Suspensa (Selecionar)
B9: Tipo | C9: =VLOOKUP($C$8,'BASE DA MATRIZ DE RISCOS'!$C$30:$E$36,3) -> 3 | E9: <<<<<< Automático - Valores de 1 a 5 conforme metodologia
B10: Probabilidade | C10: =VLOOKUP(C6,'BASE DA MATRIZ DE RISCOS'!$C$78:$H$109,5,) -> #N/A | E10: <<<<<< Valores de 1 a 5 conforme metodologia
B11: Impacto | C11: =VLOOKUP(C6,'BASE DA MATRIZ DE RISCOS'!$C$78:$H$109,6,) -> #N/A | E11: <<<<<< Valores de 1 a 5 conforme metodologia
B12: Exposição | C12: =C9*C10*C11 -> #N/A | E12: <<<<<< Calculado
B13: Testes/Áreas | C13: =VLOOKUP(C6,'BASE DA MATRIZ DE RISCOS'!$C$78:$J$109,8,) -> #N/A | E13: <<<<<< Automático - conforme Matriz de Risco
B14: Descrição | C14: =VLOOKUP(C$6,'RESUMO DE PONTOS'!$C$9:$H$47,3,) -> 0
B15: Riscos e Implicações | C15: =IFERROR(VLOOKUP(C$6,'RESUMO DE PONTOS'!$C$9:$H$47,4,),"") -> 0
B16: Impacto Financeiro | C16: =IFERROR(VLOOKUP(C$6,'RESUMO DE PONTOS'!$C$9:$H$47,5,),"") -> 0
B17: Recomendações | C17: =IFERROR(VLOOKUP(C$6,'RESUMO DE PONTOS'!$C$9:$H$47,6,),"") -> 0
B18: Comentários da Administração | C18: Resposta da Administração sobre o ponto identificado e sobre as ações de melhoria sugeridas e, eventualmente, esclarecimento das prioridades recomendadas.
B19: Ações a serem Implementadas pela Administração | C19: Ações definidas pela Administração para resolução do ponto identificado.
B20: Data Limite para Resolução do Ponto Identificado | C20: Prazo estipulado pela Administração para que o ponto identificado deixe de existir.

Sheet P28
B2: Pontos de Controle
B3: Item | C3: Descrição
B4: Impacto | C4: =IF(C12>=75,"ALTO IMPACTO",IF(C12<=50,"BAIXO IMPACTO","MÉDIO IMPACTO")) -> #N/A | E4: <<<<<< Automático conforme Metodologia e baseado no grau de exposição
B5: Status | C5: =IFERROR(VLOOKUP(C6,'RESUMO DE PONTOS'!$C$9:$M$47,10,),"") -> 0
B6: Código | C6: [P28] | E6: <<<<<< Lista Suspensa (Selecionar)
B7: Título | C7: =VLOOKUP(C6,'BASE DA MATRIZ DE RISCOS'!$C$78:$D$109,2,) -> #N/A
B8: Tipo | C8: =VLOOKUP(C6,'BASE DA MATRIZ DE RISCOS'!$C$78:$E$109,3,) -> #N/A | E8: <<<<<< Lista Suspensa (Selecionar)
B9: Tipo | C9: =VLOOKUP($C$8,'BASE DA MATRIZ DE RISCOS'!$C$30:$E$36,3) -> #N/A | E9: <<<<<< Automático - Valores de 1 a 5 conforme metodologia
B10: Probabilidade | C10: =VLOOKUP(C6,'BASE DA MATRIZ DE RISCOS'!$C$78:$H$109,5,) -> #N/A | E10: <<<<<< Valores de 1 a 5 conforme metodologia
B11: Impacto | C11: =VLOOKUP(C6,'BASE DA MATRIZ DE RISCOS'!$C$78:$H$109,6,) -> #N/A | E11: <<<<<< Valores de 1 a 5 conforme metodologia
B12: Exposição | C12: =C9*C10*C11 -> #N/A | E12: <<<<<< Calculado
B13: Testes/Áreas | C13: =VLOOKUP(C6,'BASE DA MATRIZ DE RISCOS'!$C$78:$J$109,8,) -> #N/A | E13: <<<<<< Automático - conforme Matriz de Risco
B14: Descrição | C14: =VLOOKUP(C$6,'RESUMO DE PONTOS'!$C$9:$H$47,3,) -> 0
B15: Riscos e Implicações | C15: =IFERROR(VLOOKUP(C$6,'RESUMO DE PONTOS'!$C$9:$H$47,4,),"") -> 0
B16: Impacto Financeiro | C16: =IFERROR(VLOOKUP(C$6,'RESUMO DE PONTOS'!$C$9:$H$47,5,),"") -> 0
B17: Recomendações | C17: =IFERROR(VLOOKUP(C$6,'RESUMO DE PONTOS'!$C$9:$H$47,6,),"") -> 0
B18: Comentários da Administração | C18: Resposta da Administração sobre o ponto identificado e sobre as ações de melhoria sugeridas e, eventualmente, esclarecimento das prioridades recomendadas.
B19: Ações a serem Implementadas pela Administração | C19: Ações definidas pela Administração para resolução do ponto identificado.
B20: Data Limite para Resolução do Ponto Identificado | C20: Prazo estipulado pela Administração para que o ponto identificado deixe de existir.

Sheet P31
B2: Pontos de Controle
B3: Item | C3: Descrição
B4: Impacto | C4: =IF(C12>=75,"ALTO IMPACTO",IF(C12<=50,"BAIXO IMPACTO","MÉDIO IMPACTO")) -> #N/A | E4: <<<<<< Automático conforme Metodologia e baseado no grau de exposição
B5: Status | C5: =IFERROR(VLOOKUP(C6,'RESUMO DE PONTOS'!$C$9:$M$47,10,),"")
B6: Código | C6: [P31] | E6: <<<<<< Lista Suspensa (Selecionar)
B7: Título | C7: =VLOOKUP(C6,'BASE DA MATRIZ DE RISCOS'!$C$78:$D$109,2,) -> #N/A
B8: Tipo | C8: Financeiro | E8: <<<<<< Lista Suspensa (Selecionar)
B9: Tipo | C9: =VLOOKUP($C$8,'BASE DA MATRIZ DE RISCOS'!$C$30:$E$35,3) -> 5 | E9: <<<<<< Automático - Valores de 1 a 5 conforme metodologia
B10: Probabilidade | C10: =VLOOKUP(C6,'BASE DA MATRIZ DE RISCOS'!$C$78:$H$109,5,) -> #N/A | E10: <<<<<< Valores de 1 a 5 conforme metodologia
B11: Impacto | C11: =VLOOKUP(C6,'BASE DA MATRIZ DE RISCOS'!$C$78:$H$109,6,) -> #N/A | E11: <<<<<< Valores de 1 a 5 conforme metodologia
B12: Exposição | C12: =C9*C10*C11 -> #N/A | E12: <<<<<< Calculado
B13: Testes/Áreas | C13: =VLOOKUP(C6,'BASE DA MATRIZ DE RISCOS'!$C$78:$J$109,8,) -> #N/A | E13: <<<<<< Automático - conforme Matriz de Risco
B14: Descrição | C14: =VLOOKUP(C$6,'RESUMO DE PONTOS'!$C$9:$H$47,3,) -> #N/A
B15: Riscos e Implicações | C15: =IFERROR(VLOOKUP(C$6,'RESUMO DE PONTOS'!$C$9:$H$47,4,),"")
B16: Impacto Financeiro | C16: =IFERROR(VLOOKUP(C$6,'RESUMO DE PONTOS'!$C$9:$H$47,5,),"")
B17: Recomendações | C17: =IFERROR(VLOOKUP(C$6,'RESUMO DE PONTOS'!$C$9:$H$47,6,),"")
B18: Comentários da Administração | C18: Resposta da Administração sobre o ponto identificado e sobre as ações de melhoria sugeridas e, eventualmente, esclarecimento das prioridades recomendadas.
B19: Ações a serem Implementadas pela Administração | C19: Ações definidas pela Administração para resolução do ponto identificado.
B20: Data Limite para Resolução do Ponto Identificado | C20: Prazo estipulado pela Administração para que o ponto identificado deixe de existir.

Sheet P29
B2: Pontos de Controle
B3: Item | C3: Descrição
B4: Impacto | C4: =IF(C12>=75,"ALTO IMPACTO",IF(C12<=50,"BAIXO IMPACTO","MÉDIO IMPACTO")) -> #N/A | E4: <<<<<< Automático conforme Metodologia e baseado no grau de exposição
B5: Status | C5: =IFERROR(VLOOKUP(C6,'RESUMO DE PONTOS'!$C$9:$M$47,10,),"") -> 0
B6: Código | C6: [P29] | E6: <<<<<< Lista Suspensa (Selecionar)
B7: Título | C7: =VLOOKUP(C6,'BASE DA MATRIZ DE RISCOS'!$C$78:$D$109,2,) -> #N/A
B8: Tipo | C8: =VLOOKUP(C6,'BASE DA MATRIZ DE RISCOS'!$C$78:$E$109,3,) -> #N/A | E8: <<<<<< Lista Suspensa (Selecionar)
B9: Tipo | C9: =VLOOKUP($C$8,'BASE DA MATRIZ DE RISCOS'!$C$30:$E$36,3) -> #N/A | E9: <<<<<< Automático - Valores de 1 a 5 conforme metodologia
B10: Probabilidade | C10: =VLOOKUP(C6,'BASE DA MATRIZ DE RISCOS'!$C$78:$H$109,5,) -> #N/A | E10: <<<<<< Valores de 1 a 5 conforme metodologia
B11: Impacto | C11: =VLOOKUP(C6,'BASE DA MATRIZ DE RISCOS'!$C$78:$H$109,6,) -> #N/A | E11: <<<<<< Valores de 1 a 5 conforme metodologia
B12: Exposição | C12: =C9*C10*C11 -> #N/A | E12: <<<<<< Calculado
B13: Testes/Áreas | C13: =VLOOKUP(C6,'BASE DA MATRIZ DE RISCOS'!$C$78:$J$109,8,) -> #N/A | E13: <<<<<< Automático - conforme Matriz de Risco
B14: Descrição | C14: =VLOOKUP(C$6,'RESUMO DE PONTOS'!$C$9:$H$47,3,) -> 0
B15: Riscos e Implicações | C15: =IFERROR(VLOOKUP(C$6,'RESUMO DE PONTOS'!$C$9:$H$47,4,),"") -> 0
B16: Impacto Financeiro | C16: =IFERROR(VLOOKUP(C$6,'RESUMO DE PONTOS'!$C$9:$H$47,5,),"") -> 0
B17: Recomendações | C17: =IFERROR(VLOOKUP(C$6,'RESUMO DE PONTOS'!$C$9:$H$47,6,),"") -> 0
B18: Comentários da Administração | C18: Resposta da Administração sobre o ponto identificado e sobre as ações de melhoria sugeridas e, eventualmente, esclarecimento das prioridades recomendadas.
B19: Ações a serem Implementadas pela Administração | C19: Ações definidas pela Administração para resolução do ponto identificado.
B20: Data Limite para Resolução do Ponto Identificado | C20: Prazo estipulado pela Administração para que o ponto identificado deixe de existir.

Sheet P30
B2: Pontos de Controle
B3: Item | C3: Descrição
B4: Impacto | C4: =IF(C12>=75,"ALTO IMPACTO",IF(C12<=50,"BAIXO IMPACTO","MÉDIO IMPACTO")) -> #N/A | E4: <<<<<< Automático conforme Metodologia e baseado no grau de exposição
B5: Status | C5: =IFERROR(VLOOKUP(C6,'RESUMO DE PONTOS'!$C$9:$M$47,10,),"") -> 0
B6: Código | C6: [P30] | E6: <<<<<< Lista Suspensa (Selecionar)
B7: Título | C7: =VLOOKUP(C6,'BASE DA MATRIZ DE RISCOS'!$C$78:$D$109,2,) -> #N/A
B8: Tipo | C8: =VLOOKUP(C6,'BASE DA MATRIZ DE RISCOS'!$C$78:$E$109,3,) -> #N/A | E8: <<<<<< Lista Suspensa (Selecionar)
B9: Tipo | C9: =VLOOKUP($C$8,'BASE DA MATRIZ DE RISCOS'!$C$30:$E$36,3) -> #N/A | E9: <<<<<< Automático - Valores de 1 a 5 conforme metodologia
B10: Probabilidade | C10: =VLOOKUP(C6,'BASE DA MATRIZ DE RISCOS'!$C$78:$H$109,5,) -> #N/A | E10: <<<<<< Valores de 1 a 5 conforme metodologia
B11: Impacto | C11: =VLOOKUP(C6,'BASE DA MATRIZ DE RISCOS'!$C$78:$H$109,6,) -> #N/A | E11: <<<<<< Valores de 1 a 5 conforme metodologia
B12: Exposição | C12: =C9*C10*C11 -> #N/A | E12: <<<<<< Calculado
B13: Testes/Áreas | C13: =VLOOKUP(C6,'BASE DA MATRIZ DE RISCOS'!$C$78:$J$109,8,) -> #N/A | E13: <<<<<< Automático - conforme Matriz de Risco
B14: Descrição | C14: =VLOOKUP(C$6,'RESUMO DE PONTOS'!$C$9:$H$47,3,) -> 0
B15: Riscos e Implicações | C15: =IFERROR(VLOOKUP(C$6,'RESUMO DE PONTOS'!$C$9:$H$47,4,),"") -> 0
B16: Impacto Financeiro | C16: =IFERROR(VLOOKUP(C$6,'RESUMO DE PONTOS'!$C$9:$H$47,5,),"") -> 0
B17: Recomendações | C17: =IFERROR(VLOOKUP(C$6,'RESUMO DE PONTOS'!$C$9:$H$47,6,),"") -> 0
B18: Comentários da Administração | C18: Resposta da Administração sobre o ponto identificado e sobre as ações de melhoria sugeridas e, eventualmente, esclarecimento das prioridades recomendadas.
B19: Ações a serem Implementadas pela Administração | C19: Ações definidas pela Administração para resolução do ponto identificado.
B20: Data Limite para Resolução do Ponto Identificado | C20: Prazo estipulado pela Administração para que o ponto identificado deixe de existir.

Sheet MATRIZ

Sheet ASSERTIVAS ATIVO
A3: Área | B3: Assertivas Testadas | C3: Objetivos de Auditoria | D3: Exemplos de Testes Substantivos de Auditoria para Alcançar os Ojbetivos de Auditoria
A4: Caixa e Bancos | B4: Existência D&O Integridade | C4: 1. Os saldos de Caixa representam todos e somente itens de caixa, em mãos, em trânsito ou em instituições financeiras e estão corretamente registrados | D4: *Confirmação de saldos bancários *Testes de reconciliação *Revisão de Transferências interbancos e intrabancos *Procedimentos Analíticos
A5: Caixa e Bancos | B5: Apresentação e Divulgação | C5: 2. Os saldos em Caixa estão corretamente descritos e classificados, e as devidas divulgações quanto a fundos restritos ou comprometidos e os saldos não sujeitos a saque imediato estão feitas (exemplo: depósitos a prazo e depósitos em países estrangeiros sujeitos a controle cambial etc.) | D5: *Revisão das Demonstrações Financeiras e comparação das divulgações feitas com os requisitos dos princípios de contabilidade *Pesquisa de restrições sobre disponibilidade *Confirmação de restrições sobre valores de Caixa e Bancos
A6: Contas a Receber | B6: Existência D&O | C6: 1. O Contas a Receber representam direitos válidos da companhia e foram corretamente registradas | D6: *Confirmação de saldos bancários *Testes de reconciliação *Revisão de Transferências interbancos e intrabancos *Procedimentos Analíticos
A7: Contas a Receber | B7: Integridade | C7: 2. As Contas a Receber incluem todos os valores devidos à Companhia na data do balanço | D7: *Procedimentos analíticos *Circularização de contas a receber ou procedimentos alternativos
A8: Contas a Receber | B8: Valorização | C8: 3. As provições para PCLD, devoluções, abatimentos e descontos são adequadas, mas não excessivas | D8: *Testes de corte de vendas e outras receitas e recebimentos de caixa (recebimento subsequente). *Procedimentos analíticos *Avaliação de provisões de valorização
A9: Contas a Receber | B9: Apresentação e Divulgação | C9: 4. As Contas a Receber estão corretamente descritas e classificadas, e as devidas divulgações relativas a esses valores (incluindo divulgação de valores que tenham sido caucionados, descontados, cedidos, ou vendidos com direito de regresso, ou então, em poder de partes relacionadas), foram feitas. | D9: *Revisão das Demonstrações Financeiras e comparação das divulgações feitas com os requisitos dos princípios de contabilidade *Confirmação dos principais termos de venda e outros acordos.
A10: Estoques | B10: Existência D&O Integridade | C10: 1. Os saldos de Estoque representam todos e somente itens que existem fisicamente e são mantidos para venda dentro do ciclo normal de operações e estão corretamente registrados | D10: *Observação de contagens físicas dos estoques. *Confirmação de estoque em poder de terceiros. *Procedimentos analíticos.
A11: Estoques | B11: Integridade | C11: 2. A listagem do inventário incluem todos os itens de estoque que são de propriedade da entidade,estão corretamente compilados, e os totais estão corretamente incluídos nas contas de estoque. | D11: *Confronto de contagem física de estoque com as listagens de inventário. *Testes de somas e cálculos das listagens de inventário. *Anotações de corte de inventário,feitas durante as contagens físicas de estoque, são confrontadas com os registros contábeis para determinar o devido corte. *Controle de todas as etiquetas de inventário e as folhas de contagem usadas no inventário físico.
A12: Estoques | B12: Valorização | C12: 3. O inventário final foi determinado, no que se refere a quantidades, preços, cálculos, materiais em excesso etc., em uma base consistente. | D12: * Revisão dos métodos usados para determinar o inventário final, no que se refere à consistência de aplicação
A13: Estoques | B13: Valorização | C13: 4. O estoque está demonstrado ao valor de custo ou mercado, dos dois o menor, e itens excessivos, obsoletos e de movimentação morosa foram reduzidos aos valores líquidos realizáveis, em bases consistentes. | D13: *Testes de custos registrados e comparação com os valores de mercado. *Procedimentos analíticos
A14: Estoques | B14: Apresentação e Divulgação | C14: 5. O estoque está corretamente descrito e classificado, e as devidas divulgações(incluindo divulgação de valores que tenham sido caucionados e compromissos de compra) relativas a esses valores foram feitas. | D14: *Revisão das Demonstrações Financeiras e comparação das divulgações feitas com os requisitos dos princípios de contabilidade *Confirmação de estoques caucionados e compromissos de compra (cláusulas contratuais) *Pesquisa de estoques caucionados e compromissos de compra *Revisão de contratos de empréstimo
... A29: Investimentos e Outros Ativos | B29: Apresentação e Divulgação | C29: 6. Os investimentos e outros ativos estão corretamente descritos e classificados, e as devidas divulgações (incluindo valores caucionados) relativas a esses valores foram feitas. | D29: *Revisão das Demonstrações Financeiras e comparação das divulgações feitas com os requisitos dos princípios de contabilidade

Sheet ASSERTIVAS PASSIVO
A3: Área | B3: Assertivas Testadas | C3: Objetivos de Auditoria | D3: Exemplos de Testes Substantivos de Auditoria para Alcançar os Ojbetivos de Auditoria
A4: Contas a Pagar | B4: Existência D&O | C4: 1. As contas a pagar representam passivos relacionados à aquisição de materiais e serviços, são obrigações válidas da entidade e foram corretamente registradas. | D4: *Circularização de fornecedores *Análise de contas
A5: Contas a Pagar | B5: Integridade | C5: 2. As contas a pagar incluem todas as importências a pagar correntemente pela entidade pela aquisição de materiais e serviços, na data do balanço. | D5: *Circularização de fornecedores *Análise de contas *Testes de corte (Cut-Off) de compras *Testes de desembolsos subsequente
A6: Contas a Pagar | B6: Apresentação e Divulgação | C6: 3. As contas a pagar estão corretamente descritas e classificadas, e as devidas divulgações relativas a esses valores foram feitas. | D6: *Revisão das Demonstrações Financeiras e comparação das divulgações feitas com os requisitos dos princípios de contabilidade
A7: Passivos Acumulados | B7: Existência D&O | C7: 1. Os passivos acumulados representam obrigações por recursos e serviços adquiridos até a data do balanço, e foram corretamente registrados. | D7: *Procedimentos analíticos *Análise se contas
A8: Passivos Acumulados | B8: Integridade Valorização | C8: 2. Os passivos acumulados incluem todas as importâncias devidas pela entidade, por recursos e serviços adquiridos na data do balanço. | D8: *Procedimentos analíticos *Análise se contas *Recálculos e testes de exatidão aritmética *Testes de desembolsos subsequentes.
A9: Passivos Acumulados | B9: Apresentação e Divulgação | C9: 3. Os passivos acumulados estão corretamente descritas e classificadas, e as devidas divulgações relativas a esses valores foram feitas. | D9: *Revisão das Demonstrações Financeiras e comparação das divulgações feitas com os requisitos dos princípios de contabilidade
A10: Empréstimos e Outras Dívidas | B10: Existência D&O | C10: 1. Os empréstimos e outras dívidas representam passivos válidos da entidade e foram corretamente registrados. | D10: *Confirmação de importências devidas * Análise de Contas
A11: Empréstimos e Outras Dívidas | B11: Integridade | C11: 2. Todas as importências devidas por empréstimos e outras dívidas estão incluídas nas contas , na data do balanço. | D11: *Confirmação de importências devidas * Análise de Contas
A12: Empréstimos e Outras Dívidas | B12: Existência e Integridade | C12: 3. Todas as cláusulas contratuais e obrigações "extrabalanço" foram identificadas e consideradas (por exemplo: índice de lucro operacional, índice de capital de giro, índice de dívida versus patrimônio, exigibilidade imediata(covenants), nível de cobertura de seguro. | D12: *Revisão de cláusulas contratuais ou acordos *Confirmação de cláusulas contratuais ou acordos.
A13: Empréstimos e Outras Dívidas | B13: Apresentação e Divulgação | C13: 4. Émpréstimos e outras dívidas estão corretamente descritos e classificados, e as devidas divulgações relacionadas a garantias de obrigações contratuais e condições de pagamento) relativas a esses valores e divulgações relativas a obrigações "extrabalanço" foram feitas. | D13: *Revisão das Demonstrações Financeiras e comparação das divulgações feitas com os requisitos dos princípios de contabilidade *Confirmação de cláusulas contratuais ou outros acordos. *Revisão para determinar o cumprimento das obrigações contratuais.
A14: Imposto de Renda | B14: Existência D&O Valorização | C14: 1. As obrigações(Ativos) registradas, relativas a IR representam impostos a pagar (pagos antecipadamente ou a recuperar), e foram corretamente registradas. | D14: *Procedimentos Analíticos *Teste de comparação do passivo(ou ativo) registrado com uma estimativa da provável obrigação(ou crédito) *Análises das contas
... A22: PL - CAPITAL e Outros Itens Patrimoniais | B22: Apresentação e Divulgação | C22: 4. O Capital e Outros Itens Patrimoniais estão corretamente descritos e classificadas nas demonstrações financeiras, e as devidas divulgações relativas a esses valores foram feitas. | D22: *Revisão das Demonstrações Financeiras e comparação das divulgações feitas com os requisitos dos princípios de contabilidade

Sheet ASSERTIVAS RESULTADO
A3: Área | B3: Assertivas Testadas | C3: Objetivos de Auditoria | D3: Exemplos de Testes Substantivos de Auditoria para Alcançar os Ojbetivos de Auditoria | G3: Principais Contas de Resultado | H3: Assertivas de Auditoria | I3: Principais Objetivos de Auditoria | J3: Exemplos de Testes Substantivos de Auditoria
A4: Vendas e outras receitas e provisões relacionadas | B4: Ocorrência Integridade | C4: 1. As vendas e outras receitas representam todas e somente transações(produtos despachados ou serviços prestados) que ocorreram durante o período e foram corretamente registradas | D4: *Circularização de contas a receber ou procedimentos alternativos *Procedimentos analíticos *Testes de corte (Cut-off) de vendas e outras receitas *Teste de reconhecimento de receita | G4: Receita de Vendas | H4: Existência, Ocorrência, Integridade, Exatidão, Direitos e Obrigações | I4: Verificar se as vendas registradas existem e foram efetuadas durante o período, se foram realizadas corretamente, se estão completas, precisas e refletem os valores corretos e se a empresa tem direitos e obrigações relacionados à receita. | J4: Revisão de contratos e pedidos de vendas, confirmação de vendas com clientes, análise das políticas e práticas contábeis aplicadas pela empresa para reconhecimento de receita, teste de amostras de vendas registradas.
A5: Vendas e outras receitas e provisões relacionadas | B5: Valorização | C5: 2. As provisões para contas duvidosas, devoluções, abatimentos e descontos foram colocadas no devido período | D5: *Procedimentos analíticos *Avaliação de provisões de valorização | G5: Custo dos Produtos Vendidos | H5: Existência, Integridade, Exatidão | I5: Verificar se os custos associados aos produtos vendidos existem e foram incorridos no período, se estão completos e precisos, e se foram reconhecidos no período correto. | J5: Revisão de ordens de compra, confirmação com fornecedores, avaliação das políticas e práticas contábeis aplicadas pela empresa para reconhecimento de custo dos produtos vendidos, teste de amostras de transações de custo dos produtos vendidos.
A6: Vendas e outras receitas e provisões relacionadas | B6: Apresentação e Divulgação | C6: 3. As receitas e as provisões para contas duvidosas, devoluções, abatimentos e descontos estão corretamente classificadas, e as devidas divulgações relativas a esses valores foram feitas. | D6: *Revisão das Demonstrações Financeiras e comparação das divulgações feitas com os requisitos dos princípios de contabilidade | G6: Despesas Operacionais | H6: Existência, Integridade, Exatidão | I6: Verificar se as despesas operacionais registradas existem e foram incorridas no período, se estão completas e precisas, e se foram reconhecidas no período correto. | J6: Revisão de documentos de suporte, confirmação com fornecedores, avaliação das políticas e práticas contábeis aplicadas pela empresa para reconhecimento de despesas operacionais, teste de amostras de transações de despesas operacionais.
A7: Custo das vendas | B7: Ocorrência Integridade | C7: 1. O Custo das vendas representa todas e somente transações relativas a produtos despachados ou serviços prestados durante o ano e está corretamente registrado | D7: *Testes de corte (Cut-off) custo das vendas *Procedimentos analíticos *Análise se contas | G7: Despesas Financeiras | H7: Existência, Integridade, Exatidão | I7: Verificar se as despesas financeiras registradas existem e foram incorridas no período, se estão completas e precisas, e se foram reconhecidas no período correto. | J7: Revisão de documentos de suporte, confirmação com instituições financeiras, avaliação das políticas e práticas contábeis aplicadas pela empresa para reconhecimento de despesas financeiras, teste de amostras de transações de despesas financeiras.
A8: Custo das vendas | B8: Apresentação e Divulgação | C8: 2. O custo das vendas está corretamente descrito e classificado nas demonstrações financeiras, e devidas divulgações relativas a esses valores foram feitas | D8: *Revisão das Demonstrações Financeiras e comparação das divulgações feitas com os requisitos dos princípios de contabilidade | G8: Receitas Financeiras | H8: Existência, Ocorrência, Integridade, Exatidão, Direitos e Obrigações | I8: Verificar se as receitas financeiras registradas existem e foram efetuadas durante o período, se foram realizadas corretamente, se estão completas, precisas e refletem os valores corretos e se a empresa tem direitos e obrigações relacionados à receita. | J8: Revisão de contratos e acordos financeiros, confirmação com instituições financeiras, análise das políticas e práticas contábeis aplicadas pela empresa para reconhecimento de receita financeira, teste de amostras de transações de receita financeira.
A9: Despesas com juros | B9: Ocorrência Integridade Alocação | C9: 1. As despesas com juros (incluindo as amortizações e despesas pagas antecipadamente) representam todos e somente os juros incorridos durante o período e foram corretamente registradas | D9: *Confirmação das principais cláusulas de contratos de empréstimos com os credores * Teste preditivo de despesas de juros *Análise de contas *Recálculo de amortização de despesas | G9: Despesas não Operacionais | H9: Existência, Integridade, Exatidão | I9: Verificar se as despesas não operacionais registradas existem e foram incorridas no período, se estão completas e precisas, e se foram reconhecidas no período correto. | J9: Revisão de documentos de suporte, confirmação com fornecedores, avaliação das políticas e práticas contábeis aplicadas pela empresa para reconhecimento de despesas não operacionais, teste de amostras de transações de despesas não operacionais.
A10: Despesas com juros | B10: Apresentação e Divulgação | C10: 2. As despesas com juros estão corretamente descritas e classificadas, e as devidas divulgações relativas a esses valores foram feitas | D10: *Procedimentos analíticos **Revisão das Demonstrações Financeiras e comparação das divulgações feitas com os requisitos dos princípios de contabilidade **Confirmação das principais cláusulas de contratos de empréstimos com os credores | G10: Lucro Bruto | H10: Existência, Integridade, Exatidão | I10: Verificar se o lucro bruto foi calculado corretamente, considerando as receitas e custos dos produtos vendidos. | J10: Teste de cálculo do lucro bruto, revisão de documentos de suporte, confirmação com fornecedores.
